Workbook

Sheet README
A1: PNA business forecast - unit economics, 12-month outlook, 3-year scenarios, business-model economics, sensitivity
A2: Economics & Market Sizing agent, 2026-10-16. Build script: economics/build_scripts/build_business_forecast.py (run via run_all.py).
A4: Status | B4: Illustrative, assumption-driven planning model. PNA's actual revenue, fees, costs and enrolments are NOT known; the baseline is CA-01 (<60 students, base 50) x assumed fees (CA-02).
A5: Scenarios | B5: Conservative = adverse rates + ₹10L plan; Base = base rates + ₹30L plan; Aggressive = favourable rates + ₹50L plan. Rates vs plan are typed in Assumptions column J; Plan10L_BaseRates and Plan50L_BaseRates isolate the envelope choice (BM stress test 7).
A6: Alignment | B6: Growth agent: ladder L1-L5, A-GRO-01..50, paid-media ramp and team lines (growth_marketing_strategy.md §10). BM agent: realised L3 fee A-BM-02 (₹65k/80k/1.0L), batch cap 12, trainer pay A-BM-04, founder path A-BM-10, pop-ups A-BM-06, gates G0-G3b.
A7: Price | B7: L3 list ₹90k (A-GRO-06) vs realised ₹80k (A-BM-02): revenue uses realised. Until the proof gate (A-ECO-104: M7 base, M5 aggressive, not in Y1 conservative) PNA charges today's fee CA-02 (₹40k/60k/75k) incl. kit.
A8: Enrolment engine | B8: Career demand = seasonality x speed-to-lead factor x [non-paid share x plan target + MIN(paid share x target, budget x career share / effective paid CAC)], then limited by seat capacity. Effective CAC = funnel paid-route CAC x overhead factor calibrated so the Base budget buys the Base target.
A9: GST | B9: 18% GST on private non-recognised training (A-ECO-23, GST Council flyer). Base assumes quoted fees include GST (revenue = fee/1.18); Flex_gst_ontop shows charging it on top.
A10: Cash | B10: Net cash flow = EBITDA + instalment timing (A-ECO-34) - capex/deposits. Excludes income tax, GST input/output timing and any founder draw. Peak cash need is compared with the plan envelope (CA-03).
A11: Sheets | B11: Dashboard ; Assumptions ; Unit_Economics ; Capacity ; 3yr_Scenarios ; Sensitivity ; BM_Unit_Economics ; Outlook_* (x3 scenarios + Selected + 2 cross runs) ; Flex_* (sensitivity re-runs) ; Checks

Sheet Dashboard
A1: PNA business forecast - dashboard (₹ lakh unless stated; ex-GST; illustrative, assumption-driven)
A2: Scenario = rates + plan bundle. Conservative = adverse rates + ₹10L plan; Base = base rates + ₹30L plan; Aggressive = favourable rates + ₹50L plan. Cross runs show the ₹10L / ₹50L plans at Base rates.
A4: Year-1 (Nov-26 to Oct-27) | B4: Conservative | C4: Base | D4: Aggressive | E4: ₹10L plan @ Base rates | F4: ₹50L plan @ Base rates | G4: Note
A5: Revenue, Year 1 (ex-GST) | B5: =Outlook_Conservative!B109/100000 -> 16.714396 | C5: =Outlook_Base!B109/100000 -> 71.143533 | D5: =Outlook_Aggressive!B109/100000 -> 134.55428 | E5: =Plan10L_BaseRates!B109/100000 -> 38.134814 | F5: =Plan50L_BaseRates!B109/100000 -> 99.929187
A6: EBITDA, Year 1 | B6: =Outlook_Conservative!B110/100000 -> -13.554457 | C6: =Outlook_Base!B110/100000 -> 5.5146551 | D6: =Outlook_Aggressive!B110/100000 -> 35.066478 | E6: =Plan10L_BaseRates!B110/100000 -> 9.5491944 | F6: =Plan50L_BaseRates!B110/100000 -> -4.5479306
A7: EBITDA margin, Year 1 | B7: =Outlook_Conservative!B111 -> -0.81094506 | C7: =Outlook_Base!B111 -> 0.077514496 | D7: =Outlook_Aggressive!B111 -> 0.26061213 | E7: =Plan10L_BaseRates!B111 -> 0.25040622 | F7: =Plan50L_BaseRates!B111 -> -0.045511534
A8: Memo: Year-1 EBITDA after founder-role salary | B8: =Outlook_Conservative!B112/100000 -> -22.554457 | C8: =Outlook_Base!B112/100000 -> -3.4853449 | D8: =Outlook_Aggressive!B112/100000 -> 26.066478 | E8: =Plan10L_BaseRates!B112/100000 -> 0.54919441 | F8: =Plan50L_BaseRates!B112/100000 -> -13.547931
A9: Capex and deposits, Year 1 | B9: =Outlook_Conservative!B113/100000 -> 0.5 | C9: =Outlook_Base!B113/100000 -> 19.72 | D9: =Outlook_Aggressive!B113/100000 -> 27.04 | E9: =Plan10L_BaseRates!B113/100000 -> 0.5 | F9: =Plan50L_BaseRates!B113/100000 -> 27.04
A10: Peak cumulative cash need, Year 1 | B10: =Outlook_Conservative!B114/100000 -> 15.443217 | C10: =Outlook_Base!B114/100000 -> 26.142235 | D10: =Outlook_Aggressive!B114/100000 -> 28.80706 | E10: =Plan10L_BaseRates!B114/100000 -> 4.1372074 | F10: =Plan50L_BaseRates!B114/100000 -> 45.361828
A11: Investment envelope for this plan (CA-03) | B11: =Outlook_Conservative!B115/100000 -> 10 | C11: =Outlook_Base!B115/100000 -> 30 | D11: =Outlook_Aggressive!B115/100000 -> 50 | E11: =Plan10L_BaseRates!B115/100000 -> 10 | F11: =Plan50L_BaseRates!B115/100000 -> 50
A12: Headroom: envelope - peak cash need | B12: =Outlook_Conservative!B116/100000 -> -5.4432169 | C12: =Outlook_Base!B116/100000 -> 3.8577648 | D12: =Outlook_Aggressive!B116/100000 -> 21.19294 | E12: =Plan10L_BaseRates!B116/100000 -> 5.8627926 | F12: =Plan50L_BaseRates!B116/100000 -> 4.638172
A13: Career enrolments, Year 1 (new students) | B13: =Outlook_Conservative!B117 -> 30.376401 | C13: =Outlook_Base!B117 -> 89.450184 | D13: =Outlook_Aggressive!B117 -> 123.22992 | E13: =Plan10L_BaseRates!B117 -> 48.427721 | F13: =Plan50L_BaseRates!B117 -> 126.54821
A14: Career enrolments per month, months 7-12 average | B14: =Outlook_Conservative!B118 -> 3.6359065 | C14: =Outlook_Base!B118 -> 10.852623 | D14: =Outlook_Aggressive!B118 -> 13.744387 | E14: =Plan10L_BaseRates!B118 -> 5.4336396 | F14: =Plan50L_BaseRates!B118 -> 14.788083
A15: Masterclass seats, Year 1 | B15: =Outlook_Conservative!B119 -> 67.5 | C15: =Outlook_Base!B119 -> 153 | D15: =Outlook_Aggressive!B119 -> 202.5 | E15: =Plan10L_BaseRates!B119 -> 76.5 | F15: =Plan50L_BaseRates!B119 -> 191.25
A16: Seat utilisation, month 12 | B16: =Outlook_Conservative!B120 -> 0.4834982 | C16: =Outlook_Base!B120 -> 0.84101366 | D16: =Outlook_Aggressive!B120 -> 0.9 | E16: =Plan10L_BaseRates!B120 -> 0.80232434 | F16: =Plan50L_BaseRates!B120 -> 0.9
A17: First month seats bind (share of demand that fits < 100%) | B17: =Outlook_Conservative!B121 -> not in Y1 | C17: =Outlook_Base!B121 -> 6 | D17: =Outlook_Aggressive!B121 -> 7 | E17: =Plan10L_BaseRates!B121 -> 8 | F17: =Plan50L_BaseRates!B121 -> 7
A18: Founder share of contact hours, month 12 | B18: =Outlook_Conservative!B122 -> 0.4 | C18: =Outlook_Base!B122 -> 0.3 | D18: =Outlook_Aggressive!B122 -> 0.25 | E18: =Plan10L_BaseRates!B122 -> 0.4 | F18: =Plan50L_BaseRates!B122 -> 0.25
A19: Trainers + assistants on payroll, month 12 | B19: =Outlook_Conservative!B123 -> 1.5 | C19: =Outlook_Base!B123 -> 3 | D19: =Outlook_Aggressive!B123 -> 4 | E19: =Plan10L_BaseRates!B123 -> 1.5 | F19: =Plan50L_BaseRates!B123 -> 4
A20: Contribution per career enrolment, month 12 (career contribution share) | B20: =Outlook_Conservative!B124 -> 34929.965 | C20: =Outlook_Base!B124 -> 50195.582 | D20: =Outlook_Aggressive!B124 -> 68504.555 | E20: =Plan10L_BaseRates!B124 -> 50420.582 | F20: =Plan50L_BaseRates!B124 -> 50033.241
A21: Break-even career enrolments per month at month-12 cost base | B21: =Outlook_Conservative!B127 -> 4.3555767 | C21: =Outlook_Base!B127 -> 5.4796574 | D21: =Outlook_Aggressive!B127 -> 4.8575808 | E21: =Plan10L_BaseRates!B127 -> 1.0401147 | F21: =Plan50L_BaseRates!B127 -> 10.741123
A22: Break-even career enrolments per year (x12) | B22: =Outlook_Conservative!B128 -> 52.26692 | C22: =Outlook_Base!B128 -> 65.755889 | D22: =Outlook_Aggressive!B128 -> 58.29097 | E22: =Plan10L_BaseRates!B128 -> 12.481377 | F22: =Plan50L_BaseRates!B128 -> 128.89347
A23: Effective media CAC per paid career enrolment, months 7-12 | B23: =Outlook_Conservative!B129 -> 12834.947 | C23: =Outlook_Base!B129 -> 10750.089 | D23: =Outlook_Aggressive!B129 -> 16976.627 | E23: =Plan10L_BaseRates!B129 -> 8588.4729 | F23: =Plan50L_BaseRates!B129 -> 15778.471
A24: Effective media CAC as % of realised L3 fee (ex-GST) | B24: =Outlook_Conservative!B130 -> 0.23300365 | C24: =Outlook_Base!B130 -> 0.15856381 | D24: =Outlook_Aggressive!B130 -> 0.2003242 | E24: =Plan10L_BaseRates!B130 -> 0.12667998 | F24: =Plan50L_BaseRates!B130 -> 0.23273245
A25: Fully loaded acquisition cost / career revenue, months 7-12 (media + growth team + tools + rewards + EMI) | B25: =Outlook_Conservative!B131 -> 0.65089263 | C25: =Outlook_Base!B131 -> 0.42243028 | D25: =Outlook_Aggressive!B131 -> 0.4446932 | E25: =Plan10L_BaseRates!B131 -> 0.27821829 | F25: =Plan50L_BaseRates!B131 -> 0.55094716
A26: Career enrolments per month at which fully loaded acquisition = 25% of career revenue (month-12 cost and price) | B26: =Outlook_Conservative!B132 -> 7.5288401 | C26: =Outlook_Base!B132 -> 17.542883 | D26: =Outlook_Aggressive!B132 -> 23.95295 | E26: =Plan10L_BaseRates!B132 -> 5.6684374 | F26: =Plan50L_BaseRates!B132 -> 31.306627
A27: EBITDA, last quarter (Aug-Oct 2027) | B27: =Outlook_Conservative!B133/100000 -> -1.3244177 | C27: =Outlook_Base!B133/100000 -> 6.6793824 | D27: =Outlook_Aggressive!B133/100000 -> 18.38758 | E27: =Plan10L_BaseRates!B133/100000 -> 5.7054945 | F27: =Plan50L_BaseRates!B133/100000 -> 5.5847348
A28: First month with EBITDA >= 0 | B28: =Outlook_Conservative!B134 -> not in Y1 | C28: =Outlook_Base!B134 -> 7 | D28: =Outlook_Aggressive!B134 -> 5 | E28: =Plan10L_BaseRates!B134 -> 5 | F28: =Plan50L_BaseRates!B134 -> 7
A29: Cash position, end of Year 1 | B29: =Outlook_Conservative!B135/100000 -> -15.443217 | C29: =Outlook_Base!B135/100000 -> -17.129608 | D29: =Outlook_Aggressive!B135/100000 -> 8.0264777 | E29: =Plan10L_BaseRates!B135/100000 -> 7.6455483 | F29: =Plan50L_BaseRates!B135/100000 -> -35.528116
A31: Directional 3-year view (₹ lakh)
A32: Metric | B32: Cons Y1 | C32: Cons Y2 | D32: Cons Y3 | E32: Base Y1 | F32: Base Y2 | G32: Base Y3 | H32: Aggr Y1 | I32: Aggr Y2 | J32: Aggr Y3
A33: Total revenue | B33: =3yr_Scenarios!B38 -> 16.714396 | C33: =3yr_Scenarios!C38 -> 26.631759 | D33: =3yr_Scenarios!D38 -> 36.657299 | E33: =3yr_Scenarios!E38 -> 71.143533 | F33: =3yr_Scenarios!F38 -> 120.01493 | G33: =3yr_Scenarios!G38 -> 166.93116 | H33: =3yr_Scenarios!H38 -> 134.55428 | I33: =3yr_Scenarios!I38 -> 235.65821 | J33: =3yr_Scenarios!J38 -> 334.642
A34: EBITDA | B34: =3yr_Scenarios!B49 -> -13.554457 | C34: =3yr_Scenarios!C49 -> -7.2101524 | D34: =3yr_Scenarios!D49 -> -9.6406418 | E34: =3yr_Scenarios!E49 -> 5.5146551 | F34: =3yr_Scenarios!F49 -> 17.552053 | G34: =3yr_Scenarios!G49 -> 44.836901 | H34: =3yr_Scenarios!H49 -> 35.066478 | I34: =3yr_Scenarios!I49 -> 96.366426 | J34: =3yr_Scenarios!J49 -> 162.74302
A35: EBITDA margin | B35: =3yr_Scenarios!B50 -> -0.81094506 | C35: =3yr_Scenarios!C50 -> -0.27073512 | D35: =3yr_Scenarios!D50 -> -0.26299379 | E35: =3yr_Scenarios!E50 -> 0.077514496 | F35: =3yr_Scenarios!F50 -> 0.14624892 | G35: =3yr_Scenarios!G50 -> 0.26859515 | H35: =3yr_Scenarios!H50 -> 0.26061213 | I35: =3yr_Scenarios!I50 -> 0.40892454 | J35: =3yr_Scenarios!J50 -> 0.48631977
A36: Career enrolments delivered | B36: =3yr_Scenarios!B17 -> 30.376401 | C36: =3yr_Scenarios!C17 -> 38.989295 | D36: =3yr_Scenarios!D17 -> 40.93876 | E36: =3yr_Scenarios!E17 -> 89.450184 | F36: =3yr_Scenarios!F17 -> 121.91883 | G36: =3yr_Scenarios!G17 -> 134.11072 | H36: =3yr_Scenarios!H17 -> 123.22992 | I36: =3yr_Scenarios!I17 -> 160.7633 | J36: =3yr_Scenarios!J17 -> 162.46608
A37: Peak cash need to date | B37: =3yr_Scenarios!B54 -> 15.443217 | C37: =3yr_Scenarios!C54 -> 25.653369 | D37: =3yr_Scenarios!D54 -> 37.994011 | E37: =3yr_Scenarios!E54 -> 26.142235 | F37: =3yr_Scenarios!F54 -> 26.142235 | G37: =3yr_Scenarios!G54 -> 26.142235 | H37: =3yr_Scenarios!H54 -> 28.80706 | I37: =3yr_Scenarios!I54 -> 28.80706 | J37: =3yr_Scenarios!J54 -> 28.80706
A39: Sensitivity (Base Year-1 EBITDA swing, ₹ lakh) - see Sensitivity sheet
A40: =Sensitivity!A6 -> Conversion (all routes; low = founder step-back ÷1.25) | B40: =Sensitivity!F6/100000 -> 13.939746 | C40: =Sensitivity!G6 -> 2 | D40: =Sensitivity!L6 -> ██████████████████
A41: =Sensitivity!A7 -> Fees (all products) | B41: =Sensitivity!F7/100000 -> 23.095618 | C41: =Sensitivity!G7 -> 1 | D41: =Sensitivity!L7 -> ██████████████████████████████
A42: =Sensitivity!A8 -> Cohort fill (students per batch 8 vs 12) | B42: =Sensitivity!F8/100000 -> 2.08 | C42: =Sensitivity!G8 -> 7 | D42: =Sensitivity!L8 -> ███
A43: =Sensitivity!A9 -> CPL / CAC (paid routes) | B43: =Sensitivity!F9/100000 -> 3.0316349 | C43: =Sensitivity!G9 -> 6 | D43: =Sensitivity!L9 -> ████
A44: =Sensitivity!A10 -> Variable delivery cost (kit, consumables) | B44: =Sensitivity!F10/100000 -> 4.3370314 | C44: =Sensitivity!G10 -> 5 | D44: =Sensitivity!L10 -> ██████
A45: =Sensitivity!A11 -> Rent (₹130 vs ₹47 per sq ft vs ₹80) | B45: =Sensitivity!F11/100000 -> 8.65275 | C45: =Sensitivity!G11 -> 4 | D45: =Sensitivity!L11 -> ███████████
A46: =Sensitivity!A12 -> Paid-media budget (holding the target) | B46: =Sensitivity!F12/100000 -> 1.4651452 | C46: =Sensitivity!G12 -> 8 | D46: =Sensitivity!L12 -> ██
A47: =Sensitivity!A13 -> GST charged on top of list fees (vs absorbed in quoted fee) | B47: =Sensitivity!F13/100000 -> 12.739674 | C47: =Sensitivity!G13 -> 3 | D47: =Sensitivity!L13 -> █████████████████

Sheet Assumptions
A1: Assumptions register (inputs)
A2: Blue = input. Scenario columns: Conservative = adverse rates + ₹10L plan; Base = base rates + ₹30L plan; Aggressive = favourable rates + ₹50L plan. Column J 'Type': rate (prices, conversion, wages) or plan (what the plan buys).
A3: Scenario selector | C3: Base | D3: <- choose Conservative / Base / Aggressive (drives column I 'Selected' and any sheet that uses it)
A4: Scenario index | C4: =MATCH($C$3,$K$4:$M$4,0) -> 2 | K4: Conservative | L4: Base | M4: Aggressive
A6: ID | B6: Description | C6: Conservative | D6: Base | E6: Aggressive | F6: Unit | G6: Source / rationale | H6: Tag | I6: Selected | J6: Type
A8: 1. Shared with funnel_economics.xlsx (assumption_values.py): canonical, prices, funnel, delivery costs, Growth budget lines
A9: CA-01 | B9: PNA paying students per year today (all courses) | C9: 30 | D9: 50 | E9: 60 | F9: students/yr | G9: Founder: 'under 60' (2026-10-16) | H9: [FOUNDER] | I9: =INDEX(C9:E9,$C$4) -> 50 | J9: rate
A10: CA-02 | B10: Current flagship professional course fee (incl. kit) | C10: 40000 | D10: 60000 | E10: 75000 | F10: ₹ | G10: Not supplied; local diploma band ₹35-75k (S-LC §6) | H10: [HYP] | I10: =INDEX(C10:E10,$C$4) -> 60000 | J10: rate
A11: CA-03 | B11: Growth investment envelope, 12 months | C11: 1000000 | D11: 3000000 | E11: 5000000 | F11: ₹ | G11: Founder: moderate ₹10-50L | H11: [FOUNDER] | I11: =INDEX(C11:E11,$C$4) -> 3000000 | J11: plan
A12: A-ECO-101 | B12: Career (L2/L3-type) share of today's students | C12: 0.6 | D12: 0.6 | E12: 0.6 | F12: % | G12: Assumed mix; founder data pull (V1) to replace | H12: [HYP] | I12: =INDEX(C12:E12,$C$4) -> 0.6 | J12: rate
A13: A-ECO-102 | B13: Average fee of today's short courses / masterclasses | C13: 6000 | D13: 8000 | E13: 10000 | F13: ₹ | G13: Local short-course band ₹6.5-25k (S-LC §6) | H13: [HYP] | I13: =INDEX(C13:E13,$C$4) -> 8000 | J13: rate
A14: A-ECO-103 | B14: Pro kit cost borne by PNA while fee includes kit (pre price-step) | C14: 15000 | D14: 12000 | E14: 10000 | F14: ₹/student | G14: Growth agent: optional kit ₹18-25k at near cost; basic included kit assumed cheaper | H14: [HYP] | I14: =INDEX(C14:E14,$C$4) -> 12000 | J14: rate
A15: A-ECO-23 | B15: GST rate on PNA training (private, non-recognised; SAC 9992) | C15: 0.18 | D15: 0.18 | E15: 0.18 | F15: % | G15: GST Council education flyer: private/unrecognised coaching not exempt (https://www.gstcouncil.gov.in/sites/default/files/e-version-gst-flyers/GST_Education_Services.pdf, accessed 2026-10-16); AAR Kerala 2022 -> 18% under 9992 | H15: [FACT] rule / [HYP] PNA | I15: =INDEX(C15:E15,$C$4) -> 0.18 | J15: rate
A16: A-ECO-24 | B16: Fees quoted GST-inclusive? (1 = PNA absorbs GST from list fee; 0 = GST charged on top) | C16: 1 | D16: 1 | E16: 1 | F16: switch | G16: Consumer academies mostly quote one number; DBA quotes ex-GST, Pearl incl. GST (S-NC-26, S-IND-23). Sensitivity flips it | H16: [HYP] | I16: =INDEX(C16:E16,$C$4) -> 1 | J16: rate
A17: A-GRO-04 | B17: L1 Career Taster ticket | C17: 999 | D17: 999 | E17: 999 | F17: ₹ | G17: A-GRO-04 base (range ₹499-1,999); credited on enrolment | H17: [HYP] | I17: =INDEX(C17:E17,$C$4) -> 999 | J17: rate
A18: A-GRO-05 | B18: L2 Foundation fee (4 weeks, ~80 h) | C18: 30000 | D18: 39900 | E18: 45000 | F18: ₹ | G18: A-GRO-05 (Aggressive = midpoint of Growth base/high to avoid stacking upsides) | H18: [HYP] | I18: =INDEX(C18:E18,$C$4) -> 39900 | J18: rate
A19: A-GRO-06 | B19: L3 Professional Bridal Programme list tuition (after proof gate; kit optional) | C19: 75000 | D19: 90000 | E19: 120000 | F19: ₹ | G19: A-GRO-06 | H19: [HYP] | I19: =INDEX(C19:E19,$C$4) -> 90000 | J19: rate
A20: A-BM-02 | B20: L3 realised fee after discounts/credits (after proof gate) | C20: 65000 | D20: 80000 | E20: 100000 | F20: ₹ | G20: A-BM-02 (list ₹90k-1.25L) | H20: [HYP] | I20: =INDEX(C20:E20,$C$4) -> 80000 | J20: rate
... A113: A-GRO-50 | B113: SEO content freelancer | C113: 0 | D113: 15000 | E113: 25000 | F113: ₹/mo | G113: Growth §10 | H113: [EST] | I113: =INDEX(C113:E113,$C$4) -> 15000 | J113: plan
A114: 2. Forecast-specific (A-ECO, A-BM, Growth budget ramp, seasonality, 3-year drivers)
A115: A-ECO-FUN-01 | B115: Paid-route media CAC (CTWA + Search + Taster net), from funnel_economics.xlsx Summary | C115: 16680 | D115: 4826 | E115: 1422 | F115: ₹/enrol | G115: Pasted by run_all.py from funnel_economics.xlsx (Funnel_* row 'Paid-route media CAC') | H115: [EST] model output | I115: =INDEX(C115:E115,$C$4) -> 4826 | J115: rate
A116: A-ECO-FUN-02 | B116: Funnel-required career media per month at target, from funnel_economics.xlsx | C116: 64548 | D116: 37633 | E116: 9387 | F116: ₹/mo | G116: Pasted by run_all.py (comparison only) | H116: [EST] model output | I116: =INDEX(C116:E116,$C$4) -> 37633 | J116: rate
A117: A-ECO-FUN-03 | B117: Masterclass media per seat (inside the Growth paid budget), from funnel_economics.xlsx | C117: 1400 | D117: 300 | E117: 43 | F117: ₹/seat | G117: Pasted by run_all.py | H117: [EST] model output | I117: =INDEX(C117:E117,$C$4) -> 300 | J117: rate
A118: A-ECO-FUN-04 | B118: Self-makeup media per seat (inside the Growth paid budget), from funnel_economics.xlsx | C118: 3200 | D118: 706 | E118: 160 | F118: ₹/seat | G118: Pasted by run_all.py | H118: [EST] model output | I118: =INDEX(C118:E118,$C$4) -> 706 | J118: rate
A119: A-ECO-50 | B119: Share of the paid-media budget that buys career (L2/L3) leads | C119: 0.7 | D119: 0.7 | E119: 0.7 | F119: % | G119: marketing_channel_plan.md rows 8-15: career CTWA, regional, Search, brand, taster half of M3, retargeting ≈70% of base ₹1.0L | H119: [EST] | I119: =INDEX(C119:E119,$C$4) -> 0.7 | J119: rate
A120: A-ECO-51 | B120: Awareness/retargeting overhead factor on funnel CAC (calibrated so the Base plan budget buys the Base target at steady state) | C120: =Assumptions!$D$119*Assumptions!$D$132/(Assumptions!$D$25*(Assumptions!$D$27+Assumptions!$D$28+Assumptions!$D$31)*Assumptions!$D$115) -> 2.417461 | D120: =Assumptions!$D$119*Assumptions!$D$132/(Assumptions!$D$25*(Assumptions!$D$27+Assumptions!$D$28+Assumptions!$D$31)*Assumptions!$D$115) -> 2.417461 | E120: =Assumptions!$D$119*Assumptions!$D$132/(Assumptions!$D$25*(Assumptions!$D$27+Assumptions!$D$28+Assumptions!$D$31)*Assumptions!$D$115) -> 2.417461 | F120: x | G120: Calibrated: A-ECO-50 x Base Oct-27 budget / (A-GRO-01 base x paid mix x A-ECO-FUN-01 base) | H120: [EST] calibration | I120: =INDEX(C120:E120,$C$4) -> 2.417461 | J120: rate
A121: A-GRO-BUD-01 | B121: Paid media budget, month 1 (Nov-26) | C121: 10000 | D121: 15000 | E121: 15000 | F121: ₹ | G121: growth_marketing_strategy.md §6.4/§10; marketing_channel_plan.md §3.2 (Mar+ only if spend gates green) | H121: [EST] | I121: =INDEX(C121:E121,$C$4) -> 15000 | J121: plan
A122: A-GRO-BUD-02 | B122: Paid media budget, month 2 (Dec-26) | C122: 25000 | D122: 40000 | E122: 50000 | F122: ₹ | G122: growth_marketing_strategy.md §6.4/§10; marketing_channel_plan.md §3.2 (Mar+ only if spend gates green) | H122: [EST] | I122: =INDEX(C122:E122,$C$4) -> 40000 | J122: plan
A123: A-GRO-BUD-03 | B123: Paid media budget, month 3 (Jan-27) | C123: 30000 | D123: 50000 | E123: 60000 | F123: ₹ | G123: growth_marketing_strategy.md §6.4/§10; marketing_channel_plan.md §3.2 (Mar+ only if spend gates green) | H123: [EST] | I123: =INDEX(C123:E123,$C$4) -> 50000 | J123: plan
A124: A-GRO-BUD-04 | B124: Paid media budget, month 4 (Feb-27) | C124: 35000 | D124: 60000 | E124: 70000 | F124: ₹ | G124: growth_marketing_strategy.md §6.4/§10; marketing_channel_plan.md §3.2 (Mar+ only if spend gates green) | H124: [EST] | I124: =INDEX(C124:E124,$C$4) -> 60000 | J124: plan
A125: A-GRO-BUD-05 | B125: Paid media budget, month 5 (Mar-27) | C125: 40000 | D125: 80000 | E125: 120000 | F125: ₹ | G125: growth_marketing_strategy.md §6.4/§10; marketing_channel_plan.md §3.2 (Mar+ only if spend gates green) | H125: [EST] | I125: =INDEX(C125:E125,$C$4) -> 80000 | J125: plan
A126: A-GRO-BUD-06 | B126: Paid media budget, month 6 (Apr-27) | C126: 40000 | D126: 90000 | E126: 170000 | F126: ₹ | G126: growth_marketing_strategy.md §6.4/§10; marketing_channel_plan.md §3.2 (Mar+ only if spend gates green) | H126: [EST] | I126: =INDEX(C126:E126,$C$4) -> 90000 | J126: plan
A127: A-GRO-BUD-07 | B127: Paid media budget, month 7 (May-27) | C127: 40000 | D127: 100000 | E127: 200000 | F127: ₹ | G127: growth_marketing_strategy.md §6.4/§10; marketing_channel_plan.md §3.2 (Mar+ only if spend gates green) | H127: [EST] | I127: =INDEX(C127:E127,$C$4) -> 100000 | J127: plan
A128: A-GRO-BUD-08 | B128: Paid media budget, month 8 (Jun-27) | C128: 40000 | D128: 100000 | E128: 200000 | F128: ₹ | G128: growth_marketing_strategy.md §6.4/§10; marketing_channel_plan.md §3.2 (Mar+ only if spend gates green) | H128: [EST] | I128: =INDEX(C128:E128,$C$4) -> 100000 | J128: plan
A129: A-GRO-BUD-09 | B129: Paid media budget, month 9 (Jul-27) | C129: 40000 | D129: 100000 | E129: 200000 | F129: ₹ | G129: growth_marketing_strategy.md §6.4/§10; marketing_channel_plan.md §3.2 (Mar+ only if spend gates green) | H129: [EST] | I129: =INDEX(C129:E129,$C$4) -> 100000 | J129: plan
A130: A-GRO-BUD-10 | B130: Paid media budget, month 10 (Aug-27) | C130: 40000 | D130: 100000 | E130: 200000 | F130: ₹ | G130: growth_marketing_strategy.md §6.4/§10; marketing_channel_plan.md §3.2 (Mar+ only if spend gates green) | H130: [EST] | I130: =INDEX(C130:E130,$C$4) -> 100000 | J130: plan
A131: A-GRO-BUD-11 | B131: Paid media budget, month 11 (Sep-27) | C131: 40000 | D131: 100000 | E131: 200000 | F131: ₹ | G131: growth_marketing_strategy.md §6.4/§10; marketing_channel_plan.md §3.2 (Mar+ only if spend gates green) | H131: [EST] | I131: =INDEX(C131:E131,$C$4) -> 100000 | J131: plan
A132: A-GRO-BUD-12 | B132: Paid media budget, month 12 (Oct-27) | C132: 40000 | D132: 100000 | E132: 200000 | F132: ₹ | G132: growth_marketing_strategy.md §6.4/§10; marketing_channel_plan.md §3.2 (Mar+ only if spend gates green) | H132: [EST] | I132: =INDEX(C132:E132,$C$4) -> 100000 | J132: plan
... A229: A-ECO-220a | B229: Batch slots per day, Y2 | C229: 2.5 | D229: 3 | E229: 3 | F229: slots | G229: Weekend / evening batches | H229: [HYP] | I229: =INDEX(C229:E229,$C$4) -> 3 | J229: plan
A230: A-ECO-220b | B230: Batch slots per day, Y3 | C230: 3 | D230: 3 | E230: 3 | F230: slots | H230: [HYP] | I230: =INDEX(C230:E230,$C$4) -> 3 | J230: plan
A231: A-ECO-221a | B231: Stations, Y2 | C231: 8 | D231: 12 | E231: 16 | F231: stations | H231: [HYP] | I231: =INDEX(C231:E231,$C$4) -> 12 | J231: plan
A232: A-ECO-221b | B232: Stations, Y3 | C232: 10 | D232: 14 | E232: 18 | F232: stations | H232: [HYP] | I232: =INDEX(C232:E232,$C$4) -> 14 | J232: plan
A233: A-ECO-222a | B233: Counsellor FTE, Y2 | C233: 1 | D233: 1.5 | E233: 2 | F233: FTE | G233: Counsellor load A-GRO-38 | H233: [HYP] | I233: =INDEX(C233:E233,$C$4) -> 1.5 | J233: plan
A234: A-ECO-222b | B234: Counsellor FTE, Y3 | C234: 1 | D234: 2 | E234: 2.5 | F234: FTE | H234: [HYP] | I234: =INDEX(C234:E234,$C$4) -> 2 | J234: plan
A235: A-ECO-223a | B235: Academy manager in post, Y2 (FTE) | C235: 0 | D235: 1 | E235: 1 | F235: FTE | G235: BM: M12-18 | H235: [HYP] | I235: =INDEX(C235:E235,$C$4) -> 1 | J235: plan
A236: A-ECO-223b | B236: Academy manager in post, Y3 (FTE; Conservative part-time ops lead) | C236: 0.5 | D236: 1 | E236: 1 | F236: FTE | H236: [HYP] | I236: =INDEX(C236:E236,$C$4) -> 1 | J236: plan
A237: A-ECO-224a | B237: Paid media, Y2 | C237: 300000 | D237: 1200000 | E237: 2400000 | F237: ₹/yr | G237: Growth steady-state x 12; Conservative = test level after failed spend gates (stop-loss) | H237: [EST] | I237: =INDEX(C237:E237,$C$4) -> 1200000 | J237: plan
A238: A-ECO-224b | B238: Paid media, Y3 | C238: 300000 | D238: 1300000 | E238: 2600000 | F238: ₹/yr | G238: Conservative held at test level | H238: [EST] | I238: =INDEX(C238:E238,$C$4) -> 1300000 | J238: plan
A239: A-BM-15 | B239: Regional acquisition cost per incremental destination student | C239: 15000 | D239: 12500 | E239: 10000 | F239: ₹/student | G239: A-BM-15 out-of-town CAC ₹10-15k | H239: [HYP] | I239: =INDEX(C239:E239,$C$4) -> 12500 | J239: rate
A240: A-ECO-225 | B240: Accommodation-partner coordination cost per destination student | C240: 2500 | D240: 2000 | E240: 1500 | F240: ₹/student | G240: geographic_expansion §4.1(a) ₹2k | H240: [EST] | I240: =INDEX(C240:E240,$C$4) -> 2000 | J240: rate
A241: A-ECO-226a | B241: Capex Y2 (hybrid content refresh / build, stations, photo studio) | C241: 300000 | D241: 300000 | E241: 500000 | F241: ₹ | G241: Directional | H241: [EST] | I241: =INDEX(C241:E241,$C$4) -> 300000 | J241: plan
A242: A-ECO-226b | B242: Capex Y3 (content refresh, stations) | C242: 200000 | D242: 300000 | E242: 400000 | F242: ₹ | G242: Directional | H242: [EST] | I242: =INDEX(C242:E242,$C$4) -> 300000 | J242: plan
A243: A-ECO-227 | B243: Kit / product margin on retail sales to students & alumni, per career student per year (post price-step) | C243: 600 | D243: 960 | E243: 1400 | F243: ₹/student | G243: Same basis as A-ECO-37 (optional kit at near cost) | H243: [HYP] | I243: =INDEX(C243:E243,$C$4) -> 960 | J243: rate

Sheet Unit_Economics
A1: Programme unit economics - per seat and per cohort (scenario = Assumptions!C3 selector)
A2: Ladder from positioning_and_segments.md §6 (Growth) with BM realised fees. Fees incl. GST as quoted; revenue ex-GST. Trainer cost is a standard cost (salary / slots / fill).
A4: Metric | B4: L1 Career Taster | C4: L1-S5 Self-makeup | D4: L2 Foundation | E4: L3 Pro - today's fee (CA-02, incl. kit) | F4: L3 Pro - after price step (A-BM-02) | G4: L3 Destination / hybrid | H4: L4 Masterclass | I4: L5 Pro Circle (per yr) | J4: Notes
A5: Duration (on-campus months; seat-months per student) | B5: =0.1 -> 0.1 | C5: =0.1 -> 0.1 | D5: =1 -> 1 | E5: =Assumptions!$I$103 -> 3 | F5: =Assumptions!$I$103 -> 3 | G5: =Assumptions!$I$104 -> 2.5 | H5: =0.07 -> 0.07 | I5: =0 -> 0
A6: Contact hours (indicative) | B6: =3 -> 3 | C6: =6 -> 6 | D6: =80 -> 80 | E6: =290 -> 290 | F6: =290 -> 290 | G6: =250 -> 250 | H6: =12 -> 12 | I6: =24 -> 24
A7: Batch cap (A-BM-01) / seats per session | B7: =12 -> 12 | C7: =12 -> 12 | D7: =12 -> 12 | E7: =12 -> 12 | F7: =12 -> 12 | G7: =12 -> 12 | H7: =14 -> 14 | I7: =0 -> 0
A8: Cohort fill used (A-ECO-47; masterclass x A-ECO-132) | B8: =Assumptions!$I$102 -> 10 | C8: =Assumptions!$I$102 -> 10 | D8: =Assumptions!$I$102 -> 10 | E8: =Assumptions!$I$102 -> 10 | F8: =Assumptions!$I$102 -> 10 | G8: =Assumptions!$I$102 -> 10 | H8: =14*Assumptions!$I$193 -> 11.9 | I8: =0 -> 0
A9: Fee incl. GST (as quoted) | B9: =Assumptions!$I$17 -> 999 | C9: =Assumptions!$I$22 -> 4999 | D9: =Assumptions!$I$18 -> 39900 | E9: =Assumptions!$I$10 -> 60000 | F9: =Assumptions!$I$20 -> 80000 | G9: =Assumptions!$I$20 -> 80000 | H9: =Assumptions!$I$21 -> 10000 | I9: =Assumptions!$I$23 -> 9999
A10: Revenue per seat ex-GST | B10: =B9/(1+Assumptions!$I$15*Assumptions!$I$16) -> 846.61017 | C10: =C9/(1+Assumptions!$I$15*Assumptions!$I$16) -> 4236.4407 | D10: =D9/(1+Assumptions!$I$15*Assumptions!$I$16) -> 33813.559 | E10: =E9/(1+Assumptions!$I$15*Assumptions!$I$16) -> 50847.458 | F10: =F9/(1+Assumptions!$I$15*Assumptions!$I$16) -> 67796.61 | G10: =G9/(1+Assumptions!$I$15*Assumptions!$I$16) -> 67796.61 | H10: =H9/(1+Assumptions!$I$15*Assumptions!$I$16) -> 8474.5763 | I10: =I9/(1+Assumptions!$I$15*Assumptions!$I$16) -> 8473.7288
A11: Kit cost borne by PNA | B11: =0 -> 0 | C11: =0 -> 0 | D11: =0 -> 0 | E11: =Assumptions!$I$14 -> 12000 | F11: =0 -> 0 | G11: =0 -> 0 | H11: =0 -> 0 | I11: =0 -> 0
A12: Consumables / models / delivery | B12: =Assumptions!$I$96 -> 250 | C12: =Assumptions!$I$95 -> 400 | D12: =Assumptions!$I$92 -> 2000 | E12: =Assumptions!$I$91 -> 6000 | F12: =Assumptions!$I$91 -> 6000 | G12: =Assumptions!$I$93 -> 7500 | H12: =Assumptions!$I$94 -> 1000 | I12: =Assumptions!$I$97 -> 2000
A13: Trainer + assistant cost per batch (standard: salary x months / slots) | B13: =0 -> 0 | C13: =0 -> 0 | D13: =(Assumptions!$I$99+Assumptions!$I$100)/Assumptions!$I$101*D5 -> 28000 | E13: =(Assumptions!$I$99+Assumptions!$I$100)/Assumptions!$I$101*E5 -> 84000 | F13: =(Assumptions!$I$99+Assumptions!$I$100)/Assumptions!$I$101*F5 -> 84000 | G13: =(Assumptions!$I$99+Assumptions!$I$100)/Assumptions!$I$101*G5 -> 70000 | H13: =0 -> 0 | I13: =0 -> 0
A14: Trainer cost per student (batch cost / fill) | B14: =IFERROR(B13/B8,0) -> 0 | C14: =IFERROR(C13/C8,0) -> 0 | D14: =IFERROR(D13/D8,0) -> 2800 | E14: =IFERROR(E13/E8,0) -> 8400 | F14: =IFERROR(F13/F8,0) -> 8400 | G14: =IFERROR(G13/G8,0) -> 7000 | H14: =IFERROR(H13/H8,0) -> 0 | I14: =IFERROR(I13/I8,0) -> 0
A15: Payment gateway + EMI subvention | B15: =B9*Assumptions!$I$76 -> 19.98 | C15: =C9*Assumptions!$I$76 -> 99.98 | D15: =D9*Assumptions!$I$76 -> 798 | E15: =E9*(Assumptions!$I$76+Assumptions!$I$70*Assumptions!$I$71) -> 2250 | F15: =F9*(Assumptions!$I$76+Assumptions!$I$70*Assumptions!$I$71) -> 3000 | G15: =G9*(Assumptions!$I$76+Assumptions!$I$70*Assumptions!$I$71) -> 3000 | H15: =H9*Assumptions!$I$76 -> 200 | I15: =I9*Assumptions!$I$76 -> 199.98
A16: Contribution per seat before CAC | B16: =B10-B11-B12-B14-B15 -> 576.63017 | C16: =C10-C11-C12-C14-C15 -> 3736.4607 | D16: =D10-D11-D12-D14-D15 -> 28215.559 | E16: =E10-E11-E12-E14-E15 -> 22197.458 | F16: =F10-F11-F12-F14-F15 -> 50396.61 | G16: =G10-G11-G12-G14-G15 -> 50296.61 | H16: =H10-H11-H12-H14-H15 -> 7274.5763 | I16: =I10-I11-I12-I14-I15 -> 6273.7488
A17: Contribution margin % | B17: =IFERROR(B16/B10,0) -> 0.6811047 | C17: =IFERROR(C16/C10,0) -> 0.88198112 | D17: =IFERROR(D16/D10,0) -> 0.83444511 | E17: =IFERROR(E16/E10,0) -> 0.43655 | F17: =IFERROR(F16/F10,0) -> 0.74335 | G17: =IFERROR(G16/G10,0) -> 0.741875 | H17: =IFERROR(H16/H10,0) -> 0.8584 | I17: =IFERROR(I16/I10,0) -> 0.7403764
A18: Acquisition cost per seat (career: effective paid CAC x paid share + referral reward share; L4/L1-S5: funnel media per seat) | B18: =Assumptions!$I$35 -> 400 | C18: =Assumptions!$I$118 -> 706 | D18: =Assumptions!$I$115*Assumptions!$I$120*(Assumptions!$I$27+Assumptions!$I$28+Assumptions!$I$31)+Assumptions!$I$198*Assumptions!$I$69 -> 7600 | E18: =Assumptions!$I$115*Assumptions!$I$120*(Assumptions!$I$27+Assumptions!$I$28+Assumptions!$I$31)+Assumptions!$I$198*Assumptions!$I$69 -> 7600 | F18: =Assumptions!$I$115*Assumptions!$I$120*(Assumptions!$I$27+Assumptions!$I$28+Assumptions!$I$31)+Assumptions!$I$198*Assumptions!$I$69 -> 7600 | G18: =Assumptions!$I$115*Assumptions!$I$120*(Assumptions!$I$27+Assumptions!$I$28+Assumptions!$I$31)+Assumptions!$I$198*Assumptions!$I$69 -> 7600 | H18: =Assumptions!$I$117 -> 300 | I18: =0 -> 0
A19: Contribution per seat after CAC | B19: =B16-B18 -> 176.63017 | C19: =C16-C18 -> 3030.4607 | D19: =D16-D18 -> 20615.559 | E19: =E16-E18 -> 14597.458 | F19: =F16-F18 -> 42796.61 | G19: =G16-G18 -> 42696.61 | H19: =H16-H18 -> 6974.5763 | I19: =I16-I18 -> 6273.7488
A20: Occupancy cost per seat (today's space: rent + utilities / seat-months) | B20: =(Assumptions!$I$179+Assumptions!$I$180)/(Assumptions!$I$171*Assumptions!$I$172)*B5 -> 281.25 | C20: =(Assumptions!$I$179+Assumptions!$I$180)/(Assumptions!$I$171*Assumptions!$I$172)*C5 -> 281.25 | D20: =(Assumptions!$I$179+Assumptions!$I$180)/(Assumptions!$I$171*Assumptions!$I$172)*D5 -> 2812.5 | E20: =(Assumptions!$I$179+Assumptions!$I$180)/(Assumptions!$I$171*Assumptions!$I$172)*E5 -> 8437.5 | F20: =(Assumptions!$I$179+Assumptions!$I$180)/(Assumptions!$I$171*Assumptions!$I$172)*F5 -> 8437.5 | G20: =(Assumptions!$I$179+Assumptions!$I$180)/(Assumptions!$I$171*Assumptions!$I$172)*G5 -> 7031.25 | H20: =(Assumptions!$I$179+Assumptions!$I$180)/(Assumptions!$I$171*Assumptions!$I$172)*H5 -> 196.875 | I20: =(Assumptions!$I$179+Assumptions!$I$180)/(Assumptions!$I$171*Assumptions!$I$172)*I5 -> 0
A21: Cohort fixed cost (trainer batch cost + occupancy x batch cap) | B21: =B13+B20*B7 -> 3375 | C21: =C13+C20*C7 -> 3375 | D21: =D13+D20*D7 -> 61750 | E21: =E13+E20*E7 -> 185250 | F21: =F13+F20*F7 -> 185250 | G21: =G13+G20*G7 -> 154375 | H21: =H13+H20*H7 -> 2756.25 | I21: =I13+I20*I7 -> 0
A22: Variable cost per seat (kit + consumables + payment + CAC) | B22: =B11+B12+B15+B18 -> 669.98 | C22: =C11+C12+C15+C18 -> 1205.98 | D22: =D11+D12+D15+D18 -> 10398 | E22: =E11+E12+E15+E18 -> 27850 | F22: =F11+F12+F15+F18 -> 16600 | G22: =G11+G12+G15+G18 -> 18100 | H22: =H11+H12+H15+H18 -> 1500 | I22: =I11+I12+I15+I18 -> 2199.98
A23: Breakeven students per cohort | B23: =IFERROR(B21/(B10-B22),0) -> 19.107721 | C23: =IFERROR(C21/(C10-C22),0) -> 1.1136921 | D23: =IFERROR(D21/(D10-D22),0) -> 2.6371354 | E23: =IFERROR(E21/(E10-E22),0) -> 8.0552382 | F23: =IFERROR(F21/(F10-F22),0) -> 3.6184036 | G23: =IFERROR(G21/(G10-G22),0) -> 3.1063487 | H23: =IFERROR(H21/(H10-H22),0) -> 0.3951853 | I23: =IFERROR(I21/(I10-I22),0) -> 0
A24: Breakeven fill % of batch cap (BM M1) | B24: =IFERROR(B23/B7,0) -> 1.5923101 | C24: =IFERROR(C23/C7,0) -> 0.092807672 | D24: =IFERROR(D23/D7,0) -> 0.21976128 | E24: =IFERROR(E23/E7,0) -> 0.67126985 | F24: =IFERROR(F23/F7,0) -> 0.30153364 | G24: =IFERROR(G23/G7,0) -> 0.25886239 | H24: =IFERROR(H23/H7,0) -> 0.028227521 | I24: =IFERROR(I23/I7,0) -> 0
A25: Cohort contribution at 10 students (after CAC, trainer, occupancy) | B25: =10*(B10-B22)-B21 -> -1608.6983 | C25: =10*(C10-C22)-C21 -> 26929.607 | D25: =10*(D10-D22)-D21 -> 172405.59 | E25: =10*(E10-E22)-E21 -> 44724.576 | F25: =10*(F10-F22)-F21 -> 326716.1 | G25: =10*(G10-G22)-G21 -> 342591.1 | H25: =10*(H10-H22)-H21 -> 66989.513 | I25: =10*(I10-I22)-I21 -> 62737.488
A26: Cohort contribution at 12 students | B26: =12*(B10-B22)-B21 -> -1255.438 | C26: =12*(C10-C22)-C21 -> 32990.528 | D26: =12*(D10-D22)-D21 -> 219236.71 | E26: =12*(E10-E22)-E21 -> 90719.492 | F26: =12*(F10-F22)-F21 -> 429109.32 | G26: =12*(G10-G22)-G21 -> 441984.32 | H26: =12*(H10-H22)-H21 -> 80938.665 | I26: =12*(I10-I22)-I21 -> 75284.986
A27: Cohort contribution at 14 students (cap raised; quality risk) | B27: =14*(B10-B22)-B21 -> -902.17763 | C27: =14*(C10-C22)-C21 -> 39051.449 | D27: =14*(D10-D22)-D21 -> 266067.83 | E27: =14*(E10-E22)-E21 -> 136714.41 | F27: =14*(F10-F22)-F21 -> 531502.54 | G27: =14*(G10-G22)-G21 -> 541377.54 | H27: =14*(H10-H22)-H21 -> 94887.818 | I27: =14*(I10-I22)-I21 -> 87832.483
A28: Batches per year per slot (12 / duration) | B28: =IFERROR(12/B5,0) -> 120 | C28: =IFERROR(12/C5,0) -> 120 | D28: =IFERROR(12/D5,0) -> 12 | E28: =IFERROR(12/E5,0) -> 4 | F28: =IFERROR(12/F5,0) -> 4 | G28: =IFERROR(12/G5,0) -> 4.8 | H28: =IFERROR(12/H5,0) -> 171.42857 | I28: =IFERROR(12/I5,0) -> 0
A30: Today's illustrative baseline (CA-01 x CA-02 mix) - NOT actual revenue; founder data pull (V1) to replace
A31: Students per year (CA-01) | B31: =Assumptions!$I$9 -> 50
A32: Career share (A-ECO-101) | B32: =Assumptions!$I$12 -> 0.6
A33: Career students | B33: =B31*B32 -> 30
A34: Short-course students | B34: =B31-B33 -> 20
A35: Illustrative revenue incl. GST (career x CA-02 + short x A-ECO-102) | B35: =B33*Assumptions!$I$10+B34*Assumptions!$I$13 -> 1960000
A36: Illustrative revenue ex-GST | B36: =B35/(1+Assumptions!$I$15*Assumptions!$I$16) -> 1661016.9
A37: Illustrative contribution (kit + consumables + payment) | B37: =B36-B33*(Assumptions!$I$14+Assumptions!$I$91)-B34*Assumptions!$I$94-B35*Assumptions!$I$76 -> 1061816.9
A38: Less academy occupancy share x 12 | B38: =-12*(Assumptions!$I$179+Assumptions!$I$180) -> -540000
A39: Illustrative academy surplus before founder's time (NOT actual profit) | B39: =B37+B38 -> 521816.95
A41: BM's '~₹0.3 crore today' is this same CA-01 x CA-02 arithmetic (50 x ₹60k), an estimate, not PNA's reported revenue.

Sheet 3yr_Scenarios
A1: Directional 3-year scenarios (₹ lakh, ex-GST) - Year 1 = 12-month outlook; Years 2-3 driver-based
A2: Layers: flagship (tricity + regional offline), destination/hybrid, CPD (masterclasses + Pro Circle), online, adjacents, and a partner-hosted satellite only if gate G3a is met (Aggressive Y3).
A4: Line (₹ lakh unless stated) | B4: Conservative Y1 | C4: Conservative Y2 | D4: Conservative Y3 | E4: Base Y1 | F4: Base Y2 | G4: Base Y3 | H4: Aggressive Y1 | I4: Aggressive Y2 | J4: Aggressive Y3 | K4: Basis
A5: Volumes
A6: Career enrolments, flagship (L2 + L3 new students) | B6: =Outlook_Conservative!O31 -> 30.376401 | C6: =2*SUM(Outlook_Conservative!I31:N31)/(SUM(Outlook_Conservative!I9:N9)/6)*(1+INDEX(Assumptions!$C$199:$E$199,1)) -> 38.989295 | D6: =C6*(1+INDEX(Assumptions!$C$200:$E$200,1)) -> 40.93876 | E6: =Outlook_Base!O31 -> 89.450184 | F6: =2*SUM(Outlook_Base!I31:N31)/(SUM(Outlook_Base!I9:N9)/6)*(1+INDEX(Assumptions!$C$199:$E$199,2)) -> 121.91883 | G6: =F6*(1+INDEX(Assumptions!$C$200:$E$200,2)) -> 134.11072 | H6: =Outlook_Aggressive!O31 -> 123.22992 | I6: =2*SUM(Outlook_Aggressive!I31:N31)/(SUM(Outlook_Aggressive!I9:N9)/6)*(1+INDEX(Assumptions!$C$199:$E$199,3)) -> 161.42344 | J6: =I6*(1+INDEX(Assumptions!$C$200:$E$200,3)) -> 180.79425 | K6: Y2 = 2 x Y1 H2 run-rate, de-seasonalised (May-Oct index), x (1+A-ECO-201); Y3 x (1+A-ECO-202); capacity-capped below
A7: L3 share of career enrolments | B7: =INDEX(Assumptions!$C$26:$E$26,1) -> 0.5 | C7: =INDEX(Assumptions!$C$26:$E$26,1) -> 0.5 | D7: =INDEX(Assumptions!$C$26:$E$26,1) -> 0.5 | E7: =INDEX(Assumptions!$C$26:$E$26,2) -> 0.6 | F7: =INDEX(Assumptions!$C$26:$E$26,2) -> 0.6 | G7: =INDEX(Assumptions!$C$26:$E$26,2) -> 0.6 | H7: =INDEX(Assumptions!$C$26:$E$26,3) -> 0.7 | I7: =INDEX(Assumptions!$C$26:$E$26,3) -> 0.7 | J7: =INDEX(Assumptions!$C$26:$E$26,3) -> 0.7
A8: Out-of-town share of career enrolments | B8: =INDEX(Assumptions!$C$74:$E$74,1) -> 0.15 | C8: =INDEX(Assumptions!$C$201:$E$201,1) -> 0.15 | D8: =INDEX(Assumptions!$C$202:$E$202,1) -> 0.18 | E8: =INDEX(Assumptions!$C$74:$E$74,2) -> 0.25 | F8: =INDEX(Assumptions!$C$201:$E$201,2) -> 0.25 | G8: =INDEX(Assumptions!$C$202:$E$202,2) -> 0.3 | H8: =INDEX(Assumptions!$C$74:$E$74,3) -> 0.35 | I8: =INDEX(Assumptions!$C$201:$E$201,3) -> 0.35 | J8: =INDEX(Assumptions!$C$202:$E$202,3) -> 0.4
A9: Incremental destination/hybrid regional students (G2 engine) | B9: =Outlook_Conservative!O28*0 -> 0 | C9: =INDEX(Assumptions!$C$203:$E$203,1) -> 0 | D9: =INDEX(Assumptions!$C$204:$E$204,1) -> 8 | E9: =Outlook_Base!O28*0 -> 0 | F9: =INDEX(Assumptions!$C$203:$E$203,2) -> 15 | G9: =INDEX(Assumptions!$C$204:$E$204,2) -> 35 | H9: =Outlook_Aggressive!O28*0 -> 0 | I9: =INDEX(Assumptions!$C$203:$E$203,3) -> 30 | J9: =INDEX(Assumptions!$C$204:$E$204,3) -> 60 | K9: Y1 destination-format students are inside career enrolments
A10: L2 -> L3 upgrades | B10: =Outlook_Conservative!O30 -> 3.4102516 | C10: =C6*(1-INDEX(Assumptions!$C$26:$E$26,1))*INDEX(Assumptions!$C$89:$E$89,1) -> 4.8736619 | D10: =D6*(1-INDEX(Assumptions!$C$26:$E$26,1))*INDEX(Assumptions!$C$89:$E$89,1) -> 5.117345 | E10: =Outlook_Base!O30 -> 8.6225776 | F10: =F6*(1-INDEX(Assumptions!$C$26:$E$26,2))*INDEX(Assumptions!$C$89:$E$89,2) -> 14.63026 | G10: =G6*(1-INDEX(Assumptions!$C$26:$E$26,2))*INDEX(Assumptions!$C$89:$E$89,2) -> 16.093286 | H10: =Outlook_Aggressive!O30 -> 11.079757 | I10: =I6*(1-INDEX(Assumptions!$C$26:$E$26,3))*INDEX(Assumptions!$C$89:$E$89,3) -> 19.370813 | J10: =J6*(1-INDEX(Assumptions!$C$26:$E$26,3))*INDEX(Assumptions!$C$89:$E$89,3) -> 21.69531
A11: Stations | B11: =Outlook_Conservative!N20 -> 8 | C11: =INDEX(Assumptions!$C$231:$E$231,1) -> 8 | D11: =INDEX(Assumptions!$C$232:$E$232,1) -> 10 | E11: =Outlook_Base!N20 -> 12 | F11: =INDEX(Assumptions!$C$231:$E$231,2) -> 12 | G11: =INDEX(Assumptions!$C$232:$E$232,2) -> 14 | H11: =Outlook_Aggressive!N20 -> 16 | I11: =INDEX(Assumptions!$C$231:$E$231,3) -> 16 | J11: =INDEX(Assumptions!$C$232:$E$232,3) -> 18
A12: Batch slots per day | B12: =Outlook_Conservative!N21 -> 2 | C12: =INDEX(Assumptions!$C$229:$E$229,1) -> 2.5 | D12: =INDEX(Assumptions!$C$230:$E$230,1) -> 3 | E12: =Outlook_Base!N21 -> 2.5 | F12: =INDEX(Assumptions!$C$229:$E$229,2) -> 3 | G12: =INDEX(Assumptions!$C$230:$E$230,2) -> 3 | H12: =Outlook_Aggressive!N21 -> 2.5 | I12: =INDEX(Assumptions!$C$229:$E$229,3) -> 3 | J12: =INDEX(Assumptions!$C$230:$E$230,3) -> 3
A13: Usable seat-months per year | B13: =B11*B12*12*INDEX(Assumptions!$C$178:$E$178,1) -> 172.8 | C13: =C11*C12*12*INDEX(Assumptions!$C$178:$E$178,1) -> 216 | D13: =D11*D12*12*INDEX(Assumptions!$C$178:$E$178,1) -> 324 | E13: =E11*E12*12*INDEX(Assumptions!$C$178:$E$178,2) -> 324 | F13: =F11*F12*12*INDEX(Assumptions!$C$178:$E$178,2) -> 388.8 | G13: =G11*G12*12*INDEX(Assumptions!$C$178:$E$178,2) -> 453.6 | H13: =H11*H12*12*INDEX(Assumptions!$C$178:$E$178,3) -> 432 | I13: =I11*I12*12*INDEX(Assumptions!$C$178:$E$178,3) -> 518.4 | J13: =J11*J12*12*INDEX(Assumptions!$C$178:$E$178,3) -> 583.2
A14: Seat-months needed (L3 x3, L2 x1, upgrades x3, destination x2.5) | B14: =Outlook_Conservative!O33*12 -> 65.026859 | C14: =C6*(C7*INDEX(Assumptions!$C$103:$E$103,1)+(1-C7))+C10*INDEX(Assumptions!$C$103:$E$103,1)+C9*INDEX(Assumptions!$C$104:$E$104,1) -> 92.599576 | D14: =D6*(D7*INDEX(Assumptions!$C$103:$E$103,1)+(1-D7))+D10*INDEX(Assumptions!$C$103:$E$103,1)+D9*INDEX(Assumptions!$C$104:$E$104,1) -> 117.22955 | E14: =Outlook_Base!O33*12 -> 200.9605 | F14: =F6*(F7*INDEX(Assumptions!$C$103:$E$103,2)+(1-F7))+F10*INDEX(Assumptions!$C$103:$E$103,2)+F9*INDEX(Assumptions!$C$104:$E$104,2) -> 349.61221 | G14: =G6*(G7*INDEX(Assumptions!$C$103:$E$103,2)+(1-G7))+G10*INDEX(Assumptions!$C$103:$E$103,2)+G9*INDEX(Assumptions!$C$104:$E$104,2) -> 430.82343 | H14: =Outlook_Aggressive!O33*12 -> 294.49261 | I14: =I6*(I7*INDEX(Assumptions!$C$103:$E$103,3)+(1-I7))+I10*INDEX(Assumptions!$C$103:$E$103,3)+I9*INDEX(Assumptions!$C$104:$E$104,3) -> 520.5287 | J14: =J6*(J7*INDEX(Assumptions!$C$103:$E$103,3)+(1-J7))+J10*INDEX(Assumptions!$C$103:$E$103,3)+J9*INDEX(Assumptions!$C$104:$E$104,3) -> 648.99214
A15: Capacity factor (share of planned volume that fits) | B15: =1 -> 1 | C15: =MIN(1,C13/C14) -> 1 | D15: =MIN(1,D13/D14) -> 1 | E15: =1 -> 1 | F15: =MIN(1,F13/F14) -> 1 | G15: =MIN(1,G13/G14) -> 1 | H15: =1 -> 1 | I15: =MIN(1,I13/I14) -> 0.99591051 | J15: =MIN(1,J13/J14) -> 0.89862413
A16: Seat utilisation | B16: =Outlook_Conservative!N34 -> 0.4834982 | C16: =MIN(1,C14/(C11*C12*12)) -> 0.38583156 | D16: =MIN(1,D14/(D11*D12*12)) -> 0.32563765 | E16: =Outlook_Base!N34 -> 0.84101366 | F16: =MIN(1,F14/(F11*F12*12)) -> 0.80928753 | G16: =MIN(1,G14/(G11*G12*12)) -> 0.8548084 | H16: =Outlook_Aggressive!N34 -> 0.9 | I16: =MIN(1,I14/(I11*I12*12)) -> 0.90369565 | J16: =MIN(1,J14/(J11*J12*12)) -> 1
A17: Career enrolments delivered (after capacity) | B17: =B6*B15 -> 30.376401 | C17: =C6*C15 -> 38.989295 | D17: =D6*D15 -> 40.93876 | E17: =E6*E15 -> 89.450184 | F17: =F6*F15 -> 121.91883 | G17: =G6*G15 -> 134.11072 | H17: =H6*H15 -> 123.22992 | I17: =I6*I15 -> 160.7633 | J17: =J6*J15 -> 162.46608
A18: Destination/hybrid incremental students delivered | B18: =B9*B15 -> 0 | C18: =C9*C15 -> 0 | D18: =D9*D15 -> 8 | E18: =E9*E15 -> 0 | F18: =F9*F15 -> 15 | G18: =G9*G15 -> 35 | H18: =H9*H15 -> 0 | I18: =I9*I15 -> 29.877315 | J18: =J9*J15 -> 53.917448
A19: Masterclass seats | B19: =Outlook_Conservative!O37 -> 67.5 | C19: =INDEX(Assumptions!$C$205:$E$205,1) -> 110 | D19: =INDEX(Assumptions!$C$206:$E$206,1) -> 130 | E19: =Outlook_Base!O37 -> 153 | F19: =INDEX(Assumptions!$C$205:$E$205,2) -> 220 | G19: =INDEX(Assumptions!$C$206:$E$206,2) -> 280 | H19: =Outlook_Aggressive!O37 -> 202.5 | I19: =INDEX(Assumptions!$C$205:$E$205,3) -> 330 | J19: =INDEX(Assumptions!$C$206:$E$206,3) -> 420
A20: Self-makeup seats | B20: =Outlook_Conservative!O38 -> 106.66667 | C20: =INDEX(Assumptions!$C$207:$E$207,1) -> 110 | D20: =INDEX(Assumptions!$C$208:$E$208,1) -> 120 | E20: =Outlook_Base!O38 -> 160 | F20: =INDEX(Assumptions!$C$207:$E$207,2) -> 170 | G20: =INDEX(Assumptions!$C$208:$E$208,2) -> 190 | H20: =Outlook_Aggressive!O38 -> 234.66667 | I20: =INDEX(Assumptions!$C$207:$E$207,3) -> 250 | J20: =INDEX(Assumptions!$C$208:$E$208,3) -> 280
A21: Pop-up events | B21: =Outlook_Conservative!O40 -> 0 | C21: =INDEX(Assumptions!$C$209:$E$209,1) -> 0 | D21: =INDEX(Assumptions!$C$210:$E$210,1) -> 2 | E21: =Outlook_Base!O40 -> 2 | F21: =INDEX(Assumptions!$C$209:$E$209,2) -> 6 | G21: =INDEX(Assumptions!$C$210:$E$210,2) -> 12 | H21: =Outlook_Aggressive!O40 -> 7 | I21: =INDEX(Assumptions!$C$209:$E$209,3) -> 12 | J21: =INDEX(Assumptions!$C$210:$E$210,3) -> 16
A22: Online short-course buyers | B22: =0 -> 0 | C22: =INDEX(Assumptions!$C$211:$E$211,1) -> 0 | D22: =INDEX(Assumptions!$C$212:$E$212,1) -> 150 | E22: =0 -> 0 | F22: =INDEX(Assumptions!$C$211:$E$211,2) -> 300 | G22: =INDEX(Assumptions!$C$212:$E$212,2) -> 900 | H22: =0 -> 0 | I22: =INDEX(Assumptions!$C$211:$E$211,3) -> 800 | J22: =INDEX(Assumptions!$C$212:$E$212,3) -> 2000
A23: Pro Circle paid members (graduates after free year + S3 buyers) | B23: =Outlook_Conservative!O42 -> 2.3625 | C23: =B17*B7*INDEX(Assumptions!$C$67:$E$67,1)*INDEX(Assumptions!$C$72:$E$72,1)+C19*0.7*INDEX(Assumptions!$C$73:$E$73,1) -> 6.4319941 | D23: =C17*C7*INDEX(Assumptions!$C$67:$E$67,1)*INDEX(Assumptions!$C$72:$E$72,1)+D19*0.7*INDEX(Assumptions!$C$73:$E$73,1) -> 7.8640901 | E23: =Outlook_Base!O42 -> 10.71 | F23: =E17*E7*INDEX(Assumptions!$C$67:$E$67,2)*INDEX(Assumptions!$C$72:$E$72,2)+F19*0.7*INDEX(Assumptions!$C$73:$E$73,2) -> 29.89093 | G23: =F17*F7*INDEX(Assumptions!$C$67:$E$67,2)*INDEX(Assumptions!$C$72:$E$72,2)+G19*0.7*INDEX(Assumptions!$C$73:$E$73,2) -> 39.350851 | H23: =Outlook_Aggressive!O42 -> 28.35 | I23: =H17*H7*INDEX(Assumptions!$C$67:$E$67,3)*INDEX(Assumptions!$C$72:$E$72,3)+I19*0.7*INDEX(Assumptions!$C$73:$E$73,3) -> 83.076554 | J23: =I17*I7*INDEX(Assumptions!$C$67:$E$67,3)*INDEX(Assumptions!$C$72:$E$72,3)+J19*0.7*INDEX(Assumptions!$C$73:$E$73,3) -> 106.90842
A24: Partner-hosted satellite students (only if G3a met) | B24: =0 -> 0 | C24: =0 -> 0 | D24: =INDEX(Assumptions!$C$222:$E$222,1) -> 0 | E24: =0 -> 0 | F24: =0 -> 0 | G24: =INDEX(Assumptions!$C$222:$E$222,2) -> 0 | H24: =0 -> 0 | I24: =0 -> 0 | J24: =INDEX(Assumptions!$C$222:$E$222,3) -> 30
A25: Founder share of contact hours | B25: =Outlook_Conservative!N11 -> 0.4 | C25: =INDEX(Assumptions!$C$159:$E$159,1) -> 0.2 | D25: =INDEX(Assumptions!$C$160:$E$160,1) -> 0.12 | E25: =Outlook_Base!N11 -> 0.3 | F25: =INDEX(Assumptions!$C$159:$E$159,2) -> 0.15 | G25: =INDEX(Assumptions!$C$160:$E$160,2) -> 0.1 | H25: =Outlook_Aggressive!N11 -> 0.25 | I25: =INDEX(Assumptions!$C$159:$E$159,3) -> 0.12 | J25: =INDEX(Assumptions!$C$160:$E$160,3) -> 0.08
A26: Prices (incl. GST)
A27: L3 / destination realised fee | B27: =Outlook_Conservative!N44 -> 65000 | C27: =INDEX(Assumptions!$C$20:$E$20,1) -> 65000 | D27: =C27*(1+INDEX(Assumptions!$C$226:$E$226,1)) -> 68250 | E27: =Outlook_Base!N44 -> 80000 | F27: =INDEX(Assumptions!$C$20:$E$20,2) -> 80000 | G27: =F27*(1+INDEX(Assumptions!$C$226:$E$226,2)) -> 84800 | H27: =Outlook_Aggressive!N44 -> 100000 | I27: =INDEX(Assumptions!$C$20:$E$20,3) -> 100000 | J27: =I27*(1+INDEX(Assumptions!$C$226:$E$226,3)) -> 108000
A28: L2 Foundation fee | B28: =INDEX(Assumptions!$C$18:$E$18,1) -> 30000 | C28: =INDEX(Assumptions!$C$18:$E$18,1) -> 30000 | D28: =INDEX(Assumptions!$C$18:$E$18,1)*(1+INDEX(Assumptions!$C$226:$E$226,1)) -> 31500 | E28: =INDEX(Assumptions!$C$18:$E$18,2) -> 39900 | F28: =INDEX(Assumptions!$C$18:$E$18,2) -> 39900 | G28: =INDEX(Assumptions!$C$18:$E$18,2)*(1+INDEX(Assumptions!$C$226:$E$226,2)) -> 42294 | H28: =INDEX(Assumptions!$C$18:$E$18,3) -> 45000 | I28: =INDEX(Assumptions!$C$18:$E$18,3) -> 45000 | J28: =INDEX(Assumptions!$C$18:$E$18,3)*(1+INDEX(Assumptions!$C$226:$E$226,3)) -> 48600
A29: Revenue (₹ lakh, ex-GST)
A30: Flagship career revenue - tricity-origin | B30: =(Outlook_Conservative!O58)*(1-INDEX(Assumptions!$C$74:$E$74,1))/100000 -> 9.0186151 | C30: =(C17*(C7*C27+(1-C7)*C28)+C10*C15*(C27-C28))/(1+INDEX(Assumptions!$C$15:$E$15,1)*INDEX(Assumptions!$C$16:$E$16,1))*(1-C8)/100000 -> 14.569358 | D30: =(D17*(D7*D27+(1-D7)*D28)+D10*D15*(D27-D28))/(1+INDEX(Assumptions!$C$15:$E$15,1)*INDEX(Assumptions!$C$16:$E$16,1))*(1-D8)/100000 -> 15.495798 | E30: =(Outlook_Base!O58)*(1-INDEX(Assumptions!$C$74:$E$74,2))/100000 -> 36.457657 | F30: =(F17*(F7*F27+(1-F7)*F28)+F10*F15*(F27-F28))/(1+INDEX(Assumptions!$C$15:$E$15,2)*INDEX(Assumptions!$C$16:$E$16,2))*(1-F8)/100000 -> 53.291962 | G30: =(G17*(G7*G27+(1-G7)*G28)+G10*G15*(G27-G28))/(1+INDEX(Assumptions!$C$15:$E$15,2)*INDEX(Assumptions!$C$16:$E$16,2))*(1-G8)/100000 -> 57.995866 | H30: =(Outlook_Aggressive!O58)*(1-INDEX(Assumptions!$C$74:$E$74,3))/100000 -> 58.139093 | I30: =(I17*(I7*I27+(1-I7)*I28)+I10*I15*(I27-I28))/(1+INDEX(Assumptions!$C$15:$E$15,3)*INDEX(Assumptions!$C$16:$E$16,3))*(1-I8)/100000 -> 79.789006 | J30: =(J17*(J7*J27+(1-J7)*J28)+J10*J15*(J27-J28))/(1+INDEX(Assumptions!$C$15:$E$15,3)*INDEX(Assumptions!$C$16:$E$16,3))*(1-J8)/100000 -> 80.386013 | K30: career revenue x (1 - out-of-town share)
A31: Flagship career revenue - out-of-town (regional destination, offline) | B31: =(Outlook_Conservative!O58)*INDEX(Assumptions!$C$74:$E$74,1)/100000 -> 1.5915203 | C31: =(C17*(C7*C27+(1-C7)*C28)+C10*C15*(C27-C28))/(1+INDEX(Assumptions!$C$15:$E$15,1)*INDEX(Assumptions!$C$16:$E$16,1))*C8/100000 -> 2.5710631 | D31: =(D17*(D7*D27+(1-D7)*D28)+D10*D15*(D27-D28))/(1+INDEX(Assumptions!$C$15:$E$15,1)*INDEX(Assumptions!$C$16:$E$16,1))*D8/100000 -> 3.4015165 | E31: =(Outlook_Base!O58)*INDEX(Assumptions!$C$74:$E$74,2)/100000 -> 12.152552 | F31: =(F17*(F7*F27+(1-F7)*F28)+F10*F15*(F27-F28))/(1+INDEX(Assumptions!$C$15:$E$15,2)*INDEX(Assumptions!$C$16:$E$16,2))*F8/100000 -> 17.763987 | G31: =(G17*(G7*G27+(1-G7)*G28)+G10*G15*(G27-G28))/(1+INDEX(Assumptions!$C$15:$E$15,2)*INDEX(Assumptions!$C$16:$E$16,2))*G8/100000 -> 24.855371 | H31: =(Outlook_Aggressive!O58)*INDEX(Assumptions!$C$74:$E$74,3)/100000 -> 31.305665 | I31: =(I17*(I7*I27+(1-I7)*I28)+I10*I15*(I27-I28))/(1+INDEX(Assumptions!$C$15:$E$15,3)*INDEX(Assumptions!$C$16:$E$16,3))*I8/100000 -> 42.963311 | J31: =(J17*(J7*J27+(1-J7)*J28)+J10*J15*(J27-J28))/(1+INDEX(Assumptions!$C$15:$E$15,3)*INDEX(Assumptions!$C$16:$E$16,3))*J8/100000 -> 53.590676
A32: Destination/hybrid incremental regional students | B32: =0 -> 0 | C32: =C18*C27/(1+INDEX(Assumptions!$C$15:$E$15,1)*INDEX(Assumptions!$C$16:$E$16,1))/100000 -> 0 | D32: =D18*D27/(1+INDEX(Assumptions!$C$15:$E$15,1)*INDEX(Assumptions!$C$16:$E$16,1))/100000 -> 4.6271186 | E32: =0 -> 0 | F32: =F18*F27/(1+INDEX(Assumptions!$C$15:$E$15,2)*INDEX(Assumptions!$C$16:$E$16,2))/100000 -> 10.169492 | G32: =G18*G27/(1+INDEX(Assumptions!$C$15:$E$15,2)*INDEX(Assumptions!$C$16:$E$16,2))/100000 -> 25.152542 | H32: =0 -> 0 | I32: =I18*I27/(1+INDEX(Assumptions!$C$15:$E$15,3)*INDEX(Assumptions!$C$16:$E$16,3))/100000 -> 25.319759 | J32: =J18*J27/(1+INDEX(Assumptions!$C$15:$E$15,3)*INDEX(Assumptions!$C$16:$E$16,3))/100000 -> 49.348173
A33: Entry products: taster, self-makeup, pop-up tickets | B33: =(Outlook_Conservative!O51+Outlook_Conservative!O53+Outlook_Conservative!O54)/100000 -> 3.1147636 | C33: =(C20*INDEX(Assumptions!$C$22:$E$22,1)+C21*INDEX(Assumptions!$C$82:$E$82,1)*INDEX(Assumptions!$C$83:$E$83,1)+C17*INDEX(Assumptions!$C$31:$E$31,1)/(INDEX(Assumptions!$C$56:$E$56,1)*INDEX(Assumptions!$C$57:$E$57,1)*INDEX(Assumptions!$C$58:$E$58,1))*(1-INDEX(Assumptions!$C$56:$E$56,1)*INDEX(Assumptions!$C$57:$E$57,1)*INDEX(Assumptions!$C$58:$E$58,1))*INDEX(Assumptions!$C$17:$E$17,1))/(1+INDEX(Assumptions!$C$15:$E$15,1)*INDEX(Assumptions!$C$16:$E$16,1))/100000 -> 3.313747 | D33: =(D20*INDEX(Assumptions!$C$22:$E$22,1)+D21*INDEX(Assumptions!$C$82:$E$82,1)*INDEX(Assumptions!$C$83:$E$83,1)+D17*INDEX(Assumptions!$C$31:$E$31,1)/(INDEX(Assumptions!$C$56:$E$56,1)*INDEX(Assumptions!$C$57:$E$57,1)*INDEX(Assumptions!$C$58:$E$58,1))*(1-INDEX(Assumptions!$C$56:$E$56,1)*INDEX(Assumptions!$C$57:$E$57,1)*INDEX(Assumptions!$C$58:$E$58,1))*INDEX(Assumptions!$C$17:$E$17,1))/(1+INDEX(Assumptions!$C$15:$E$15,1)*INDEX(Assumptions!$C$16:$E$16,1))/100000 -> 4.0171462 | E33: =(Outlook_Base!O51+Outlook_Base!O53+Outlook_Base!O54)/100000 -> 8.2846181 | F33: =(F20*INDEX(Assumptions!$C$22:$E$22,2)+F21*INDEX(Assumptions!$C$82:$E$82,2)*INDEX(Assumptions!$C$83:$E$83,2)+F17*INDEX(Assumptions!$C$31:$E$31,2)/(INDEX(Assumptions!$C$56:$E$56,2)*INDEX(Assumptions!$C$57:$E$57,2)*INDEX(Assumptions!$C$58:$E$58,2))*(1-INDEX(Assumptions!$C$56:$E$56,2)*INDEX(Assumptions!$C$57:$E$57,2)*INDEX(Assumptions!$C$58:$E$58,2))*INDEX(Assumptions!$C$17:$E$17,2))/(1+INDEX(Assumptions!$C$15:$E$15,2)*INDEX(Assumptions!$C$16:$E$16,2))/100000 -> 10.506054 | G33: =(G20*INDEX(Assumptions!$C$22:$E$22,2)+G21*INDEX(Assumptions!$C$82:$E$82,2)*INDEX(Assumptions!$C$83:$E$83,2)+G17*INDEX(Assumptions!$C$31:$E$31,2)/(INDEX(Assumptions!$C$56:$E$56,2)*INDEX(Assumptions!$C$57:$E$57,2)*INDEX(Assumptions!$C$58:$E$58,2))*(1-INDEX(Assumptions!$C$56:$E$56,2)*INDEX(Assumptions!$C$57:$E$57,2)*INDEX(Assumptions!$C$58:$E$58,2))*INDEX(Assumptions!$C$17:$E$17,2))/(1+INDEX(Assumptions!$C$15:$E$15,2)*INDEX(Assumptions!$C$16:$E$16,2))/100000 -> 13.878898 | H33: =(Outlook_Aggressive!O51+Outlook_Aggressive!O53+Outlook_Aggressive!O54)/100000 -> 17.048573 | I33: =(I20*INDEX(Assumptions!$C$22:$E$22,3)+I21*INDEX(Assumptions!$C$82:$E$82,3)*INDEX(Assumptions!$C$83:$E$83,3)+I17*INDEX(Assumptions!$C$31:$E$31,3)/(INDEX(Assumptions!$C$56:$E$56,3)*INDEX(Assumptions!$C$57:$E$57,3)*INDEX(Assumptions!$C$58:$E$58,3))*(1-INDEX(Assumptions!$C$56:$E$56,3)*INDEX(Assumptions!$C$57:$E$57,3)*INDEX(Assumptions!$C$58:$E$58,3))*INDEX(Assumptions!$C$17:$E$17,3))/(1+INDEX(Assumptions!$C$15:$E$15,3)*INDEX(Assumptions!$C$16:$E$16,3))/100000 -> 20.488842 | J33: =(J20*INDEX(Assumptions!$C$22:$E$22,3)+J21*INDEX(Assumptions!$C$82:$E$82,3)*INDEX(Assumptions!$C$83:$E$83,3)+J17*INDEX(Assumptions!$C$31:$E$31,3)/(INDEX(Assumptions!$C$56:$E$56,3)*INDEX(Assumptions!$C$57:$E$57,3)*INDEX(Assumptions!$C$58:$E$58,3))*(1-INDEX(Assumptions!$C$56:$E$56,3)*INDEX(Assumptions!$C$57:$E$57,3)*INDEX(Assumptions!$C$58:$E$58,3))*INDEX(Assumptions!$C$17:$E$17,3))/(1+INDEX(Assumptions!$C$15:$E$15,3)*INDEX(Assumptions!$C$16:$E$16,3))/100000 -> 24.180494
A34: Working-artist CPD: L4 masterclasses + L5 Pro Circle | B34: =(Outlook_Conservative!O52+Outlook_Conservative!O55)/100000 -> 2.9602554 | C34: =(C19*INDEX(Assumptions!$C$21:$E$21,1)+C23*INDEX(Assumptions!$C$23:$E$23,1))/(1+INDEX(Assumptions!$C$15:$E$15,1)*INDEX(Assumptions!$C$16:$E$16,1))/100000 -> 4.9335046 | D34: =(D19*INDEX(Assumptions!$C$21:$E$21,1)+D23*INDEX(Assumptions!$C$23:$E$23,1))/(1+INDEX(Assumptions!$C$15:$E$15,1)*INDEX(Assumptions!$C$16:$E$16,1))/100000 -> 5.8416321 | E34: =(Outlook_Base!O52+Outlook_Base!O55)/100000 -> 13.873638 | F34: =(F19*INDEX(Assumptions!$C$21:$E$21,2)+F23*INDEX(Assumptions!$C$23:$E$23,2))/(1+INDEX(Assumptions!$C$15:$E$15,2)*INDEX(Assumptions!$C$16:$E$16,2))/100000 -> 21.176944 | G34: =(G19*INDEX(Assumptions!$C$21:$E$21,2)+G23*INDEX(Assumptions!$C$23:$E$23,2))/(1+INDEX(Assumptions!$C$15:$E$15,2)*INDEX(Assumptions!$C$16:$E$16,2))/100000 -> 27.063298 | H34: =(Outlook_Aggressive!O52+Outlook_Aggressive!O55)/100000 -> 27.028361 | I34: =(I19*INDEX(Assumptions!$C$21:$E$21,3)+I23*INDEX(Assumptions!$C$23:$E$23,3))/(1+INDEX(Assumptions!$C$15:$E$15,3)*INDEX(Assumptions!$C$16:$E$16,3))/100000 -> 47.952321 | J34: =(J19*INDEX(Assumptions!$C$21:$E$21,3)+J23*INDEX(Assumptions!$C$23:$E$23,3))/(1+INDEX(Assumptions!$C$15:$E$15,3)*INDEX(Assumptions!$C$16:$E$16,3))/100000 -> 61.154647
A35: Online short courses | B35: =0 -> 0 | C35: =C22*INDEX(Assumptions!$C$213:$E$213,1)/(1+INDEX(Assumptions!$C$15:$E$15,1)*INDEX(Assumptions!$C$16:$E$16,1))/100000 -> 0 | D35: =D22*INDEX(Assumptions!$C$213:$E$213,1)/(1+INDEX(Assumptions!$C$15:$E$15,1)*INDEX(Assumptions!$C$16:$E$16,1))/100000 -> 1.2699153 | E35: =0 -> 0 | F35: =F22*INDEX(Assumptions!$C$213:$E$213,2)/(1+INDEX(Assumptions!$C$15:$E$15,2)*INDEX(Assumptions!$C$16:$E$16,2))/100000 -> 3.8110169 | G35: =G22*INDEX(Assumptions!$C$213:$E$213,2)/(1+INDEX(Assumptions!$C$15:$E$15,2)*INDEX(Assumptions!$C$16:$E$16,2))/100000 -> 11.433051 | H35: =0 -> 0 | I35: =I22*INDEX(Assumptions!$C$213:$E$213,3)/(1+INDEX(Assumptions!$C$15:$E$15,3)*INDEX(Assumptions!$C$16:$E$16,3))/100000 -> 13.552542 | J35: =J22*INDEX(Assumptions!$C$213:$E$213,3)/(1+INDEX(Assumptions!$C$15:$E$15,3)*INDEX(Assumptions!$C$16:$E$16,3))/100000 -> 33.881356
A36: Adjacents: kit margin, alumni booking desk, brand partnerships | B36: =Outlook_Conservative!O56/100000 -> 0.029241971 | C36: =(C17*C7*INDEX(Assumptions!$C$243:$E$243,1)+INDEX(Assumptions!$C$217:$E$217,1)*INDEX(Assumptions!$C$219:$E$219,1)/(1+INDEX(Assumptions!$C$15:$E$15,1)*INDEX(Assumptions!$C$16:$E$16,1))+INDEX(Assumptions!$C$220:$E$220,1))/100000 -> 1.2440865 | D36: =(D17*D7*INDEX(Assumptions!$C$243:$E$243,1)+INDEX(Assumptions!$C$218:$E$218,1)*INDEX(Assumptions!$C$219:$E$219,1)/(1+INDEX(Assumptions!$C$15:$E$15,1)*INDEX(Assumptions!$C$16:$E$16,1))+INDEX(Assumptions!$C$221:$E$221,1))/100000 -> 2.0041722 | E36: =Outlook_Base!O56/100000 -> 0.37506667 | F36: =(F17*F7*INDEX(Assumptions!$C$243:$E$243,2)+INDEX(Assumptions!$C$217:$E$217,2)*INDEX(Assumptions!$C$219:$E$219,2)/(1+INDEX(Assumptions!$C$15:$E$15,2)*INDEX(Assumptions!$C$16:$E$16,2))+INDEX(Assumptions!$C$220:$E$220,2))/100000 -> 3.2954728 | G36: =(G17*G7*INDEX(Assumptions!$C$243:$E$243,2)+INDEX(Assumptions!$C$218:$E$218,2)*INDEX(Assumptions!$C$219:$E$219,2)/(1+INDEX(Assumptions!$C$15:$E$15,2)*INDEX(Assumptions!$C$16:$E$16,2))+INDEX(Assumptions!$C$221:$E$221,2))/100000 -> 6.5521387 | H36: =Outlook_Aggressive!O56/100000 -> 1.03259 | I36: =(I17*I7*INDEX(Assumptions!$C$243:$E$243,3)+INDEX(Assumptions!$C$217:$E$217,3)*INDEX(Assumptions!$C$219:$E$219,3)/(1+INDEX(Assumptions!$C$15:$E$15,3)*INDEX(Assumptions!$C$16:$E$16,3))+INDEX(Assumptions!$C$220:$E$220,3))/100000 -> 5.5924295 | J36: =(J17*J7*INDEX(Assumptions!$C$243:$E$243,3)+INDEX(Assumptions!$C$218:$E$218,3)*INDEX(Assumptions!$C$219:$E$219,3)/(1+INDEX(Assumptions!$C$15:$E$15,3)*INDEX(Assumptions!$C$16:$E$16,3))+INDEX(Assumptions!$C$221:$E$221,3))/100000 -> 10.13454
A37: Partner-hosted satellite (PNA share after host revenue share) | B37: =0 -> 0 | C37: =0 -> 0 | D37: =D24*D27/(1+INDEX(Assumptions!$C$15:$E$15,1)*INDEX(Assumptions!$C$16:$E$16,1))*(1-INDEX(Assumptions!$C$223:$E$223,1))/100000 -> 0 | E37: =0 -> 0 | F37: =0 -> 0 | G37: =G24*G27/(1+INDEX(Assumptions!$C$15:$E$15,2)*INDEX(Assumptions!$C$16:$E$16,2))*(1-INDEX(Assumptions!$C$223:$E$223,2))/100000 -> 0 | H37: =0 -> 0 | I37: =0 -> 0 | J37: =J24*J27/(1+INDEX(Assumptions!$C$15:$E$15,3)*INDEX(Assumptions!$C$16:$E$16,3))*(1-INDEX(Assumptions!$C$223:$E$223,3))/100000 -> 21.966102
A38: Total revenue | B38: =SUM(B30:B37) -> 16.714396 | C38: =SUM(C30:C37) -> 26.631759 | D38: =SUM(D30:D37) -> 36.657299 | E38: =SUM(E30:E37) -> 71.143533 | F38: =SUM(F30:F37) -> 120.01493 | G38: =SUM(G30:G37) -> 166.93116 | H38: =SUM(H30:H37) -> 134.55428 | I38: =SUM(I30:I37) -> 235.65821 | J38: =SUM(J30:J37) -> 334.642
A39: Revenue growth | B39: =0 -> 0 | C39: =C38/B38-1 -> 0.59334256 | D39: =D38/C38-1 -> 0.37645052 | E39: =0 -> 0 | F39: =F38/E38-1 -> 0.6869408 | G39: =G38/F38-1 -> 0.39092001 | H39: =0 -> 0 | I39: =I38/H38-1 -> 0.75139881 | J39: =J38/I38-1 -> 0.42003115
A40: Costs (₹ lakh)
A41: Variable delivery: consumables, kits, payment/EMI, rewards, pop-ups, Pro Circle service, satellite trainer | B41: =Outlook_Conservative!O68/100000 -> 5.8388935 | C41: =((C17*C7+C10*C15)*INDEX(Assumptions!$C$91:$E$91,1)+C18*(INDEX(Assumptions!$C$93:$E$93,1)+INDEX(Assumptions!$C$240:$E$240,1))+C17*(1-C7)*INDEX(Assumptions!$C$92:$E$92,1)+C19*INDEX(Assumptions!$C$94:$E$94,1)+C20*INDEX(Assumptions!$C$95:$E$95,1)+C21*INDEX(Assumptions!$C$84:$E$84,1)+C23*INDEX(Assumptions!$C$97:$E$97,1)+C17*INDEX(Assumptions!$C$198:$E$198,1)*INDEX(Assumptions!$C$69:$E$69,1)+C24*INDEX(Assumptions!$C$224:$E$224,1)+(C30+C31+C32)*100000*(1+INDEX(Assumptions!$C$15:$E$15,1)*INDEX(Assumptions!$C$16:$E$16,1))*INDEX(Assumptions!$C$70:$E$70,1)*INDEX(Assumptions!$C$71:$E$71,1)+C38*100000*(1+INDEX(Assumptions!$C$15:$E$15,1)*INDEX(Assumptions!$C$16:$E$16,1))*INDEX(Assumptions!$C$76:$E$76,1)+C35*100000*INDEX(Assumptions!$C$216:$E$216,1))/100000 -> 6.0759514 | D41: =((D17*D7+D10*D15)*INDEX(Assumptions!$C$91:$E$91,1)+D18*(INDEX(Assumptions!$C$93:$E$93,1)+INDEX(Assumptions!$C$240:$E$240,1))+D17*(1-D7)*INDEX(Assumptions!$C$92:$E$92,1)+D19*INDEX(Assumptions!$C$94:$E$94,1)+D20*INDEX(Assumptions!$C$95:$E$95,1)+D21*INDEX(Assumptions!$C$84:$E$84,1)+D23*INDEX(Assumptions!$C$97:$E$97,1)+D17*INDEX(Assumptions!$C$198:$E$198,1)*INDEX(Assumptions!$C$69:$E$69,1)+D24*INDEX(Assumptions!$C$224:$E$224,1)+(D30+D31+D32)*100000*(1+INDEX(Assumptions!$C$15:$E$15,1)*INDEX(Assumptions!$C$16:$E$16,1))*INDEX(Assumptions!$C$70:$E$70,1)*INDEX(Assumptions!$C$71:$E$71,1)+D38*100000*(1+INDEX(Assumptions!$C$15:$E$15,1)*INDEX(Assumptions!$C$16:$E$16,1))*INDEX(Assumptions!$C$76:$E$76,1)+D35*100000*INDEX(Assumptions!$C$216:$E$216,1))/100000 -> 9.3254804 | E41: =Outlook_Base!O68/100000 -> 12.897918 | F41: =((F17*F7+F10*F15)*INDEX(Assumptions!$C$91:$E$91,2)+F18*(INDEX(Assumptions!$C$93:$E$93,2)+INDEX(Assumptions!$C$240:$E$240,2))+F17*(1-F7)*INDEX(Assumptions!$C$92:$E$92,2)+F19*INDEX(Assumptions!$C$94:$E$94,2)+F20*INDEX(Assumptions!$C$95:$E$95,2)+F21*INDEX(Assumptions!$C$84:$E$84,2)+F23*INDEX(Assumptions!$C$97:$E$97,2)+F17*INDEX(Assumptions!$C$198:$E$198,2)*INDEX(Assumptions!$C$69:$E$69,2)+F24*INDEX(Assumptions!$C$224:$E$224,2)+(F30+F31+F32)*100000*(1+INDEX(Assumptions!$C$15:$E$15,2)*INDEX(Assumptions!$C$16:$E$16,2))*INDEX(Assumptions!$C$70:$E$70,2)*INDEX(Assumptions!$C$71:$E$71,2)+F38*100000*(1+INDEX(Assumptions!$C$15:$E$15,2)*INDEX(Assumptions!$C$16:$E$16,2))*INDEX(Assumptions!$C$76:$E$76,2)+F35*100000*INDEX(Assumptions!$C$216:$E$216,2))/100000 -> 19.811115 | G41: =((G17*G7+G10*G15)*INDEX(Assumptions!$C$91:$E$91,2)+G18*(INDEX(Assumptions!$C$93:$E$93,2)+INDEX(Assumptions!$C$240:$E$240,2))+G17*(1-G7)*INDEX(Assumptions!$C$92:$E$92,2)+G19*INDEX(Assumptions!$C$94:$E$94,2)+G20*INDEX(Assumptions!$C$95:$E$95,2)+G21*INDEX(Assumptions!$C$84:$E$84,2)+G23*INDEX(Assumptions!$C$97:$E$97,2)+G17*INDEX(Assumptions!$C$198:$E$198,2)*INDEX(Assumptions!$C$69:$E$69,2)+G24*INDEX(Assumptions!$C$224:$E$224,2)+(G30+G31+G32)*100000*(1+INDEX(Assumptions!$C$15:$E$15,2)*INDEX(Assumptions!$C$16:$E$16,2))*INDEX(Assumptions!$C$70:$E$70,2)*INDEX(Assumptions!$C$71:$E$71,2)+G38*100000*(1+INDEX(Assumptions!$C$15:$E$15,2)*INDEX(Assumptions!$C$16:$E$16,2))*INDEX(Assumptions!$C$76:$E$76,2)+G35*100000*INDEX(Assumptions!$C$216:$E$216,2))/100000 -> 28.667648 | H41: =Outlook_Aggressive!O68/100000 -> 16.779765 | I41: =((I17*I7+I10*I15)*INDEX(Assumptions!$C$91:$E$91,3)+I18*(INDEX(Assumptions!$C$93:$E$93,3)+INDEX(Assumptions!$C$240:$E$240,3))+I17*(1-I7)*INDEX(Assumptions!$C$92:$E$92,3)+I19*INDEX(Assumptions!$C$94:$E$94,3)+I20*INDEX(Assumptions!$C$95:$E$95,3)+I21*INDEX(Assumptions!$C$84:$E$84,3)+I23*INDEX(Assumptions!$C$97:$E$97,3)+I17*INDEX(Assumptions!$C$198:$E$198,3)*INDEX(Assumptions!$C$69:$E$69,3)+I24*INDEX(Assumptions!$C$224:$E$224,3)+(I30+I31+I32)*100000*(1+INDEX(Assumptions!$C$15:$E$15,3)*INDEX(Assumptions!$C$16:$E$16,3))*INDEX(Assumptions!$C$70:$E$70,3)*INDEX(Assumptions!$C$71:$E$71,3)+I38*100000*(1+INDEX(Assumptions!$C$15:$E$15,3)*INDEX(Assumptions!$C$16:$E$16,3))*INDEX(Assumptions!$C$76:$E$76,3)+I35*100000*INDEX(Assumptions!$C$216:$E$216,3))/100000 -> 27.101614 | J41: =((J17*J7+J10*J15)*INDEX(Assumptions!$C$91:$E$91,3)+J18*(INDEX(Assumptions!$C$93:$E$93,3)+INDEX(Assumptions!$C$240:$E$240,3))+J17*(1-J7)*INDEX(Assumptions!$C$92:$E$92,3)+J19*INDEX(Assumptions!$C$94:$E$94,3)+J20*INDEX(Assumptions!$C$95:$E$95,3)+J21*INDEX(Assumptions!$C$84:$E$84,3)+J23*INDEX(Assumptions!$C$97:$E$97,3)+J17*INDEX(Assumptions!$C$198:$E$198,3)*INDEX(Assumptions!$C$69:$E$69,3)+J24*INDEX(Assumptions!$C$224:$E$224,3)+(J30+J31+J32)*100000*(1+INDEX(Assumptions!$C$15:$E$15,3)*INDEX(Assumptions!$C$16:$E$16,3))*INDEX(Assumptions!$C$70:$E$70,3)*INDEX(Assumptions!$C$71:$E$71,3)+J38*100000*(1+INDEX(Assumptions!$C$15:$E$15,3)*INDEX(Assumptions!$C$16:$E$16,3))*INDEX(Assumptions!$C$76:$E$76,3)+J35*100000*INDEX(Assumptions!$C$216:$E$216,3))/100000 -> 38.528123
A42: Trainers + assistants (batch-slots x (1 - founder share) / slots per FTE; wage escalation) | B42: =SUM(Outlook_Conservative!C77:N77)/100000 -> 6.15 | C42: =(MAX(1,ROUNDUP(C14*C15/12/INDEX(Assumptions!$C$102:$E$102,1)*(1-C25)/INDEX(Assumptions!$C$101:$E$101,1),0))*(INDEX(Assumptions!$C$98:$E$98,1)+INDEX(Assumptions!$C$99:$E$99,1))/2+ROUNDUP(C14*C15/12/INDEX(Assumptions!$C$102:$E$102,1)/2,0)*INDEX(Assumptions!$C$100:$E$100,1))*12*(1+INDEX(Assumptions!$C$227:$E$227,1))^1/100000 -> 10.56 | D42: =(MAX(1,ROUNDUP(D14*D15/12/INDEX(Assumptions!$C$102:$E$102,1)*(1-D25)/INDEX(Assumptions!$C$101:$E$101,1),0))*(INDEX(Assumptions!$C$98:$E$98,1)+INDEX(Assumptions!$C$99:$E$99,1))/2+ROUNDUP(D14*D15/12/INDEX(Assumptions!$C$102:$E$102,1)/2,0)*INDEX(Assumptions!$C$100:$E$100,1))*12*(1+INDEX(Assumptions!$C$227:$E$227,1))^2/100000 -> 11.616 | E42: =SUM(Outlook_Base!C77:N77)/100000 -> 9.84 | F42: =(MAX(1,ROUNDUP(F14*F15/12/INDEX(Assumptions!$C$102:$E$102,2)*(1-F25)/INDEX(Assumptions!$C$101:$E$101,2),0))*(INDEX(Assumptions!$C$98:$E$98,2)+INDEX(Assumptions!$C$99:$E$99,2))/2+ROUNDUP(F14*F15/12/INDEX(Assumptions!$C$102:$E$102,2)/2,0)*INDEX(Assumptions!$C$100:$E$100,2))*12*(1+INDEX(Assumptions!$C$227:$E$227,2))^1/100000 -> 17.3664 | G42: =(MAX(1,ROUNDUP(G14*G15/12/INDEX(Assumptions!$C$102:$E$102,2)*(1-G25)/INDEX(Assumptions!$C$101:$E$101,2),0))*(INDEX(Assumptions!$C$98:$E$98,2)+INDEX(Assumptions!$C$99:$E$99,2))/2+ROUNDUP(G14*G15/12/INDEX(Assumptions!$C$102:$E$102,2)/2,0)*INDEX(Assumptions!$C$100:$E$100,2))*12*(1+INDEX(Assumptions!$C$227:$E$227,2))^2/100000 -> 18.755712 | H42: =SUM(Outlook_Aggressive!C77:N77)/100000 -> 11.56 | I42: =(MAX(1,ROUNDUP(I14*I15/12/INDEX(Assumptions!$C$102:$E$102,3)*(1-I25)/INDEX(Assumptions!$C$101:$E$101,3),0))*(INDEX(Assumptions!$C$98:$E$98,3)+INDEX(Assumptions!$C$99:$E$99,3))/2+ROUNDUP(I14*I15/12/INDEX(Assumptions!$C$102:$E$102,3)/2,0)*INDEX(Assumptions!$C$100:$E$100,3))*12*(1+INDEX(Assumptions!$C$227:$E$227,3))^1/100000 -> 15.4224 | J42: =(MAX(1,ROUNDUP(J14*J15/12/INDEX(Assumptions!$C$102:$E$102,3)*(1-J25)/INDEX(Assumptions!$C$101:$E$101,3),0))*(INDEX(Assumptions!$C$98:$E$98,3)+INDEX(Assumptions!$C$99:$E$99,3))/2+ROUNDUP(J14*J15/12/INDEX(Assumptions!$C$102:$E$102,3)/2,0)*INDEX(Assumptions!$C$100:$E$100,3))*12*(1+INDEX(Assumptions!$C$227:$E$227,3))^2/100000 -> 24.984288
A43: Growth team: counsellors, marketing/content, freelancers (Y2+: counsellor FTE input + Y1 M12 team run-rate) | B43: =SUM(Outlook_Conservative!C78:N79)/100000 -> 3.44 | C43: =(INDEX(Assumptions!$C$233:$E$233,1)*INDEX(Assumptions!$C$108:$E$108,1)+Outlook_Conservative!N79)*12*(1+INDEX(Assumptions!$C$227:$E$227,1))^1/100000 -> 4.224 | D43: =(INDEX(Assumptions!$C$234:$E$234,1)*INDEX(Assumptions!$C$108:$E$108,1)+Outlook_Conservative!N79)*12*(1+INDEX(Assumptions!$C$227:$E$227,1))^2/100000 -> 4.6464 | E43: =SUM(Outlook_Base!C78:N79)/100000 -> 13.825 | F43: =(INDEX(Assumptions!$C$233:$E$233,2)*INDEX(Assumptions!$C$108:$E$108,2)+Outlook_Base!N79)*12*(1+INDEX(Assumptions!$C$227:$E$227,2))^1/100000 -> 16.524 | G43: =(INDEX(Assumptions!$C$234:$E$234,2)*INDEX(Assumptions!$C$108:$E$108,2)+Outlook_Base!N79)*12*(1+INDEX(Assumptions!$C$227:$E$227,2))^2/100000 -> 19.59552 | H43: =SUM(Outlook_Aggressive!C78:N79)/100000 -> 22.85 | I43: =(INDEX(Assumptions!$C$233:$E$233,3)*INDEX(Assumptions!$C$108:$E$108,3)+Outlook_Aggressive!N79)*12*(1+INDEX(Assumptions!$C$227:$E$227,3))^1/100000 -> 27.216 | J43: =(INDEX(Assumptions!$C$234:$E$234,3)*INDEX(Assumptions!$C$108:$E$108,3)+Outlook_Aggressive!N79)*12*(1+INDEX(Assumptions!$C$227:$E$227,3))^2/100000 -> 31.14288
A44: Academy manager + front desk | B44: =SUM(Outlook_Conservative!C80:N81)/100000 -> 0 | C44: =(INDEX(Assumptions!$C$235:$E$235,1)*INDEX(Assumptions!$C$186:$E$186,1)+Outlook_Conservative!N80)*12*(1+INDEX(Assumptions!$C$227:$E$227,1))^1/100000 -> 0 | D44: =(INDEX(Assumptions!$C$236:$E$236,1)*INDEX(Assumptions!$C$186:$E$186,1)+Outlook_Conservative!N80)*12*(1+INDEX(Assumptions!$C$227:$E$227,1))^2/100000 -> 4.719 | E44: =SUM(Outlook_Base!C80:N81)/100000 -> 1.08 | F44: =(INDEX(Assumptions!$C$235:$E$235,2)*INDEX(Assumptions!$C$186:$E$186,2)+Outlook_Base!N80)*12*(1+INDEX(Assumptions!$C$227:$E$227,2))^1/100000 -> 10.7568 | G44: =(INDEX(Assumptions!$C$236:$E$236,2)*INDEX(Assumptions!$C$186:$E$186,2)+Outlook_Base!N80)*12*(1+INDEX(Assumptions!$C$227:$E$227,2))^2/100000 -> 11.617344 | H44: =SUM(Outlook_Aggressive!C80:N81)/100000 -> 3.57 | I44: =(INDEX(Assumptions!$C$235:$E$235,3)*INDEX(Assumptions!$C$186:$E$186,3)+Outlook_Aggressive!N80)*12*(1+INDEX(Assumptions!$C$227:$E$227,3))^1/100000 -> 10.7568 | J44: =(INDEX(Assumptions!$C$236:$E$236,3)*INDEX(Assumptions!$C$186:$E$186,3)+Outlook_Aggressive!N80)*12*(1+INDEX(Assumptions!$C$227:$E$227,3))^2/100000 -> 11.617344
A45: Rent + utilities | B45: =(Outlook_Conservative!O84+Outlook_Conservative!O85)/100000 -> 6.84 | C45: =(Outlook_Conservative!N84+Outlook_Conservative!N85)*12*(1+INDEX(Assumptions!$C$228:$E$228,1))^1/100000 -> 7.182 | D45: =(Outlook_Conservative!N84+Outlook_Conservative!N85)*12*(1+INDEX(Assumptions!$C$228:$E$228,1))^2/100000 -> 7.5411 | E45: =(Outlook_Base!O84+Outlook_Base!O85)/100000 -> 9.876 | F45: =(Outlook_Base!N84+Outlook_Base!N85)*12*(1+INDEX(Assumptions!$C$228:$E$228,2))^1/100000 -> 15.0696 | G45: =(Outlook_Base!N84+Outlook_Base!N85)*12*(1+INDEX(Assumptions!$C$228:$E$228,2))^2/100000 -> 15.82308 | H45: =(Outlook_Aggressive!O84+Outlook_Aggressive!O85)/100000 -> 14.598 | I45: =(Outlook_Aggressive!N84+Outlook_Aggressive!N85)*12*(1+INDEX(Assumptions!$C$228:$E$228,3))^1/100000 -> 18.5472 | J45: =(Outlook_Aggressive!N84+Outlook_Aggressive!N85)*12*(1+INDEX(Assumptions!$C$228:$E$228,3))^2/100000 -> 19.47456
A46: Paid media + regional acquisition + online CAC | B46: =Outlook_Conservative!O87/100000 -> 4.2 | C46: =(INDEX(Assumptions!$C$237:$E$237,1)+C18*INDEX(Assumptions!$C$239:$E$239,1)+C22*INDEX(Assumptions!$C$214:$E$214,1)*0.5)/100000 -> 3 | D46: =(INDEX(Assumptions!$C$238:$E$238,1)+D18*INDEX(Assumptions!$C$239:$E$239,1)+D22*INDEX(Assumptions!$C$214:$E$214,1)*0.5)/100000 -> 4.65 | E46: =Outlook_Base!O87/100000 -> 9.35 | F46: =(INDEX(Assumptions!$C$237:$E$237,2)+F18*INDEX(Assumptions!$C$239:$E$239,2)+F22*INDEX(Assumptions!$C$214:$E$214,2)*0.5)/100000 -> 14.475 | G46: =(INDEX(Assumptions!$C$238:$E$238,2)+G18*INDEX(Assumptions!$C$239:$E$239,2)+G22*INDEX(Assumptions!$C$214:$E$214,2)*0.5)/100000 -> 19.175 | H46: =Outlook_Aggressive!O87/100000 -> 16.85 | I46: =(INDEX(Assumptions!$C$237:$E$237,3)+I18*INDEX(Assumptions!$C$239:$E$239,3)+I22*INDEX(Assumptions!$C$214:$E$214,3)*0.5)/100000 -> 27.987732 | J46: =(INDEX(Assumptions!$C$238:$E$238,3)+J18*INDEX(Assumptions!$C$239:$E$239,3)+J22*INDEX(Assumptions!$C$214:$E$214,3)*0.5)/100000 -> 33.891745
A47: Tech, partnerships/PR, admin, online content, one-offs | B47: =(Outlook_Conservative!O86+Outlook_Conservative!O88+Outlook_Conservative!O89+Outlook_Conservative!O90)/100000 -> 3.79996 | C47: =((Outlook_Conservative!N86+INDEX(Assumptions!$C$170:$E$170,1)+INDEX(Assumptions!$C$195:$E$195,1))*12+IF(C22>0,INDEX(Assumptions!$C$215:$E$215,1),0))/100000 -> 2.79996 | D47: =((Outlook_Conservative!N86+INDEX(Assumptions!$C$170:$E$170,1)+INDEX(Assumptions!$C$195:$E$195,1))*12+IF(D22>0,INDEX(Assumptions!$C$215:$E$215,1),0))/100000 -> 3.79996 | E47: =(Outlook_Base!O86+Outlook_Base!O88+Outlook_Base!O89+Outlook_Base!O90)/100000 -> 8.75996 | F47: =((Outlook_Base!N86+INDEX(Assumptions!$C$170:$E$170,2)+INDEX(Assumptions!$C$195:$E$195,2))*12+IF(F22>0,INDEX(Assumptions!$C$215:$E$215,2),0))/100000 -> 8.45996 | G47: =((Outlook_Base!N86+INDEX(Assumptions!$C$170:$E$170,2)+INDEX(Assumptions!$C$195:$E$195,2))*12+IF(G22>0,INDEX(Assumptions!$C$215:$E$215,2),0))/100000 -> 8.45996 | H47: =(Outlook_Aggressive!O86+Outlook_Aggressive!O88+Outlook_Aggressive!O89+Outlook_Aggressive!O90)/100000 -> 13.28004 | I47: =((Outlook_Aggressive!N86+INDEX(Assumptions!$C$170:$E$170,3)+INDEX(Assumptions!$C$195:$E$195,3))*12+IF(I22>0,INDEX(Assumptions!$C$215:$E$215,3),0))/100000 -> 12.26004 | J47: =((Outlook_Aggressive!N86+INDEX(Assumptions!$C$170:$E$170,3)+INDEX(Assumptions!$C$195:$E$195,3))*12+IF(J22>0,INDEX(Assumptions!$C$215:$E$215,3),0))/100000 -> 12.26004
A48: Total costs | B48: =SUM(B41:B47) -> 30.268853 | C48: =SUM(C41:C47) -> 33.841911 | D48: =SUM(D41:D47) -> 46.29794 | E48: =SUM(E41:E47) -> 65.628878 | F48: =SUM(F41:F47) -> 102.46287 | G48: =SUM(G41:G47) -> 122.09426 | H48: =SUM(H41:H47) -> 99.487805 | I48: =SUM(I41:I47) -> 139.29179 | J48: =SUM(J41:J47) -> 171.89898
A49: EBITDA | B49: =B38-B48 -> -13.554457 | C49: =C38-C48 -> -7.2101524 | D49: =D38-D48 -> -9.6406418 | E49: =E38-E48 -> 5.5146551 | F49: =F38-F48 -> 17.552053 | G49: =G38-G48 -> 44.836901 | H49: =H38-H48 -> 35.066478 | I49: =I38-I48 -> 96.366426 | J49: =J38-J48 -> 162.74302
A50: EBITDA margin | B50: =IFERROR(B49/B38,0) -> -0.81094506 | C50: =IFERROR(C49/C38,0) -> -0.27073512 | D50: =IFERROR(D49/D38,0) -> -0.26299379 | E50: =IFERROR(E49/E38,0) -> 0.077514496 | F50: =IFERROR(F49/F38,0) -> 0.14624892 | G50: =IFERROR(G49/G38,0) -> 0.26859515 | H50: =IFERROR(H49/H38,0) -> 0.26061213 | I50: =IFERROR(I49/I38,0) -> 0.40892454 | J50: =IFERROR(J49/J38,0) -> 0.48631977
A51: Capex and deposits | B51: =Outlook_Conservative!O101/100000 -> 0.5 | C51: =(INDEX(Assumptions!$C$241:$E$241,1)+MAX(0,C11-B11)*INDEX(Assumptions!$C$183:$E$183,1)+IF(C24>0,INDEX(Assumptions!$C$225:$E$225,1),0))/100000 -> 3 | D51: =(INDEX(Assumptions!$C$242:$E$242,1)+MAX(0,D11-C11)*INDEX(Assumptions!$C$183:$E$183,1)+IF(D24>0,INDEX(Assumptions!$C$225:$E$225,1),0))/100000 -> 2.7 | E51: =Outlook_Base!O101/100000 -> 19.72 | F51: =(INDEX(Assumptions!$C$241:$E$241,2)+MAX(0,F11-E11)*INDEX(Assumptions!$C$183:$E$183,2)+IF(F24>0,INDEX(Assumptions!$C$225:$E$225,2),0))/100000 -> 3 | G51: =(INDEX(Assumptions!$C$242:$E$242,2)+MAX(0,G11-F11)*INDEX(Assumptions!$C$183:$E$183,2)+IF(G24>0,INDEX(Assumptions!$C$225:$E$225,2),0))/100000 -> 3.6 | H51: =Outlook_Aggressive!O101/100000 -> 27.04 | I51: =(INDEX(Assumptions!$C$241:$E$241,3)+MAX(0,I11-H11)*INDEX(Assumptions!$C$183:$E$183,3)+IF(I24>0,INDEX(Assumptions!$C$225:$E$225,3),0))/100000 -> 5 | J51: =(INDEX(Assumptions!$C$242:$E$242,3)+MAX(0,J11-I11)*INDEX(Assumptions!$C$183:$E$183,3)+IF(J24>0,INDEX(Assumptions!$C$225:$E$225,3),0))/100000 -> 8.1
A52: Net cash flow (Y1 incl. instalment timing) | B52: =Outlook_Conservative!N104/100000 -> -15.443217 | C52: =C49-C51 -> -10.210152 | D52: =D49-D51 -> -12.340642 | E52: =Outlook_Base!N104/100000 -> -17.129608 | F52: =F49-F51 -> 14.552053 | G52: =G49-G51 -> 41.236901 | H52: =Outlook_Aggressive!N104/100000 -> 8.0264777 | I52: =I49-I51 -> 91.366426 | J52: =J49-J51 -> 154.64302
A53: Cumulative cash position | B53: =B52 -> -15.443217 | C53: =B53+C52 -> -25.653369 | D53: =C53+D52 -> -37.994011 | E53: =E52 -> -17.129608 | F53: =E53+F52 -> -2.5775542 | G53: =F53+G52 -> 38.659347 | H53: =H52 -> 8.0264777 | I53: =H53+I52 -> 99.392903 | J53: =I53+J52 -> 254.03592
A54: Peak cash need to date (Y1 monthly peak; Y2-3 year-end) | B54: =Outlook_Conservative!O105/100000 -> 15.443217 | C54: =MAX(B54,-MIN(0,C53)) -> 25.653369 | D54: =MAX(C54,-MIN(0,D53)) -> 37.994011 | E54: =Outlook_Base!O105/100000 -> 26.142235 | F54: =MAX(E54,-MIN(0,F53)) -> 26.142235 | G54: =MAX(F54,-MIN(0,G53)) -> 26.142235 | H54: =Outlook_Aggressive!O105/100000 -> 28.80706 | I54: =MAX(H54,-MIN(0,I53)) -> 28.80706 | J54: =MAX(I54,-MIN(0,J53)) -> 28.80706
A55: SOM layers for market_sizing_model.xlsx (Year 3, ₹ lakh ex-GST)
A56: Tricity flagship (career tricity-origin + entry products) | B56: =B30+B33 -> 12.133379 | C56: =C30+C33 -> 17.883105 | D56: =D30+D33 -> 19.512944 | E56: =E30+E33 -> 44.742276 | F56: =F30+F33 -> 63.798016 | G56: =G30+G33 -> 71.874764 | H56: =H30+H33 -> 75.187666 | I56: =I30+I33 -> 100.27785 | J56: =J30+J33 -> 104.56651
A57: Regional destination offline (+ satellite) | B57: =B31+B37 -> 1.5915203 | C57: =C31+C37 -> 2.5710631 | D57: =D31+D37 -> 3.4015165 | E57: =E31+E37 -> 12.152552 | F57: =F31+F37 -> 17.763987 | G57: =G31+G37 -> 24.855371 | H57: =H31+H37 -> 31.305665 | I57: =I31+I37 -> 42.963311 | J57: =J31+J37 -> 75.556777
A58: Hybrid incremental | B58: =B32 -> 0 | C58: =C32 -> 0 | D58: =D32 -> 4.6271186 | E58: =E32 -> 0 | F58: =F32 -> 10.169492 | G58: =G32 -> 25.152542 | H58: =H32 -> 0 | I58: =I32 -> 25.319759 | J58: =J32 -> 49.348173
A59: CPD (L4 + L5) | B59: =B34 -> 2.9602554 | C59: =C34 -> 4.9335046 | D59: =D34 -> 5.8416321 | E59: =E34 -> 13.873638 | F59: =F34 -> 21.176944 | G59: =G34 -> 27.063298 | H59: =H34 -> 27.028361 | I59: =I34 -> 47.952321 | J59: =J34 -> 61.154647
A60: Online | B60: =B35 -> 0 | C60: =C35 -> 0 | D60: =D35 -> 1.2699153 | E60: =E35 -> 0 | F60: =F35 -> 3.8110169 | G60: =G35 -> 11.433051 | H60: =H35 -> 0 | I60: =I35 -> 13.552542 | J60: =J35 -> 33.881356
A61: Adjacent (outside training market) | B61: =B36 -> 0.029241971 | C61: =C36 -> 1.2440865 | D61: =D36 -> 2.0041722 | E61: =E36 -> 0.37506667 | F61: =F36 -> 3.2954728 | G61: =G36 -> 6.5521387 | H61: =H36 -> 1.03259 | I61: =I36 -> 5.5924295 | J61: =J36 -> 10.13454
A62: SOM learners: tricity-origin career students (L2 + L3 new) | B62: =B17*(1-B8) -> 25.819941 | C62: =C17*(1-C8) -> 33.140901 | D62: =D17*(1-D8) -> 33.569783 | E62: =E17*(1-E8) -> 67.087638 | F62: =F17*(1-F8) -> 91.439125 | G62: =G17*(1-G8) -> 93.877502 | H62: =H17*(1-H8) -> 80.09945 | I62: =I17*(1-I8) -> 104.49615 | J62: =J17*(1-J8) -> 97.479648
A63: SOM learners: out-of-town career students (+ satellite) | B63: =B17*B8+B24 -> 4.5564601 | C63: =C17*C8+C24 -> 5.8483942 | D63: =D17*D8+D24 -> 7.3689767 | E63: =E17*E8+E24 -> 22.362546 | F63: =F17*F8+F24 -> 30.479708 | G63: =G17*G8+G24 -> 40.233215 | H63: =H17*H8+H24 -> 43.130473 | I63: =I17*I8+I24 -> 56.267155 | J63: =J17*J8+J24 -> 94.986432
A64: SOM learners: incremental destination/hybrid students | B64: =B18 -> 0 | C64: =C18 -> 0 | D64: =D18 -> 8 | E64: =E18 -> 0 | F64: =F18 -> 15 | G64: =G18 -> 35 | H64: =H18 -> 0 | I64: =I18 -> 29.877315 | J64: =J18 -> 53.917448
A65: Checks
A66: Layers reconcile to total revenue (should be 0) | B66: =ROUND(B38-SUM(B56:B61),6) -> 0 | C66: =ROUND(C38-SUM(C56:C61),6) -> 0 | D66: =ROUND(D38-SUM(D56:D61),6) -> 0 | E66: =ROUND(E38-SUM(E56:E61),6) -> 0 | F66: =ROUND(F38-SUM(F56:F61),6) -> 0 | G66: =ROUND(G38-SUM(G56:G61),6) -> 0 | H66: =ROUND(H38-SUM(H56:H61),6) -> 0 | I66: =ROUND(I38-SUM(I56:I61),6) -> 0 | J66: =ROUND(J38-SUM(J56:J61),6) -> 0

Sheet BM_Unit_Economics
A1: Unit economics by business model (directional, Base rates, at maturity) - ₹ unless stated
A2: Side-by-side with the same metric rows. Inputs are in this sheet's input block (blue) with IDs; models link to 3yr_Scenarios where they are part of the recommended plan.
A4: Input ID | B4: Description | C4: Value | D4: Unit | E4: Source
A5: A-ECO-301 | B5: B1 owned regional centre: annual fixed cost (rent, lead trainer, trainer, counsellor, utilities, local brand, management) | C5: 2910000 | D5: ₹/yr | E5: A-BM-13 [HYP]
A6: A-ECO-302 | B6: B1 owned centre: capex + launch | C6: 1650000 | D6: ₹ | E6: A-BM-13 ₹13-20L [HYP]
A7: A-ECO-303 | B7: B1 owned centre: P1 students per year at maturity (Base) | C7: 46 | D7: students | E7: BM breakeven ~46 [HYP]
A8: A-ECO-304 | B8: B2 partner-hosted satellite: students per year | C8: 25 | D8: students | E8: geographic_expansion §4.1 [HYP]
A9: A-ECO-305 | B9: B3 franchise: royalty rate | C9: 0.15 | D9: % | E9: A-BM-08 15-20% [HYP]
A10: A-ECO-306 | B10: B3 franchise: franchisee revenue per unit per year | C10: 4000000 | D10: ₹/yr | E10: Assumed: 46 P1 x ₹80k + short courses [HYP]
A11: A-ECO-307 | B11: B3 franchise: PNA support cost per unit per year | C11: 400000 | D11: ₹/yr | E11: geographic_expansion §4.1(d) ₹3-5L [HYP]
A12: A-ECO-308 | B12: B3 franchise: brand/franchise fee per unit (one-off) and system build cost | C12: 450000 | D12: ₹ | E12: A-BM-08 ₹4.3-5.0L; system ₹5-10L [HYP]
A13: A-ECO-309 | B13: B3 franchise system build (manuals, audits, legal) | C13: 750000 | D13: ₹ | E13: geographic_expansion §4.1(d) [HYP]
A14: A-ECO-310 | B14: C digital stand-alone: buyers per year at maturity | C14: 2000 | D14: buyers | E14: Gate: ≥200/month organic (BM §6.3) [HYP]
A15: A-ECO-311 | B15: C digital: content + platform fixed cost per year | C15: 600000 | D15: ₹/yr | E15: Production + LMS + live sessions [HYP]
A16: A-ECO-312 | B16: E marketplace: average order value (bridal + party mix) | C16: 6000 | D16: ₹ | E16: Bridal ₹15-25k; party ₹1.5-3k (S-CHD-12; A-CUS-02) [HYP]
... A24: A-ECO-320 | B24: Ludhiana: destination students that would travel to Chandigarh per year (N_dest) | C24: 10 | D24: students | E24: geographic_expansion §4.1 indifference rule [HYP]
A27: Metric | B27: A Flagship (Y3 Base, whole academy) | C27: B1 Owned regional centre (Ludhiana) | D27: B2 Partner-hosted satellite | E27: B3 Franchise / licence (per unit, PNA view) | F27: C Digital stand-alone | G27: D Destination / hybrid (incremental student) | H27: E Services marketplace (full) | I27: E-lite Alumni booking desk | J27: F1 Masterclasses (CPD) | K27: F2 Kits + brand partnership | L27: F3 Pro Circle
A28: Unit of sale | B28: Academy (all lines) | C28: P1 student | D28: P1 student | E28: Franchise unit | F28: Online buyer | G28: Destination student | H28: Booking | I28: Referred booking | J28: Masterclass seat | K28: Career student (kit) + sponsor | L28: Paid member-year
A29: Price / AOV incl. GST (₹) | B29: =3yr_Scenarios!G27 -> 84800 | C29: =Assumptions!$D$20 -> 80000 | D29: =Assumptions!$D$20 -> 80000 | E29: =$C$10 -> 4000000 | F29: =Assumptions!$D$213 -> 1499 | G29: =Assumptions!$D$20 -> 80000 | H29: =$C$16 -> 6000 | I29: =Assumptions!$D$219 -> 1750 | J29: =Assumptions!$D$21 -> 10000 | K29: =20000 -> 20000 | L29: =Assumptions!$D$23 -> 9999
A30: Net revenue per unit ex-GST (₹) | B30: =B29/(1+Assumptions!$D$15*Assumptions!$D$16) -> 71864.407 | C30: =Assumptions!$D$20/(1+Assumptions!$D$15*Assumptions!$D$16) -> 67796.61 | D30: =Assumptions!$D$20/(1+Assumptions!$D$15*Assumptions!$D$16)*(1-Assumptions!$D$223) -> 50847.458 | E30: =$C$10*$C$9 -> 600000 | F30: =F29/(1+Assumptions!$D$15*Assumptions!$D$16) -> 1270.339 | G30: =Assumptions!$D$20/(1+Assumptions!$D$15*Assumptions!$D$16) -> 67796.61 | H30: =H29/(1+Assumptions!$D$15*Assumptions!$D$16)*$C$17 -> 1016.9492 | I30: =I29/(1+Assumptions!$D$15*Assumptions!$D$16) -> 1483.0508 | J30: =J29/(1+Assumptions!$D$15*Assumptions!$D$16) -> 8474.5763 | K30: =Assumptions!$D$243 -> 960 | L30: =L29/(1+Assumptions!$D$15*Assumptions!$D$16) -> 8473.7288
A31: Units per year at maturity | B31: =3yr_Scenarios!G17 -> 134.11072 | C31: =$C$7 -> 46 | D31: =$C$8 -> 25 | E31: =3 -> 3 | F31: =$C$14 -> 2000 | G31: =3yr_Scenarios!G18 -> 35 | H31: =$C$22 -> 800 | I31: =Assumptions!$D$218 -> 120 | J31: =3yr_Scenarios!G19 -> 280 | K31: =3yr_Scenarios!G17*3yr_Scenarios!G7 -> 80.46643 | L31: =3yr_Scenarios!G23 -> 39.350851
A32: Revenue per year (₹ lakh) | B32: =3yr_Scenarios!G38 -> 166.93116 | C32: =C31*C30/100000 -> 31.186441 | D32: =D31*D30/100000 -> 12.711864 | E32: =E31*E30/100000 -> 18 | F32: =F31*F30/100000 -> 25.40678 | G32: =G31*G30/100000 -> 23.728814 | H32: =H31*H30/100000 -> 8.1355932 | I32: =I31*I30/100000 -> 1.779661 | J32: =J31*J30/100000 -> 23.728814 | K32: =K31*K30/100000+Assumptions!$D$221/100000 -> 4.7724777 | L32: =L31*L30/100000 -> 3.3344844
A33: Variable cost per unit (₹) | B33: =IFERROR(3yr_Scenarios!G41*100000/B31,0) -> 21376.105 | C33: =Assumptions!$D$91+Assumptions!$D$20*(Assumptions!$D$76+Assumptions!$D$70*Assumptions!$D$71)+Assumptions!$D$115*Assumptions!$D$120 -> 20666.667 | D33: =Assumptions!$D$91+Assumptions!$D$224+Assumptions!$D$20*(Assumptions!$D$76+Assumptions!$D$70*Assumptions!$D$71)+Assumptions!$D$239 -> 31500 | E33: =$C$11 -> 400000 | F33: =F30*Assumptions!$D$216+Assumptions!$D$214*0.5 -> 301.62712 | G33: =Assumptions!$D$93+Assumptions!$D$240+Assumptions!$D$20*(Assumptions!$D$76+Assumptions!$D$70*Assumptions!$D$71)+Assumptions!$D$104*(Assumptions!$D$99+Assumptions!$D$100)/Assumptions!$D$101/Assumptions!$D$102+Assumptions!$D$239 -> 32000 | H33: =$C$18+H29*Assumptions!$D$76+$C$19/$C$20 -> 1948.5714 | I33: =250 -> 250 | J33: =Assumptions!$D$94+J29*Assumptions!$D$76+300 -> 1500 | K33: =0 -> 0 | L33: =Assumptions!$D$97+L29*Assumptions!$D$76 -> 2199.98
A34: Contribution per unit (₹) | B34: =IFERROR((B32-3yr_Scenarios!G41)*100000/B31,0) -> 103096.55 | C34: =C30-C33 -> 47129.944 | D34: =D30-D33 -> 19347.458 | E34: =E30-E33 -> 200000 | F34: =F30-F33 -> 968.71186 | G34: =G30-G33 -> 35796.61 | H34: =H30-H33 -> -931.62228 | I34: =I30-I33 -> 1233.0508 | J34: =J30-J33 -> 6974.5763 | K34: =K30 -> 960 | L34: =L30-L33 -> 6273.7488
A35: Contribution margin % | B35: =IFERROR((3yr_Scenarios!G38-3yr_Scenarios!G41)/3yr_Scenarios!G38,0) -> 0.82826665 | C35: =C34/C30 -> 0.69516667 | D35: =D34/D30 -> 0.3805 | E35: =E34/E30 -> 0.33333333 | F35: =F34/F30 -> 0.76256171 | G35: =G34/G30 -> 0.528 | H35: =H34/H30 -> -0.91609524 | I35: =I34/I30 -> 0.83142857 | J35: =J34/J30 -> 0.823 | K35: =1 -> 1 | L35: =L34/L30 -> 0.7403764
A36: Contribution per year (₹ lakh) | B36: =3yr_Scenarios!G38-3yr_Scenarios!G41 -> 138.26352 | C36: =C34*C31/100000 -> 21.679774 | D36: =D34*D31/100000 -> 4.8368644 | E36: =E34*E31/100000 -> 6 | F36: =F34*F31/100000 -> 19.374237 | G36: =G34*G31/100000 -> 12.528814 | H36: =H34*H31/100000 -> -7.4529782 | I36: =I34*I31/100000 -> 1.479661 | J36: =J34*J31/100000 -> 19.528814 | K36: =K32 -> 4.7724777 | L36: =L34*L31/100000 -> 2.4687735
A37: Fixed cost per year attributable (₹ lakh) | B37: =3yr_Scenarios!G48-3yr_Scenarios!G41 -> 93.426616 | C37: =$C$5/100000 -> 29.1 | D37: =1 -> 1 | E37: =5 -> 5 | F37: =$C$15/100000 -> 6 | G37: =Assumptions!$D$188*12/100000 -> 0.6 | H37: =$C$21/100000 -> 24 | I37: =0.5 -> 0.5 | J37: =0 -> 0 | K37: =0 -> 0 | L37: =0.6 -> 0.6
A38: EBITDA per year (₹ lakh) | B38: =3yr_Scenarios!G49 -> 44.836901 | C38: =C36-C37 -> -7.420226 | D38: =D36-D37 -> 3.8368644 | E38: =E36-E37 -> 1 | F38: =F36-F37 -> 13.374237 | G38: =G36-G37 -> 11.928814 | H38: =H36-H37 -> -31.452978 | I38: =I36-I37 -> 0.97966102 | J38: =J36-J37 -> 19.528814 | K38: =K36 -> 4.7724777 | L38: =L36-L37 -> 1.8687735
A39: Upfront investment (₹ lakh) | B39: =3yr_Scenarios!G54 -> 26.142235 | C39: =$C$6/100000 -> 16.5 | D39: =Assumptions!$D$225/100000 -> 3.5 | E39: =($C$13-E31*$C$12*0.5)/100000 -> 0.75 | F39: =3 -> 3 | G39: =Assumptions!$D$190/100000 -> 3.5 | H39: =15 -> 15 | I39: =0.2 -> 0.2 | J39: =0 -> 0 | K39: =0 -> 0 | L39: =0 -> 0
A40: Payback (years) | B40: =IFERROR(B39/B38,"n/m") -> 0.58305179 | C40: =IF(C38<=0,"never at this volume",C39/C38) -> never at this volume | D40: =IF(D38<=0,"never",D39/D38) -> 0.9122032 | E40: =IF(E38<=0,"never at 3 units",E39/E38) -> 0.75 | F40: =IF(F38<=0,"never",F39/F38) -> 0.22431186 | G40: =IF(G38<=0,"never",G39/G38) -> 0.29340722 | H40: =IF(H38<=0,"never",H39/H38) -> never | I40: =IF(I38<=0,"never",I39/I38) -> 0.20415225 | J40: immediate | K40: immediate | L40: immediate
A41: CAC per customer (₹) | B41: =Assumptions!$D$115*Assumptions!$D$120*(Assumptions!$D$27+Assumptions!$D$28+Assumptions!$D$31) -> 7000 | C41: =Assumptions!$D$115*Assumptions!$D$120 -> 11666.667 | D41: =Assumptions!$D$239 -> 12500 | E41: =0 -> 0 | F41: =Assumptions!$D$214 -> 400 | G41: =Assumptions!$D$239 -> 12500 | H41: =$C$19 -> 2000 | I41: =0 -> 0 | J41: =300 -> 300 | K41: =0 -> 0 | L41: =0 -> 0
A42: LTV per customer, contribution (₹) | B42: =B34 -> 103096.55 | C42: =C34+Assumptions!$D$115*Assumptions!$D$120 -> 58796.61 | D42: =D34+Assumptions!$D$239 -> 31847.458 | E42: n/a | F42: =F34*1.3+Assumptions!$D$214*0.5 -> 1459.3254 | G42: =G34+Assumptions!$D$239 -> 48296.61 | H42: =$C$20*(H30-$C$18-H29*Assumptions!$D$76) -> 695.72881 | I42: n/a (studio enquiries) | J42: =J34*(1+Assumptions!$D$65) -> 9066.9492 | K42: n/a | L42: =L34*2 -> 12547.498
A43: LTV / CAC | B43: =IFERROR(B42/B41,0) -> 14.728078 | C43: =C42/C41 -> 5.0397094 | D43: =D42/D41 -> 2.5477966 | E43: n/a | F43: =F42/F41 -> 3.6483136 | G43: =G42/G41 -> 3.8637288 | H43: =H42/H41 -> 0.34786441 | I43: n/a | J43: =J42/J41 -> 30.223164 | K43: n/a | L43: n/a
A44: Break-even units per year | B44: =IFERROR(B37*100000/B34,0) -> 90.62051 | C44: =$C$5/C34 -> 61.744186 | D44: =D37*100000/D34 -> 5.1686378 | E44: =IFERROR(E37*100000/E34,0) -> 2.5 | F44: =F37*100000/F34 -> 619.37922 | G44: =G37*100000/G34 -> 1.6761364 | H44: =IF(H34<=0,"no break-even",H37*100000/H34) -> no break-even | I44: =I37*100000/I34 -> 40.549828 | J44: =0 -> 0 | K44: =0 -> 0 | L44: =L37*100000/L34 -> 9.5636599
A45: Founder dependence | B45: High -> falling (A-BM-10) | C45: Medium (needs site lead) | D45: Medium | E45: Low for PNA; brand dilution risk high | F45: Medium (founder content) | G45: Medium | H45: Low | I45: Low | J45: High (founder-led ~19-25 days/yr) | K45: Low | L45: Medium
A46: Capital intensity | B46: Low-medium | C46: High | D46: Low | E46: Low (franchisee-funded) | F46: Low | G46: Low (uses flagship seats) | H46: Very high (two-sided, density) | I46: Very low | J46: Very low | K46: Very low | L46: Very low
A47: Verdict (directional) | B47: Core: necessary | C47: Defer to G3a | D47: Pilot after G3a | E47: G3b only | F47: Defer: audience gate | G47: Adopt after G2 | H47: Reject (H5) | I47: Adopt inside flagship | J47: Adopt (founder's future role) | K47: Adopt; kits optional (trust) | L47: Pilot; gate ≥150 alumni
A49: A uses Base Y3 from 3yr_Scenarios (whole academy; 'unit' = career student). Contribution per unit for A is (revenue - variable) / career students, so it includes CPD/online/adjacent lines.
A50: E marketplace: 20% take on a ₹6k AOV leaves ~₹1k per booking before CAC; with ~1.4 bookings per customer LTV/CAC is <1 - confirms H5 (reject).
A52: Ludhiana: four routes compared (BM spec M4; P1 at ₹80k realised) - contribution to PNA per year and 5-year NPV
A53: Metric | B53: (a) Destination to Chandigarh | C53: (b) Partner-hosted satellite | D53: (c) Owned centre | E53: (d) Franchise (1 unit) | F53: Note
A54: Students per year enrolled through this route | B54: =$C$24 -> 10 | C54: =D31 -> 25 | D54: =C31 -> 46 | E54: =C31 -> 46 | F54: destination N_dest vs local-site volume
A55: Contribution per student to PNA (₹) | B55: =G34 -> 35796.61 | C55: =D34 -> 19347.458 | D55: =C34 -> 47129.944 | E55: =E30/C31 -> 13043.478 | F55: franchise = royalty per student
A56: Annual fixed cost to PNA (₹) | B56: =0 -> 0 | C56: =100000 -> 100000 | D56: =$C$5 -> 2910000 | E56: =$C$11 -> 400000
A57: Annual contribution after fixed (₹) | B57: =B54*B55-B56 -> 357966.1 | C57: =C54*C55-C56 -> 383686.44 | D57: =D54*D55-D56 -> -742022.6 | E57: =E54*E55-E56 -> 200000
A58: Upfront capex to PNA (₹) | B58: =0.5*Assumptions!$D$190 -> 175000 | C58: =Assumptions!$D$225 -> 350000 | D58: =$C$6 -> 1650000 | E58: =$C$13-$C$12 -> 300000 | F58: destination shares hybrid content with flagship
A59: 5-year NPV at A-ECO-319 (₹) | B59: =-B58+B57*(1-(1+$C$23)^-5)/$C$23 -> 1024957.9 | C59: =-C58+C57*(1-(1+$C$23)^-5)/$C$23 -> 936176.46 | D59: =-D58+D57*(1-(1+$C$23)^-5)/$C$23 -> -4137374.8 | E59: =-E58+E57*(1-(1+$C$23)^-5)/$C$23 -> 370431.02
A60: Payback (years) | B60: =IFERROR(IF(B57<=0,"never",B58/B57),0) -> 0.48887311 | C60: =IFERROR(IF(C57<=0,"never",C58/C57),0) -> 0.9122032 | D60: =IFERROR(IF(D57<=0,"never",D58/D57),0) -> never | E60: =IFERROR(IF(E57<=0,"never",E58/E57),0) -> 1.5
A61: Break-even students per year | B61: =0 -> 0 | C61: =C56/C55 -> 5.1686378 | D61: =D56/D55 -> 61.744186 | E61: =E56/E55 -> 30.666667 | F61: BM: owned ≈46
A62: Owned centre beats destination only if local enrolments exceed (fixed + N_dest x dest contribution) / owned contribution | D62: =(D56+B54*B55)/D55 -> 69.339487 | F62: BM indifference rule ≈46 + 0.9 x N_dest
A63: Partner satellite beats destination if it enrols more than (x N_dest) | C63: =(C56+B54*B55)/C55/B54 -> 2.3670609 | F63: BM: ≈1.7x
A64: Student all-in cost: fee + living/travel (₹, A-BM-12 mid) | B64: =Assumptions!$D$20+22500 -> 102500 | C64: =Assumptions!$D$20+2500 -> 82500 | D64: =Assumptions!$D$20+2500 -> 82500 | E64: =Assumptions!$D$20+2500 -> 82500 | F64: hybrid stay ₹17-28k; local commute ₹0-5k
A66: Local-site enrolment lift vs destination (x N_dest) -> annual contribution after fixed (₹)
B67: 1 | C67: 1.5 | D67: 2 | E67: 3 | F67: 4.6
A68: Partner-hosted satellite | B68: =B67*$B$54*$C$55-$C$56 -> 93474.576 | C68: =C67*$B$54*$C$55-$C$56 -> 190211.86 | D68: =D67*$B$54*$C$55-$C$56 -> 286949.15 | E68: =E67*$B$54*$C$55-$C$56 -> 480423.73 | F68: =F67*$B$54*$C$55-$C$56 -> 789983.05
A69: Owned centre | B69: =B67*$B$54*$D$55-$D$56 -> -2438700.6 | C69: =C67*$B$54*$D$55-$D$56 -> -2203050.8 | D69: =D67*$B$54*$D$55-$D$56 -> -1967401.1 | E69: =E67*$B$54*$D$55-$D$56 -> -1496101.7 | F69: =F67*$B$54*$D$55-$D$56 -> -742022.6
A70: Destination (reference) | B70: =$B$57 -> 357966.1 | C70: =$B$57 -> 357966.1 | D70: =$B$57 -> 357966.1 | E70: =$B$57 -> 357966.1 | F70: =$B$57 -> 357966.1

Sheet Capacity
A1: Capacity: stations, batch slots, trainers and founder hours (Selected scenario)
A4: Metric | B4: Today's Sector 8 space | C4: New academy space (plan) | D4: Notes
A5: Stations | B5: =Assumptions!$I$171 -> 8 | C5: =MAX(Assumptions!$I$176,Assumptions!$I$171) -> 12 | D5: A-ECO-110 / 115 (founder to confirm today's count)
A6: Batch slots per day | B6: =Assumptions!$I$172 -> 2 | C6: =Assumptions!$I$177 -> 2.5 | D6: morning / afternoon (+ weekend/flex)
A7: Seat capacity (concurrent students) | B7: =B5*B6 -> 16 | C7: =C5*C6 -> 30
A8: Usable seat-months per month (x A-ECO-117) | B8: =B7*Assumptions!$I$178 -> 14.4 | C8: =C7*Assumptions!$I$178 -> 27
A9: Max new L3 students per year if seats held 3 months | B9: =B8*12/Assumptions!$I$103 -> 57.6 | C9: =C8*12/Assumptions!$I$103 -> 108 | D9: upper bound with no L2/destination/hybrid
A10: Seat-months needed per year at A-GRO-01 (L3 x3 + L2 x1) | B10: =Assumptions!$I$25*12*(Assumptions!$I$26*Assumptions!$I$103+(1-Assumptions!$I$26)) -> 264 | C10: =B10 -> 264
A11: Utilisation at A-GRO-01 steady state | B11: =B10/(B8*12) -> 1.5277778 | C11: =C10/(C8*12) -> 0.81481481 | D11: >100% = target does not fit
A12: Batch-slots active at A-GRO-01 (seat-months/12 / cohort fill) | B12: =B10/12/Assumptions!$I$102 -> 2.2 | C12: =B12 -> 2.2
A13: Trainer FTE needed at month-12 founder share (A-BM-10b) | B13: =B12*(1-Assumptions!$I$158)/Assumptions!$I$101 -> 0.77 | C13: =B13 -> 0.77 | D13: slots one FTE leads: A-ECO-46
A14: Founder contact hours per month at month 12 (slots x 4 h x 22 days x share) | B14: =B12*4*22*Assumptions!$I$158 -> 58.08 | C14: =B14 -> 58.08 | D14: plus masterclasses ~19-25 days/yr (A-BM-05)
A15: Rent per month | B15: =Assumptions!$I$179 -> 35000 | C15: =Assumptions!$I$174*Assumptions!$I$175 -> 104000 | D15: S-CHD-22 bands; today's share unknown
A16: Rent per usable seat-month | B16: =B15/B8 -> 2430.5556 | C16: =IFERROR(C15/C8,0) -> 3851.8519
A17: First month seat capacity binds (Base outlook) | B17: =Outlook_Base!B121 -> 6 | D17: drives the move decision (A-ECO-112)

Sheet Sensitivity
A1: Sensitivity - tornado on Base Year-1 EBITDA and peak cash need (each row = full monthly model re-run, Flex_* sheets)
A2: Low/high are 'adverse'/'favourable' settings of one driver; all else at Base. Bars are text-based so they render anywhere.
A4: Driver | B4: Adverse setting | C4: Favourable setting | D4: EBITDA adverse | E4: EBITDA favourable | F4: EBITDA swing | G4: Rank | H4: Peak cash adverse | I4: Peak cash favourable | J4: Career enrol. adverse | K4: Career enrol. favourable | L4: Tornado (EBITDA swing)
A5: Base case | D5: =Outlook_Base!B110 -> 551465.51 | E5: =Outlook_Base!B110 -> 551465.51 | H5: =Outlook_Base!B114 -> 2614223.5 | J5: =Outlook_Base!B117 -> 89.450184
A6: Conversion (all routes; low = founder step-back ÷1.25) | B6: x0.8 | C6: x1.2 | D6: =Flex_conv_lo!B110 -> -309678.67 | E6: =Flex_conv_hi!B110 -> 1084295.9 | F6: =ABS(E6-D6) -> 1393974.6 | G6: =RANK(F6,$F$6:$F$13) -> 2 | H6: =Flex_conv_lo!B114 -> 2982142.8 | I6: =Flex_conv_hi!B114 -> 2450758.6 | J6: =Flex_conv_lo!B117 -> 78.574564 | K6: =Flex_conv_hi!B117 -> 93.217769 | L6: =REPT("█",ROUND(F6/MAX($F$6:$F$13)*30,0)) -> ██████████████████
A7: Fees (all products) | B7: x0.8 | C7: x1.15 | D7: =Flex_fee_lo!B110 -> -768284.12 | E7: =Flex_fee_hi!B110 -> 1541277.7 | F7: =ABS(E7-D7) -> 2309561.8 | G7: =RANK(F7,$F$6:$F$13) -> 1 | H7: =Flex_fee_lo!B114 -> 3182607.4 | I7: =Flex_fee_hi!B114 -> 2381836.4 | J7: =Flex_fee_lo!B117 -> 89.450184 | K7: =Flex_fee_hi!B117 -> 89.450184 | L7: =REPT("█",ROUND(F7/MAX($F$6:$F$13)*30,0)) -> ██████████████████████████████
A8: Cohort fill (students per batch 8 vs 12) | B8: x0.8 | C8: x1.2 | D8: =Flex_fill_lo!B110 -> 361465.51 | E8: =Flex_fill_hi!B110 -> 569465.51 | F8: =ABS(E8-D8) -> 208000 | G8: =RANK(F8,$F$6:$F$13) -> 7 | H8: =Flex_fill_lo!B114 -> 2614223.5 | I8: =Flex_fill_hi!B114 -> 2614223.5 | J8: =Flex_fill_lo!B117 -> 89.450184 | K8: =Flex_fill_hi!B117 -> 89.450184 | L8: =REPT("█",ROUND(F8/MAX($F$6:$F$13)*30,0)) -> ███
A9: CPL / CAC (paid routes) | B9: x1.3 | C9: x0.7 | D9: =Flex_cpl_lo!B110 -> 257393.29 | E9: =Flex_cpl_hi!B110 -> 560556.78 | F9: =ABS(E9-D9) -> 303163.49 | G9: =RANK(F9,$F$6:$F$13) -> 6 | H9: =Flex_cpl_lo!B114 -> 2714928.2 | I9: =Flex_cpl_hi!B114 -> 2603498.7 | J9: =Flex_cpl_lo!B117 -> 82.814132 | K9: =Flex_cpl_hi!B117 -> 89.737143 | L9: =REPT("█",ROUND(F9/MAX($F$6:$F$13)*30,0)) -> ████
A10: Variable delivery cost (kit, consumables) | B10: x1.25 | C10: x0.75 | D10: =Flex_var_lo!B110 -> 334613.94 | E10: =Flex_var_hi!B110 -> 768317.08 | F10: =ABS(E10-D10) -> 433703.14 | G10: =RANK(F10,$F$6:$F$13) -> 5 | H10: =Flex_var_lo!B114 -> 2706012.4 | I10: =Flex_var_hi!B114 -> 2522434.6 | J10: =Flex_var_lo!B117 -> 89.450184 | K10: =Flex_var_hi!B117 -> 89.450184 | L10: =REPT("█",ROUND(F10/MAX($F$6:$F$13)*30,0)) -> ██████
A11: Rent (₹130 vs ₹47 per sq ft vs ₹80) | B11: x1.625 | C11: x0.5875 | D11: =Flex_rent_lo!B110 -> 30215.51 | E11: =Flex_rent_hi!B110 -> 895490.51 | F11: =ABS(E11-D11) -> 865275 | G11: =RANK(F11,$F$6:$F$13) -> 4 | H11: =Flex_rent_lo!B114 -> 3014947.8 | I11: =Flex_rent_hi!B114 -> 2398898.5 | J11: =Flex_rent_lo!B117 -> 89.450184 | K11: =Flex_rent_hi!B117 -> 89.450184 | L11: =REPT("█",ROUND(F11/MAX($F$6:$F$13)*30,0)) -> ███████████
A12: Paid-media budget (holding the target) | B12: x0.7 | C12: x1.3 | D12: =Flex_budget_lo!B110 -> 424303.52 | E12: =Flex_budget_hi!B110 -> 277788.99 | F12: =ABS(E12-D12) -> 146514.52 | G12: =RANK(F12,$F$6:$F$13) -> 8 | H12: =Flex_budget_lo!B114 -> 2606698.7 | I12: =Flex_budget_hi!B114 -> 2711548.9 | J12: =Flex_budget_lo!B117 -> 80.320092 | K12: =Flex_budget_hi!B117 -> 89.665956 | L12: =REPT("█",ROUND(F12/MAX($F$6:$F$13)*30,0)) -> ██
A13: GST charged on top of list fees (vs absorbed in quoted fee) | B13: incl. (base) | C13: on top | D13: =Outlook_Base!B110 -> 551465.51 | E13: =Flex_gst_ontop!B110 -> 1825432.9 | F13: =ABS(E13-D13) -> 1273967.4 | G13: =RANK(F13,$F$6:$F$13) -> 3 | H13: =Outlook_Base!B114 -> 2614223.5 | I13: =Flex_gst_ontop!B114 -> 2317977.9 | J13: =Outlook_Base!B117 -> 89.450184 | K13: =Flex_gst_ontop!B117 -> 89.450184 | L13: =REPT("█",ROUND(F13/MAX($F$6:$F$13)*30,0)) -> █████████████████
A15: Conversion low (x0.8) doubles as the BM founder step-back stress (team-led conversion = founder-led ÷1.25, A-GRO-25). Fee low (x0.8) ≈ BM price stress (₹80k -> ₹64k realised).
A16: Budget rows hold the enrolment target: a smaller budget buys fewer paid enrolments; a larger one cannot exceed the plan target (A-GRO-01) or seat capacity.
A19: Unit tornado: contribution after CAC per paid L3 student (post price-step, Base) - one driver at a time
A20: Driver | B20: Adverse | C20: Favourable | D20: Contribution adverse | E20: Contribution favourable | F20: Swing
A21: Realised L3 fee ₹64k / ₹92k (x0.8 / x1.15) | B21: x0.8 | C21: x1.15 | D21: =(Assumptions!$D$20*0.8)/(1+Assumptions!$D$15*Assumptions!$D$16)-Assumptions!$D$91-Assumptions!$D$103*(Assumptions!$D$99+Assumptions!$D$100)/Assumptions!$D$101/Assumptions!$D$102-(Assumptions!$D$20*0.8)*Assumptions!$D$70*Assumptions!$D$71-(Assumptions!$D$20*0.8)*Assumptions!$D$76-Assumptions!$D$115*Assumptions!$D$120 -> 25770.621 | E21: =(Assumptions!$D$20*1.15)/(1+Assumptions!$D$15*Assumptions!$D$16)-Assumptions!$D$91-Assumptions!$D$103*(Assumptions!$D$99+Assumptions!$D$100)/Assumptions!$D$101/Assumptions!$D$102-(Assumptions!$D$20*1.15)*Assumptions!$D$70*Assumptions!$D$71-(Assumptions!$D$20*1.15)*Assumptions!$D$76-Assumptions!$D$115*Assumptions!$D$120 -> 48449.435 | F21: =ABS(E21-D21) -> 22678.814
A22: Cohort fill 8 / 12 students | B22: x0.8 | C22: x1.2 | D22: =Assumptions!$D$20/(1+Assumptions!$D$15*Assumptions!$D$16)-Assumptions!$D$91-Assumptions!$D$103*(Assumptions!$D$99+Assumptions!$D$100)/Assumptions!$D$101/(Assumptions!$D$102*0.8)-Assumptions!$D$20*Assumptions!$D$70*Assumptions!$D$71-Assumptions!$D$20*Assumptions!$D$76-Assumptions!$D$115*Assumptions!$D$120 -> 36629.944 | E22: =Assumptions!$D$20/(1+Assumptions!$D$15*Assumptions!$D$16)-Assumptions!$D$91-Assumptions!$D$103*(Assumptions!$D$99+Assumptions!$D$100)/Assumptions!$D$101/(Assumptions!$D$102*1.2)-Assumptions!$D$20*Assumptions!$D$70*Assumptions!$D$71-Assumptions!$D$20*Assumptions!$D$76-Assumptions!$D$115*Assumptions!$D$120 -> 40129.944 | F22: =ABS(E22-D22) -> 3500
A23: Effective paid CAC per paid student x1.3 / x0.7 | B23: x1.3 | C23: x0.7 | D23: =Assumptions!$D$20/(1+Assumptions!$D$15*Assumptions!$D$16)-Assumptions!$D$91-Assumptions!$D$103*(Assumptions!$D$99+Assumptions!$D$100)/Assumptions!$D$101/Assumptions!$D$102-Assumptions!$D$20*Assumptions!$D$70*Assumptions!$D$71-Assumptions!$D$20*Assumptions!$D$76-(Assumptions!$D$115*Assumptions!$D$120*1.3) -> 35229.944 | E23: =Assumptions!$D$20/(1+Assumptions!$D$15*Assumptions!$D$16)-Assumptions!$D$91-Assumptions!$D$103*(Assumptions!$D$99+Assumptions!$D$100)/Assumptions!$D$101/Assumptions!$D$102-Assumptions!$D$20*Assumptions!$D$70*Assumptions!$D$71-Assumptions!$D$20*Assumptions!$D$76-(Assumptions!$D$115*Assumptions!$D$120*0.7) -> 42229.944 | F23: =ABS(E23-D23) -> 7000
A24: Consumables x1.25 / x0.75 | B24: x1.25 | C24: x0.75 | D24: =Assumptions!$D$20/(1+Assumptions!$D$15*Assumptions!$D$16)-(Assumptions!$D$91*1.25)-Assumptions!$D$103*(Assumptions!$D$99+Assumptions!$D$100)/Assumptions!$D$101/Assumptions!$D$102-Assumptions!$D$20*Assumptions!$D$70*Assumptions!$D$71-Assumptions!$D$20*Assumptions!$D$76-Assumptions!$D$115*Assumptions!$D$120 -> 37229.944 | E24: =Assumptions!$D$20/(1+Assumptions!$D$15*Assumptions!$D$16)-(Assumptions!$D$91*0.75)-Assumptions!$D$103*(Assumptions!$D$99+Assumptions!$D$100)/Assumptions!$D$101/Assumptions!$D$102-Assumptions!$D$20*Assumptions!$D$70*Assumptions!$D$71-Assumptions!$D$20*Assumptions!$D$76-Assumptions!$D$115*Assumptions!$D$120 -> 40229.944 | F24: =ABS(E24-D24) -> 3000
A25: EMI subvention 7% / 3% | B25: x1.4 | C25: x0.6 | D25: =Assumptions!$D$20/(1+Assumptions!$D$15*Assumptions!$D$16)-Assumptions!$D$91-Assumptions!$D$103*(Assumptions!$D$99+Assumptions!$D$100)/Assumptions!$D$101/Assumptions!$D$102-Assumptions!$D$20*Assumptions!$D$70*(Assumptions!$D$71*1.4)-Assumptions!$D$20*Assumptions!$D$76-Assumptions!$D$115*Assumptions!$D$120 -> 38169.944 | E25: =Assumptions!$D$20/(1+Assumptions!$D$15*Assumptions!$D$16)-Assumptions!$D$91-Assumptions!$D$103*(Assumptions!$D$99+Assumptions!$D$100)/Assumptions!$D$101/Assumptions!$D$102-Assumptions!$D$20*Assumptions!$D$70*(Assumptions!$D$71*0.6)-Assumptions!$D$20*Assumptions!$D$76-Assumptions!$D$115*Assumptions!$D$120 -> 39289.944 | F25: =ABS(E25-D25) -> 1120
A26: Base contribution after CAC per L3 student | D26: =Assumptions!$D$20/(1+Assumptions!$D$15*Assumptions!$D$16)-Assumptions!$D$91-Assumptions!$D$103*(Assumptions!$D$99+Assumptions!$D$100)/Assumptions!$D$101/Assumptions!$D$102-Assumptions!$D$20*Assumptions!$D$70*Assumptions!$D$71-Assumptions!$D$20*Assumptions!$D$76-Assumptions!$D$115*Assumptions!$D$120 -> 38729.944

Sheet Outlook_Conservative
A1: 12-month operating outlook - Conservative (adverse rates, ₹10L plan) (₹, ex-GST, Nov-2026 to Oct-2027)
A2: Cash/booking basis. Enrolments follow the Growth plan target (A-GRO-01) limited by what the paid budget can buy and by seat capacity. Blue cells in rows 3-4 are flex switches used by Sensitivity.
A3: Rate index (1 Cons / 2 Base / 3 Aggr) | B3: 1 | C3: Plan index | D3: 1 | E3: conv x | F3: 1 | G3: fee x | H3: 1 | I3: fill x | J3: 1 | K3: CPL x | L3: 1 | M3: var cost x | N3: 1
E4: rent x | F4: 1 | G4: GST incl.? | H4: =INDEX(Assumptions!$C$16:$E$16,$B$3) -> 1 | I4: budget x | J4: 1
A5: Line | B5: Note | C5: Nov-26 | D5: Dec-26 | E5: Jan-27 | F5: Feb-27 | G5: Mar-27 | H5: Apr-27 | I5: May-27 | J5: Jun-27 | K5: Jul-27 | L5: Aug-27 | M5: Sep-27 | N5: Oct-27 | O5: Year 1 | P5: Basis / IDs
A6: A. Timeline
A7: Month # | C7: =1 -> 1 | D7: =2 -> 2 | E7: =3 -> 3 | F7: =4 -> 4 | G7: =5 -> 5 | H7: =6 -> 6 | I7: =7 -> 7 | J7: =8 -> 8 | K7: =9 -> 9 | L7: =10 -> 10 | M7: =11 -> 11 | N7: =12 -> 12
A8: Calendar month number | C8: =MOD(C7+9,12)+1 -> 11 | D8: =MOD(D7+9,12)+1 -> 12 | E8: =MOD(E7+9,12)+1 -> 1 | F8: =MOD(F7+9,12)+1 -> 2 | G8: =MOD(G7+9,12)+1 -> 3 | H8: =MOD(H7+9,12)+1 -> 4 | I8: =MOD(I7+9,12)+1 -> 5 | J8: =MOD(J7+9,12)+1 -> 6 | ... N8: =MOD(N7+9,12)+1 -> 10
A9: Career-enquiry seasonality (A-GRO-40) | C9: =INDEX(Assumptions!$D$133:$D$144,C8) -> 0.8 | D9: =INDEX(Assumptions!$D$133:$D$144,D8) -> 0.75 | E9: =INDEX(Assumptions!$D$133:$D$144,E8) -> 0.7 | F9: =INDEX(Assumptions!$D$133:$D$144,F8) -> 0.8 | G9: =INDEX(Assumptions!$D$133:$D$144,G8) -> 0.9 | H9: =INDEX(Assumptions!$D$133:$D$144,H8) -> 1 | I9: =INDEX(Assumptions!$D$133:$D$144,I8) -> 1.3 | J9: =INDEX(Assumptions!$D$133:$D$144,J8) -> 1.35 | ... N9: =INDEX(Assumptions!$D$133:$D$144,N8) -> 1 | O9: =AVERAGE(C9:N9) -> 1
A10: Self-makeup seasonality (A-ECO-60) | C10: =INDEX(Assumptions!$D$145:$D$156,C8) -> 1.4 | D10: =INDEX(Assumptions!$D$145:$D$156,D8) -> 1.2 | E10: =INDEX(Assumptions!$D$145:$D$156,E8) -> 1.2 | F10: =INDEX(Assumptions!$D$145:$D$156,F8) -> 1.3 | G10: =INDEX(Assumptions!$D$145:$D$156,G8) -> 0.9 | H10: =INDEX(Assumptions!$D$145:$D$156,H8) -> 0.8 | I10: =INDEX(Assumptions!$D$145:$D$156,I8) -> 0.7 | J10: =INDEX(Assumptions!$D$145:$D$156,J8) -> 0.6 | ... N10: =INDEX(Assumptions!$D$145:$D$156,N8) -> 1.4 | O10: =AVERAGE(C10:N10) -> 1
A11: Founder share of contact hours (A-BM-10 path) | C11: =IF(1<=6,1-(1-INDEX(Assumptions!$C$157:$E$157,$D$3))*1/6,INDEX(Assumptions!$C$157:$E$157,$D$3)-(INDEX(Assumptions!$C$157:$E$157,$D$3)-INDEX(Assumptions!$C$158:$E$158,$D$3))*(1-6)/6) -> 0.93333333 | D11: =IF(2<=6,1-(1-INDEX(Assumptions!$C$157:$E$157,$D$3))*2/6,INDEX(Assumptions!$C$157:$E$157,$D$3)-(INDEX(Assumptions!$C$157:$E$157,$D$3)-INDEX(Assumptions!$C$158:$E$158,$D$3))*(2-6)/6) -> 0.86666667 | E11: =IF(3<=6,1-(1-INDEX(Assumptions!$C$157:$E$157,$D$3))*3/6,INDEX(Assumptions!$C$157:$E$157,$D$3)-(INDEX(Assumptions!$C$157:$E$157,$D$3)-INDEX(Assumptions!$C$158:$E$158,$D$3))*(3-6)/6) -> 0.8 | F11: =IF(4<=6,1-(1-INDEX(Assumptions!$C$157:$E$157,$D$3))*4/6,INDEX(Assumptions!$C$157:$E$157,$D$3)-(INDEX(Assumptions!$C$157:$E$157,$D$3)-INDEX(Assumptions!$C$158:$E$158,$D$3))*(4-6)/6) -> 0.73333333 | G11: =IF(5<=6,1-(1-INDEX(Assumptions!$C$157:$E$157,$D$3))*5/6,INDEX(Assumptions!$C$157:$E$157,$D$3)-(INDEX(Assumptions!$C$157:$E$157,$D$3)-INDEX(Assumptions!$C$158:$E$158,$D$3))*(5-6)/6) -> 0.66666667 | H11: =IF(6<=6,1-(1-INDEX(Assumptions!$C$157:$E$157,$D$3))*6/6,INDEX(Assumptions!$C$157:$E$157,$D$3)-(INDEX(Assumptions!$C$157:$E$157,$D$3)-INDEX(Assumptions!$C$158:$E$158,$D$3))*(6-6)/6) -> 0.6 | I11: =IF(7<=6,1-(1-INDEX(Assumptions!$C$157:$E$157,$D$3))*7/6,INDEX(Assumptions!$C$157:$E$157,$D$3)-(INDEX(Assumptions!$C$157:$E$157,$D$3)-INDEX(Assumptions!$C$158:$E$158,$D$3))*(7-6)/6) -> 0.56666667 | J11: =IF(8<=6,1-(1-INDEX(Assumptions!$C$157:$E$157,$D$3))*8/6,INDEX(Assumptions!$C$157:$E$157,$D$3)-(INDEX(Assumptions!$C$157:$E$157,$D$3)-INDEX(Assumptions!$C$158:$E$158,$D$3))*(8-6)/6) -> 0.53333333 | K11: =IF(9<=6,1-(1-INDEX(Assumptions!$C$157:$E$157,$D$3))*9/6,INDEX(Assumptions!$C$157:$E$157,$D$3)-(INDEX(Assumptions!$C$157:$E$157,$D$3)-INDEX(Assumptions!$C$158:$E$158,$D$3))*(9-6)/6) -> 0.5 | L11: =IF(10<=6,1-(1-INDEX(Assumptions!$C$157:$E$157,$D$3))*10/6,INDEX(Assumptions!$C$157:$E$157,$D$3)-(INDEX(Assumptions!$C$157:$E$157,$D$3)-INDEX(Assumptions!$C$158:$E$158,$D$3))*(10-6)/6) -> 0.46666667 | M11: =IF(11<=6,1-(1-INDEX(Assumptions!$C$157:$E$157,$D$3))*11/6,INDEX(Assumptions!$C$157:$E$157,$D$3)-(INDEX(Assumptions!$C$157:$E$157,$D$3)-INDEX(Assumptions!$C$158:$E$158,$D$3))*(11-6)/6) -> 0.43333333 | N11: =IF(12<=6,1-(1-INDEX(Assumptions!$C$157:$E$157,$D$3))*12/6,INDEX(Assumptions!$C$157:$E$157,$D$3)-(INDEX(Assumptions!$C$157:$E$157,$D$3)-INDEX(Assumptions!$C$158:$E$158,$D$3))*(12-6)/6) -> 0.4 | O11: =N11 -> 0.4
A12: B. Career enrolments (L2 + L3) - demand, budget and capacity
A13: Today's career enrolments per month (CA-01 x A-ECO-101 / 12) - illustrative | C13: =INDEX(Assumptions!$C$9:$E$9,$B$3)*INDEX(Assumptions!$C$12:$E$12,$B$3)/12 -> 1.5 | D13: =INDEX(Assumptions!$C$9:$E$9,$B$3)*INDEX(Assumptions!$C$12:$E$12,$B$3)/12 -> 1.5 | E13: =INDEX(Assumptions!$C$9:$E$9,$B$3)*INDEX(Assumptions!$C$12:$E$12,$B$3)/12 -> 1.5 | F13: =INDEX(Assumptions!$C$9:$E$9,$B$3)*INDEX(Assumptions!$C$12:$E$12,$B$3)/12 -> 1.5 | G13: =INDEX(Assumptions!$C$9:$E$9,$B$3)*INDEX(Assumptions!$C$12:$E$12,$B$3)/12 -> 1.5 | H13: =INDEX(Assumptions!$C$9:$E$9,$B$3)*INDEX(Assumptions!$C$12:$E$12,$B$3)/12 -> 1.5 | I13: =INDEX(Assumptions!$C$9:$E$9,$B$3)*INDEX(Assumptions!$C$12:$E$12,$B$3)/12 -> 1.5 | J13: =INDEX(Assumptions!$C$9:$E$9,$B$3)*INDEX(Assumptions!$C$12:$E$12,$B$3)/12 -> 1.5 | ... N13: =INDEX(Assumptions!$C$9:$E$9,$B$3)*INDEX(Assumptions!$C$12:$E$12,$B$3)/12 -> 1.5 | O13: =SUM(C13:N13) -> 18
A14: Plan target path (ramps to A-GRO-01 by month 7) | C14: =C13+(INDEX(Assumptions!$C$25:$E$25,$D$3)-C13)*MIN(1,(1-1)/6) -> 1.5 | D14: =D13+(INDEX(Assumptions!$C$25:$E$25,$D$3)-D13)*MIN(1,(2-1)/6) -> 2.25 | E14: =E13+(INDEX(Assumptions!$C$25:$E$25,$D$3)-E13)*MIN(1,(3-1)/6) -> 3 | F14: =F13+(INDEX(Assumptions!$C$25:$E$25,$D$3)-F13)*MIN(1,(4-1)/6) -> 3.75 | G14: =G13+(INDEX(Assumptions!$C$25:$E$25,$D$3)-G13)*MIN(1,(5-1)/6) -> 4.5 | H14: =H13+(INDEX(Assumptions!$C$25:$E$25,$D$3)-H13)*MIN(1,(6-1)/6) -> 5.25 | I14: =I13+(INDEX(Assumptions!$C$25:$E$25,$D$3)-I13)*MIN(1,(7-1)/6) -> 6 | J14: =J13+(INDEX(Assumptions!$C$25:$E$25,$D$3)-J13)*MIN(1,(8-1)/6) -> 6 | K14: =K13+(INDEX(Assumptions!$C$25:$E$25,$D$3)-K13)*MIN(1,(9-1)/6) -> 6 | L14: =L13+(INDEX(Assumptions!$C$25:$E$25,$D$3)-L13)*MIN(1,(10-1)/6) -> 6 | M14: =M13+(INDEX(Assumptions!$C$25:$E$25,$D$3)-M13)*MIN(1,(11-1)/6) -> 6 | N14: =N13+(INDEX(Assumptions!$C$25:$E$25,$D$3)-N13)*MIN(1,(12-1)/6) -> 6 | O14: =SUM(C14:N14) -> 56.25
A15: Paid media budget (Growth ramp) | C15: =INDEX(Assumptions!$C$121:$E$121,$D$3)*$J$4 -> 10000 | D15: =INDEX(Assumptions!$C$122:$E$122,$D$3)*$J$4 -> 25000 | E15: =INDEX(Assumptions!$C$123:$E$123,$D$3)*$J$4 -> 30000 | F15: =INDEX(Assumptions!$C$124:$E$124,$D$3)*$J$4 -> 35000 | G15: =INDEX(Assumptions!$C$125:$E$125,$D$3)*$J$4 -> 40000 | H15: =INDEX(Assumptions!$C$126:$E$126,$D$3)*$J$4 -> 40000 | I15: =INDEX(Assumptions!$C$127:$E$127,$D$3)*$J$4 -> 40000 | J15: =INDEX(Assumptions!$C$128:$E$128,$D$3)*$J$4 -> 40000 | K15: =INDEX(Assumptions!$C$129:$E$129,$D$3)*$J$4 -> 40000 | L15: =INDEX(Assumptions!$C$130:$E$130,$D$3)*$J$4 -> 40000 | M15: =INDEX(Assumptions!$C$131:$E$131,$D$3)*$J$4 -> 40000 | N15: =INDEX(Assumptions!$C$132:$E$132,$D$3)*$J$4 -> 40000 | O15: =SUM(C15:N15) -> 420000 | P15: A-GRO-BUD-01..12
A16: Effective paid CAC = funnel paid CAC x overhead factor x CPL flex / conversion flex | C16: =INDEX(Assumptions!$C$115:$E$115,$B$3)*INDEX(Assumptions!$C$120:$E$120,$B$3)*$L$3/$F$3 -> 40323.249 | D16: =INDEX(Assumptions!$C$115:$E$115,$B$3)*INDEX(Assumptions!$C$120:$E$120,$B$3)*$L$3/$F$3 -> 40323.249 | E16: =INDEX(Assumptions!$C$115:$E$115,$B$3)*INDEX(Assumptions!$C$120:$E$120,$B$3)*$L$3/$F$3 -> 40323.249 | F16: =INDEX(Assumptions!$C$115:$E$115,$B$3)*INDEX(Assumptions!$C$120:$E$120,$B$3)*$L$3/$F$3 -> 40323.249 | G16: =INDEX(Assumptions!$C$115:$E$115,$B$3)*INDEX(Assumptions!$C$120:$E$120,$B$3)*$L$3/$F$3 -> 40323.249 | H16: =INDEX(Assumptions!$C$115:$E$115,$B$3)*INDEX(Assumptions!$C$120:$E$120,$B$3)*$L$3/$F$3 -> 40323.249 | I16: =INDEX(Assumptions!$C$115:$E$115,$B$3)*INDEX(Assumptions!$C$120:$E$120,$B$3)*$L$3/$F$3 -> 40323.249 | J16: =INDEX(Assumptions!$C$115:$E$115,$B$3)*INDEX(Assumptions!$C$120:$E$120,$B$3)*$L$3/$F$3 -> 40323.249 | ... N16: =INDEX(Assumptions!$C$115:$E$115,$B$3)*INDEX(Assumptions!$C$120:$E$120,$B$3)*$L$3/$F$3 -> 40323.249 | O16: =AVERAGE(C16:N16) -> 40323.249
A17: Speed-to-lead factor (A-GRO-24 on CTWA/Search/Organic before SLA month) | C17: =IF(1>=INDEX(Assumptions!$C$106:$E$106,$D$3),1,1-(INDEX(Assumptions!$C$27:$E$27,$B$3)+INDEX(Assumptions!$C$28:$E$28,$B$3)+INDEX(Assumptions!$C$29:$E$29,$B$3))*(1-INDEX(Assumptions!$C$59:$E$59,$B$3))) -> 0.65 | D17: =IF(2>=INDEX(Assumptions!$C$106:$E$106,$D$3),1,1-(INDEX(Assumptions!$C$27:$E$27,$B$3)+INDEX(Assumptions!$C$28:$E$28,$B$3)+INDEX(Assumptions!$C$29:$E$29,$B$3))*(1-INDEX(Assumptions!$C$59:$E$59,$B$3))) -> 0.65 | E17: =IF(3>=INDEX(Assumptions!$C$106:$E$106,$D$3),1,1-(INDEX(Assumptions!$C$27:$E$27,$B$3)+INDEX(Assumptions!$C$28:$E$28,$B$3)+INDEX(Assumptions!$C$29:$E$29,$B$3))*(1-INDEX(Assumptions!$C$59:$E$59,$B$3))) -> 0.65 | F17: =IF(4>=INDEX(Assumptions!$C$106:$E$106,$D$3),1,1-(INDEX(Assumptions!$C$27:$E$27,$B$3)+INDEX(Assumptions!$C$28:$E$28,$B$3)+INDEX(Assumptions!$C$29:$E$29,$B$3))*(1-INDEX(Assumptions!$C$59:$E$59,$B$3))) -> 1 | G17: =IF(5>=INDEX(Assumptions!$C$106:$E$106,$D$3),1,1-(INDEX(Assumptions!$C$27:$E$27,$B$3)+INDEX(Assumptions!$C$28:$E$28,$B$3)+INDEX(Assumptions!$C$29:$E$29,$B$3))*(1-INDEX(Assumptions!$C$59:$E$59,$B$3))) -> 1 | H17: =IF(6>=INDEX(Assumptions!$C$106:$E$106,$D$3),1,1-(INDEX(Assumptions!$C$27:$E$27,$B$3)+INDEX(Assumptions!$C$28:$E$28,$B$3)+INDEX(Assumptions!$C$29:$E$29,$B$3))*(1-INDEX(Assumptions!$C$59:$E$59,$B$3))) -> 1 | I17: =IF(7>=INDEX(Assumptions!$C$106:$E$106,$D$3),1,1-(INDEX(Assumptions!$C$27:$E$27,$B$3)+INDEX(Assumptions!$C$28:$E$28,$B$3)+INDEX(Assumptions!$C$29:$E$29,$B$3))*(1-INDEX(Assumptions!$C$59:$E$59,$B$3))) -> 1 | J17: =IF(8>=INDEX(Assumptions!$C$106:$E$106,$D$3),1,1-(INDEX(Assumptions!$C$27:$E$27,$B$3)+INDEX(Assumptions!$C$28:$E$28,$B$3)+INDEX(Assumptions!$C$29:$E$29,$B$3))*(1-INDEX(Assumptions!$C$59:$E$59,$B$3))) -> 1 | K17: =IF(9>=INDEX(Assumptions!$C$106:$E$106,$D$3),1,1-(INDEX(Assumptions!$C$27:$E$27,$B$3)+INDEX(Assumptions!$C$28:$E$28,$B$3)+INDEX(Assumptions!$C$29:$E$29,$B$3))*(1-INDEX(Assumptions!$C$59:$E$59,$B$3))) -> 1 | L17: =IF(10>=INDEX(Assumptions!$C$106:$E$106,$D$3),1,1-(INDEX(Assumptions!$C$27:$E$27,$B$3)+INDEX(Assumptions!$C$28:$E$28,$B$3)+INDEX(Assumptions!$C$29:$E$29,$B$3))*(1-INDEX(Assumptions!$C$59:$E$59,$B$3))) -> 1 | M17: =IF(11>=INDEX(Assumptions!$C$106:$E$106,$D$3),1,1-(INDEX(Assumptions!$C$27:$E$27,$B$3)+INDEX(Assumptions!$C$28:$E$28,$B$3)+INDEX(Assumptions!$C$29:$E$29,$B$3))*(1-INDEX(Assumptions!$C$59:$E$59,$B$3))) -> 1 | N17: =IF(12>=INDEX(Assumptions!$C$106:$E$106,$D$3),1,1-(INDEX(Assumptions!$C$27:$E$27,$B$3)+INDEX(Assumptions!$C$28:$E$28,$B$3)+INDEX(Assumptions!$C$29:$E$29,$B$3))*(1-INDEX(Assumptions!$C$59:$E$59,$B$3))) -> 1 | O17: =AVERAGE(C17:N17) -> 0.9125
A18: Paid career enrolments the budget can buy | C18: =C15*INDEX(Assumptions!$C$119:$E$119,$B$3)/C16 -> 0.17359712 | D18: =D15*INDEX(Assumptions!$C$119:$E$119,$B$3)/D16 -> 0.43399281 | E18: =E15*INDEX(Assumptions!$C$119:$E$119,$B$3)/E16 -> 0.52079137 | F18: =F15*INDEX(Assumptions!$C$119:$E$119,$B$3)/F16 -> 0.60758993 | G18: =G15*INDEX(Assumptions!$C$119:$E$119,$B$3)/G16 -> 0.69438849 | H18: =H15*INDEX(Assumptions!$C$119:$E$119,$B$3)/H16 -> 0.69438849 | I18: =I15*INDEX(Assumptions!$C$119:$E$119,$B$3)/I16 -> 0.69438849 | J18: =J15*INDEX(Assumptions!$C$119:$E$119,$B$3)/J16 -> 0.69438849 | ... N18: =N15*INDEX(Assumptions!$C$119:$E$119,$B$3)/N16 -> 0.69438849 | O18: =SUM(C18:N18) -> 7.2910791
A19: Career demand = seasonality x SLA x (non-paid share x target x conv + MIN(paid share x target, budget-bought)) | C19: =C9*C17*((1-(INDEX(Assumptions!$C$27:$E$27,$B$3)+INDEX(Assumptions!$C$28:$E$28,$B$3)+INDEX(Assumptions!$C$31:$E$31,$B$3)))*C14*$F$3+MIN((INDEX(Assumptions!$C$27:$E$27,$B$3)+INDEX(Assumptions!$C$28:$E$28,$B$3)+INDEX(Assumptions!$C$31:$E$31,$B$3))*C14,C18)) -> 0.4022705 | D19: =D9*D17*((1-(INDEX(Assumptions!$C$27:$E$27,$B$3)+INDEX(Assumptions!$C$28:$E$28,$B$3)+INDEX(Assumptions!$C$31:$E$31,$B$3)))*D14*$F$3+MIN((INDEX(Assumptions!$C$27:$E$27,$B$3)+INDEX(Assumptions!$C$28:$E$28,$B$3)+INDEX(Assumptions!$C$31:$E$31,$B$3))*D14,D18)) -> 0.65032149 | E19: =E9*E17*((1-(INDEX(Assumptions!$C$27:$E$27,$B$3)+INDEX(Assumptions!$C$28:$E$28,$B$3)+INDEX(Assumptions!$C$31:$E$31,$B$3)))*E14*$F$3+MIN((INDEX(Assumptions!$C$27:$E$27,$B$3)+INDEX(Assumptions!$C$28:$E$28,$B$3)+INDEX(Assumptions!$C$31:$E$31,$B$3))*E14,E18)) -> 0.78296007 | F19: =F9*F17*((1-(INDEX(Assumptions!$C$27:$E$27,$B$3)+INDEX(Assumptions!$C$28:$E$28,$B$3)+INDEX(Assumptions!$C$31:$E$31,$B$3)))*F14*$F$3+MIN((INDEX(Assumptions!$C$27:$E$27,$B$3)+INDEX(Assumptions!$C$28:$E$28,$B$3)+INDEX(Assumptions!$C$31:$E$31,$B$3))*F14,F18)) -> 1.6860719 | G19: =G9*G17*((1-(INDEX(Assumptions!$C$27:$E$27,$B$3)+INDEX(Assumptions!$C$28:$E$28,$B$3)+INDEX(Assumptions!$C$31:$E$31,$B$3)))*G14*$F$3+MIN((INDEX(Assumptions!$C$27:$E$27,$B$3)+INDEX(Assumptions!$C$28:$E$28,$B$3)+INDEX(Assumptions!$C$31:$E$31,$B$3))*G14,G18)) -> 2.2449496 | H19: =H9*H17*((1-(INDEX(Assumptions!$C$27:$E$27,$B$3)+INDEX(Assumptions!$C$28:$E$28,$B$3)+INDEX(Assumptions!$C$31:$E$31,$B$3)))*H14*$F$3+MIN((INDEX(Assumptions!$C$27:$E$27,$B$3)+INDEX(Assumptions!$C$28:$E$28,$B$3)+INDEX(Assumptions!$C$31:$E$31,$B$3))*H14,H18)) -> 2.7943885 | I19: =I9*I17*((1-(INDEX(Assumptions!$C$27:$E$27,$B$3)+INDEX(Assumptions!$C$28:$E$28,$B$3)+INDEX(Assumptions!$C$31:$E$31,$B$3)))*I14*$F$3+MIN((INDEX(Assumptions!$C$27:$E$27,$B$3)+INDEX(Assumptions!$C$28:$E$28,$B$3)+INDEX(Assumptions!$C$31:$E$31,$B$3))*I14,I18)) -> 4.022705 | J19: =J9*J17*((1-(INDEX(Assumptions!$C$27:$E$27,$B$3)+INDEX(Assumptions!$C$28:$E$28,$B$3)+INDEX(Assumptions!$C$31:$E$31,$B$3)))*J14*$F$3+MIN((INDEX(Assumptions!$C$27:$E$27,$B$3)+INDEX(Assumptions!$C$28:$E$28,$B$3)+INDEX(Assumptions!$C$31:$E$31,$B$3))*J14,J18)) -> 4.1774245 | ... N19: =N9*N17*((1-(INDEX(Assumptions!$C$27:$E$27,$B$3)+INDEX(Assumptions!$C$28:$E$28,$B$3)+INDEX(Assumptions!$C$31:$E$31,$B$3)))*N14*$F$3+MIN((INDEX(Assumptions!$C$27:$E$27,$B$3)+INDEX(Assumptions!$C$28:$E$28,$B$3)+INDEX(Assumptions!$C$31:$E$31,$B$3))*N14,N18)) -> 3.0943885 | O19: =SUM(C19:N19) -> 30.376401
A20: Stations available | C20: =IF(1>=INDEX(Assumptions!$C$173:$E$173,$D$3),INDEX(Assumptions!$C$176:$E$176,$D$3),INDEX(Assumptions!$C$171:$E$171,$B$3)) -> 8 | D20: =IF(2>=INDEX(Assumptions!$C$173:$E$173,$D$3),INDEX(Assumptions!$C$176:$E$176,$D$3),INDEX(Assumptions!$C$171:$E$171,$B$3)) -> 8 | E20: =IF(3>=INDEX(Assumptions!$C$173:$E$173,$D$3),INDEX(Assumptions!$C$176:$E$176,$D$3),INDEX(Assumptions!$C$171:$E$171,$B$3)) -> 8 | F20: =IF(4>=INDEX(Assumptions!$C$173:$E$173,$D$3),INDEX(Assumptions!$C$176:$E$176,$D$3),INDEX(Assumptions!$C$171:$E$171,$B$3)) -> 8 | G20: =IF(5>=INDEX(Assumptions!$C$173:$E$173,$D$3),INDEX(Assumptions!$C$176:$E$176,$D$3),INDEX(Assumptions!$C$171:$E$171,$B$3)) -> 8 | H20: =IF(6>=INDEX(Assumptions!$C$173:$E$173,$D$3),INDEX(Assumptions!$C$176:$E$176,$D$3),INDEX(Assumptions!$C$171:$E$171,$B$3)) -> 8 | I20: =IF(7>=INDEX(Assumptions!$C$173:$E$173,$D$3),INDEX(Assumptions!$C$176:$E$176,$D$3),INDEX(Assumptions!$C$171:$E$171,$B$3)) -> 8 | J20: =IF(8>=INDEX(Assumptions!$C$173:$E$173,$D$3),INDEX(Assumptions!$C$176:$E$176,$D$3),INDEX(Assumptions!$C$171:$E$171,$B$3)) -> 8 | K20: =IF(9>=INDEX(Assumptions!$C$173:$E$173,$D$3),INDEX(Assumptions!$C$176:$E$176,$D$3),INDEX(Assumptions!$C$171:$E$171,$B$3)) -> 8 | L20: =IF(10>=INDEX(Assumptions!$C$173:$E$173,$D$3),INDEX(Assumptions!$C$176:$E$176,$D$3),INDEX(Assumptions!$C$171:$E$171,$B$3)) -> 8 | M20: =IF(11>=INDEX(Assumptions!$C$173:$E$173,$D$3),INDEX(Assumptions!$C$176:$E$176,$D$3),INDEX(Assumptions!$C$171:$E$171,$B$3)) -> 8 | N20: =IF(12>=INDEX(Assumptions!$C$173:$E$173,$D$3),INDEX(Assumptions!$C$176:$E$176,$D$3),INDEX(Assumptions!$C$171:$E$171,$B$3)) -> 8 | O20: =N20 -> 8
A21: Batch slots per day | C21: =IF(1>=INDEX(Assumptions!$C$173:$E$173,$D$3),INDEX(Assumptions!$C$177:$E$177,$D$3),INDEX(Assumptions!$C$172:$E$172,$D$3)) -> 2 | D21: =IF(2>=INDEX(Assumptions!$C$173:$E$173,$D$3),INDEX(Assumptions!$C$177:$E$177,$D$3),INDEX(Assumptions!$C$172:$E$172,$D$3)) -> 2 | E21: =IF(3>=INDEX(Assumptions!$C$173:$E$173,$D$3),INDEX(Assumptions!$C$177:$E$177,$D$3),INDEX(Assumptions!$C$172:$E$172,$D$3)) -> 2 | F21: =IF(4>=INDEX(Assumptions!$C$173:$E$173,$D$3),INDEX(Assumptions!$C$177:$E$177,$D$3),INDEX(Assumptions!$C$172:$E$172,$D$3)) -> 2 | G21: =IF(5>=INDEX(Assumptions!$C$173:$E$173,$D$3),INDEX(Assumptions!$C$177:$E$177,$D$3),INDEX(Assumptions!$C$172:$E$172,$D$3)) -> 2 | H21: =IF(6>=INDEX(Assumptions!$C$173:$E$173,$D$3),INDEX(Assumptions!$C$177:$E$177,$D$3),INDEX(Assumptions!$C$172:$E$172,$D$3)) -> 2 | I21: =IF(7>=INDEX(Assumptions!$C$173:$E$173,$D$3),INDEX(Assumptions!$C$177:$E$177,$D$3),INDEX(Assumptions!$C$172:$E$172,$D$3)) -> 2 | J21: =IF(8>=INDEX(Assumptions!$C$173:$E$173,$D$3),INDEX(Assumptions!$C$177:$E$177,$D$3),INDEX(Assumptions!$C$172:$E$172,$D$3)) -> 2 | K21: =IF(9>=INDEX(Assumptions!$C$173:$E$173,$D$3),INDEX(Assumptions!$C$177:$E$177,$D$3),INDEX(Assumptions!$C$172:$E$172,$D$3)) -> 2 | L21: =IF(10>=INDEX(Assumptions!$C$173:$E$173,$D$3),INDEX(Assumptions!$C$177:$E$177,$D$3),INDEX(Assumptions!$C$172:$E$172,$D$3)) -> 2 | M21: =IF(11>=INDEX(Assumptions!$C$173:$E$173,$D$3),INDEX(Assumptions!$C$177:$E$177,$D$3),INDEX(Assumptions!$C$172:$E$172,$D$3)) -> 2 | N21: =IF(12>=INDEX(Assumptions!$C$173:$E$173,$D$3),INDEX(Assumptions!$C$177:$E$177,$D$3),INDEX(Assumptions!$C$172:$E$172,$D$3)) -> 2 | O21: =N21 -> 2
A22: Usable seat capacity (stations x slots x max use) | C22: =C20*C21*INDEX(Assumptions!$C$178:$E$178,$B$3) -> 14.4 | D22: =D20*D21*INDEX(Assumptions!$C$178:$E$178,$B$3) -> 14.4 | E22: =E20*E21*INDEX(Assumptions!$C$178:$E$178,$B$3) -> 14.4 | F22: =F20*F21*INDEX(Assumptions!$C$178:$E$178,$B$3) -> 14.4 | G22: =G20*G21*INDEX(Assumptions!$C$178:$E$178,$B$3) -> 14.4 | H22: =H20*H21*INDEX(Assumptions!$C$178:$E$178,$B$3) -> 14.4 | I22: =I20*I21*INDEX(Assumptions!$C$178:$E$178,$B$3) -> 14.4 | J22: =J20*J21*INDEX(Assumptions!$C$178:$E$178,$B$3) -> 14.4 | ... N22: =N20*N21*INDEX(Assumptions!$C$178:$E$178,$B$3) -> 14.4 | O22: =N22 -> 14.4
A23: Destination/hybrid format share of new L3 (out-of-town students after launch) | C23: =IF(1>=INDEX(Assumptions!$C$189:$E$189,$D$3),INDEX(Assumptions!$C$74:$E$74,$B$3),0) -> 0 | D23: =IF(2>=INDEX(Assumptions!$C$189:$E$189,$D$3),INDEX(Assumptions!$C$74:$E$74,$B$3),0) -> 0 | E23: =IF(3>=INDEX(Assumptions!$C$189:$E$189,$D$3),INDEX(Assumptions!$C$74:$E$74,$B$3),0) -> 0 | F23: =IF(4>=INDEX(Assumptions!$C$189:$E$189,$D$3),INDEX(Assumptions!$C$74:$E$74,$B$3),0) -> 0 | G23: =IF(5>=INDEX(Assumptions!$C$189:$E$189,$D$3),INDEX(Assumptions!$C$74:$E$74,$B$3),0) -> 0 | H23: =IF(6>=INDEX(Assumptions!$C$189:$E$189,$D$3),INDEX(Assumptions!$C$74:$E$74,$B$3),0) -> 0 | I23: =IF(7>=INDEX(Assumptions!$C$189:$E$189,$D$3),INDEX(Assumptions!$C$74:$E$74,$B$3),0) -> 0 | J23: =IF(8>=INDEX(Assumptions!$C$189:$E$189,$D$3),INDEX(Assumptions!$C$74:$E$74,$B$3),0) -> 0 | K23: =IF(9>=INDEX(Assumptions!$C$189:$E$189,$D$3),INDEX(Assumptions!$C$74:$E$74,$B$3),0) -> 0 | L23: =IF(10>=INDEX(Assumptions!$C$189:$E$189,$D$3),INDEX(Assumptions!$C$74:$E$74,$B$3),0) -> 0 | M23: =IF(11>=INDEX(Assumptions!$C$189:$E$189,$D$3),INDEX(Assumptions!$C$74:$E$74,$B$3),0) -> 0 | N23: =IF(12>=INDEX(Assumptions!$C$189:$E$189,$D$3),INDEX(Assumptions!$C$74:$E$74,$B$3),0) -> 0 | O23: =N23 -> 0
A24: Seats held by continuing students (L3 from m-1, m-2; destination from m-1 x1.25) | C24: =0+0+0+0+1.25*0 -> 0 | D24: =C27+0+C30+0+1.25*C28 -> 0.20113525 | E24: =D27+C27+D30+C30+1.25*D28 -> 0.57657981 | F24: =E27+D27+E30+D30+1.25*E28 -> 0.84821478 | G24: =F27+E27+F30+E30+1.25*F28 -> 1.4136762 | H24: =G27+F27+G30+F30+1.25*G28 -> 2.2741398 | I24: =H27+G27+H30+G30+1.25*H28 -> 3.0110468 | J24: =I27+H27+I30+H30+1.25*I28 -> 4.038464 | K24: =J27+I27+J30+I30+1.25*J28 -> 4.9522014 | L24: =K27+J27+K30+J30+1.25*K28 -> 5.0477212 | ... N24: =M27+L27+M30+L30+1.25*M28 -> 4.2354442
A25: Seats needed for this month's new starts | C25: =C19*(INDEX(Assumptions!$C$26:$E$26,$B$3)*(1-C23)+INDEX(Assumptions!$C$26:$E$26,$B$3)*C23*1.25+(1-INDEX(Assumptions!$C$26:$E$26,$B$3)))+0*INDEX(Assumptions!$C$89:$E$89,$B$3) -> 0.4022705 | D25: =D19*(INDEX(Assumptions!$C$26:$E$26,$B$3)*(1-D23)+INDEX(Assumptions!$C$26:$E$26,$B$3)*D23*1.25+(1-INDEX(Assumptions!$C$26:$E$26,$B$3)))+C29*INDEX(Assumptions!$C$89:$E$89,$B$3) -> 0.70060531 | E25: =E19*(INDEX(Assumptions!$C$26:$E$26,$B$3)*(1-E23)+INDEX(Assumptions!$C$26:$E$26,$B$3)*E23*1.25+(1-INDEX(Assumptions!$C$26:$E$26,$B$3)))+D29*INDEX(Assumptions!$C$89:$E$89,$B$3) -> 0.86425026 | F25: =F19*(INDEX(Assumptions!$C$26:$E$26,$B$3)*(1-F23)+INDEX(Assumptions!$C$26:$E$26,$B$3)*F23*1.25+(1-INDEX(Assumptions!$C$26:$E$26,$B$3)))+E29*INDEX(Assumptions!$C$89:$E$89,$B$3) -> 1.783942 | G25: =G19*(INDEX(Assumptions!$C$26:$E$26,$B$3)*(1-G23)+INDEX(Assumptions!$C$26:$E$26,$B$3)*G23*1.25+(1-INDEX(Assumptions!$C$26:$E$26,$B$3)))+F29*INDEX(Assumptions!$C$89:$E$89,$B$3) -> 2.4557086 | H25: =H19*(INDEX(Assumptions!$C$26:$E$26,$B$3)*(1-H23)+INDEX(Assumptions!$C$26:$E$26,$B$3)*H23*1.25+(1-INDEX(Assumptions!$C$26:$E$26,$B$3)))+G29*INDEX(Assumptions!$C$89:$E$89,$B$3) -> 3.0750072 | I25: =I19*(INDEX(Assumptions!$C$26:$E$26,$B$3)*(1-I23)+INDEX(Assumptions!$C$26:$E$26,$B$3)*I23*1.25+(1-INDEX(Assumptions!$C$26:$E$26,$B$3)))+H29*INDEX(Assumptions!$C$89:$E$89,$B$3) -> 4.3720036 | J25: =J19*(INDEX(Assumptions!$C$26:$E$26,$B$3)*(1-J23)+INDEX(Assumptions!$C$26:$E$26,$B$3)*J23*1.25+(1-INDEX(Assumptions!$C$26:$E$26,$B$3)))+I29*INDEX(Assumptions!$C$89:$E$89,$B$3) -> 4.6802626 | K25: =K19*(INDEX(Assumptions!$C$26:$E$26,$B$3)*(1-K23)+INDEX(Assumptions!$C$26:$E$26,$B$3)*K23*1.25+(1-INDEX(Assumptions!$C$26:$E$26,$B$3)))+J29*INDEX(Assumptions!$C$89:$E$89,$B$3) -> 4.3901637 | ... N25: =N19*(INDEX(Assumptions!$C$26:$E$26,$B$3)*(1-N23)+INDEX(Assumptions!$C$26:$E$26,$B$3)*N23*1.25+(1-INDEX(Assumptions!$C$26:$E$26,$B$3)))+M29*INDEX(Assumptions!$C$89:$E$89,$B$3) -> 3.500527
A26: Share of demand that fits (capacity constraint) | C26: =IF(C25<=0,1,MAX(0,MIN(1,(C22-C24)/C25))) -> 1 | D26: =IF(D25<=0,1,MAX(0,MIN(1,(D22-D24)/D25))) -> 1 | E26: =IF(E25<=0,1,MAX(0,MIN(1,(E22-E24)/E25))) -> 1 | F26: =IF(F25<=0,1,MAX(0,MIN(1,(F22-F24)/F25))) -> 1 | G26: =IF(G25<=0,1,MAX(0,MIN(1,(G22-G24)/G25))) -> 1 | H26: =IF(H25<=0,1,MAX(0,MIN(1,(H22-H24)/H25))) -> 1 | I26: =IF(I25<=0,1,MAX(0,MIN(1,(I22-I24)/I25))) -> 1 | J26: =IF(J25<=0,1,MAX(0,MIN(1,(J22-J24)/J25))) -> 1 | ... N26: =IF(N25<=0,1,MAX(0,MIN(1,(N22-N24)/N25))) -> 1 | O26: =MIN(C26:N26) -> 1
A27: L3 Professional Bridal Programme - local formats (weekday/flex) enrolments | C27: =C19*INDEX(Assumptions!$C$26:$E$26,$B$3)*(1-C23)*C26 -> 0.20113525 | D27: =D19*INDEX(Assumptions!$C$26:$E$26,$B$3)*(1-D23)*D26 -> 0.32516075 | E27: =E19*INDEX(Assumptions!$C$26:$E$26,$B$3)*(1-E23)*E26 -> 0.39148004 | F27: =F19*INDEX(Assumptions!$C$26:$E$26,$B$3)*(1-F23)*F26 -> 0.84303597 | G27: =G19*INDEX(Assumptions!$C$26:$E$26,$B$3)*(1-G23)*G26 -> 1.1224748 | H27: =H19*INDEX(Assumptions!$C$26:$E$26,$B$3)*(1-H23)*H26 -> 1.3971942 | I27: =I19*INDEX(Assumptions!$C$26:$E$26,$B$3)*(1-I23)*I26 -> 2.0113525 | J27: =J19*INDEX(Assumptions!$C$26:$E$26,$B$3)*(1-J23)*J26 -> 2.0887122 | ... N27: =N19*INDEX(Assumptions!$C$26:$E$26,$B$3)*(1-N23)*N26 -> 1.5471942 | O27: =SUM(C27:N27) -> 15.1882
A28: L3 destination/hybrid format enrolments (out-of-town) | C28: =C19*INDEX(Assumptions!$C$26:$E$26,$B$3)*C23*C26 -> 0 | D28: =D19*INDEX(Assumptions!$C$26:$E$26,$B$3)*D23*D26 -> 0 | E28: =E19*INDEX(Assumptions!$C$26:$E$26,$B$3)*E23*E26 -> 0 | F28: =F19*INDEX(Assumptions!$C$26:$E$26,$B$3)*F23*F26 -> 0 | G28: =G19*INDEX(Assumptions!$C$26:$E$26,$B$3)*G23*G26 -> 0 | H28: =H19*INDEX(Assumptions!$C$26:$E$26,$B$3)*H23*H26 -> 0 | I28: =I19*INDEX(Assumptions!$C$26:$E$26,$B$3)*I23*I26 -> 0 | J28: =J19*INDEX(Assumptions!$C$26:$E$26,$B$3)*J23*J26 -> 0 | ... N28: =N19*INDEX(Assumptions!$C$26:$E$26,$B$3)*N23*N26 -> 0 | O28: =SUM(C28:N28) -> 0
A29: L2 Foundation enrolments | C29: =C19*(1-INDEX(Assumptions!$C$26:$E$26,$B$3))*C26 -> 0.20113525 | D29: =D19*(1-INDEX(Assumptions!$C$26:$E$26,$B$3))*D26 -> 0.32516075 | E29: =E19*(1-INDEX(Assumptions!$C$26:$E$26,$B$3))*E26 -> 0.39148004 | F29: =F19*(1-INDEX(Assumptions!$C$26:$E$26,$B$3))*F26 -> 0.84303597 | G29: =G19*(1-INDEX(Assumptions!$C$26:$E$26,$B$3))*G26 -> 1.1224748 | H29: =H19*(1-INDEX(Assumptions!$C$26:$E$26,$B$3))*H26 -> 1.3971942 | I29: =I19*(1-INDEX(Assumptions!$C$26:$E$26,$B$3))*I26 -> 2.0113525 | J29: =J19*(1-INDEX(Assumptions!$C$26:$E$26,$B$3))*J26 -> 2.0887122 | ... N29: =N19*(1-INDEX(Assumptions!$C$26:$E$26,$B$3))*N26 -> 1.5471942 | O29: =SUM(C29:N29) -> 15.1882
A30: L2 -> L3 upgrades (fee credited; A-ECO-36) | C30: =0*INDEX(Assumptions!$C$89:$E$89,$B$3)*C26 -> 0 | D30: =C29*INDEX(Assumptions!$C$89:$E$89,$B$3)*D26 -> 0.050283813 | E30: =D29*INDEX(Assumptions!$C$89:$E$89,$B$3)*E26 -> 0.081290187 | F30: =E29*INDEX(Assumptions!$C$89:$E$89,$B$3)*F26 -> 0.097870009 | G30: =F29*INDEX(Assumptions!$C$89:$E$89,$B$3)*G26 -> 0.21075899 | H30: =G29*INDEX(Assumptions!$C$89:$E$89,$B$3)*H26 -> 0.28061871 | I30: =H29*INDEX(Assumptions!$C$89:$E$89,$B$3)*I26 -> 0.34929856 | J30: =I29*INDEX(Assumptions!$C$89:$E$89,$B$3)*J26 -> 0.50283813 | K30: =J29*INDEX(Assumptions!$C$89:$E$89,$B$3)*K26 -> 0.52217806 | ... N30: =M29*INDEX(Assumptions!$C$89:$E$89,$B$3)*N26 -> 0.40613849 | O30: =SUM(C30:N30) -> 3.4102516
A31: Career enrolments (new students, L2 + L3) | C31: =C27+C28+C29 -> 0.4022705 | D31: =D27+D28+D29 -> 0.65032149 | E31: =E27+E28+E29 -> 0.78296007 | F31: =F27+F28+F29 -> 1.6860719 | G31: =G27+G28+G29 -> 2.2449496 | H31: =H27+H28+H29 -> 2.7943885 | I31: =I27+I28+I29 -> 4.022705 | J31: =J27+J28+J29 -> 4.1774245 | ... N31: =N27+N28+N29 -> 3.0943885 | O31: =SUM(C31:N31) -> 30.376401
A32: of which out-of-town (A-GRO-37) | C32: =C31*INDEX(Assumptions!$C$74:$E$74,$B$3) -> 0.060340576 | D32: =D31*INDEX(Assumptions!$C$74:$E$74,$B$3) -> 0.097548224 | E32: =E31*INDEX(Assumptions!$C$74:$E$74,$B$3) -> 0.11744401 | F32: =F31*INDEX(Assumptions!$C$74:$E$74,$B$3) -> 0.25291079 | G32: =G31*INDEX(Assumptions!$C$74:$E$74,$B$3) -> 0.33674245 | H32: =H31*INDEX(Assumptions!$C$74:$E$74,$B$3) -> 0.41915827 | I32: =I31*INDEX(Assumptions!$C$74:$E$74,$B$3) -> 0.60340576 | J32: =J31*INDEX(Assumptions!$C$74:$E$74,$B$3) -> 0.62661367 | ... N32: =N31*INDEX(Assumptions!$C$74:$E$74,$B$3) -> 0.46415827 | O32: =SUM(C32:N32) -> 4.5564601
A33: Seats occupied | C33: =C24+C27+C30+C29+1.25*C28 -> 0.4022705 | D33: =D24+D27+D30+D29+1.25*D28 -> 0.90174056 | E33: =E24+E27+E30+E29+1.25*E28 -> 1.4408301 | F33: =F24+F27+F30+F29+1.25*F28 -> 2.6321567 | G33: =G24+G27+G30+G29+1.25*G28 -> 3.8693848 | H33: =H24+H27+H30+H29+1.25*H28 -> 5.349147 | I33: =I24+I27+I30+I29+1.25*I28 -> 7.3830504 | J33: =J24+J27+J30+J29+1.25*J28 -> 8.7187266 | ... N33: =N24+N27+N30+N29+1.25*N28 -> 7.7359712 | O33: =AVERAGE(C33:N33) -> 5.4189049
A34: Seat utilisation (occupied / stations x slots) | C34: =C33/(C20*C21) -> 0.025141906 | D34: =D33/(D20*D21) -> 0.056358785 | E34: =E33/(E20*E21) -> 0.090051879 | F34: =F33/(F20*F21) -> 0.1645098 | G34: =G33/(G20*G21) -> 0.24183655 | H34: =H33/(H20*H21) -> 0.33432169 | I34: =I33/(I20*I21) -> 0.46144065 | J34: =J33/(J20*J21) -> 0.54492041 | ... N34: =N33/(N20*N21) -> 0.4834982 | O34: =N34 -> 0.4834982
A35: Capacity binds flag (1 = demand does not fully fit) | C35: =IF(C26<0.999,1,0) -> 0 | D35: =IF(D26<0.999,1,0) -> 0 | E35: =IF(E26<0.999,1,0) -> 0 | F35: =IF(F26<0.999,1,0) -> 0 | G35: =IF(G26<0.999,1,0) -> 0 | H35: =IF(H26<0.999,1,0) -> 0 | I35: =IF(I26<0.999,1,0) -> 0 | J35: =IF(J26<0.999,1,0) -> 0 | ... N35: =IF(N26<0.999,1,0) -> 0 | O35: =SUM(C35:N35) -> 0
A36: C. Other products
A37: L4 masterclass seats sold (from M3, 6-month ramp) | C37: =IF(1>=3,INDEX(Assumptions!$C$192:$E$192,$D$3)*INDEX(Assumptions!$C$193:$E$193,$B$3)*MIN(1,(1-2)/6),0)*$F$3 -> 0 | D37: =IF(2>=3,INDEX(Assumptions!$C$192:$E$192,$D$3)*INDEX(Assumptions!$C$193:$E$193,$B$3)*MIN(1,(2-2)/6),0)*$F$3 -> 0 | E37: =IF(3>=3,INDEX(Assumptions!$C$192:$E$192,$D$3)*INDEX(Assumptions!$C$193:$E$193,$B$3)*MIN(1,(3-2)/6),0)*$F$3 -> 1.5 | F37: =IF(4>=3,INDEX(Assumptions!$C$192:$E$192,$D$3)*INDEX(Assumptions!$C$193:$E$193,$B$3)*MIN(1,(4-2)/6),0)*$F$3 -> 3 | G37: =IF(5>=3,INDEX(Assumptions!$C$192:$E$192,$D$3)*INDEX(Assumptions!$C$193:$E$193,$B$3)*MIN(1,(5-2)/6),0)*$F$3 -> 4.5 | H37: =IF(6>=3,INDEX(Assumptions!$C$192:$E$192,$D$3)*INDEX(Assumptions!$C$193:$E$193,$B$3)*MIN(1,(6-2)/6),0)*$F$3 -> 6 | I37: =IF(7>=3,INDEX(Assumptions!$C$192:$E$192,$D$3)*INDEX(Assumptions!$C$193:$E$193,$B$3)*MIN(1,(7-2)/6),0)*$F$3 -> 7.5 | J37: =IF(8>=3,INDEX(Assumptions!$C$192:$E$192,$D$3)*INDEX(Assumptions!$C$193:$E$193,$B$3)*MIN(1,(8-2)/6),0)*$F$3 -> 9 | K37: =IF(9>=3,INDEX(Assumptions!$C$192:$E$192,$D$3)*INDEX(Assumptions!$C$193:$E$193,$B$3)*MIN(1,(9-2)/6),0)*$F$3 -> 9 | L37: =IF(10>=3,INDEX(Assumptions!$C$192:$E$192,$D$3)*INDEX(Assumptions!$C$193:$E$193,$B$3)*MIN(1,(10-2)/6),0)*$F$3 -> 9 | M37: =IF(11>=3,INDEX(Assumptions!$C$192:$E$192,$D$3)*INDEX(Assumptions!$C$193:$E$193,$B$3)*MIN(1,(11-2)/6),0)*$F$3 -> 9 | N37: =IF(12>=3,INDEX(Assumptions!$C$192:$E$192,$D$3)*INDEX(Assumptions!$C$193:$E$193,$B$3)*MIN(1,(12-2)/6),0)*$F$3 -> 9 | O37: =SUM(C37:N37) -> 67.5
A38: L1-S5 self-makeup seats | C38: =INDEX(Assumptions!$C$194:$E$194,$D$3)*C10*MIN(1,1/3)*$F$3 -> 4.6666667 | D38: =INDEX(Assumptions!$C$194:$E$194,$D$3)*D10*MIN(1,2/3)*$F$3 -> 8 | E38: =INDEX(Assumptions!$C$194:$E$194,$D$3)*E10*MIN(1,3/3)*$F$3 -> 12 | F38: =INDEX(Assumptions!$C$194:$E$194,$D$3)*F10*MIN(1,4/3)*$F$3 -> 13 | G38: =INDEX(Assumptions!$C$194:$E$194,$D$3)*G10*MIN(1,5/3)*$F$3 -> 9 | H38: =INDEX(Assumptions!$C$194:$E$194,$D$3)*H10*MIN(1,6/3)*$F$3 -> 8 | I38: =INDEX(Assumptions!$C$194:$E$194,$D$3)*I10*MIN(1,7/3)*$F$3 -> 7 | J38: =INDEX(Assumptions!$C$194:$E$194,$D$3)*J10*MIN(1,8/3)*$F$3 -> 6 | K38: =INDEX(Assumptions!$C$194:$E$194,$D$3)*K10*MIN(1,9/3)*$F$3 -> 6 | L38: =INDEX(Assumptions!$C$194:$E$194,$D$3)*L10*MIN(1,10/3)*$F$3 -> 8 | M38: =INDEX(Assumptions!$C$194:$E$194,$D$3)*M10*MIN(1,11/3)*$F$3 -> 11 | N38: =INDEX(Assumptions!$C$194:$E$194,$D$3)*N10*MIN(1,12/3)*$F$3 -> 14 | O38: =SUM(C38:N38) -> 106.66667
A39: L1 Career Taster tickets (taster-route enrolments / per-ticket conversion) | C39: =C19*INDEX(Assumptions!$C$31:$E$31,$B$3)/(INDEX(Assumptions!$C$56:$E$56,$B$3)*INDEX(Assumptions!$C$57:$E$57,$B$3)*INDEX(Assumptions!$C$58:$E$58,$B$3)) -> 0.67045084 | D39: =D19*INDEX(Assumptions!$C$31:$E$31,$B$3)/(INDEX(Assumptions!$C$56:$E$56,$B$3)*INDEX(Assumptions!$C$57:$E$57,$B$3)*INDEX(Assumptions!$C$58:$E$58,$B$3)) -> 1.0838692 | E39: =E19*INDEX(Assumptions!$C$31:$E$31,$B$3)/(INDEX(Assumptions!$C$56:$E$56,$B$3)*INDEX(Assumptions!$C$57:$E$57,$B$3)*INDEX(Assumptions!$C$58:$E$58,$B$3)) -> 1.3049335 | F39: =F19*INDEX(Assumptions!$C$31:$E$31,$B$3)/(INDEX(Assumptions!$C$56:$E$56,$B$3)*INDEX(Assumptions!$C$57:$E$57,$B$3)*INDEX(Assumptions!$C$58:$E$58,$B$3)) -> 2.8101199 | G39: =G19*INDEX(Assumptions!$C$31:$E$31,$B$3)/(INDEX(Assumptions!$C$56:$E$56,$B$3)*INDEX(Assumptions!$C$57:$E$57,$B$3)*INDEX(Assumptions!$C$58:$E$58,$B$3)) -> 3.7415827 | H39: =H19*INDEX(Assumptions!$C$31:$E$31,$B$3)/(INDEX(Assumptions!$C$56:$E$56,$B$3)*INDEX(Assumptions!$C$57:$E$57,$B$3)*INDEX(Assumptions!$C$58:$E$58,$B$3)) -> 4.6573141 | I39: =I19*INDEX(Assumptions!$C$31:$E$31,$B$3)/(INDEX(Assumptions!$C$56:$E$56,$B$3)*INDEX(Assumptions!$C$57:$E$57,$B$3)*INDEX(Assumptions!$C$58:$E$58,$B$3)) -> 6.7045084 | J39: =J19*INDEX(Assumptions!$C$31:$E$31,$B$3)/(INDEX(Assumptions!$C$56:$E$56,$B$3)*INDEX(Assumptions!$C$57:$E$57,$B$3)*INDEX(Assumptions!$C$58:$E$58,$B$3)) -> 6.9623741 | ... N39: =N19*INDEX(Assumptions!$C$31:$E$31,$B$3)/(INDEX(Assumptions!$C$56:$E$56,$B$3)*INDEX(Assumptions!$C$57:$E$57,$B$3)*INDEX(Assumptions!$C$58:$E$58,$B$3)) -> 5.1573141 | O39: =SUM(C39:N39) -> 50.627335
A40: Regional pop-up events | C40: =IF(1>=INDEX(Assumptions!$C$191:$E$191,$D$3),MAX(INDEX(Assumptions!$C$86:$E$86,$D$3),0.5),0) -> 0 | D40: =IF(2>=INDEX(Assumptions!$C$191:$E$191,$D$3),MAX(INDEX(Assumptions!$C$86:$E$86,$D$3),0.5),0) -> 0 | E40: =IF(3>=INDEX(Assumptions!$C$191:$E$191,$D$3),MAX(INDEX(Assumptions!$C$86:$E$86,$D$3),0.5),0) -> 0 | F40: =IF(4>=INDEX(Assumptions!$C$191:$E$191,$D$3),MAX(INDEX(Assumptions!$C$86:$E$86,$D$3),0.5),0) -> 0 | G40: =IF(5>=INDEX(Assumptions!$C$191:$E$191,$D$3),MAX(INDEX(Assumptions!$C$86:$E$86,$D$3),0.5),0) -> 0 | H40: =IF(6>=INDEX(Assumptions!$C$191:$E$191,$D$3),MAX(INDEX(Assumptions!$C$86:$E$86,$D$3),0.5),0) -> 0 | I40: =IF(7>=INDEX(Assumptions!$C$191:$E$191,$D$3),MAX(INDEX(Assumptions!$C$86:$E$86,$D$3),0.5),0) -> 0 | J40: =IF(8>=INDEX(Assumptions!$C$191:$E$191,$D$3),MAX(INDEX(Assumptions!$C$86:$E$86,$D$3),0.5),0) -> 0 | K40: =IF(9>=INDEX(Assumptions!$C$191:$E$191,$D$3),MAX(INDEX(Assumptions!$C$86:$E$86,$D$3),0.5),0) -> 0 | L40: =IF(10>=INDEX(Assumptions!$C$191:$E$191,$D$3),MAX(INDEX(Assumptions!$C$86:$E$86,$D$3),0.5),0) -> 0 | M40: =IF(11>=INDEX(Assumptions!$C$191:$E$191,$D$3),MAX(INDEX(Assumptions!$C$86:$E$86,$D$3),0.5),0) -> 0 | N40: =IF(12>=INDEX(Assumptions!$C$191:$E$191,$D$3),MAX(INDEX(Assumptions!$C$86:$E$86,$D$3),0.5),0) -> 0 | O40: =SUM(C40:N40) -> 0
A41: Pop-up paid attendees | C41: =C40*INDEX(Assumptions!$C$82:$E$82,$B$3)*$F$3 -> 0 | D41: =D40*INDEX(Assumptions!$C$82:$E$82,$B$3)*$F$3 -> 0 | E41: =E40*INDEX(Assumptions!$C$82:$E$82,$B$3)*$F$3 -> 0 | F41: =F40*INDEX(Assumptions!$C$82:$E$82,$B$3)*$F$3 -> 0 | G41: =G40*INDEX(Assumptions!$C$82:$E$82,$B$3)*$F$3 -> 0 | H41: =H40*INDEX(Assumptions!$C$82:$E$82,$B$3)*$F$3 -> 0 | I41: =I40*INDEX(Assumptions!$C$82:$E$82,$B$3)*$F$3 -> 0 | J41: =J40*INDEX(Assumptions!$C$82:$E$82,$B$3)*$F$3 -> 0 | ... N41: =N40*INDEX(Assumptions!$C$82:$E$82,$B$3)*$F$3 -> 0 | O41: =SUM(C41:N41) -> 0
A42: L5 Pro Circle new paid members (S3 buyers; graduates free in year 1) | C42: =C37*0.7*INDEX(Assumptions!$C$73:$E$73,$B$3) -> 0 | D42: =D37*0.7*INDEX(Assumptions!$C$73:$E$73,$B$3) -> 0 | E42: =E37*0.7*INDEX(Assumptions!$C$73:$E$73,$B$3) -> 0.0525 | F42: =F37*0.7*INDEX(Assumptions!$C$73:$E$73,$B$3) -> 0.105 | G42: =G37*0.7*INDEX(Assumptions!$C$73:$E$73,$B$3) -> 0.1575 | H42: =H37*0.7*INDEX(Assumptions!$C$73:$E$73,$B$3) -> 0.21 | I42: =I37*0.7*INDEX(Assumptions!$C$73:$E$73,$B$3) -> 0.2625 | J42: =J37*0.7*INDEX(Assumptions!$C$73:$E$73,$B$3) -> 0.315 | ... N42: =N37*0.7*INDEX(Assumptions!$C$73:$E$73,$B$3) -> 0.315 | O42: =SUM(C42:N42) -> 2.3625
A43: D. Prices (incl. GST as quoted)
A44: L3 realised fee (CA-02 until price step A-ECO-104, then A-BM-02) | C44: =IF(1>=INDEX(Assumptions!$C$105:$E$105,$B$3),INDEX(Assumptions!$C$20:$E$20,$B$3),INDEX(Assumptions!$C$10:$E$10,$B$3))*$H$3 -> 40000 | D44: =IF(2>=INDEX(Assumptions!$C$105:$E$105,$B$3),INDEX(Assumptions!$C$20:$E$20,$B$3),INDEX(Assumptions!$C$10:$E$10,$B$3))*$H$3 -> 40000 | E44: =IF(3>=INDEX(Assumptions!$C$105:$E$105,$B$3),INDEX(Assumptions!$C$20:$E$20,$B$3),INDEX(Assumptions!$C$10:$E$10,$B$3))*$H$3 -> 40000 | F44: =IF(4>=INDEX(Assumptions!$C$105:$E$105,$B$3),INDEX(Assumptions!$C$20:$E$20,$B$3),INDEX(Assumptions!$C$10:$E$10,$B$3))*$H$3 -> 40000 | G44: =IF(5>=INDEX(Assumptions!$C$105:$E$105,$B$3),INDEX(Assumptions!$C$20:$E$20,$B$3),INDEX(Assumptions!$C$10:$E$10,$B$3))*$H$3 -> 40000 | H44: =IF(6>=INDEX(Assumptions!$C$105:$E$105,$B$3),INDEX(Assumptions!$C$20:$E$20,$B$3),INDEX(Assumptions!$C$10:$E$10,$B$3))*$H$3 -> 40000 | I44: =IF(7>=INDEX(Assumptions!$C$105:$E$105,$B$3),INDEX(Assumptions!$C$20:$E$20,$B$3),INDEX(Assumptions!$C$10:$E$10,$B$3))*$H$3 -> 40000 | J44: =IF(8>=INDEX(Assumptions!$C$105:$E$105,$B$3),INDEX(Assumptions!$C$20:$E$20,$B$3),INDEX(Assumptions!$C$10:$E$10,$B$3))*$H$3 -> 40000 | K44: =IF(9>=INDEX(Assumptions!$C$105:$E$105,$B$3),INDEX(Assumptions!$C$20:$E$20,$B$3),INDEX(Assumptions!$C$10:$E$10,$B$3))*$H$3 -> 40000 | L44: =IF(10>=INDEX(Assumptions!$C$105:$E$105,$B$3),INDEX(Assumptions!$C$20:$E$20,$B$3),INDEX(Assumptions!$C$10:$E$10,$B$3))*$H$3 -> 65000 | M44: =IF(11>=INDEX(Assumptions!$C$105:$E$105,$B$3),INDEX(Assumptions!$C$20:$E$20,$B$3),INDEX(Assumptions!$C$10:$E$10,$B$3))*$H$3 -> 65000 | N44: =IF(12>=INDEX(Assumptions!$C$105:$E$105,$B$3),INDEX(Assumptions!$C$20:$E$20,$B$3),INDEX(Assumptions!$C$10:$E$10,$B$3))*$H$3 -> 65000 | O44: =AVERAGE(C44:N44) -> 46250
A45: Kit included in fee? (1 before step) | C45: =IF(1>=INDEX(Assumptions!$C$105:$E$105,$B$3),0,1) -> 1 | D45: =IF(2>=INDEX(Assumptions!$C$105:$E$105,$B$3),0,1) -> 1 | E45: =IF(3>=INDEX(Assumptions!$C$105:$E$105,$B$3),0,1) -> 1 | F45: =IF(4>=INDEX(Assumptions!$C$105:$E$105,$B$3),0,1) -> 1 | G45: =IF(5>=INDEX(Assumptions!$C$105:$E$105,$B$3),0,1) -> 1 | H45: =IF(6>=INDEX(Assumptions!$C$105:$E$105,$B$3),0,1) -> 1 | I45: =IF(7>=INDEX(Assumptions!$C$105:$E$105,$B$3),0,1) -> 1 | J45: =IF(8>=INDEX(Assumptions!$C$105:$E$105,$B$3),0,1) -> 1 | K45: =IF(9>=INDEX(Assumptions!$C$105:$E$105,$B$3),0,1) -> 1 | L45: =IF(10>=INDEX(Assumptions!$C$105:$E$105,$B$3),0,1) -> 0 | M45: =IF(11>=INDEX(Assumptions!$C$105:$E$105,$B$3),0,1) -> 0 | N45: =IF(12>=INDEX(Assumptions!$C$105:$E$105,$B$3),0,1) -> 0 | O45: =N45 -> 0
A46: E. Revenue (ex-GST)
A47: L3 local formats | C47: =C27*C44/(1+INDEX(Assumptions!$C$15:$E$15,$B$3)*$H$4) -> 6818.1441 | D47: =D27*D44/(1+INDEX(Assumptions!$C$15:$E$15,$B$3)*$H$4) -> 11022.398 | E47: =E27*E44/(1+INDEX(Assumptions!$C$15:$E$15,$B$3)*$H$4) -> 13270.51 | F47: =F27*F44/(1+INDEX(Assumptions!$C$15:$E$15,$B$3)*$H$4) -> 28577.491 | G47: =G27*G44/(1+INDEX(Assumptions!$C$15:$E$15,$B$3)*$H$4) -> 38049.994 | H47: =H27*H44/(1+INDEX(Assumptions!$C$15:$E$15,$B$3)*$H$4) -> 47362.517 | I47: =I27*I44/(1+INDEX(Assumptions!$C$15:$E$15,$B$3)*$H$4) -> 68181.441 | J47: =J27*J44/(1+INDEX(Assumptions!$C$15:$E$15,$B$3)*$H$4) -> 70803.804 | ... N47: =N27*N44/(1+INDEX(Assumptions!$C$15:$E$15,$B$3)*$H$4) -> 85226.802 | O47: =SUM(C47:N47) -> 618109.8
A48: L3 destination/hybrid (price parity) | C48: =C28*C44/(1+INDEX(Assumptions!$C$15:$E$15,$B$3)*$H$4) -> 0 | D48: =D28*D44/(1+INDEX(Assumptions!$C$15:$E$15,$B$3)*$H$4) -> 0 | E48: =E28*E44/(1+INDEX(Assumptions!$C$15:$E$15,$B$3)*$H$4) -> 0 | F48: =F28*F44/(1+INDEX(Assumptions!$C$15:$E$15,$B$3)*$H$4) -> 0 | G48: =G28*G44/(1+INDEX(Assumptions!$C$15:$E$15,$B$3)*$H$4) -> 0 | H48: =H28*H44/(1+INDEX(Assumptions!$C$15:$E$15,$B$3)*$H$4) -> 0 | I48: =I28*I44/(1+INDEX(Assumptions!$C$15:$E$15,$B$3)*$H$4) -> 0 | J48: =J28*J44/(1+INDEX(Assumptions!$C$15:$E$15,$B$3)*$H$4) -> 0 | ... N48: =N28*N44/(1+INDEX(Assumptions!$C$15:$E$15,$B$3)*$H$4) -> 0 | O48: =SUM(C48:N48) -> 0
A49: L2 -> L3 upgrades (L3 fee less credited L2 fee) | C49: =C30*MAX(0,C44-INDEX(Assumptions!$C$18:$E$18,$B$3)*$H$3)/(1+INDEX(Assumptions!$C$15:$E$15,$B$3)*$H$4) -> 0 | D49: =D30*MAX(0,D44-INDEX(Assumptions!$C$18:$E$18,$B$3)*$H$3)/(1+INDEX(Assumptions!$C$15:$E$15,$B$3)*$H$4) -> 426.13401 | E49: =E30*MAX(0,E44-INDEX(Assumptions!$C$18:$E$18,$B$3)*$H$3)/(1+INDEX(Assumptions!$C$15:$E$15,$B$3)*$H$4) -> 688.89989 | F49: =F30*MAX(0,F44-INDEX(Assumptions!$C$18:$E$18,$B$3)*$H$3)/(1+INDEX(Assumptions!$C$15:$E$15,$B$3)*$H$4) -> 829.40686 | G49: =G30*MAX(0,G44-INDEX(Assumptions!$C$18:$E$18,$B$3)*$H$3)/(1+INDEX(Assumptions!$C$15:$E$15,$B$3)*$H$4) -> 1786.0932 | H49: =H30*MAX(0,H44-INDEX(Assumptions!$C$18:$E$18,$B$3)*$H$3)/(1+INDEX(Assumptions!$C$15:$E$15,$B$3)*$H$4) -> 2378.1246 | I49: =I30*MAX(0,I44-INDEX(Assumptions!$C$18:$E$18,$B$3)*$H$3)/(1+INDEX(Assumptions!$C$15:$E$15,$B$3)*$H$4) -> 2960.1573 | J49: =J30*MAX(0,J44-INDEX(Assumptions!$C$18:$E$18,$B$3)*$H$3)/(1+INDEX(Assumptions!$C$15:$E$15,$B$3)*$H$4) -> 4261.3401 | ... N49: =N30*MAX(0,N44-INDEX(Assumptions!$C$18:$E$18,$B$3)*$H$3)/(1+INDEX(Assumptions!$C$15:$E$15,$B$3)*$H$4) -> 12046.481 | O49: =SUM(C49:N49) -> 56763.045
A50: L2 Foundation | C50: =C29*INDEX(Assumptions!$C$18:$E$18,$B$3)*$H$3/(1+INDEX(Assumptions!$C$15:$E$15,$B$3)*$H$4) -> 5113.6081 | D50: =D29*INDEX(Assumptions!$C$18:$E$18,$B$3)*$H$3/(1+INDEX(Assumptions!$C$15:$E$15,$B$3)*$H$4) -> 8266.7986 | E50: =E29*INDEX(Assumptions!$C$18:$E$18,$B$3)*$H$3/(1+INDEX(Assumptions!$C$15:$E$15,$B$3)*$H$4) -> 9952.8823 | F50: =F29*INDEX(Assumptions!$C$18:$E$18,$B$3)*$H$3/(1+INDEX(Assumptions!$C$15:$E$15,$B$3)*$H$4) -> 21433.118 | G50: =G29*INDEX(Assumptions!$C$18:$E$18,$B$3)*$H$3/(1+INDEX(Assumptions!$C$15:$E$15,$B$3)*$H$4) -> 28537.495 | H50: =H29*INDEX(Assumptions!$C$18:$E$18,$B$3)*$H$3/(1+INDEX(Assumptions!$C$15:$E$15,$B$3)*$H$4) -> 35521.888 | I50: =I29*INDEX(Assumptions!$C$18:$E$18,$B$3)*$H$3/(1+INDEX(Assumptions!$C$15:$E$15,$B$3)*$H$4) -> 51136.081 | J50: =J29*INDEX(Assumptions!$C$18:$E$18,$B$3)*$H$3/(1+INDEX(Assumptions!$C$15:$E$15,$B$3)*$H$4) -> 53102.853 | ... N50: =N29*INDEX(Assumptions!$C$18:$E$18,$B$3)*$H$3/(1+INDEX(Assumptions!$C$15:$E$15,$B$3)*$H$4) -> 39335.447 | O50: =SUM(C50:N50) -> 386140.69
A51: L1 Taster tickets (net of credits to enrollers) | C51: =C39*(1-INDEX(Assumptions!$C$56:$E$56,$B$3)*INDEX(Assumptions!$C$57:$E$57,$B$3)*INDEX(Assumptions!$C$58:$E$58,$B$3))*INDEX(Assumptions!$C$17:$E$17,$B$3)/(1+INDEX(Assumptions!$C$15:$E$15,$B$3)*$H$4) -> 533.55387 | D51: =D39*(1-INDEX(Assumptions!$C$56:$E$56,$B$3)*INDEX(Assumptions!$C$57:$E$57,$B$3)*INDEX(Assumptions!$C$58:$E$58,$B$3))*INDEX(Assumptions!$C$17:$E$17,$B$3)/(1+INDEX(Assumptions!$C$15:$E$15,$B$3)*$H$4) -> 862.55777 | E51: =E39*(1-INDEX(Assumptions!$C$56:$E$56,$B$3)*INDEX(Assumptions!$C$57:$E$57,$B$3)*INDEX(Assumptions!$C$58:$E$58,$B$3))*INDEX(Assumptions!$C$17:$E$17,$B$3)/(1+INDEX(Assumptions!$C$15:$E$15,$B$3)*$H$4) -> 1038.4837 | F51: =F39*(1-INDEX(Assumptions!$C$56:$E$56,$B$3)*INDEX(Assumptions!$C$57:$E$57,$B$3)*INDEX(Assumptions!$C$58:$E$58,$B$3))*INDEX(Assumptions!$C$17:$E$17,$B$3)/(1+INDEX(Assumptions!$C$15:$E$15,$B$3)*$H$4) -> 2236.3315 | G51: =G39*(1-INDEX(Assumptions!$C$56:$E$56,$B$3)*INDEX(Assumptions!$C$57:$E$57,$B$3)*INDEX(Assumptions!$C$58:$E$58,$B$3))*INDEX(Assumptions!$C$17:$E$17,$B$3)/(1+INDEX(Assumptions!$C$15:$E$15,$B$3)*$H$4) -> 2977.6023 | H51: =H39*(1-INDEX(Assumptions!$C$56:$E$56,$B$3)*INDEX(Assumptions!$C$57:$E$57,$B$3)*INDEX(Assumptions!$C$58:$E$58,$B$3))*INDEX(Assumptions!$C$17:$E$17,$B$3)/(1+INDEX(Assumptions!$C$15:$E$15,$B$3)*$H$4) -> 3706.3537 | I51: =I39*(1-INDEX(Assumptions!$C$56:$E$56,$B$3)*INDEX(Assumptions!$C$57:$E$57,$B$3)*INDEX(Assumptions!$C$58:$E$58,$B$3))*INDEX(Assumptions!$C$17:$E$17,$B$3)/(1+INDEX(Assumptions!$C$15:$E$15,$B$3)*$H$4) -> 5335.5387 | J51: =J39*(1-INDEX(Assumptions!$C$56:$E$56,$B$3)*INDEX(Assumptions!$C$57:$E$57,$B$3)*INDEX(Assumptions!$C$58:$E$58,$B$3))*INDEX(Assumptions!$C$17:$E$17,$B$3)/(1+INDEX(Assumptions!$C$15:$E$15,$B$3)*$H$4) -> 5540.7517 | ... N51: =N39*(1-INDEX(Assumptions!$C$56:$E$56,$B$3)*INDEX(Assumptions!$C$57:$E$57,$B$3)*INDEX(Assumptions!$C$58:$E$58,$B$3))*INDEX(Assumptions!$C$17:$E$17,$B$3)/(1+INDEX(Assumptions!$C$15:$E$15,$B$3)*$H$4) -> 4104.2605 | O51: =SUM(C51:N51) -> 40289.92
A52: L4 masterclasses | C52: =C37*INDEX(Assumptions!$C$21:$E$21,$B$3)*$H$3/(1+INDEX(Assumptions!$C$15:$E$15,$B$3)*$H$4) -> 0 | D52: =D37*INDEX(Assumptions!$C$21:$E$21,$B$3)*$H$3/(1+INDEX(Assumptions!$C$15:$E$15,$B$3)*$H$4) -> 0 | E52: =E37*INDEX(Assumptions!$C$21:$E$21,$B$3)*$H$3/(1+INDEX(Assumptions!$C$15:$E$15,$B$3)*$H$4) -> 6355.9322 | F52: =F37*INDEX(Assumptions!$C$21:$E$21,$B$3)*$H$3/(1+INDEX(Assumptions!$C$15:$E$15,$B$3)*$H$4) -> 12711.864 | G52: =G37*INDEX(Assumptions!$C$21:$E$21,$B$3)*$H$3/(1+INDEX(Assumptions!$C$15:$E$15,$B$3)*$H$4) -> 19067.797 | H52: =H37*INDEX(Assumptions!$C$21:$E$21,$B$3)*$H$3/(1+INDEX(Assumptions!$C$15:$E$15,$B$3)*$H$4) -> 25423.729 | I52: =I37*INDEX(Assumptions!$C$21:$E$21,$B$3)*$H$3/(1+INDEX(Assumptions!$C$15:$E$15,$B$3)*$H$4) -> 31779.661 | J52: =J37*INDEX(Assumptions!$C$21:$E$21,$B$3)*$H$3/(1+INDEX(Assumptions!$C$15:$E$15,$B$3)*$H$4) -> 38135.593 | ... N52: =N37*INDEX(Assumptions!$C$21:$E$21,$B$3)*$H$3/(1+INDEX(Assumptions!$C$15:$E$15,$B$3)*$H$4) -> 38135.593 | O52: =SUM(C52:N52) -> 286016.95
A53: L1-S5 self-makeup | C53: =C38*INDEX(Assumptions!$C$22:$E$22,$B$3)*$H$3/(1+INDEX(Assumptions!$C$15:$E$15,$B$3)*$H$4) -> 11864.407 | D53: =D38*INDEX(Assumptions!$C$22:$E$22,$B$3)*$H$3/(1+INDEX(Assumptions!$C$15:$E$15,$B$3)*$H$4) -> 20338.983 | E53: =E38*INDEX(Assumptions!$C$22:$E$22,$B$3)*$H$3/(1+INDEX(Assumptions!$C$15:$E$15,$B$3)*$H$4) -> 30508.475 | F53: =F38*INDEX(Assumptions!$C$22:$E$22,$B$3)*$H$3/(1+INDEX(Assumptions!$C$15:$E$15,$B$3)*$H$4) -> 33050.847 | G53: =G38*INDEX(Assumptions!$C$22:$E$22,$B$3)*$H$3/(1+INDEX(Assumptions!$C$15:$E$15,$B$3)*$H$4) -> 22881.356 | H53: =H38*INDEX(Assumptions!$C$22:$E$22,$B$3)*$H$3/(1+INDEX(Assumptions!$C$15:$E$15,$B$3)*$H$4) -> 20338.983 | I53: =I38*INDEX(Assumptions!$C$22:$E$22,$B$3)*$H$3/(1+INDEX(Assumptions!$C$15:$E$15,$B$3)*$H$4) -> 17796.61 | J53: =J38*INDEX(Assumptions!$C$22:$E$22,$B$3)*$H$3/(1+INDEX(Assumptions!$C$15:$E$15,$B$3)*$H$4) -> 15254.237 | ... N53: =N38*INDEX(Assumptions!$C$22:$E$22,$B$3)*$H$3/(1+INDEX(Assumptions!$C$15:$E$15,$B$3)*$H$4) -> 35593.22 | O53: =SUM(C53:N53) -> 271186.44
A54: Pop-up tickets | C54: =C41*INDEX(Assumptions!$C$83:$E$83,$B$3)/(1+INDEX(Assumptions!$C$15:$E$15,$B$3)*$H$4) -> 0 | D54: =D41*INDEX(Assumptions!$C$83:$E$83,$B$3)/(1+INDEX(Assumptions!$C$15:$E$15,$B$3)*$H$4) -> 0 | E54: =E41*INDEX(Assumptions!$C$83:$E$83,$B$3)/(1+INDEX(Assumptions!$C$15:$E$15,$B$3)*$H$4) -> 0 | F54: =F41*INDEX(Assumptions!$C$83:$E$83,$B$3)/(1+INDEX(Assumptions!$C$15:$E$15,$B$3)*$H$4) -> 0 | G54: =G41*INDEX(Assumptions!$C$83:$E$83,$B$3)/(1+INDEX(Assumptions!$C$15:$E$15,$B$3)*$H$4) -> 0 | H54: =H41*INDEX(Assumptions!$C$83:$E$83,$B$3)/(1+INDEX(Assumptions!$C$15:$E$15,$B$3)*$H$4) -> 0 | I54: =I41*INDEX(Assumptions!$C$83:$E$83,$B$3)/(1+INDEX(Assumptions!$C$15:$E$15,$B$3)*$H$4) -> 0 | J54: =J41*INDEX(Assumptions!$C$83:$E$83,$B$3)/(1+INDEX(Assumptions!$C$15:$E$15,$B$3)*$H$4) -> 0 | ... N54: =N41*INDEX(Assumptions!$C$83:$E$83,$B$3)/(1+INDEX(Assumptions!$C$15:$E$15,$B$3)*$H$4) -> 0 | O54: =SUM(C54:N54) -> 0
A55: L5 Pro Circle | C55: =C42*INDEX(Assumptions!$C$23:$E$23,$B$3)/(1+INDEX(Assumptions!$C$15:$E$15,$B$3)*$H$4) -> 0 | D55: =D42*INDEX(Assumptions!$C$23:$E$23,$B$3)/(1+INDEX(Assumptions!$C$15:$E$15,$B$3)*$H$4) -> 0 | E55: =E42*INDEX(Assumptions!$C$23:$E$23,$B$3)/(1+INDEX(Assumptions!$C$15:$E$15,$B$3)*$H$4) -> 222.41314 | F55: =F42*INDEX(Assumptions!$C$23:$E$23,$B$3)/(1+INDEX(Assumptions!$C$15:$E$15,$B$3)*$H$4) -> 444.82627 | G55: =G42*INDEX(Assumptions!$C$23:$E$23,$B$3)/(1+INDEX(Assumptions!$C$15:$E$15,$B$3)*$H$4) -> 667.23941 | H55: =H42*INDEX(Assumptions!$C$23:$E$23,$B$3)/(1+INDEX(Assumptions!$C$15:$E$15,$B$3)*$H$4) -> 889.65254 | I55: =I42*INDEX(Assumptions!$C$23:$E$23,$B$3)/(1+INDEX(Assumptions!$C$15:$E$15,$B$3)*$H$4) -> 1112.0657 | J55: =J42*INDEX(Assumptions!$C$23:$E$23,$B$3)/(1+INDEX(Assumptions!$C$15:$E$15,$B$3)*$H$4) -> 1334.4788 | ... N55: =N42*INDEX(Assumptions!$C$23:$E$23,$B$3)/(1+INDEX(Assumptions!$C$15:$E$15,$B$3)*$H$4) -> 1334.4788 | O55: =SUM(C55:N55) -> 10008.591
A56: Optional kit margin (post-step, near-cost kit) | C56: =(C27+C28)*(1-C45)*INDEX(Assumptions!$C$90:$E$90,$B$3) -> 0 | D56: =(D27+D28)*(1-D45)*INDEX(Assumptions!$C$90:$E$90,$B$3) -> 0 | E56: =(E27+E28)*(1-E45)*INDEX(Assumptions!$C$90:$E$90,$B$3) -> 0 | F56: =(F27+F28)*(1-F45)*INDEX(Assumptions!$C$90:$E$90,$B$3) -> 0 | G56: =(G27+G28)*(1-G45)*INDEX(Assumptions!$C$90:$E$90,$B$3) -> 0 | H56: =(H27+H28)*(1-H45)*INDEX(Assumptions!$C$90:$E$90,$B$3) -> 0 | I56: =(I27+I28)*(1-I45)*INDEX(Assumptions!$C$90:$E$90,$B$3) -> 0 | J56: =(J27+J28)*(1-J45)*INDEX(Assumptions!$C$90:$E$90,$B$3) -> 0 | ... N56: =(N27+N28)*(1-N45)*INDEX(Assumptions!$C$90:$E$90,$B$3) -> 928.31655 | O56: =SUM(C56:N56) -> 2924.1971
A57: Total revenue | C57: =SUM(C47:C56) -> 24329.713 | D57: =SUM(D47:D56) -> 40916.872 | E57: =SUM(E47:E56) -> 62037.596 | F57: =SUM(F47:F56) -> 99283.885 | G57: =SUM(G47:G56) -> 113967.58 | H57: =SUM(H47:H56) -> 135621.25 | I57: =SUM(I47:I56) -> 178301.56 | J57: =SUM(J47:J56) -> 188433.06 | ... N57: =SUM(N47:N56) -> 216704.6 | O57: =SUM(C57:N57) -> 1671439.6
A58: of which career programmes (L2 + L3) | C58: =C47+C48+C49+C50 -> 11931.752 | D58: =D47+D48+D49+D50 -> 19715.331 | E58: =E47+E48+E49+E50 -> 23912.292 | F58: =F47+F48+F49+F50 -> 50840.015 | G58: =G47+G48+G49+G50 -> 68373.582 | H58: =H47+H48+H49+H50 -> 85262.529 | I58: =I47+I48+I49+I50 -> 122277.68 | J58: =J47+J48+J49+J50 -> 128168 | ... N58: =N47+N48+N49+N50 -> 136608.73 | O58: =SUM(C58:N58) -> 1061013.5
A59: F. Variable costs
A60: L3 consumables / models (local + upgrades: A-BM-16; destination: A-ECO-41) | C60: =((C27+C30)*INDEX(Assumptions!$C$91:$E$91,$B$3)+C28*INDEX(Assumptions!$C$93:$E$93,$B$3))*$N$3 -> 1407.9468 | D60: =((D27+D30)*INDEX(Assumptions!$C$91:$E$91,$B$3)+D28*INDEX(Assumptions!$C$93:$E$93,$B$3))*$N$3 -> 2628.1119 | E60: =((E27+E30)*INDEX(Assumptions!$C$91:$E$91,$B$3)+E28*INDEX(Assumptions!$C$93:$E$93,$B$3))*$N$3 -> 3309.3916 | F60: =((F27+F30)*INDEX(Assumptions!$C$91:$E$91,$B$3)+F28*INDEX(Assumptions!$C$93:$E$93,$B$3))*$N$3 -> 6586.3419 | G60: =((G27+G30)*INDEX(Assumptions!$C$91:$E$91,$B$3)+G28*INDEX(Assumptions!$C$93:$E$93,$B$3))*$N$3 -> 9332.6367 | H60: =((H27+H30)*INDEX(Assumptions!$C$91:$E$91,$B$3)+H28*INDEX(Assumptions!$C$93:$E$93,$B$3))*$N$3 -> 11744.691 | I60: =((I27+I30)*INDEX(Assumptions!$C$91:$E$91,$B$3)+I28*INDEX(Assumptions!$C$93:$E$93,$B$3))*$N$3 -> 16524.558 | J60: =((J27+J30)*INDEX(Assumptions!$C$91:$E$91,$B$3)+J28*INDEX(Assumptions!$C$93:$E$93,$B$3))*$N$3 -> 18140.853 | ... N60: =((N27+N30)*INDEX(Assumptions!$C$91:$E$91,$B$3)+N28*INDEX(Assumptions!$C$93:$E$93,$B$3))*$N$3 -> 13673.329 | O60: =SUM(C60:N60) -> 130189.16
A61: Kit cost while fee includes kit (A-ECO-103) | C61: =(C27+C28)*C45*INDEX(Assumptions!$C$14:$E$14,$B$3)*$N$3 -> 3017.0288 | D61: =(D27+D28)*D45*INDEX(Assumptions!$C$14:$E$14,$B$3)*$N$3 -> 4877.4112 | E61: =(E27+E28)*E45*INDEX(Assumptions!$C$14:$E$14,$B$3)*$N$3 -> 5872.2005 | F61: =(F27+F28)*F45*INDEX(Assumptions!$C$14:$E$14,$B$3)*$N$3 -> 12645.54 | G61: =(G27+G28)*G45*INDEX(Assumptions!$C$14:$E$14,$B$3)*$N$3 -> 16837.122 | H61: =(H27+H28)*H45*INDEX(Assumptions!$C$14:$E$14,$B$3)*$N$3 -> 20957.914 | I61: =(I27+I28)*I45*INDEX(Assumptions!$C$14:$E$14,$B$3)*$N$3 -> 30170.288 | J61: =(J27+J28)*J45*INDEX(Assumptions!$C$14:$E$14,$B$3)*$N$3 -> 31330.683 | ... N61: =(N27+N28)*N45*INDEX(Assumptions!$C$14:$E$14,$B$3)*$N$3 -> 0 | O61: =SUM(C61:N61) -> 154718.08
A62: L2 consumables | C62: =C29*INDEX(Assumptions!$C$92:$E$92,$B$3)*$N$3 -> 502.83813 | D62: =D29*INDEX(Assumptions!$C$92:$E$92,$B$3)*$N$3 -> 812.90187 | E62: =E29*INDEX(Assumptions!$C$92:$E$92,$B$3)*$N$3 -> 978.70009 | F62: =F29*INDEX(Assumptions!$C$92:$E$92,$B$3)*$N$3 -> 2107.5899 | G62: =G29*INDEX(Assumptions!$C$92:$E$92,$B$3)*$N$3 -> 2806.1871 | H62: =H29*INDEX(Assumptions!$C$92:$E$92,$B$3)*$N$3 -> 3492.9856 | I62: =I29*INDEX(Assumptions!$C$92:$E$92,$B$3)*$N$3 -> 5028.3813 | J62: =J29*INDEX(Assumptions!$C$92:$E$92,$B$3)*$N$3 -> 5221.7806 | ... N62: =N29*INDEX(Assumptions!$C$92:$E$92,$B$3)*$N$3 -> 3867.9856 | O62: =SUM(C62:N62) -> 37970.501
A63: Masterclass, self-makeup and taster delivery costs | C63: =(C37*INDEX(Assumptions!$C$94:$E$94,$B$3)+C38*INDEX(Assumptions!$C$95:$E$95,$B$3)+C39*INDEX(Assumptions!$C$96:$E$96,$B$3))*$N$3 -> 2534.4686 | D63: =(D37*INDEX(Assumptions!$C$94:$E$94,$B$3)+D38*INDEX(Assumptions!$C$95:$E$95,$B$3)+D39*INDEX(Assumptions!$C$96:$E$96,$B$3))*$N$3 -> 4325.1607 | E63: =(E37*INDEX(Assumptions!$C$94:$E$94,$B$3)+E38*INDEX(Assumptions!$C$95:$E$95,$B$3)+E39*INDEX(Assumptions!$C$96:$E$96,$B$3))*$N$3 -> 8191.48 | F63: =(F37*INDEX(Assumptions!$C$94:$E$94,$B$3)+F38*INDEX(Assumptions!$C$95:$E$95,$B$3)+F39*INDEX(Assumptions!$C$96:$E$96,$B$3))*$N$3 -> 10943.036 | G63: =(G37*INDEX(Assumptions!$C$94:$E$94,$B$3)+G38*INDEX(Assumptions!$C$95:$E$95,$B$3)+G39*INDEX(Assumptions!$C$96:$E$96,$B$3))*$N$3 -> 11022.475 | H63: =(H37*INDEX(Assumptions!$C$94:$E$94,$B$3)+H38*INDEX(Assumptions!$C$95:$E$95,$B$3)+H39*INDEX(Assumptions!$C$96:$E$96,$B$3))*$N$3 -> 12597.194 | I63: =(I37*INDEX(Assumptions!$C$94:$E$94,$B$3)+I38*INDEX(Assumptions!$C$95:$E$95,$B$3)+I39*INDEX(Assumptions!$C$96:$E$96,$B$3))*$N$3 -> 14511.353 | J63: =(J37*INDEX(Assumptions!$C$94:$E$94,$B$3)+J38*INDEX(Assumptions!$C$95:$E$95,$B$3)+J39*INDEX(Assumptions!$C$96:$E$96,$B$3))*$N$3 -> 15888.712 | ... N63: =(N37*INDEX(Assumptions!$C$94:$E$94,$B$3)+N38*INDEX(Assumptions!$C$95:$E$95,$B$3)+N39*INDEX(Assumptions!$C$96:$E$96,$B$3))*$N$3 -> 19347.194 | O63: =SUM(C63:N63) -> 149521.53
A64: Pop-up event costs (A-BM-06c) | C64: =C40*INDEX(Assumptions!$C$84:$E$84,$B$3) -> 0 | D64: =D40*INDEX(Assumptions!$C$84:$E$84,$B$3) -> 0 | E64: =E40*INDEX(Assumptions!$C$84:$E$84,$B$3) -> 0 | F64: =F40*INDEX(Assumptions!$C$84:$E$84,$B$3) -> 0 | G64: =G40*INDEX(Assumptions!$C$84:$E$84,$B$3) -> 0 | H64: =H40*INDEX(Assumptions!$C$84:$E$84,$B$3) -> 0 | I64: =I40*INDEX(Assumptions!$C$84:$E$84,$B$3) -> 0 | J64: =J40*INDEX(Assumptions!$C$84:$E$84,$B$3) -> 0 | ... N64: =N40*INDEX(Assumptions!$C$84:$E$84,$B$3) -> 0 | O64: =SUM(C64:N64) -> 0
A65: Pro Circle cost to serve | C65: =C42*INDEX(Assumptions!$C$97:$E$97,$B$3) -> 0 | D65: =D42*INDEX(Assumptions!$C$97:$E$97,$B$3) -> 0 | E65: =E42*INDEX(Assumptions!$C$97:$E$97,$B$3) -> 131.25 | F65: =F42*INDEX(Assumptions!$C$97:$E$97,$B$3) -> 262.5 | G65: =G42*INDEX(Assumptions!$C$97:$E$97,$B$3) -> 393.75 | H65: =H42*INDEX(Assumptions!$C$97:$E$97,$B$3) -> 525 | I65: =I42*INDEX(Assumptions!$C$97:$E$97,$B$3) -> 656.25 | J65: =J42*INDEX(Assumptions!$C$97:$E$97,$B$3) -> 787.5 | ... N65: =N42*INDEX(Assumptions!$C$97:$E$97,$B$3) -> 787.5 | O65: =SUM(C65:N65) -> 5906.25
A66: Payment gateway (A-GRO-41) + no-cost EMI subvention on L3 (A-GRO-35 x 35b) | C66: =C57*(1+INDEX(Assumptions!$C$15:$E$15,$B$3)*$H$4)*INDEX(Assumptions!$C$76:$E$76,$B$3)+(C47+C48+C49)*(1+INDEX(Assumptions!$C$15:$E$15,$B$3)*$H$4)*INDEX(Assumptions!$C$70:$E$70,$B$3)*INDEX(Assumptions!$C$71:$E$71,$B$3) -> 970.60682 | D66: =D57*(1+INDEX(Assumptions!$C$15:$E$15,$B$3)*$H$4)*INDEX(Assumptions!$C$76:$E$76,$B$3)+(D47+D48+D49)*(1+INDEX(Assumptions!$C$15:$E$15,$B$3)*$H$4)*INDEX(Assumptions!$C$70:$E$70,$B$3)*INDEX(Assumptions!$C$71:$E$71,$B$3) -> 1631.5902 | E66: =E57*(1+INDEX(Assumptions!$C$15:$E$15,$B$3)*$H$4)*INDEX(Assumptions!$C$76:$E$76,$B$3)+(E47+E48+E49)*(1+INDEX(Assumptions!$C$15:$E$15,$B$3)*$H$4)*INDEX(Assumptions!$C$70:$E$70,$B$3)*INDEX(Assumptions!$C$71:$E$71,$B$3) -> 2333.4283 | F66: =F57*(1+INDEX(Assumptions!$C$15:$E$15,$B$3)*$H$4)*INDEX(Assumptions!$C$76:$E$76,$B$3)+(F47+F48+F49)*(1+INDEX(Assumptions!$C$15:$E$15,$B$3)*$H$4)*INDEX(Assumptions!$C$70:$E$70,$B$3)*INDEX(Assumptions!$C$71:$E$71,$B$3) -> 4026.2245 | G66: =G57*(1+INDEX(Assumptions!$C$15:$E$15,$B$3)*$H$4)*INDEX(Assumptions!$C$76:$E$76,$B$3)+(G47+G48+G49)*(1+INDEX(Assumptions!$C$15:$E$15,$B$3)*$H$4)*INDEX(Assumptions!$C$70:$E$70,$B$3)*INDEX(Assumptions!$C$71:$E$71,$B$3) -> 4872.7922 | H66: =H57*(1+INDEX(Assumptions!$C$15:$E$15,$B$3)*$H$4)*INDEX(Assumptions!$C$76:$E$76,$B$3)+(H47+H48+H49)*(1+INDEX(Assumptions!$C$15:$E$15,$B$3)*$H$4)*INDEX(Assumptions!$C$70:$E$70,$B$3)*INDEX(Assumptions!$C$71:$E$71,$B$3) -> 5895.0822 | I66: =I57*(1+INDEX(Assumptions!$C$15:$E$15,$B$3)*$H$4)*INDEX(Assumptions!$C$76:$E$76,$B$3)+(I47+I48+I49)*(1+INDEX(Assumptions!$C$15:$E$15,$B$3)*$H$4)*INDEX(Assumptions!$C$70:$E$70,$B$3)*INDEX(Assumptions!$C$71:$E$71,$B$3) -> 7987.6481 | J66: =J57*(1+INDEX(Assumptions!$C$15:$E$15,$B$3)*$H$4)*INDEX(Assumptions!$C$76:$E$76,$B$3)+(J47+J48+J49)*(1+INDEX(Assumptions!$C$15:$E$15,$B$3)*$H$4)*INDEX(Assumptions!$C$70:$E$70,$B$3)*INDEX(Assumptions!$C$71:$E$71,$B$3) -> 8436.6147 | ... N66: =N57*(1+INDEX(Assumptions!$C$15:$E$15,$B$3)*$H$4)*INDEX(Assumptions!$C$76:$E$76,$B$3)+(N47+N48+N49)*(1+INDEX(Assumptions!$C$15:$E$15,$B$3)*$H$4)*INDEX(Assumptions!$C$70:$E$70,$B$3)*INDEX(Assumptions!$C$71:$E$71,$B$3) -> 10154.461 | O66: =SUM(C66:N66) -> 75207.419
A67: Referral rewards (A-GRO-34 x referral-route enrolments) | C67: =C31*INDEX(Assumptions!$C$198:$E$198,$B$3)*INDEX(Assumptions!$C$69:$E$69,$B$3) -> 402.2705 | D67: =D31*INDEX(Assumptions!$C$198:$E$198,$B$3)*INDEX(Assumptions!$C$69:$E$69,$B$3) -> 650.32149 | E67: =E31*INDEX(Assumptions!$C$198:$E$198,$B$3)*INDEX(Assumptions!$C$69:$E$69,$B$3) -> 782.96007 | F67: =F31*INDEX(Assumptions!$C$198:$E$198,$B$3)*INDEX(Assumptions!$C$69:$E$69,$B$3) -> 1686.0719 | G67: =G31*INDEX(Assumptions!$C$198:$E$198,$B$3)*INDEX(Assumptions!$C$69:$E$69,$B$3) -> 2244.9496 | H67: =H31*INDEX(Assumptions!$C$198:$E$198,$B$3)*INDEX(Assumptions!$C$69:$E$69,$B$3) -> 2794.3885 | I67: =I31*INDEX(Assumptions!$C$198:$E$198,$B$3)*INDEX(Assumptions!$C$69:$E$69,$B$3) -> 4022.705 | J67: =J31*INDEX(Assumptions!$C$198:$E$198,$B$3)*INDEX(Assumptions!$C$69:$E$69,$B$3) -> 4177.4245 | ... N67: =N31*INDEX(Assumptions!$C$198:$E$198,$B$3)*INDEX(Assumptions!$C$69:$E$69,$B$3) -> 3094.3885 | O67: =SUM(C67:N67) -> 30376.401
A68: Total variable costs | C68: =SUM(C60:C67) -> 8835.1596 | D68: =SUM(D60:D67) -> 14925.497 | E68: =SUM(E60:E67) -> 21599.411 | F68: =SUM(F60:F67) -> 38257.304 | G68: =SUM(G60:G67) -> 47509.913 | H68: =SUM(H60:H67) -> 58007.255 | I68: =SUM(I60:I67) -> 78901.182 | J68: =SUM(J60:J67) -> 83983.568 | ... N68: =SUM(N60:N67) -> 50924.858 | O68: =SUM(C68:N68) -> 583889.35
A69: Contribution (revenue - variable) | C69: =C57-C68 -> 15494.553 | D69: =D57-D68 -> 25991.374 | E69: =E57-E68 -> 40438.185 | F69: =F57-F68 -> 61026.581 | G69: =G57-G68 -> 66457.664 | H69: =H57-H68 -> 77613.992 | I69: =I57-I68 -> 99400.373 | J69: =J57-J68 -> 104449.49 | ... N69: =N57-N68 -> 165779.74 | O69: =SUM(C69:N69) -> 1087550.3
A70: Contribution margin % | C70: =IFERROR(C69/C57,0) -> 0.63685722 | D70: =IFERROR(D69/D57,0) -> 0.63522389 | E70: =IFERROR(E69/E57,0) -> 0.65183353 | F70: =IFERROR(F69/F57,0) -> 0.61466754 | G70: =IFERROR(G69/G57,0) -> 0.58312782 | H70: =IFERROR(H69/H57,0) -> 0.5722849 | I70: =IFERROR(I69/I57,0) -> 0.55748461 | J70: =IFERROR(J69/J57,0) -> 0.55430555 | ... O70: =IFERROR(O69/O57,0) -> 0.6506668
A71: G. People (trainers follow batches and the founder step-back path)
A72: Active batch-slots (seats occupied / cohort fill) | C72: =ROUNDUP(C33/(INDEX(Assumptions!$C$102:$E$102,$B$3)*$J$3),0) -> 1 | D72: =ROUNDUP(D33/(INDEX(Assumptions!$C$102:$E$102,$B$3)*$J$3),0) -> 1 | E72: =ROUNDUP(E33/(INDEX(Assumptions!$C$102:$E$102,$B$3)*$J$3),0) -> 1 | F72: =ROUNDUP(F33/(INDEX(Assumptions!$C$102:$E$102,$B$3)*$J$3),0) -> 1 | G72: =ROUNDUP(G33/(INDEX(Assumptions!$C$102:$E$102,$B$3)*$J$3),0) -> 1 | H72: =ROUNDUP(H33/(INDEX(Assumptions!$C$102:$E$102,$B$3)*$J$3),0) -> 1 | I72: =ROUNDUP(I33/(INDEX(Assumptions!$C$102:$E$102,$B$3)*$J$3),0) -> 1 | J72: =ROUNDUP(J33/(INDEX(Assumptions!$C$102:$E$102,$B$3)*$J$3),0) -> 2 | ... N72: =ROUNDUP(N33/(INDEX(Assumptions!$C$102:$E$102,$B$3)*$J$3),0) -> 1 | O72: =MAX(C72:N72) -> 2
A73: Batch-slots taught by trainers (x (1 - founder share)) | C73: =C72*(1-C11) -> 0.066666667 | D73: =D72*(1-D11) -> 0.13333333 | E73: =E72*(1-E11) -> 0.2 | F73: =F72*(1-F11) -> 0.26666667 | G73: =G72*(1-G11) -> 0.33333333 | H73: =H72*(1-H11) -> 0.4 | I73: =I72*(1-I11) -> 0.43333333 | J73: =J72*(1-J11) -> 0.93333333 | ... N73: =N72*(1-N11) -> 0.6 | O73: =MAX(C73:N73) -> 1.1333333
A74: Lead trainer (FTE) | C74: =IF(1>=INDEX(Assumptions!$C$161:$E$161,$D$3),INDEX(Assumptions!$C$162:$E$162,$D$3),0) -> 0 | D74: =IF(2>=INDEX(Assumptions!$C$161:$E$161,$D$3),INDEX(Assumptions!$C$162:$E$162,$D$3),0) -> 0 | E74: =IF(3>=INDEX(Assumptions!$C$161:$E$161,$D$3),INDEX(Assumptions!$C$162:$E$162,$D$3),0) -> 0.5 | F74: =IF(4>=INDEX(Assumptions!$C$161:$E$161,$D$3),INDEX(Assumptions!$C$162:$E$162,$D$3),0) -> 0.5 | G74: =IF(5>=INDEX(Assumptions!$C$161:$E$161,$D$3),INDEX(Assumptions!$C$162:$E$162,$D$3),0) -> 0.5 | H74: =IF(6>=INDEX(Assumptions!$C$161:$E$161,$D$3),INDEX(Assumptions!$C$162:$E$162,$D$3),0) -> 0.5 | I74: =IF(7>=INDEX(Assumptions!$C$161:$E$161,$D$3),INDEX(Assumptions!$C$162:$E$162,$D$3),0) -> 0.5 | J74: =IF(8>=INDEX(Assumptions!$C$161:$E$161,$D$3),INDEX(Assumptions!$C$162:$E$162,$D$3),0) -> 0.5 | K74: =IF(9>=INDEX(Assumptions!$C$161:$E$161,$D$3),INDEX(Assumptions!$C$162:$E$162,$D$3),0) -> 0.5 | L74: =IF(10>=INDEX(Assumptions!$C$161:$E$161,$D$3),INDEX(Assumptions!$C$162:$E$162,$D$3),0) -> 0.5 | M74: =IF(11>=INDEX(Assumptions!$C$161:$E$161,$D$3),INDEX(Assumptions!$C$162:$E$162,$D$3),0) -> 0.5 | N74: =IF(12>=INDEX(Assumptions!$C$161:$E$161,$D$3),INDEX(Assumptions!$C$162:$E$162,$D$3),0) -> 0.5 | O74: =N74 -> 0.5
A75: Additional trainers (FTE; 0.1 FTE overflow absorbed by founder/assistant) | C75: =IF(C74=0,0,MAX(0,ROUNDUP((C73-C74*INDEX(Assumptions!$C$101:$E$101,$B$3))/INDEX(Assumptions!$C$101:$E$101,$B$3)-0.1,0))) -> 0 | D75: =IF(D74=0,0,MAX(0,ROUNDUP((D73-D74*INDEX(Assumptions!$C$101:$E$101,$B$3))/INDEX(Assumptions!$C$101:$E$101,$B$3)-0.1,0))) -> 0 | E75: =IF(E74=0,0,MAX(0,ROUNDUP((E73-E74*INDEX(Assumptions!$C$101:$E$101,$B$3))/INDEX(Assumptions!$C$101:$E$101,$B$3)-0.1,0))) -> 0 | F75: =IF(F74=0,0,MAX(0,ROUNDUP((F73-F74*INDEX(Assumptions!$C$101:$E$101,$B$3))/INDEX(Assumptions!$C$101:$E$101,$B$3)-0.1,0))) -> 0 | G75: =IF(G74=0,0,MAX(0,ROUNDUP((G73-G74*INDEX(Assumptions!$C$101:$E$101,$B$3))/INDEX(Assumptions!$C$101:$E$101,$B$3)-0.1,0))) -> 0 | H75: =IF(H74=0,0,MAX(0,ROUNDUP((H73-H74*INDEX(Assumptions!$C$101:$E$101,$B$3))/INDEX(Assumptions!$C$101:$E$101,$B$3)-0.1,0))) -> 0 | I75: =IF(I74=0,0,MAX(0,ROUNDUP((I73-I74*INDEX(Assumptions!$C$101:$E$101,$B$3))/INDEX(Assumptions!$C$101:$E$101,$B$3)-0.1,0))) -> 0 | J75: =IF(J74=0,0,MAX(0,ROUNDUP((J73-J74*INDEX(Assumptions!$C$101:$E$101,$B$3))/INDEX(Assumptions!$C$101:$E$101,$B$3)-0.1,0))) -> 0 | ... N75: =IF(N74=0,0,MAX(0,ROUNDUP((N73-N74*INDEX(Assumptions!$C$101:$E$101,$B$3))/INDEX(Assumptions!$C$101:$E$101,$B$3)-0.1,0))) -> 0 | O75: =MAX(C75:N75) -> 0
A76: Assistants (FTE; 1 per 2 active batch-slots, practical ratio ≤1:6) | C76: =ROUNDUP(C72/2,0) -> 1 | D76: =ROUNDUP(D72/2,0) -> 1 | E76: =ROUNDUP(E72/2,0) -> 1 | F76: =ROUNDUP(F72/2,0) -> 1 | G76: =ROUNDUP(G72/2,0) -> 1 | H76: =ROUNDUP(H72/2,0) -> 1 | I76: =ROUNDUP(I72/2,0) -> 1 | J76: =ROUNDUP(J72/2,0) -> 1 | ... N76: =ROUNDUP(N72/2,0) -> 1 | O76: =MAX(C76:N76) -> 1
A77: Trainer + assistant cost | C77: =C74*INDEX(Assumptions!$C$98:$E$98,$B$3)+C75*INDEX(Assumptions!$C$99:$E$99,$B$3)+C76*INDEX(Assumptions!$C$100:$E$100,$B$3) -> 20000 | D77: =D74*INDEX(Assumptions!$C$98:$E$98,$B$3)+D75*INDEX(Assumptions!$C$99:$E$99,$B$3)+D76*INDEX(Assumptions!$C$100:$E$100,$B$3) -> 20000 | E77: =E74*INDEX(Assumptions!$C$98:$E$98,$B$3)+E75*INDEX(Assumptions!$C$99:$E$99,$B$3)+E76*INDEX(Assumptions!$C$100:$E$100,$B$3) -> 57500 | F77: =F74*INDEX(Assumptions!$C$98:$E$98,$B$3)+F75*INDEX(Assumptions!$C$99:$E$99,$B$3)+F76*INDEX(Assumptions!$C$100:$E$100,$B$3) -> 57500 | G77: =G74*INDEX(Assumptions!$C$98:$E$98,$B$3)+G75*INDEX(Assumptions!$C$99:$E$99,$B$3)+G76*INDEX(Assumptions!$C$100:$E$100,$B$3) -> 57500 | H77: =H74*INDEX(Assumptions!$C$98:$E$98,$B$3)+H75*INDEX(Assumptions!$C$99:$E$99,$B$3)+H76*INDEX(Assumptions!$C$100:$E$100,$B$3) -> 57500 | I77: =I74*INDEX(Assumptions!$C$98:$E$98,$B$3)+I75*INDEX(Assumptions!$C$99:$E$99,$B$3)+I76*INDEX(Assumptions!$C$100:$E$100,$B$3) -> 57500 | J77: =J74*INDEX(Assumptions!$C$98:$E$98,$B$3)+J75*INDEX(Assumptions!$C$99:$E$99,$B$3)+J76*INDEX(Assumptions!$C$100:$E$100,$B$3) -> 57500 | ... N77: =N74*INDEX(Assumptions!$C$98:$E$98,$B$3)+N75*INDEX(Assumptions!$C$99:$E$99,$B$3)+N76*INDEX(Assumptions!$C$100:$E$100,$B$3) -> 57500 | O77: =SUM(C77:N77) -> 615000
A78: Admissions counsellors (A-GRO-45 x FTE) | C78: =(IF(1>=INDEX(Assumptions!$C$164:$E$164,$D$3),1,0)+IF(1>=INDEX(Assumptions!$C$166:$E$166,$D$3),INDEX(Assumptions!$C$165:$E$165,$D$3),0))*INDEX(Assumptions!$C$108:$E$108,$D$3) -> 0 | D78: =(IF(2>=INDEX(Assumptions!$C$164:$E$164,$D$3),1,0)+IF(2>=INDEX(Assumptions!$C$166:$E$166,$D$3),INDEX(Assumptions!$C$165:$E$165,$D$3),0))*INDEX(Assumptions!$C$108:$E$108,$D$3) -> 0 | E78: =(IF(3>=INDEX(Assumptions!$C$164:$E$164,$D$3),1,0)+IF(3>=INDEX(Assumptions!$C$166:$E$166,$D$3),INDEX(Assumptions!$C$165:$E$165,$D$3),0))*INDEX(Assumptions!$C$108:$E$108,$D$3) -> 20000 | F78: =(IF(4>=INDEX(Assumptions!$C$164:$E$164,$D$3),1,0)+IF(4>=INDEX(Assumptions!$C$166:$E$166,$D$3),INDEX(Assumptions!$C$165:$E$165,$D$3),0))*INDEX(Assumptions!$C$108:$E$108,$D$3) -> 20000 | G78: =(IF(5>=INDEX(Assumptions!$C$164:$E$164,$D$3),1,0)+IF(5>=INDEX(Assumptions!$C$166:$E$166,$D$3),INDEX(Assumptions!$C$165:$E$165,$D$3),0))*INDEX(Assumptions!$C$108:$E$108,$D$3) -> 20000 | H78: =(IF(6>=INDEX(Assumptions!$C$164:$E$164,$D$3),1,0)+IF(6>=INDEX(Assumptions!$C$166:$E$166,$D$3),INDEX(Assumptions!$C$165:$E$165,$D$3),0))*INDEX(Assumptions!$C$108:$E$108,$D$3) -> 20000 | I78: =(IF(7>=INDEX(Assumptions!$C$164:$E$164,$D$3),1,0)+IF(7>=INDEX(Assumptions!$C$166:$E$166,$D$3),INDEX(Assumptions!$C$165:$E$165,$D$3),0))*INDEX(Assumptions!$C$108:$E$108,$D$3) -> 20000 | J78: =(IF(8>=INDEX(Assumptions!$C$164:$E$164,$D$3),1,0)+IF(8>=INDEX(Assumptions!$C$166:$E$166,$D$3),INDEX(Assumptions!$C$165:$E$165,$D$3),0))*INDEX(Assumptions!$C$108:$E$108,$D$3) -> 20000 | K78: =(IF(9>=INDEX(Assumptions!$C$164:$E$164,$D$3),1,0)+IF(9>=INDEX(Assumptions!$C$166:$E$166,$D$3),INDEX(Assumptions!$C$165:$E$165,$D$3),0))*INDEX(Assumptions!$C$108:$E$108,$D$3) -> 20000 | L78: =(IF(10>=INDEX(Assumptions!$C$164:$E$164,$D$3),1,0)+IF(10>=INDEX(Assumptions!$C$166:$E$166,$D$3),INDEX(Assumptions!$C$165:$E$165,$D$3),0))*INDEX(Assumptions!$C$108:$E$108,$D$3) -> 20000 | M78: =(IF(11>=INDEX(Assumptions!$C$164:$E$164,$D$3),1,0)+IF(11>=INDEX(Assumptions!$C$166:$E$166,$D$3),INDEX(Assumptions!$C$165:$E$165,$D$3),0))*INDEX(Assumptions!$C$108:$E$108,$D$3) -> 20000 | N78: =(IF(12>=INDEX(Assumptions!$C$164:$E$164,$D$3),1,0)+IF(12>=INDEX(Assumptions!$C$166:$E$166,$D$3),INDEX(Assumptions!$C$165:$E$165,$D$3),0))*INDEX(Assumptions!$C$108:$E$108,$D$3) -> 20000 | O78: =SUM(C78:N78) -> 200000
A79: Marketing/content team, shooter/editor, performance and SEO freelancers (Growth §10) | C79: =IF(1>=INDEX(Assumptions!$C$167:$E$167,$D$3),INDEX(Assumptions!$C$109:$E$109,$D$3),0)+INDEX(Assumptions!$C$110:$E$110,$D$3)+IF(1>=INDEX(Assumptions!$C$168:$E$168,$D$3),INDEX(Assumptions!$C$111:$E$111,$D$3),0)+IF(1>=INDEX(Assumptions!$C$169:$E$169,$D$3),INDEX(Assumptions!$C$113:$E$113,$D$3),0) -> 12000 | D79: =IF(2>=INDEX(Assumptions!$C$167:$E$167,$D$3),INDEX(Assumptions!$C$109:$E$109,$D$3),0)+INDEX(Assumptions!$C$110:$E$110,$D$3)+IF(2>=INDEX(Assumptions!$C$168:$E$168,$D$3),INDEX(Assumptions!$C$111:$E$111,$D$3),0)+IF(2>=INDEX(Assumptions!$C$169:$E$169,$D$3),INDEX(Assumptions!$C$113:$E$113,$D$3),0) -> 12000 | E79: =IF(3>=INDEX(Assumptions!$C$167:$E$167,$D$3),INDEX(Assumptions!$C$109:$E$109,$D$3),0)+INDEX(Assumptions!$C$110:$E$110,$D$3)+IF(3>=INDEX(Assumptions!$C$168:$E$168,$D$3),INDEX(Assumptions!$C$111:$E$111,$D$3),0)+IF(3>=INDEX(Assumptions!$C$169:$E$169,$D$3),INDEX(Assumptions!$C$113:$E$113,$D$3),0) -> 12000 | F79: =IF(4>=INDEX(Assumptions!$C$167:$E$167,$D$3),INDEX(Assumptions!$C$109:$E$109,$D$3),0)+INDEX(Assumptions!$C$110:$E$110,$D$3)+IF(4>=INDEX(Assumptions!$C$168:$E$168,$D$3),INDEX(Assumptions!$C$111:$E$111,$D$3),0)+IF(4>=INDEX(Assumptions!$C$169:$E$169,$D$3),INDEX(Assumptions!$C$113:$E$113,$D$3),0) -> 12000 | G79: =IF(5>=INDEX(Assumptions!$C$167:$E$167,$D$3),INDEX(Assumptions!$C$109:$E$109,$D$3),0)+INDEX(Assumptions!$C$110:$E$110,$D$3)+IF(5>=INDEX(Assumptions!$C$168:$E$168,$D$3),INDEX(Assumptions!$C$111:$E$111,$D$3),0)+IF(5>=INDEX(Assumptions!$C$169:$E$169,$D$3),INDEX(Assumptions!$C$113:$E$113,$D$3),0) -> 12000 | H79: =IF(6>=INDEX(Assumptions!$C$167:$E$167,$D$3),INDEX(Assumptions!$C$109:$E$109,$D$3),0)+INDEX(Assumptions!$C$110:$E$110,$D$3)+IF(6>=INDEX(Assumptions!$C$168:$E$168,$D$3),INDEX(Assumptions!$C$111:$E$111,$D$3),0)+IF(6>=INDEX(Assumptions!$C$169:$E$169,$D$3),INDEX(Assumptions!$C$113:$E$113,$D$3),0) -> 12000 | I79: =IF(7>=INDEX(Assumptions!$C$167:$E$167,$D$3),INDEX(Assumptions!$C$109:$E$109,$D$3),0)+INDEX(Assumptions!$C$110:$E$110,$D$3)+IF(7>=INDEX(Assumptions!$C$168:$E$168,$D$3),INDEX(Assumptions!$C$111:$E$111,$D$3),0)+IF(7>=INDEX(Assumptions!$C$169:$E$169,$D$3),INDEX(Assumptions!$C$113:$E$113,$D$3),0) -> 12000 | J79: =IF(8>=INDEX(Assumptions!$C$167:$E$167,$D$3),INDEX(Assumptions!$C$109:$E$109,$D$3),0)+INDEX(Assumptions!$C$110:$E$110,$D$3)+IF(8>=INDEX(Assumptions!$C$168:$E$168,$D$3),INDEX(Assumptions!$C$111:$E$111,$D$3),0)+IF(8>=INDEX(Assumptions!$C$169:$E$169,$D$3),INDEX(Assumptions!$C$113:$E$113,$D$3),0) -> 12000 | K79: =IF(9>=INDEX(Assumptions!$C$167:$E$167,$D$3),INDEX(Assumptions!$C$109:$E$109,$D$3),0)+INDEX(Assumptions!$C$110:$E$110,$D$3)+IF(9>=INDEX(Assumptions!$C$168:$E$168,$D$3),INDEX(Assumptions!$C$111:$E$111,$D$3),0)+IF(9>=INDEX(Assumptions!$C$169:$E$169,$D$3),INDEX(Assumptions!$C$113:$E$113,$D$3),0) -> 12000 | L79: =IF(10>=INDEX(Assumptions!$C$167:$E$167,$D$3),INDEX(Assumptions!$C$109:$E$109,$D$3),0)+INDEX(Assumptions!$C$110:$E$110,$D$3)+IF(10>=INDEX(Assumptions!$C$168:$E$168,$D$3),INDEX(Assumptions!$C$111:$E$111,$D$3),0)+IF(10>=INDEX(Assumptions!$C$169:$E$169,$D$3),INDEX(Assumptions!$C$113:$E$113,$D$3),0) -> 12000 | M79: =IF(11>=INDEX(Assumptions!$C$167:$E$167,$D$3),INDEX(Assumptions!$C$109:$E$109,$D$3),0)+INDEX(Assumptions!$C$110:$E$110,$D$3)+IF(11>=INDEX(Assumptions!$C$168:$E$168,$D$3),INDEX(Assumptions!$C$111:$E$111,$D$3),0)+IF(11>=INDEX(Assumptions!$C$169:$E$169,$D$3),INDEX(Assumptions!$C$113:$E$113,$D$3),0) -> 12000 | N79: =IF(12>=INDEX(Assumptions!$C$167:$E$167,$D$3),INDEX(Assumptions!$C$109:$E$109,$D$3),0)+INDEX(Assumptions!$C$110:$E$110,$D$3)+IF(12>=INDEX(Assumptions!$C$168:$E$168,$D$3),INDEX(Assumptions!$C$111:$E$111,$D$3),0)+IF(12>=INDEX(Assumptions!$C$169:$E$169,$D$3),INDEX(Assumptions!$C$113:$E$113,$D$3),0) -> 12000 | O79: =SUM(C79:N79) -> 144000
A80: Front-desk / operations coordinator (from move) | C80: =IF(1>=INDEX(Assumptions!$C$173:$E$173,$D$3),INDEX(Assumptions!$C$185:$E$185,$D$3),0) -> 0 | D80: =IF(2>=INDEX(Assumptions!$C$173:$E$173,$D$3),INDEX(Assumptions!$C$185:$E$185,$D$3),0) -> 0 | E80: =IF(3>=INDEX(Assumptions!$C$173:$E$173,$D$3),INDEX(Assumptions!$C$185:$E$185,$D$3),0) -> 0 | F80: =IF(4>=INDEX(Assumptions!$C$173:$E$173,$D$3),INDEX(Assumptions!$C$185:$E$185,$D$3),0) -> 0 | G80: =IF(5>=INDEX(Assumptions!$C$173:$E$173,$D$3),INDEX(Assumptions!$C$185:$E$185,$D$3),0) -> 0 | H80: =IF(6>=INDEX(Assumptions!$C$173:$E$173,$D$3),INDEX(Assumptions!$C$185:$E$185,$D$3),0) -> 0 | I80: =IF(7>=INDEX(Assumptions!$C$173:$E$173,$D$3),INDEX(Assumptions!$C$185:$E$185,$D$3),0) -> 0 | J80: =IF(8>=INDEX(Assumptions!$C$173:$E$173,$D$3),INDEX(Assumptions!$C$185:$E$185,$D$3),0) -> 0 | K80: =IF(9>=INDEX(Assumptions!$C$173:$E$173,$D$3),INDEX(Assumptions!$C$185:$E$185,$D$3),0) -> 0 | L80: =IF(10>=INDEX(Assumptions!$C$173:$E$173,$D$3),INDEX(Assumptions!$C$185:$E$185,$D$3),0) -> 0 | M80: =IF(11>=INDEX(Assumptions!$C$173:$E$173,$D$3),INDEX(Assumptions!$C$185:$E$185,$D$3),0) -> 0 | N80: =IF(12>=INDEX(Assumptions!$C$173:$E$173,$D$3),INDEX(Assumptions!$C$185:$E$185,$D$3),0) -> 0 | O80: =SUM(C80:N80) -> 0
A81: Academy manager / admissions head | C81: =IF(1>=INDEX(Assumptions!$C$187:$E$187,$D$3),INDEX(Assumptions!$C$186:$E$186,$B$3),0) -> 0 | D81: =IF(2>=INDEX(Assumptions!$C$187:$E$187,$D$3),INDEX(Assumptions!$C$186:$E$186,$B$3),0) -> 0 | E81: =IF(3>=INDEX(Assumptions!$C$187:$E$187,$D$3),INDEX(Assumptions!$C$186:$E$186,$B$3),0) -> 0 | F81: =IF(4>=INDEX(Assumptions!$C$187:$E$187,$D$3),INDEX(Assumptions!$C$186:$E$186,$B$3),0) -> 0 | G81: =IF(5>=INDEX(Assumptions!$C$187:$E$187,$D$3),INDEX(Assumptions!$C$186:$E$186,$B$3),0) -> 0 | H81: =IF(6>=INDEX(Assumptions!$C$187:$E$187,$D$3),INDEX(Assumptions!$C$186:$E$186,$B$3),0) -> 0 | I81: =IF(7>=INDEX(Assumptions!$C$187:$E$187,$D$3),INDEX(Assumptions!$C$186:$E$186,$B$3),0) -> 0 | J81: =IF(8>=INDEX(Assumptions!$C$187:$E$187,$D$3),INDEX(Assumptions!$C$186:$E$186,$B$3),0) -> 0 | K81: =IF(9>=INDEX(Assumptions!$C$187:$E$187,$D$3),INDEX(Assumptions!$C$186:$E$186,$B$3),0) -> 0 | L81: =IF(10>=INDEX(Assumptions!$C$187:$E$187,$D$3),INDEX(Assumptions!$C$186:$E$186,$B$3),0) -> 0 | M81: =IF(11>=INDEX(Assumptions!$C$187:$E$187,$D$3),INDEX(Assumptions!$C$186:$E$186,$B$3),0) -> 0 | N81: =IF(12>=INDEX(Assumptions!$C$187:$E$187,$D$3),INDEX(Assumptions!$C$186:$E$186,$B$3),0) -> 0 | O81: =SUM(C81:N81) -> 0
A82: Total people cost (founder not charged - owner's return) | C82: =SUM(C77:C81) -> 32000 | D82: =SUM(D77:D81) -> 32000 | E82: =SUM(E77:E81) -> 89500 | F82: =SUM(F77:F81) -> 89500 | G82: =SUM(G77:G81) -> 89500 | H82: =SUM(H77:H81) -> 89500 | I82: =SUM(I77:I81) -> 89500 | J82: =SUM(J77:J81) -> 89500 | ... N82: =SUM(N77:N81) -> 89500 | O82: =SUM(C82:N82) -> 959000
A83: H. Occupancy, marketing and overheads
A84: Rent: today's academy share, or new space from move month | C84: =IF(1>=INDEX(Assumptions!$C$173:$E$173,$D$3),INDEX(Assumptions!$C$174:$E$174,$D$3)*INDEX(Assumptions!$C$175:$E$175,$B$3),INDEX(Assumptions!$C$179:$E$179,$B$3))*$F$4 -> 45000 | D84: =IF(2>=INDEX(Assumptions!$C$173:$E$173,$D$3),INDEX(Assumptions!$C$174:$E$174,$D$3)*INDEX(Assumptions!$C$175:$E$175,$B$3),INDEX(Assumptions!$C$179:$E$179,$B$3))*$F$4 -> 45000 | E84: =IF(3>=INDEX(Assumptions!$C$173:$E$173,$D$3),INDEX(Assumptions!$C$174:$E$174,$D$3)*INDEX(Assumptions!$C$175:$E$175,$B$3),INDEX(Assumptions!$C$179:$E$179,$B$3))*$F$4 -> 45000 | F84: =IF(4>=INDEX(Assumptions!$C$173:$E$173,$D$3),INDEX(Assumptions!$C$174:$E$174,$D$3)*INDEX(Assumptions!$C$175:$E$175,$B$3),INDEX(Assumptions!$C$179:$E$179,$B$3))*$F$4 -> 45000 | G84: =IF(5>=INDEX(Assumptions!$C$173:$E$173,$D$3),INDEX(Assumptions!$C$174:$E$174,$D$3)*INDEX(Assumptions!$C$175:$E$175,$B$3),INDEX(Assumptions!$C$179:$E$179,$B$3))*$F$4 -> 45000 | H84: =IF(6>=INDEX(Assumptions!$C$173:$E$173,$D$3),INDEX(Assumptions!$C$174:$E$174,$D$3)*INDEX(Assumptions!$C$175:$E$175,$B$3),INDEX(Assumptions!$C$179:$E$179,$B$3))*$F$4 -> 45000 | I84: =IF(7>=INDEX(Assumptions!$C$173:$E$173,$D$3),INDEX(Assumptions!$C$174:$E$174,$D$3)*INDEX(Assumptions!$C$175:$E$175,$B$3),INDEX(Assumptions!$C$179:$E$179,$B$3))*$F$4 -> 45000 | J84: =IF(8>=INDEX(Assumptions!$C$173:$E$173,$D$3),INDEX(Assumptions!$C$174:$E$174,$D$3)*INDEX(Assumptions!$C$175:$E$175,$B$3),INDEX(Assumptions!$C$179:$E$179,$B$3))*$F$4 -> 45000 | K84: =IF(9>=INDEX(Assumptions!$C$173:$E$173,$D$3),INDEX(Assumptions!$C$174:$E$174,$D$3)*INDEX(Assumptions!$C$175:$E$175,$B$3),INDEX(Assumptions!$C$179:$E$179,$B$3))*$F$4 -> 45000 | L84: =IF(10>=INDEX(Assumptions!$C$173:$E$173,$D$3),INDEX(Assumptions!$C$174:$E$174,$D$3)*INDEX(Assumptions!$C$175:$E$175,$B$3),INDEX(Assumptions!$C$179:$E$179,$B$3))*$F$4 -> 45000 | M84: =IF(11>=INDEX(Assumptions!$C$173:$E$173,$D$3),INDEX(Assumptions!$C$174:$E$174,$D$3)*INDEX(Assumptions!$C$175:$E$175,$B$3),INDEX(Assumptions!$C$179:$E$179,$B$3))*$F$4 -> 45000 | N84: =IF(12>=INDEX(Assumptions!$C$173:$E$173,$D$3),INDEX(Assumptions!$C$174:$E$174,$D$3)*INDEX(Assumptions!$C$175:$E$175,$B$3),INDEX(Assumptions!$C$179:$E$179,$B$3))*$F$4 -> 45000 | O84: =SUM(C84:N84) -> 540000
A85: Utilities, housekeeping, maintenance | C85: =IF(1>=INDEX(Assumptions!$C$173:$E$173,$D$3),INDEX(Assumptions!$C$174:$E$174,$D$3)*INDEX(Assumptions!$C$181:$E$181,$B$3),INDEX(Assumptions!$C$180:$E$180,$B$3)) -> 12000 | D85: =IF(2>=INDEX(Assumptions!$C$173:$E$173,$D$3),INDEX(Assumptions!$C$174:$E$174,$D$3)*INDEX(Assumptions!$C$181:$E$181,$B$3),INDEX(Assumptions!$C$180:$E$180,$B$3)) -> 12000 | E85: =IF(3>=INDEX(Assumptions!$C$173:$E$173,$D$3),INDEX(Assumptions!$C$174:$E$174,$D$3)*INDEX(Assumptions!$C$181:$E$181,$B$3),INDEX(Assumptions!$C$180:$E$180,$B$3)) -> 12000 | F85: =IF(4>=INDEX(Assumptions!$C$173:$E$173,$D$3),INDEX(Assumptions!$C$174:$E$174,$D$3)*INDEX(Assumptions!$C$181:$E$181,$B$3),INDEX(Assumptions!$C$180:$E$180,$B$3)) -> 12000 | G85: =IF(5>=INDEX(Assumptions!$C$173:$E$173,$D$3),INDEX(Assumptions!$C$174:$E$174,$D$3)*INDEX(Assumptions!$C$181:$E$181,$B$3),INDEX(Assumptions!$C$180:$E$180,$B$3)) -> 12000 | H85: =IF(6>=INDEX(Assumptions!$C$173:$E$173,$D$3),INDEX(Assumptions!$C$174:$E$174,$D$3)*INDEX(Assumptions!$C$181:$E$181,$B$3),INDEX(Assumptions!$C$180:$E$180,$B$3)) -> 12000 | I85: =IF(7>=INDEX(Assumptions!$C$173:$E$173,$D$3),INDEX(Assumptions!$C$174:$E$174,$D$3)*INDEX(Assumptions!$C$181:$E$181,$B$3),INDEX(Assumptions!$C$180:$E$180,$B$3)) -> 12000 | J85: =IF(8>=INDEX(Assumptions!$C$173:$E$173,$D$3),INDEX(Assumptions!$C$174:$E$174,$D$3)*INDEX(Assumptions!$C$181:$E$181,$B$3),INDEX(Assumptions!$C$180:$E$180,$B$3)) -> 12000 | K85: =IF(9>=INDEX(Assumptions!$C$173:$E$173,$D$3),INDEX(Assumptions!$C$174:$E$174,$D$3)*INDEX(Assumptions!$C$181:$E$181,$B$3),INDEX(Assumptions!$C$180:$E$180,$B$3)) -> 12000 | L85: =IF(10>=INDEX(Assumptions!$C$173:$E$173,$D$3),INDEX(Assumptions!$C$174:$E$174,$D$3)*INDEX(Assumptions!$C$181:$E$181,$B$3),INDEX(Assumptions!$C$180:$E$180,$B$3)) -> 12000 | M85: =IF(11>=INDEX(Assumptions!$C$173:$E$173,$D$3),INDEX(Assumptions!$C$174:$E$174,$D$3)*INDEX(Assumptions!$C$181:$E$181,$B$3),INDEX(Assumptions!$C$180:$E$180,$B$3)) -> 12000 | N85: =IF(12>=INDEX(Assumptions!$C$173:$E$173,$D$3),INDEX(Assumptions!$C$174:$E$174,$D$3)*INDEX(Assumptions!$C$181:$E$181,$B$3),INDEX(Assumptions!$C$180:$E$180,$B$3)) -> 12000 | O85: =SUM(C85:N85) -> 144000
A86: Martech stack (A-GRO-42) + LMS after hybrid launch | C86: =INDEX(Assumptions!$C$107:$E$107,$D$3)+IF(1>=INDEX(Assumptions!$C$189:$E$189,$D$3)-1,INDEX(Assumptions!$C$188:$E$188,$D$3),0) -> 8000 | D86: =INDEX(Assumptions!$C$107:$E$107,$D$3)+IF(2>=INDEX(Assumptions!$C$189:$E$189,$D$3)-1,INDEX(Assumptions!$C$188:$E$188,$D$3),0) -> 8000 | E86: =INDEX(Assumptions!$C$107:$E$107,$D$3)+IF(3>=INDEX(Assumptions!$C$189:$E$189,$D$3)-1,INDEX(Assumptions!$C$188:$E$188,$D$3),0) -> 8000 | F86: =INDEX(Assumptions!$C$107:$E$107,$D$3)+IF(4>=INDEX(Assumptions!$C$189:$E$189,$D$3)-1,INDEX(Assumptions!$C$188:$E$188,$D$3),0) -> 8000 | G86: =INDEX(Assumptions!$C$107:$E$107,$D$3)+IF(5>=INDEX(Assumptions!$C$189:$E$189,$D$3)-1,INDEX(Assumptions!$C$188:$E$188,$D$3),0) -> 8000 | H86: =INDEX(Assumptions!$C$107:$E$107,$D$3)+IF(6>=INDEX(Assumptions!$C$189:$E$189,$D$3)-1,INDEX(Assumptions!$C$188:$E$188,$D$3),0) -> 8000 | I86: =INDEX(Assumptions!$C$107:$E$107,$D$3)+IF(7>=INDEX(Assumptions!$C$189:$E$189,$D$3)-1,INDEX(Assumptions!$C$188:$E$188,$D$3),0) -> 8000 | J86: =INDEX(Assumptions!$C$107:$E$107,$D$3)+IF(8>=INDEX(Assumptions!$C$189:$E$189,$D$3)-1,INDEX(Assumptions!$C$188:$E$188,$D$3),0) -> 8000 | K86: =INDEX(Assumptions!$C$107:$E$107,$D$3)+IF(9>=INDEX(Assumptions!$C$189:$E$189,$D$3)-1,INDEX(Assumptions!$C$188:$E$188,$D$3),0) -> 8000 | L86: =INDEX(Assumptions!$C$107:$E$107,$D$3)+IF(10>=INDEX(Assumptions!$C$189:$E$189,$D$3)-1,INDEX(Assumptions!$C$188:$E$188,$D$3),0) -> 8000 | M86: =INDEX(Assumptions!$C$107:$E$107,$D$3)+IF(11>=INDEX(Assumptions!$C$189:$E$189,$D$3)-1,INDEX(Assumptions!$C$188:$E$188,$D$3),0) -> 8000 | N86: =INDEX(Assumptions!$C$107:$E$107,$D$3)+IF(12>=INDEX(Assumptions!$C$189:$E$189,$D$3)-1,INDEX(Assumptions!$C$188:$E$188,$D$3),0) -> 8000 | O86: =SUM(C86:N86) -> 96000
A87: Paid media (Growth budget) | C87: =C15 -> 10000 | D87: =D15 -> 25000 | E87: =E15 -> 30000 | F87: =F15 -> 35000 | G87: =G15 -> 40000 | H87: =H15 -> 40000 | I87: =I15 -> 40000 | J87: =J15 -> 40000 | ... N87: =N15 -> 40000 | O87: =SUM(C87:N87) -> 420000
A88: Partnerships, PR / outcomes report, contingency (A-ECO-58) | C88: =INDEX(Assumptions!$C$170:$E$170,$D$3) -> 3333 | D88: =INDEX(Assumptions!$C$170:$E$170,$D$3) -> 3333 | E88: =INDEX(Assumptions!$C$170:$E$170,$D$3) -> 3333 | F88: =INDEX(Assumptions!$C$170:$E$170,$D$3) -> 3333 | G88: =INDEX(Assumptions!$C$170:$E$170,$D$3) -> 3333 | H88: =INDEX(Assumptions!$C$170:$E$170,$D$3) -> 3333 | I88: =INDEX(Assumptions!$C$170:$E$170,$D$3) -> 3333 | J88: =INDEX(Assumptions!$C$170:$E$170,$D$3) -> 3333 | ... N88: =INDEX(Assumptions!$C$170:$E$170,$D$3) -> 3333 | O88: =SUM(C88:N88) -> 39996
A89: Admin, accounting, insurance, misc. (A-ECO-134) | C89: =INDEX(Assumptions!$C$195:$E$195,$D$3) -> 12000 | D89: =INDEX(Assumptions!$C$195:$E$195,$D$3) -> 12000 | E89: =INDEX(Assumptions!$C$195:$E$195,$D$3) -> 12000 | F89: =INDEX(Assumptions!$C$195:$E$195,$D$3) -> 12000 | G89: =INDEX(Assumptions!$C$195:$E$195,$D$3) -> 12000 | H89: =INDEX(Assumptions!$C$195:$E$195,$D$3) -> 12000 | I89: =INDEX(Assumptions!$C$195:$E$195,$D$3) -> 12000 | J89: =INDEX(Assumptions!$C$195:$E$195,$D$3) -> 12000 | ... N89: =INDEX(Assumptions!$C$195:$E$195,$D$3) -> 12000 | O89: =SUM(C89:N89) -> 144000
A90: One-offs: website rebuild (M1, A-GRO-49); B&WSSC/legal/accounting (M3, A-ECO-135) | C90: =IF(1=1,INDEX(Assumptions!$C$112:$E$112,$D$3),0)+IF(1=3,INDEX(Assumptions!$C$196:$E$196,$D$3),0) -> 50000 | D90: =IF(2=1,INDEX(Assumptions!$C$112:$E$112,$D$3),0)+IF(2=3,INDEX(Assumptions!$C$196:$E$196,$D$3),0) -> 0 | E90: =IF(3=1,INDEX(Assumptions!$C$112:$E$112,$D$3),0)+IF(3=3,INDEX(Assumptions!$C$196:$E$196,$D$3),0) -> 50000 | F90: =IF(4=1,INDEX(Assumptions!$C$112:$E$112,$D$3),0)+IF(4=3,INDEX(Assumptions!$C$196:$E$196,$D$3),0) -> 0 | G90: =IF(5=1,INDEX(Assumptions!$C$112:$E$112,$D$3),0)+IF(5=3,INDEX(Assumptions!$C$196:$E$196,$D$3),0) -> 0 | H90: =IF(6=1,INDEX(Assumptions!$C$112:$E$112,$D$3),0)+IF(6=3,INDEX(Assumptions!$C$196:$E$196,$D$3),0) -> 0 | I90: =IF(7=1,INDEX(Assumptions!$C$112:$E$112,$D$3),0)+IF(7=3,INDEX(Assumptions!$C$196:$E$196,$D$3),0) -> 0 | J90: =IF(8=1,INDEX(Assumptions!$C$112:$E$112,$D$3),0)+IF(8=3,INDEX(Assumptions!$C$196:$E$196,$D$3),0) -> 0 | K90: =IF(9=1,INDEX(Assumptions!$C$112:$E$112,$D$3),0)+IF(9=3,INDEX(Assumptions!$C$196:$E$196,$D$3),0) -> 0 | L90: =IF(10=1,INDEX(Assumptions!$C$112:$E$112,$D$3),0)+IF(10=3,INDEX(Assumptions!$C$196:$E$196,$D$3),0) -> 0 | M90: =IF(11=1,INDEX(Assumptions!$C$112:$E$112,$D$3),0)+IF(11=3,INDEX(Assumptions!$C$196:$E$196,$D$3),0) -> 0 | N90: =IF(12=1,INDEX(Assumptions!$C$112:$E$112,$D$3),0)+IF(12=3,INDEX(Assumptions!$C$196:$E$196,$D$3),0) -> 0 | O90: =SUM(C90:N90) -> 100000
A91: Total fixed and overhead opex (incl. people) | C91: =C82+SUM(C84:C90) -> 172333 | D91: =D82+SUM(D84:D90) -> 137333 | E91: =E82+SUM(E84:E90) -> 249833 | F91: =F82+SUM(F84:F90) -> 204833 | G91: =G82+SUM(G84:G90) -> 209833 | H91: =H82+SUM(H84:H90) -> 209833 | I91: =I82+SUM(I84:I90) -> 209833 | J91: =J82+SUM(J84:J90) -> 209833 | ... N91: =N82+SUM(N84:N90) -> 209833 | O91: =SUM(C91:N91) -> 2442996
A92: EBITDA | C92: =C69-C91 -> -156838.45 | D92: =D69-D91 -> -111341.63 | E92: =E69-E91 -> -209394.82 | F92: =F69-F91 -> -143806.42 | G92: =G69-G91 -> -143375.34 | H92: =H69-H91 -> -132219.01 | I92: =I69-I91 -> -110432.63 | J92: =J69-J91 -> -105383.51 | ... N92: =N69-N91 -> -44053.26 | O92: =SUM(C92:N92) -> -1355445.7
A93: EBITDA margin | C93: =IFERROR(C92/C57,0) -> -6.4463747 | D93: =IFERROR(D92/D57,0) -> -2.7211666 | E93: =IFERROR(E92/E57,0) -> -3.375289 | F93: =IFERROR(F92/F57,0) -> -1.4484367 | G93: =IFERROR(G92/G57,0) -> -1.2580362 | H93: =IFERROR(H92/H57,0) -> -0.97491367 | I93: =IFERROR(I92/I57,0) -> -0.61935874 | J93: =IFERROR(J92/J57,0) -> -0.55926232 | ... O93: =IFERROR(O92/O57,0) -> -0.81094506
A94: Memo: EBITDA after a founder-role market salary (A-ECO-138) | C94: =C92-INDEX(Assumptions!$C$163:$E$163,$B$3) -> -231838.45 | D94: =D92-INDEX(Assumptions!$C$163:$E$163,$B$3) -> -186341.63 | E94: =E92-INDEX(Assumptions!$C$163:$E$163,$B$3) -> -284394.82 | F94: =F92-INDEX(Assumptions!$C$163:$E$163,$B$3) -> -218806.42 | G94: =G92-INDEX(Assumptions!$C$163:$E$163,$B$3) -> -218375.34 | H94: =H92-INDEX(Assumptions!$C$163:$E$163,$B$3) -> -207219.01 | I94: =I92-INDEX(Assumptions!$C$163:$E$163,$B$3) -> -185432.63 | J94: =J92-INDEX(Assumptions!$C$163:$E$163,$B$3) -> -180383.51 | ... N94: =N92-INDEX(Assumptions!$C$163:$E$163,$B$3) -> -119053.26 | O94: =SUM(C94:N94) -> -2255445.7
A95: I. Capex, deposits and cash
A96: Fit-out of new space (month before move) | C96: =IF(1=INDEX(Assumptions!$C$173:$E$173,$D$3)-1,INDEX(Assumptions!$C$174:$E$174,$D$3)*INDEX(Assumptions!$C$182:$E$182,$B$3),0) -> 0 | D96: =IF(2=INDEX(Assumptions!$C$173:$E$173,$D$3)-1,INDEX(Assumptions!$C$174:$E$174,$D$3)*INDEX(Assumptions!$C$182:$E$182,$B$3),0) -> 0 | E96: =IF(3=INDEX(Assumptions!$C$173:$E$173,$D$3)-1,INDEX(Assumptions!$C$174:$E$174,$D$3)*INDEX(Assumptions!$C$182:$E$182,$B$3),0) -> 0 | F96: =IF(4=INDEX(Assumptions!$C$173:$E$173,$D$3)-1,INDEX(Assumptions!$C$174:$E$174,$D$3)*INDEX(Assumptions!$C$182:$E$182,$B$3),0) -> 0 | G96: =IF(5=INDEX(Assumptions!$C$173:$E$173,$D$3)-1,INDEX(Assumptions!$C$174:$E$174,$D$3)*INDEX(Assumptions!$C$182:$E$182,$B$3),0) -> 0 | H96: =IF(6=INDEX(Assumptions!$C$173:$E$173,$D$3)-1,INDEX(Assumptions!$C$174:$E$174,$D$3)*INDEX(Assumptions!$C$182:$E$182,$B$3),0) -> 0 | I96: =IF(7=INDEX(Assumptions!$C$173:$E$173,$D$3)-1,INDEX(Assumptions!$C$174:$E$174,$D$3)*INDEX(Assumptions!$C$182:$E$182,$B$3),0) -> 0 | J96: =IF(8=INDEX(Assumptions!$C$173:$E$173,$D$3)-1,INDEX(Assumptions!$C$174:$E$174,$D$3)*INDEX(Assumptions!$C$182:$E$182,$B$3),0) -> 0 | K96: =IF(9=INDEX(Assumptions!$C$173:$E$173,$D$3)-1,INDEX(Assumptions!$C$174:$E$174,$D$3)*INDEX(Assumptions!$C$182:$E$182,$B$3),0) -> 0 | L96: =IF(10=INDEX(Assumptions!$C$173:$E$173,$D$3)-1,INDEX(Assumptions!$C$174:$E$174,$D$3)*INDEX(Assumptions!$C$182:$E$182,$B$3),0) -> 0 | M96: =IF(11=INDEX(Assumptions!$C$173:$E$173,$D$3)-1,INDEX(Assumptions!$C$174:$E$174,$D$3)*INDEX(Assumptions!$C$182:$E$182,$B$3),0) -> 0 | N96: =IF(12=INDEX(Assumptions!$C$173:$E$173,$D$3)-1,INDEX(Assumptions!$C$174:$E$174,$D$3)*INDEX(Assumptions!$C$182:$E$182,$B$3),0) -> 0 | O96: =SUM(C96:N96) -> 0
A97: Additional stations | C97: =IF(1=INDEX(Assumptions!$C$173:$E$173,$D$3)-1,MAX(0,INDEX(Assumptions!$C$176:$E$176,$D$3)-INDEX(Assumptions!$C$171:$E$171,$B$3))*INDEX(Assumptions!$C$183:$E$183,$B$3),0) -> 0 | D97: =IF(2=INDEX(Assumptions!$C$173:$E$173,$D$3)-1,MAX(0,INDEX(Assumptions!$C$176:$E$176,$D$3)-INDEX(Assumptions!$C$171:$E$171,$B$3))*INDEX(Assumptions!$C$183:$E$183,$B$3),0) -> 0 | E97: =IF(3=INDEX(Assumptions!$C$173:$E$173,$D$3)-1,MAX(0,INDEX(Assumptions!$C$176:$E$176,$D$3)-INDEX(Assumptions!$C$171:$E$171,$B$3))*INDEX(Assumptions!$C$183:$E$183,$B$3),0) -> 0 | F97: =IF(4=INDEX(Assumptions!$C$173:$E$173,$D$3)-1,MAX(0,INDEX(Assumptions!$C$176:$E$176,$D$3)-INDEX(Assumptions!$C$171:$E$171,$B$3))*INDEX(Assumptions!$C$183:$E$183,$B$3),0) -> 0 | G97: =IF(5=INDEX(Assumptions!$C$173:$E$173,$D$3)-1,MAX(0,INDEX(Assumptions!$C$176:$E$176,$D$3)-INDEX(Assumptions!$C$171:$E$171,$B$3))*INDEX(Assumptions!$C$183:$E$183,$B$3),0) -> 0 | H97: =IF(6=INDEX(Assumptions!$C$173:$E$173,$D$3)-1,MAX(0,INDEX(Assumptions!$C$176:$E$176,$D$3)-INDEX(Assumptions!$C$171:$E$171,$B$3))*INDEX(Assumptions!$C$183:$E$183,$B$3),0) -> 0 | I97: =IF(7=INDEX(Assumptions!$C$173:$E$173,$D$3)-1,MAX(0,INDEX(Assumptions!$C$176:$E$176,$D$3)-INDEX(Assumptions!$C$171:$E$171,$B$3))*INDEX(Assumptions!$C$183:$E$183,$B$3),0) -> 0 | J97: =IF(8=INDEX(Assumptions!$C$173:$E$173,$D$3)-1,MAX(0,INDEX(Assumptions!$C$176:$E$176,$D$3)-INDEX(Assumptions!$C$171:$E$171,$B$3))*INDEX(Assumptions!$C$183:$E$183,$B$3),0) -> 0 | K97: =IF(9=INDEX(Assumptions!$C$173:$E$173,$D$3)-1,MAX(0,INDEX(Assumptions!$C$176:$E$176,$D$3)-INDEX(Assumptions!$C$171:$E$171,$B$3))*INDEX(Assumptions!$C$183:$E$183,$B$3),0) -> 0 | L97: =IF(10=INDEX(Assumptions!$C$173:$E$173,$D$3)-1,MAX(0,INDEX(Assumptions!$C$176:$E$176,$D$3)-INDEX(Assumptions!$C$171:$E$171,$B$3))*INDEX(Assumptions!$C$183:$E$183,$B$3),0) -> 0 | M97: =IF(11=INDEX(Assumptions!$C$173:$E$173,$D$3)-1,MAX(0,INDEX(Assumptions!$C$176:$E$176,$D$3)-INDEX(Assumptions!$C$171:$E$171,$B$3))*INDEX(Assumptions!$C$183:$E$183,$B$3),0) -> 0 | N97: =IF(12=INDEX(Assumptions!$C$173:$E$173,$D$3)-1,MAX(0,INDEX(Assumptions!$C$176:$E$176,$D$3)-INDEX(Assumptions!$C$171:$E$171,$B$3))*INDEX(Assumptions!$C$183:$E$183,$B$3),0) -> 0 | O97: =SUM(C97:N97) -> 0
A98: Security deposit (refundable; cash out) | C98: =IF(1=INDEX(Assumptions!$C$173:$E$173,$D$3)-1,INDEX(Assumptions!$C$184:$E$184,$B$3)*INDEX(Assumptions!$C$174:$E$174,$D$3)*INDEX(Assumptions!$C$175:$E$175,$B$3)*$F$4,0) -> 0 | D98: =IF(2=INDEX(Assumptions!$C$173:$E$173,$D$3)-1,INDEX(Assumptions!$C$184:$E$184,$B$3)*INDEX(Assumptions!$C$174:$E$174,$D$3)*INDEX(Assumptions!$C$175:$E$175,$B$3)*$F$4,0) -> 0 | E98: =IF(3=INDEX(Assumptions!$C$173:$E$173,$D$3)-1,INDEX(Assumptions!$C$184:$E$184,$B$3)*INDEX(Assumptions!$C$174:$E$174,$D$3)*INDEX(Assumptions!$C$175:$E$175,$B$3)*$F$4,0) -> 0 | F98: =IF(4=INDEX(Assumptions!$C$173:$E$173,$D$3)-1,INDEX(Assumptions!$C$184:$E$184,$B$3)*INDEX(Assumptions!$C$174:$E$174,$D$3)*INDEX(Assumptions!$C$175:$E$175,$B$3)*$F$4,0) -> 0 | G98: =IF(5=INDEX(Assumptions!$C$173:$E$173,$D$3)-1,INDEX(Assumptions!$C$184:$E$184,$B$3)*INDEX(Assumptions!$C$174:$E$174,$D$3)*INDEX(Assumptions!$C$175:$E$175,$B$3)*$F$4,0) -> 0 | H98: =IF(6=INDEX(Assumptions!$C$173:$E$173,$D$3)-1,INDEX(Assumptions!$C$184:$E$184,$B$3)*INDEX(Assumptions!$C$174:$E$174,$D$3)*INDEX(Assumptions!$C$175:$E$175,$B$3)*$F$4,0) -> 0 | I98: =IF(7=INDEX(Assumptions!$C$173:$E$173,$D$3)-1,INDEX(Assumptions!$C$184:$E$184,$B$3)*INDEX(Assumptions!$C$174:$E$174,$D$3)*INDEX(Assumptions!$C$175:$E$175,$B$3)*$F$4,0) -> 0 | J98: =IF(8=INDEX(Assumptions!$C$173:$E$173,$D$3)-1,INDEX(Assumptions!$C$184:$E$184,$B$3)*INDEX(Assumptions!$C$174:$E$174,$D$3)*INDEX(Assumptions!$C$175:$E$175,$B$3)*$F$4,0) -> 0 | K98: =IF(9=INDEX(Assumptions!$C$173:$E$173,$D$3)-1,INDEX(Assumptions!$C$184:$E$184,$B$3)*INDEX(Assumptions!$C$174:$E$174,$D$3)*INDEX(Assumptions!$C$175:$E$175,$B$3)*$F$4,0) -> 0 | L98: =IF(10=INDEX(Assumptions!$C$173:$E$173,$D$3)-1,INDEX(Assumptions!$C$184:$E$184,$B$3)*INDEX(Assumptions!$C$174:$E$174,$D$3)*INDEX(Assumptions!$C$175:$E$175,$B$3)*$F$4,0) -> 0 | M98: =IF(11=INDEX(Assumptions!$C$173:$E$173,$D$3)-1,INDEX(Assumptions!$C$184:$E$184,$B$3)*INDEX(Assumptions!$C$174:$E$174,$D$3)*INDEX(Assumptions!$C$175:$E$175,$B$3)*$F$4,0) -> 0 | N98: =IF(12=INDEX(Assumptions!$C$173:$E$173,$D$3)-1,INDEX(Assumptions!$C$184:$E$184,$B$3)*INDEX(Assumptions!$C$174:$E$174,$D$3)*INDEX(Assumptions!$C$175:$E$175,$B$3)*$F$4,0) -> 0 | O98: =SUM(C98:N98) -> 0
A99: CRM / WhatsApp BSP / GBP / photo-video proof kit (M1) | C99: =IF(1=1,INDEX(Assumptions!$C$197:$E$197,$D$3),0) -> 50000 | D99: =IF(2=1,INDEX(Assumptions!$C$197:$E$197,$D$3),0) -> 0 | E99: =IF(3=1,INDEX(Assumptions!$C$197:$E$197,$D$3),0) -> 0 | F99: =IF(4=1,INDEX(Assumptions!$C$197:$E$197,$D$3),0) -> 0 | G99: =IF(5=1,INDEX(Assumptions!$C$197:$E$197,$D$3),0) -> 0 | H99: =IF(6=1,INDEX(Assumptions!$C$197:$E$197,$D$3),0) -> 0 | I99: =IF(7=1,INDEX(Assumptions!$C$197:$E$197,$D$3),0) -> 0 | J99: =IF(8=1,INDEX(Assumptions!$C$197:$E$197,$D$3),0) -> 0 | K99: =IF(9=1,INDEX(Assumptions!$C$197:$E$197,$D$3),0) -> 0 | L99: =IF(10=1,INDEX(Assumptions!$C$197:$E$197,$D$3),0) -> 0 | M99: =IF(11=1,INDEX(Assumptions!$C$197:$E$197,$D$3),0) -> 0 | N99: =IF(12=1,INDEX(Assumptions!$C$197:$E$197,$D$3),0) -> 0 | O99: =SUM(C99:N99) -> 50000
A100: Hybrid pre-work content + LMS set-up (2 months before launch) | C100: =IF(1=INDEX(Assumptions!$C$189:$E$189,$D$3)-2,INDEX(Assumptions!$C$190:$E$190,$D$3),0) -> 0 | D100: =IF(2=INDEX(Assumptions!$C$189:$E$189,$D$3)-2,INDEX(Assumptions!$C$190:$E$190,$D$3),0) -> 0 | E100: =IF(3=INDEX(Assumptions!$C$189:$E$189,$D$3)-2,INDEX(Assumptions!$C$190:$E$190,$D$3),0) -> 0 | F100: =IF(4=INDEX(Assumptions!$C$189:$E$189,$D$3)-2,INDEX(Assumptions!$C$190:$E$190,$D$3),0) -> 0 | G100: =IF(5=INDEX(Assumptions!$C$189:$E$189,$D$3)-2,INDEX(Assumptions!$C$190:$E$190,$D$3),0) -> 0 | H100: =IF(6=INDEX(Assumptions!$C$189:$E$189,$D$3)-2,INDEX(Assumptions!$C$190:$E$190,$D$3),0) -> 0 | I100: =IF(7=INDEX(Assumptions!$C$189:$E$189,$D$3)-2,INDEX(Assumptions!$C$190:$E$190,$D$3),0) -> 0 | J100: =IF(8=INDEX(Assumptions!$C$189:$E$189,$D$3)-2,INDEX(Assumptions!$C$190:$E$190,$D$3),0) -> 0 | K100: =IF(9=INDEX(Assumptions!$C$189:$E$189,$D$3)-2,INDEX(Assumptions!$C$190:$E$190,$D$3),0) -> 0 | L100: =IF(10=INDEX(Assumptions!$C$189:$E$189,$D$3)-2,INDEX(Assumptions!$C$190:$E$190,$D$3),0) -> 0 | M100: =IF(11=INDEX(Assumptions!$C$189:$E$189,$D$3)-2,INDEX(Assumptions!$C$190:$E$190,$D$3),0) -> 0 | N100: =IF(12=INDEX(Assumptions!$C$189:$E$189,$D$3)-2,INDEX(Assumptions!$C$190:$E$190,$D$3),0) -> 0 | O100: =SUM(C100:N100) -> 0
...

Sheet Outlook_Base
A1: 12-month operating outlook - Base (base rates, ₹30L plan) (₹, ex-GST, Nov-2026 to Oct-2027)
A2: Cash/booking basis. Enrolments follow the Growth plan target (A-GRO-01) limited by what the paid budget can buy and by seat capacity. Blue cells in rows 3-4 are flex switches used by Sensitivity.
A3: Rate index (1 Cons / 2 Base / 3 Aggr) | B3: 2 | C3: Plan index | D3: 2 | E3: conv x | F3: 1 | G3: fee x | H3: 1 | I3: fill x | J3: 1 | K3: CPL x | L3: 1 | M3: var cost x | N3: 1
E4: rent x | F4: 1 | G4: GST incl.? | H4: =INDEX(Assumptions!$C$16:$E$16,$B$3) -> 1 | I4: budget x | J4: 1
A5: Line | B5: Note | C5: Nov-26 | D5: Dec-26 | E5: Jan-27 | F5: Feb-27 | G5: Mar-27 | H5: Apr-27 | I5: May-27 | J5: Jun-27 | K5: Jul-27 | L5: Aug-27 | M5: Sep-27 | N5: Oct-27 | O5: Year 1 | P5: Basis / IDs
A6: A. Timeline
A7: Month # | C7: =1 -> 1 | D7: =2 -> 2 | E7: =3 -> 3 | F7: =4 -> 4 | G7: =5 -> 5 | H7: =6 -> 6 | I7: =7 -> 7 | J7: =8 -> 8 | K7: =9 -> 9 | L7: =10 -> 10 | M7: =11 -> 11 | N7: =12 -> 12
A8: Calendar month number | C8: =MOD(C7+9,12)+1 -> 11 | D8: =MOD(D7+9,12)+1 -> 12 | E8: =MOD(E7+9,12)+1 -> 1 | F8: =MOD(F7+9,12)+1 -> 2 | G8: =MOD(G7+9,12)+1 -> 3 | H8: =MOD(H7+9,12)+1 -> 4 | I8: =MOD(I7+9,12)+1 -> 5 | J8: =MOD(J7+9,12)+1 -> 6 | ... N8: =MOD(N7+9,12)+1 -> 10
A9: Career-enquiry seasonality (A-GRO-40) | C9: =INDEX(Assumptions!$D$133:$D$144,C8) -> 0.8 | D9: =INDEX(Assumptions!$D$133:$D$144,D8) -> 0.75 | E9: =INDEX(Assumptions!$D$133:$D$144,E8) -> 0.7 | F9: =INDEX(Assumptions!$D$133:$D$144,F8) -> 0.8 | G9: =INDEX(Assumptions!$D$133:$D$144,G8) -> 0.9 | H9: =INDEX(Assumptions!$D$133:$D$144,H8) -> 1 | I9: =INDEX(Assumptions!$D$133:$D$144,I8) -> 1.3 | J9: =INDEX(Assumptions!$D$133:$D$144,J8) -> 1.35 | ... N9: =INDEX(Assumptions!$D$133:$D$144,N8) -> 1 | O9: =AVERAGE(C9:N9) -> 1
A10: Self-makeup seasonality (A-ECO-60) | C10: =INDEX(Assumptions!$D$145:$D$156,C8) -> 1.4 | D10: =INDEX(Assumptions!$D$145:$D$156,D8) -> 1.2 | E10: =INDEX(Assumptions!$D$145:$D$156,E8) -> 1.2 | F10: =INDEX(Assumptions!$D$145:$D$156,F8) -> 1.3 | G10: =INDEX(Assumptions!$D$145:$D$156,G8) -> 0.9 | H10: =INDEX(Assumptions!$D$145:$D$156,H8) -> 0.8 | I10: =INDEX(Assumptions!$D$145:$D$156,I8) -> 0.7 | J10: =INDEX(Assumptions!$D$145:$D$156,J8) -> 0.6 | ... N10: =INDEX(Assumptions!$D$145:$D$156,N8) -> 1.4 | O10: =AVERAGE(C10:N10) -> 1
