Workbook

Sheet README
A1: PNA funnel economics - instrumented admissions funnel by channel
A2: Economics & Market Sizing agent, 2026-10-16. Build script: economics/build_scripts/build_funnel_economics.py
A4: Alignment | B4: Uses the Growth agent's master assumption table (strategy/admissions_funnel.md §9, A-GRO-01..50) with its IDs and values, mapped Low/Base/High -> scenario columns per its convention (cost 'High' = Conservative). Adds A-BM (Business Model agent) pop-up inputs and A-ECO delivery-cost inputs.
A5: Method | B5: Target-driven per month at steady state (months 7-12): A-GRO-01 x route mix (A-GRO-03) / route conversion (A-GRO-18..22) = leads; leads x CPL = spend. Webinar + regional pop-up route (S7) is additive. Unit economics per career student: first-course revenue (ex-GST) - variable delivery cost = contribution; + 24-month follow-on = LTV.
A6: Sheets | B6: Summary (Cons/Base/Aggr side by side) ; Assumptions ; Funnel_Selected (driven by Assumptions!C3) ; Funnel_Conservative / _Base / _Aggressive ; Speed_to_Lead (H7) ; Popup_Events (BM M5).
A7: Feeds | B7: Summary 'FEED' rows -> business_forecast.xlsx Assumptions A-ECO-FUN-01..03 (pasted by run_all.py).
A8: GST | B8: Fees assumed quoted GST-inclusive (A-ECO-24 = 1): revenue = fee / 1.18. 18% GST applies to private non-recognised training (A-ECO-23).
A9: Limitations | B9: All conversion and CPL inputs are hypotheses from vendor/US benchmarks (A-CUS/A-GRO); replace with PNA CRM data after 6-8 weeks of instrumentation. Organic and referral volumes are derived from the target, not observed.

Sheet Summary
A1: Funnel economics - scenario summary (per month at steady state unless stated)
A2: Read with admissions_funnel.md §10 (Growth agent). Outputs in the yellow rows feed business_forecast.xlsx (pasted by run_all.py).
A4: Metric | B4: Conservative | C4: Base | D4: Aggressive | E4: Selected | F4: Source row
A5: Career enrolment target / month | B5: =Funnel_Conservative!H7 -> 6 | C5: =Funnel_Base!H7 -> 10 | D5: =Funnel_Aggressive!H7 -> 15 | E5: =Funnel_Selected!H7 -> 10 | F5: H7
A6: Career + webinar/pop-up enrolments / month | B6: =Funnel_Conservative!H16 -> 6.28125 | C6: =Funnel_Base!H16 -> 12.516 | D6: =Funnel_Aggressive!H16 -> 23.142 | E6: =Funnel_Selected!H16 -> 12.516 | F6: H16
A7: Leads / month (career routes + webinar/pop-up) | B7: =Funnel_Conservative!H17 -> 184.07407 | C7: =Funnel_Base!H17 -> 188.96803 | D7: =Funnel_Aggressive!H17 -> 214.0413 | E7: =Funnel_Selected!H17 -> 188.96803 | F7: H17
A8: Overall lead -> enrolled | B8: =Funnel_Conservative!H14 -> 0.034123491 | C8: =Funnel_Base!H14 -> 0.066233427 | D8: =Funnel_Aggressive!H14 -> 0.10811932 | E8: =Funnel_Selected!H14 -> 0.066233427 | F8: H14
A9: Media spend / month, career routes (₹) | B9: =Funnel_Conservative!H52 -> 64548.184 | C9: =Funnel_Base!H52 -> 37633.023 | D9: =Funnel_Aggressive!H52 -> 9386.9905 | E9: =Funnel_Selected!H52 -> 37633.023 | F9: H52
A10: Channel spend incl. content + rewards (₹) | B10: =Funnel_Conservative!H24 -> 82548.184 | C10: =Funnel_Base!H24 -> 78633.023 | D10: =Funnel_Aggressive!H24 -> 65386.99 | E10: =Funnel_Selected!H24 -> 78633.023 | F10: H24
A11: Meta CTWA CAC (₹) | B11: =Funnel_Conservative!B42 -> 19809.524 | C11: =Funnel_Base!B42 -> 5445.0758 | D11: =Funnel_Aggressive!B42 -> 1603.1028 | E11: =Funnel_Selected!B42 -> 5445.0758 | F11: B42
A12: Google Search CAC (₹) | B12: =Funnel_Conservative!C42 -> 19047.619 | C12: =Funnel_Base!C42 -> 7233.7963 | D12: =Funnel_Aggressive!C42 -> 3102.7796 | E12: =Funnel_Selected!C42 -> 7233.7963 | F12: C42
A13: Organic CAC (content cost) (₹) | B13: =Funnel_Conservative!D42 -> 10000 | C13: =Funnel_Base!D42 -> 17500 | D13: =Funnel_Aggressive!D42 -> 16666.667 | E13: =Funnel_Selected!D42 -> 17500 | F13: D42
A14: Referral CAC (reward) (₹) | B14: =Funnel_Conservative!E42 -> 5000 | C14: =Funnel_Base!E42 -> 3000 | D14: =Funnel_Aggressive!E42 -> 2000 | E14: =Funnel_Selected!E42 -> 3000 | F14: E42
A15: Taster CAC net of tickets (₹) | B15: =Funnel_Conservative!F42 -> 2556.4972 | C15: =Funnel_Base!F42 -> -1844.3731 | D15: =Funnel_Aggressive!F42 -> -2481.1676 | E15: =Funnel_Selected!F42 -> -1844.3731 | F15: F42
A16: Webinar + pop-up CAC (₹) | B16: =Funnel_Conservative!G42 -> 16000 | C16: =Funnel_Base!G42 -> 3447.7648 | D16: =Funnel_Aggressive!G42 -> -419.25317 | E16: =Funnel_Selected!G42 -> 3447.7648 | F16: G42
A17: Blended CAC, all routes (₹) | B17: =Funnel_Conservative!H42 -> 13141.999 | C17: =Funnel_Base!H42 -> 6282.6001 | D17: =Funnel_Aggressive!H42 -> 2825.4684 | E17: =Funnel_Selected!H42 -> 6282.6001 | F17: H42
A18: Paid-only CAC (₹) | B18: =Funnel_Conservative!H46 -> 16630.772 | C18: =Funnel_Base!H46 -> 4419.0962 | D18: =Funnel_Aggressive!H46 -> 547.60183 | E18: =Funnel_Selected!H46 -> 4419.0962 | F18: H46
A19: Fully loaded CAC incl. counsellor (₹) | B19: =Funnel_Conservative!H51 -> 17599.711 | C19: =Funnel_Base!H51 -> 11316.157 | D19: =Funnel_Aggressive!H51 -> 6714.5014 | E19: =Funnel_Selected!H51 -> 11316.157 | F19: H51
A20: Blended CAC as % of first-course revenue | B20: =Funnel_Conservative!H43 -> 0.44428446 | C20: =Funnel_Base!H43 -> 0.11605271 | D20: =Funnel_Aggressive!H43 -> 0.039959763 | E20: =Funnel_Selected!H43 -> 0.11605271 | F20: H43
A21: First-course revenue per career student, ex-GST (₹) | B21: =Funnel_Conservative!H28 -> 29580.147 | C21: =Funnel_Base!H28 -> 54135.748 | D21: =Funnel_Aggressive!H28 -> 70707.837 | E21: =Funnel_Selected!H28 -> 54135.748 | F21: H28
A22: First-course contribution before CAC (₹) | B22: =Funnel_Conservative!H31 -> 7902.0029 | C22: =Funnel_Base!H31 -> 41781.168 | D22: =Funnel_Aggressive!H31 -> 59892.8 | E22: =Funnel_Selected!H31 -> 41781.168 | F22: H31
A23: Follow-on 24-month contribution (₹) | B23: =Funnel_Conservative!H33 -> 3023.3835 | C23: =Funnel_Base!H33 -> 8747.161 | D23: =Funnel_Aggressive!H33 -> 18188.099 | E23: =Funnel_Selected!H33 -> 8747.161 | F23: H33
A24: LTV (24-month contribution) (₹) | B24: =Funnel_Conservative!H34 -> 10925.386 | C24: =Funnel_Base!H34 -> 50528.329 | D24: =Funnel_Aggressive!H34 -> 78080.899 | E24: =Funnel_Selected!H34 -> 50528.329 | F24: H34
A25: LTV / blended CAC | B25: =Funnel_Conservative!H44 -> 0.83133365 | C25: =Funnel_Base!H44 -> 8.0425824 | D25: =Funnel_Aggressive!H44 -> 27.634674 | E25: =Funnel_Selected!H44 -> 8.0425824 | F25: H44
A26: CAC payback (months) | B26: =Funnel_Conservative!H45 -> 4.9893678 | C26: =Funnel_Base!H45 -> 0.30073837 | D26: =Funnel_Aggressive!H45 -> 0.047175427 | E26: =Funnel_Selected!H45 -> 0.30073837 | F26: H45
A27: Counsellor FTE needed | B27: =Funnel_Conservative!H50 -> 0.92197531 | C27: =Funnel_Base!H50 -> 0.78408015 | D27: =Funnel_Aggressive!H50 -> 0.65784564 | E27: =Funnel_Selected!H50 -> 0.78408015 | F27: H50
A28: FEED: variable acquisition cost per target career enrolment (₹) | B28: =Funnel_Conservative!H47 -> 11008.031 | C28: =Funnel_Base!H47 -> 3495.8447 | D28: =Funnel_Aggressive!H47 -> 1253.37 | E28: =Funnel_Selected!H47 -> 3495.8447 | F28: H47
A29: FEED: paid-route media CAC, CTWA + Search + Taster (₹) | B29: =Funnel_Conservative!H48 -> 16680.051 | C29: =Funnel_Base!H48 -> 4826.4078 | D29: =Funnel_Aggressive!H48 -> 1422.2833 | E29: =Funnel_Selected!H48 -> 4826.4078 | F29: H48
A30: Funnel-required career media / month at target (₹) | B30: =Funnel_Conservative!H52 -> 64548.184 | C30: =Funnel_Base!H52 -> 37633.023 | D30: =Funnel_Aggressive!H52 -> 9386.9905 | E30: =Funnel_Selected!H52 -> 37633.023 | F30: H52
A31: FEED: masterclass media per seat (₹) | B31: =Funnel_Conservative!B60 -> 1400 | C31: =Funnel_Base!B60 -> 300 | D31: =Funnel_Aggressive!B60 -> 42.857143 | E31: =Funnel_Selected!B60 -> 300 | F31: B60
A32: FEED: self-makeup media per seat (₹) | B32: =Funnel_Conservative!C60 -> 3200 | C32: =Funnel_Base!C60 -> 705.88235 | D32: =Funnel_Aggressive!C60 -> 160 | E32: =Funnel_Selected!C60 -> 705.88235 | F32: C60
A34: CAC payback: BM gate G1 requires CAC payback <= 3 months and CAC <= 12% of realised fee.

Sheet Assumptions
A1: Assumptions register (inputs)
A2: Blue = input. Columns are scenario values: Conservative = adverse rates + smaller plan; Aggressive = favourable rates + larger plan. A-GRO = Growth agent master table; A-BM = Business Model agent; A-ECO = Economics agent.
A3: Scenario selector | C3: Base | D3: <- choose Conservative / Base / Aggressive (drives column I 'Selected' and any sheet that uses it)
A4: Scenario index | C4: =MATCH($C$3,$K$4:$M$4,0) -> 2 | K4: Conservative | L4: Base | M4: Aggressive
A6: ID | B6: Description | C6: Conservative | D6: Base | E6: Aggressive | F6: Unit | G6: Source / rationale | H6: Tag | I6: Selected
A8: 1. Canonical, baseline and GST
A9: CA-01 | B9: PNA paying students per year today (all courses) | C9: 30 | D9: 50 | E9: 60 | F9: students/yr | G9: Founder: 'under 60' (2026-10-16) | H9: [FOUNDER] | I9: =INDEX(C9:E9,$C$4) -> 50
A10: CA-02 | B10: Current flagship professional course fee (incl. kit) | C10: 40000 | D10: 60000 | E10: 75000 | F10: ₹ | G10: Not supplied; local diploma band ₹35-75k (S-LC §6) | H10: [HYP] | I10: =INDEX(C10:E10,$C$4) -> 60000
A11: CA-03 | B11: Growth investment envelope, 12 months | C11: 1000000 | D11: 3000000 | E11: 5000000 | F11: ₹ | G11: Founder: moderate ₹10-50L | H11: [FOUNDER] | I11: =INDEX(C11:E11,$C$4) -> 3000000
A12: A-ECO-101 | B12: Career (L2/L3-type) share of today's students | C12: 0.6 | D12: 0.6 | E12: 0.6 | F12: % | G12: Assumed mix; founder data pull (V1) to replace | H12: [HYP] | I12: =INDEX(C12:E12,$C$4) -> 0.6
A13: A-ECO-102 | B13: Average fee of today's short courses / masterclasses | C13: 6000 | D13: 8000 | E13: 10000 | F13: ₹ | G13: Local short-course band ₹6.5-25k (S-LC §6) | H13: [HYP] | I13: =INDEX(C13:E13,$C$4) -> 8000
A14: A-ECO-103 | B14: Pro kit cost borne by PNA while fee includes kit (pre price-step) | C14: 15000 | D14: 12000 | E14: 10000 | F14: ₹/student | G14: Growth agent: optional kit ₹18-25k at near cost; basic included kit assumed cheaper | H14: [HYP] | I14: =INDEX(C14:E14,$C$4) -> 12000
A15: A-ECO-23 | B15: GST rate on PNA training (private, non-recognised; SAC 9992) | C15: 0.18 | D15: 0.18 | E15: 0.18 | F15: % | G15: GST Council education flyer: private/unrecognised coaching not exempt (https://www.gstcouncil.gov.in/sites/default/files/e-version-gst-flyers/GST_Education_Services.pdf, accessed 2026-10-16); AAR Kerala 2022 -> 18% under 9992 | H15: [FACT] rule / [HYP] PNA | I15: =INDEX(C15:E15,$C$4) -> 0.18
A16: A-ECO-24 | B16: Fees quoted GST-inclusive? (1 = PNA absorbs GST from list fee; 0 = GST charged on top) | C16: 1 | D16: 1 | E16: 1 | F16: switch | G16: Consumer academies mostly quote one number; DBA quotes ex-GST, Pearl incl. GST (S-NC-26, S-IND-23). Sensitivity flips it | H16: [HYP] | I16: =INDEX(C16:E16,$C$4) -> 1
A17: 2. Prices (Growth agent ladder L1-L5; BM realised fee)
A18: A-GRO-04 | B18: L1 Career Taster ticket | C18: 999 | D18: 999 | E18: 999 | F18: ₹ | G18: A-GRO-04 base (range ₹499-1,999); credited on enrolment | H18: [HYP] | I18: =INDEX(C18:E18,$C$4) -> 999
A19: A-GRO-05 | B19: L2 Foundation fee (4 weeks, ~80 h) | C19: 30000 | D19: 39900 | E19: 45000 | F19: ₹ | G19: A-GRO-05 (Aggressive = midpoint of Growth base/high to avoid stacking upsides) | H19: [HYP] | I19: =INDEX(C19:E19,$C$4) -> 39900
A20: A-GRO-06 | B20: L3 Professional Bridal Programme list tuition (after proof gate; kit optional) | C20: 75000 | D20: 90000 | E20: 120000 | F20: ₹ | G20: A-GRO-06 | H20: [HYP] | I20: =INDEX(C20:E20,$C$4) -> 90000
A21: A-BM-02 | B21: L3 realised fee after discounts/credits (after proof gate) | C21: 65000 | D21: 80000 | E21: 100000 | F21: ₹ | G21: A-BM-02 (list ₹90k-1.25L) | H21: [HYP] | I21: =INDEX(C21:E21,$C$4) -> 80000
A22: A-GRO-07 | B22: L4 masterclass average ticket | C22: 5000 | D22: 10000 | E22: 14000 | F22: ₹ | G22: A-GRO-07 (Aggressive = midpoint of base ₹10k / high ₹18k) | H22: [HYP] | I22: =INDEX(C22:E22,$C$4) -> 10000
A23: A-GRO-08 | B23: L1-S5 self-makeup workshop price | C23: 3000 | D23: 4999 | E23: 6500 | F23: ₹ | G23: A-GRO-08 (Aggressive = midpoint) | H23: [HYP] | I23: =INDEX(C23:E23,$C$4) -> 4999
A24: A-GRO-09 | B24: L5 Pro Circle membership | C24: 4999 | D24: 9999 | E24: 12499 | F24: ₹/yr | G24: A-GRO-09 (Aggressive = midpoint); free year 1 for L3 graduates | H24: [HYP] | I24: =INDEX(C24:E24,$C$4) -> 9999
A25: A-ECO-17 | B25: Hybrid Pro (online pre-work + 5-6 wk intensive) realised fee, at L3 parity | C25: 65000 | D25: 80000 | E25: 100000 | F25: ₹ | G25: Growth/BM: hybrid at L3 price parity; = A-BM-02 | H25: [HYP] | I25: =INDEX(C25:E25,$C$4) -> 80000
A26: 3. Funnel volumes, mix, media costs and conversion (A-GRO master table)
A27: A-GRO-01 | B27: Career enrolments (L2+L3) per month, steady state (months 7-12) | C27: 6 | D27: 10 | E27: 15 | F27: enrol/mo | G27: A-GRO-01 | H27: [HYP] | I27: =INDEX(C27:E27,$C$4) -> 10
A28: A-GRO-02 | B28: Pro (L3) share of career enrolments | C28: 0.5 | D28: 0.6 | E28: 0.7 | F28: % | G28: A-GRO-02 | H28: [HYP] | I28: =INDEX(C28:E28,$C$4) -> 0.6
A29: A-GRO-03a | B29: Route mix: Meta CTWA | C29: 0.3 | D29: 0.3 | E29: 0.3 | F29: % | G29: A-GRO-03 | H29: [HYP] | I29: =INDEX(C29:E29,$C$4) -> 0.3
A30: A-GRO-03b | B30: Route mix: Paid Search | C30: 0.2 | D30: 0.2 | E30: 0.2 | F30: % | G30: A-GRO-03 | H30: [HYP] | I30: =INDEX(C30:E30,$C$4) -> 0.2
A31: A-GRO-03c | B31: Route mix: Organic (IG/site/GBP/SEO) | C31: 0.2 | D31: 0.2 | E31: 0.2 | F31: % | G31: A-GRO-03 | H31: [HYP] | I31: =INDEX(C31:E31,$C$4) -> 0.2
A32: A-GRO-03d | B32: Route mix: Referral / alumni / walk-in | C32: 0.2 | D32: 0.2 | E32: 0.2 | F32: % | G32: A-GRO-03 | H32: [HYP] | I32: =INDEX(C32:E32,$C$4) -> 0.2
A33: A-GRO-03e | B33: Route mix: Paid Career Taster | C33: 0.1 | D33: 0.1 | E33: 0.1 | F33: % | G33: A-GRO-03 | H33: [HYP] | I33: =INDEX(C33:E33,$C$4) -> 0.1
A34: A-GRO-10 | B34: Meta CTWA cost per lead, tricity | C34: 600 | D34: 300 | E34: 150 | F34: ₹/lead | G34: A-GRO-10 (High=conservative) | H34: [HYP] | I34: =INDEX(C34:E34,$C$4) -> 300
A35: A-GRO-11 | B35: Meta CTWA cost per lead, regional tier-2 | C35: 500 | D35: 250 | E35: 120 | F35: ₹/lead | G35: A-GRO-11 | H35: [HYP] | I35: =INDEX(C35:E35,$C$4) -> 250
A36: A-GRO-12 | B36: Google Search cost per lead | C36: 800 | D36: 500 | E36: 300 | F36: ₹/lead | G36: A-GRO-12 | H36: [HYP] | I36: =INDEX(C36:E36,$C$4) -> 500
A37: A-GRO-15 | B37: Cost per Taster ticket sold | C37: 700 | D37: 400 | E37: 200 | F37: ₹/ticket | G37: A-GRO-15 | H37: [HYP] | I37: =INDEX(C37:E37,$C$4) -> 400
A38: A-GRO-16 | B38: Cost per masterclass lead (paid) | C38: 300 | D38: 150 | E38: 50 | F38: ₹/lead | G38: A-GRO-16 | H38: [HYP] | I38: =INDEX(C38:E38,$C$4) -> 150
... A80: A-GRO-44 | B80: Referral + walk-in career leads per month, months 7-12 (check value) | C80: 5 | D80: 8 | E80: 12 | F80: leads/mo | G80: A-GRO-44 | H80: [HYP] | I80: =INDEX(C80:E80,$C$4) -> 8
A81: 4. Webinar / pop-up, follow-on and timing (A-BM, A-ECO)
A82: A-ECO-30 | B82: Webinar / pop-up promotion cost per registrant | C82: 150 | D82: 100 | E82: 60 | F82: ₹/registrant | G82: Regional CTWA CPL ₹120-500 (A-GRO-11) x ~40% registration | H82: [HYP] | I82: =INDEX(C82:E82,$C$4) -> 100
A83: A-ECO-31 | B83: Online parents' info sessions per month (registrants per session 30) | C83: 1 | D83: 1 | E83: 1 | F83: sessions/mo | G83: Growth agent §8.1: monthly session, 30 registrants (A-GRO §10.3) | H83: [HYP] | I83: =INDEX(C83:E83,$C$4) -> 1
A84: A-ECO-32 | B84: Registrants per online session | C84: 30 | D84: 30 | E84: 40 | F84: registrants | G84: A-GRO §10.3 | H84: [HYP] | I84: =INDEX(C84:E84,$C$4) -> 30
A85: A-BM-06a | B85: Pop-up discovery workshop: paid attendees per event | C85: 25 | D85: 32 | E85: 40 | F85: attendees | G85: A-BM-06 (25-40) | H85: [HYP] | I85: =INDEX(C85:E85,$C$4) -> 32
A86: A-BM-06b | B86: Pop-up ticket price | C86: 999 | D86: 1499 | E86: 1499 | F86: ₹ | G86: A-BM-06 (₹999-1,999; breakeven ~36 at ₹1,499) | H86: [HYP] | I86: =INDEX(C86:E86,$C$4) -> 1499
A87: A-BM-06c | B87: Pop-up cost per event-day (venue, travel, models, ads, staff) | C87: 60000 | D87: 52000 | E87: 45000 | F87: ₹/event | G87: A-BM-06 ₹45-60k | H87: [HYP] | I87: =INDEX(C87:E87,$C$4) -> 52000
A88: A-BM-06d | B88: Pop-up attendee -> L3/L2 enrolment within 60 days | C88: 0.08 | D88: 0.11 | E88: 0.15 | F88: % | G88: A-BM-06 8-15%; A-CUS-19 | H88: [HYP] | I88: =INDEX(C88:E88,$C$4) -> 0.11
A89: A-ECO-33 | B89: Pop-up events per month at steady state (regional engine; G2) | C89: 0 | D89: 0.5 | E89: 1 | F89: events/mo | G89: BM §6.2: pilots ≤₹2L before G2; circuit after G2 | H89: [HYP] | I89: =INDEX(C89:E89,$C$4) -> 0.5
A90: A-ECO-34 | B90: Payment months for career fees (token + instalments / NBFC) | C90: 3 | D90: 2 | E90: 1 | F90: months | G90: Token + 2 instalments; NBFC pays upfront when EMI used | H90: [HYP] | I90: =INDEX(C90:E90,$C$4) -> 2
A91: A-ECO-35 | B91: Masterclasses bought per career graduate within 24 months | C91: 0.3 | D91: 0.5 | E91: 0.8 | F91: purchases | G91: A-GRO-29 30%/yr repeat applied to alumni | H91: [HYP] | I91: =INDEX(C91:E91,$C$4) -> 0.5
A92: A-ECO-36 | B92: L2 Foundation -> L3 upgrade share (fee credited) | C92: 0.25 | D92: 0.3 | E92: 0.4 | F92: % | G92: Growth ladder: L2 fee credited to L3 within 6 months | H92: [HYP] | I92: =INDEX(C92:E92,$C$4) -> 0.3
A93: A-ECO-37 | B93: Optional kit uptake x margin (post price-step, near-cost kit ₹20k) | C93: 600 | D93: 960 | E93: 1400 | F93: ₹/L3 student | G93: Growth: kit optional at near cost, itemised MRP | H93: [HYP] | I93: =INDEX(C93:E93,$C$4) -> 960
... A95: A-ECO-105 | B95: Month from which the <5-min speed-to-lead SLA is met (counsellor + CRM live) | C95: 4 | D95: 3 | E95: 2 | F95: month # | G95: BM gate G0 by M3 | H95: [HYP] | I95: =INDEX(C95:E95,$C$4) -> 3
A96: 5. Delivery and growth-team costs (A-BM-04/16, A-GRO-42..50, A-ECO)
A97: A-BM-16 | B97: L3 consumables / models per student (excl. kit) | C97: 7000 | D97: 6000 | E97: 5000 | F97: ₹/student | G97: A-BM-16 ₹5-7k | H97: [HYP] | I97: =INDEX(C97:E97,$C$4) -> 6000
A98: A-ECO-40 | B98: L2 consumables per student | C98: 2500 | D98: 2000 | E98: 1500 | F98: ₹/student | G98: 1/3 of L3 duration | H98: [HYP] | I98: =INDEX(C98:E98,$C$4) -> 2000
A99: A-ECO-41 | B99: Hybrid: online delivery (LMS, live Q&A) + campus consumables per student | C99: 9000 | D99: 7500 | E99: 6000 | F99: ₹/student | G99: BM D-destination: shorter campus stay | H99: [HYP] | I99: =INDEX(C99:E99,$C$4) -> 7500
A100: A-ECO-42 | B100: L4 masterclass consumables / models per seat | C100: 1200 | D100: 1000 | E100: 800 | F100: ₹/seat | G100: Judgement | H100: [HYP] | I100: =INDEX(C100:E100,$C$4) -> 1000
A101: A-ECO-43 | B101: L1-S5 self-makeup cost per seat (own products used) | C101: 500 | D101: 400 | E101: 300 | F101: ₹/seat | G101: Judgement | H101: [HYP] | I101: =INDEX(C101:E101,$C$4) -> 400
A102: A-ECO-44 | B102: Taster delivery cost per ticket (trainer time share + products) | C102: 300 | D102: 250 | E102: 200 | F102: ₹/ticket | G102: Judgement | H102: [HYP] | I102: =INDEX(C102:E102,$C$4) -> 250
A103: A-ECO-45 | B103: Pro Circle cost to serve per paid member-year | C103: 2500 | D103: 2000 | E103: 1500 | F103: ₹/member | G103: Monthly online session + quarterly practice day | H103: [HYP] | I103: =INDEX(C103:E103,$C$4) -> 2000
A104: A-BM-04a | B104: Lead trainer salary | C104: 75000 | D104: 60000 | E104: 55000 | F104: ₹/mo | G104: A-BM-04 ₹50-80k | H104: [HYP] | I104: =INDEX(C104:E104,$C$4) -> 60000
A105: A-BM-04b | B105: Trainer salary | C105: 45000 | D105: 38000 | E105: 32000 | F105: ₹/mo | G105: A-BM-04 ₹30-45k | H105: [HYP] | I105: =INDEX(C105:E105,$C$4) -> 38000
A106: A-BM-04c | B106: Assistant salary | C106: 20000 | D106: 18000 | E106: 16000 | F106: ₹/mo | G106: A-BM-04 ₹15-20k | H106: [HYP] | I106: =INDEX(C106:E106,$C$4) -> 18000
A107: A-ECO-46 | B107: Batch slots one trainer FTE can lead (morning + afternoon) | C107: 2 | D107: 2 | E107: 2 | F107: slots | G107: Judgement | H107: [HYP] | I107: =INDEX(C107:E107,$C$4) -> 2
A108: A-ECO-47 | B108: Average cohort fill (students per L3/L2 batch; cap 12, A-BM-01) | C108: 8 | D108: 10 | E108: 11 | F108: students | G108: A-BM-01 cap 12 | H108: [HYP] | I108: =INDEX(C108:E108,$C$4) -> 10
... A117: A-GRO-50 | B117: SEO content freelancer | C117: 0 | D117: 15000 | E117: 25000 | F117: ₹/mo | G117: Growth §10 | H117: [EST] | I117: =INDEX(C117:E117,$C$4) -> 15000

Sheet Funnel_Selected
A1: Instrumented funnel by channel - scenario chosen on Assumptions!C3 (per month, steady state months 7-12)
A2: Target-driven: career enrolment target (A-GRO-01) x route mix / route conversion = leads; leads x cost = spend. Webinar/pop-up is the regional (S7) route, additive to the target.
A3: Scenario index | B3: =Assumptions!$C$4 -> 2 | C3: =CHOOSE(B3,"Conservative","Base","Aggressive") -> Base
A5: Stage / metric | B5: Meta -> WhatsApp (CTWA) | C5: Google Search | D5: Organic IG / content / GBP | E5: Referral / alumni / walk-in | F5: Paid Career Taster | G5: Webinar + regional pop-up | H5: Total / blended | I5: Notes
A6: A. Volumes
A7: Career enrolment target per month (A-GRO-01) | H7: =INDEX(Assumptions!$C$27:$E$27,$B$3) -> 10 | I7: steady state, months 7-12
A8: Route mix (A-GRO-03) | B8: =INDEX(Assumptions!$C$29:$E$29,$B$3) -> 0.3 | C8: =INDEX(Assumptions!$C$30:$E$30,$B$3) -> 0.2 | D8: =INDEX(Assumptions!$C$31:$E$31,$B$3) -> 0.2 | E8: =INDEX(Assumptions!$C$32:$E$32,$B$3) -> 0.2 | F8: =INDEX(Assumptions!$C$33:$E$33,$B$3) -> 0.1 | H8: =SUM(B8:F8) -> 1
A9: B. Stage conversion (scenario sets; base rates assume the <5-min SLA is met)
A10: Lead -> Qualified lead | B10: =INDEX(Assumptions!$C$42:$E$42,$B$3) -> 0.4 | C10: =INDEX(Assumptions!$C$46:$E$46,$B$3) -> 0.45 | D10: =INDEX(Assumptions!$C$50:$E$50,$B$3) -> 0.38 | E10: =INDEX(Assumptions!$C$54:$E$54,$B$3) -> 0.7 | F10: =INDEX(Assumptions!$C$58:$E$58,$B$3) -> 0.82 | I10: Taster: ticket->attend / attend->counselled / counselled->enrolled ; Webinar/pop-up: see block F
A11: QL -> Counselled / visit / demo | B11: =INDEX(Assumptions!$C$43:$E$43,$B$3) -> 0.55 | C11: =INDEX(Assumptions!$C$47:$E$47,$B$3) -> 0.6 | D11: =INDEX(Assumptions!$C$51:$E$51,$B$3) -> 0.55 | E11: =INDEX(Assumptions!$C$55:$E$55,$B$3) -> 0.75 | F11: =INDEX(Assumptions!$C$59:$E$59,$B$3) -> 0.65
A12: Counselled -> Applied (token) | B12: =INDEX(Assumptions!$C$44:$E$44,$B$3) -> 0.3 | C12: =INDEX(Assumptions!$C$48:$E$48,$B$3) -> 0.32 | D12: =INDEX(Assumptions!$C$52:$E$52,$B$3) -> 0.3 | E12: =INDEX(Assumptions!$C$56:$E$56,$B$3) -> 0.55 | F12: =INDEX(Assumptions!$C$60:$E$60,$B$3) -> 0.2
A13: Applied -> Enrolled (fee paid) | B13: =INDEX(Assumptions!$C$45:$E$45,$B$3) -> 0.8 | C13: =INDEX(Assumptions!$C$49:$E$49,$B$3) -> 0.8 | D13: =INDEX(Assumptions!$C$53:$E$53,$B$3) -> 0.8 | E13: =INDEX(Assumptions!$C$57:$E$57,$B$3) -> 0.87 | F13: =1 -> 1
A14: Overall lead -> enrolled | B14: =B10*B11*B12*B13 -> 0.0528 | C14: =C10*C11*C12*C13 -> 0.06912 | D14: =D10*D11*D12*D13 -> 0.05016 | E14: =E10*E11*E12*E13 -> 0.2512125 | F14: =F10*F11*F12*F13 -> 0.1066 | G14: =IFERROR(G16/G17,0) -> 0.054695652 | H14: =H16/H17 -> 0.066233427 | I14: product of stages (Growth agent: CTWA 2.95/5.28/8.70%)
A15: C. Funnel counts per month
A16: Enrolled (target x mix) | B16: =$H$7*B8 -> 3 | C16: =$H$7*C8 -> 2 | D16: =$H$7*D8 -> 2 | E16: =$H$7*E8 -> 2 | F16: =$H$7*F8 -> 1 | G16: =G37+G39 -> 2.516 | H16: =SUM(B16:G16) -> 12.516
A17: Leads (Taster: tickets sold) | B17: =IFERROR(B16/B14,0) -> 56.818182 | C17: =IFERROR(C16/C14,0) -> 28.935185 | D17: =IFERROR(D16/D14,0) -> 39.872408 | E17: =IFERROR(E16/E14,0) -> 7.9613873 | F17: =IFERROR(F16/F14,0) -> 9.380863 | G17: =G36+G38 -> 46 | H17: =SUM(B17:G17) -> 188.96803 | I17: enrolled / overall rate
A18: Qualified leads (Taster: attended) | B18: =B17*B10 -> 22.727273 | C18: =C17*C10 -> 13.020833 | D18: =D17*D10 -> 15.151515 | E18: =E17*E10 -> 5.5729711 | F18: =F17*F10 -> 7.6923077 | H18: =SUM(B18:G18) -> 64.1649
A19: Counselled / visited | B19: =B18*B11 -> 12.5 | C19: =C18*C11 -> 7.8125 | D19: =D18*D11 -> 8.3333333 | E19: =E18*E11 -> 4.1797283 | F19: =F18*F11 -> 5 | H19: =SUM(B19:G19) -> 37.825562
A20: Applied (token paid) | B20: =B19*B12 -> 3.75 | C20: =C19*C12 -> 2.5 | D20: =D19*D12 -> 2.5 | E20: =E19*E12 -> 2.2988506 | F20: =F19*F12 -> 1 | H20: =SUM(B20:G20) -> 12.048851
A21: Enrolled (check = target x mix) | B21: =B20*B13 -> 3 | C21: =C20*C13 -> 2 | D21: =D20*D13 -> 2 | E21: =E20*E13 -> 2 | F21: =F20*F13 -> 1 | G21: =G16 -> 2.516 | H21: =SUM(B21:G21) -> 12.516
A22: D. Cost per lead and channel spend (₹ per month)
A23: Cost per lead / ticket | B23: =(1-INDEX(Assumptions!$C$76:$E$76,$B$3))*INDEX(Assumptions!$C$34:$E$34,$B$3)+INDEX(Assumptions!$C$76:$E$76,$B$3)*INDEX(Assumptions!$C$35:$E$35,$B$3) -> 287.5 | C23: =INDEX(Assumptions!$C$36:$E$36,$B$3) -> 500 | F23: =INDEX(Assumptions!$C$37:$E$37,$B$3) -> 400 | I23: CTWA blends tricity and regional CPL by out-of-town share; organic = content cost / leads; referral = reward per enrolment
A24: Media / reward / content spend | B24: =B17*B23 -> 16335.227 | C24: =C17*C23 -> 14467.593 | D24: =INDEX(Assumptions!$C$114:$E$114,$B$3)+INDEX(Assumptions!$C$117:$E$117,$B$3) -> 35000 | E24: =E16*INDEX(Assumptions!$C$71:$E$71,$B$3) -> 6000 | F24: =F17*(F23+INDEX(Assumptions!$C$102:$E$102,$B$3))-F17*INDEX(Assumptions!$C$18:$E$18,$B$3)/(1+INDEX(Assumptions!$C$15:$E$15,$B$3)) -> -1844.3731 | G24: =G40 -> 8674.5763 | H24: =SUM(B24:G24) -> 78633.023 | I24: Organic: shooter/editor (A-GRO-47) + SEO (A-GRO-50); fixed team cost, shown for CAC visibility
A25: of which taster ticket revenue offset (ex-GST) | F25: =-F17*INDEX(Assumptions!$C$18:$E$18,$B$3)/(1+INDEX(Assumptions!$C$15:$E$15,$B$3)) -> -7941.934 | I25: Growth §11 note 3
A26: E. Unit economics per enrolled career student (₹, ex-GST)
A27: Steady-state L3 realised fee (incl. GST if quoted inclusive) | H27: =IF(INDEX(Assumptions!$C$94:$E$94,$B$3)<=7,INDEX(Assumptions!$C$21:$E$21,$B$3),INDEX(Assumptions!$C$10:$E$10,$B$3)) -> 80000 | I27: A-BM-02 after price step (A-ECO-104 <= month 7), else CA-02
A28: First-course revenue per career enrolment (ex-GST) | B28: =(INDEX(Assumptions!$C$28:$E$28,$B$3)*$H$27+(1-INDEX(Assumptions!$C$28:$E$28,$B$3))*INDEX(Assumptions!$C$19:$E$19,$B$3))/(1+INDEX(Assumptions!$C$15:$E$15,$B$3)*INDEX(Assumptions!$C$16:$E$16,$B$3)) -> 54203.39 | C28: =(INDEX(Assumptions!$C$28:$E$28,$B$3)*$H$27+(1-INDEX(Assumptions!$C$28:$E$28,$B$3))*INDEX(Assumptions!$C$19:$E$19,$B$3))/(1+INDEX(Assumptions!$C$15:$E$15,$B$3)*INDEX(Assumptions!$C$16:$E$16,$B$3)) -> 54203.39 | D28: =(INDEX(Assumptions!$C$28:$E$28,$B$3)*$H$27+(1-INDEX(Assumptions!$C$28:$E$28,$B$3))*INDEX(Assumptions!$C$19:$E$19,$B$3))/(1+INDEX(Assumptions!$C$15:$E$15,$B$3)*INDEX(Assumptions!$C$16:$E$16,$B$3)) -> 54203.39 | E28: =(INDEX(Assumptions!$C$28:$E$28,$B$3)*$H$27+(1-INDEX(Assumptions!$C$28:$E$28,$B$3))*INDEX(Assumptions!$C$19:$E$19,$B$3))/(1+INDEX(Assumptions!$C$15:$E$15,$B$3)*INDEX(Assumptions!$C$16:$E$16,$B$3)) -> 54203.39 | F28: =(INDEX(Assumptions!$C$28:$E$28,$B$3)*$H$27+(1-INDEX(Assumptions!$C$28:$E$28,$B$3))*INDEX(Assumptions!$C$19:$E$19,$B$3)-INDEX(Assumptions!$C$18:$E$18,$B$3))/(1+INDEX(Assumptions!$C$15:$E$15,$B$3)*INDEX(Assumptions!$C$16:$E$16,$B$3)) -> 53356.78 | G28: =(INDEX(Assumptions!$C$28:$E$28,$B$3)*$H$27+(1-INDEX(Assumptions!$C$28:$E$28,$B$3))*INDEX(Assumptions!$C$19:$E$19,$B$3))/(1+INDEX(Assumptions!$C$15:$E$15,$B$3)*INDEX(Assumptions!$C$16:$E$16,$B$3)) -> 54203.39 | H28: =SUMPRODUCT(B28:G28,B16:G16)/H16 -> 54135.748 | I28: L3 share x L3 + L2 share x L2; taster route nets the ₹999 credit
A29: Trainer standard cost per seat-month (trainer + assistant / slots / fill) | H29: =(INDEX(Assumptions!$C$105:$E$105,$B$3)+INDEX(Assumptions!$C$106:$E$106,$B$3))/INDEX(Assumptions!$C$107:$E$107,$B$3)/INDEX(Assumptions!$C$108:$E$108,$B$3) -> 2800 | I29: A-BM-04b/c, A-ECO-46/47
A30: Variable delivery cost per career enrolment | B30: =INDEX(Assumptions!$C$28:$E$28,$B$3)*(INDEX(Assumptions!$C$97:$E$97,$B$3)+IF(INDEX(Assumptions!$C$94:$E$94,$B$3)<=7,0,INDEX(Assumptions!$C$14:$E$14,$B$3))+INDEX(Assumptions!$C$109:$E$109,$B$3)*$H$29+$H$27/(1+INDEX(Assumptions!$C$15:$E$15,$B$3)*INDEX(Assumptions!$C$16:$E$16,$B$3))*INDEX(Assumptions!$C$72:$E$72,$B$3)*INDEX(Assumptions!$C$73:$E$73,$B$3))+(1-INDEX(Assumptions!$C$28:$E$28,$B$3))*(INDEX(Assumptions!$C$98:$E$98,$B$3)+$H$29)+B28*INDEX(Assumptions!$C$78:$E$78,$B$3) -> 12355.932 | C30: =INDEX(Assumptions!$C$28:$E$28,$B$3)*(INDEX(Assumptions!$C$97:$E$97,$B$3)+IF(INDEX(Assumptions!$C$94:$E$94,$B$3)<=7,0,INDEX(Assumptions!$C$14:$E$14,$B$3))+INDEX(Assumptions!$C$109:$E$109,$B$3)*$H$29+$H$27/(1+INDEX(Assumptions!$C$15:$E$15,$B$3)*INDEX(Assumptions!$C$16:$E$16,$B$3))*INDEX(Assumptions!$C$72:$E$72,$B$3)*INDEX(Assumptions!$C$73:$E$73,$B$3))+(1-INDEX(Assumptions!$C$28:$E$28,$B$3))*(INDEX(Assumptions!$C$98:$E$98,$B$3)+$H$29)+C28*INDEX(Assumptions!$C$78:$E$78,$B$3) -> 12355.932 | D30: =INDEX(Assumptions!$C$28:$E$28,$B$3)*(INDEX(Assumptions!$C$97:$E$97,$B$3)+IF(INDEX(Assumptions!$C$94:$E$94,$B$3)<=7,0,INDEX(Assumptions!$C$14:$E$14,$B$3))+INDEX(Assumptions!$C$109:$E$109,$B$3)*$H$29+$H$27/(1+INDEX(Assumptions!$C$15:$E$15,$B$3)*INDEX(Assumptions!$C$16:$E$16,$B$3))*INDEX(Assumptions!$C$72:$E$72,$B$3)*INDEX(Assumptions!$C$73:$E$73,$B$3))+(1-INDEX(Assumptions!$C$28:$E$28,$B$3))*(INDEX(Assumptions!$C$98:$E$98,$B$3)+$H$29)+D28*INDEX(Assumptions!$C$78:$E$78,$B$3) -> 12355.932 | E30: =INDEX(Assumptions!$C$28:$E$28,$B$3)*(INDEX(Assumptions!$C$97:$E$97,$B$3)+IF(INDEX(Assumptions!$C$94:$E$94,$B$3)<=7,0,INDEX(Assumptions!$C$14:$E$14,$B$3))+INDEX(Assumptions!$C$109:$E$109,$B$3)*$H$29+$H$27/(1+INDEX(Assumptions!$C$15:$E$15,$B$3)*INDEX(Assumptions!$C$16:$E$16,$B$3))*INDEX(Assumptions!$C$72:$E$72,$B$3)*INDEX(Assumptions!$C$73:$E$73,$B$3))+(1-INDEX(Assumptions!$C$28:$E$28,$B$3))*(INDEX(Assumptions!$C$98:$E$98,$B$3)+$H$29)+E28*INDEX(Assumptions!$C$78:$E$78,$B$3) -> 12355.932 | F30: =INDEX(Assumptions!$C$28:$E$28,$B$3)*(INDEX(Assumptions!$C$97:$E$97,$B$3)+IF(INDEX(Assumptions!$C$94:$E$94,$B$3)<=7,0,INDEX(Assumptions!$C$14:$E$14,$B$3))+INDEX(Assumptions!$C$109:$E$109,$B$3)*$H$29+$H$27/(1+INDEX(Assumptions!$C$15:$E$15,$B$3)*INDEX(Assumptions!$C$16:$E$16,$B$3))*INDEX(Assumptions!$C$72:$E$72,$B$3)*INDEX(Assumptions!$C$73:$E$73,$B$3))+(1-INDEX(Assumptions!$C$28:$E$28,$B$3))*(INDEX(Assumptions!$C$98:$E$98,$B$3)+$H$29)+F28*INDEX(Assumptions!$C$78:$E$78,$B$3) -> 12339 | G30: =INDEX(Assumptions!$C$28:$E$28,$B$3)*(INDEX(Assumptions!$C$97:$E$97,$B$3)+IF(INDEX(Assumptions!$C$94:$E$94,$B$3)<=7,0,INDEX(Assumptions!$C$14:$E$14,$B$3))+INDEX(Assumptions!$C$109:$E$109,$B$3)*$H$29+$H$27/(1+INDEX(Assumptions!$C$15:$E$15,$B$3)*INDEX(Assumptions!$C$16:$E$16,$B$3))*INDEX(Assumptions!$C$72:$E$72,$B$3)*INDEX(Assumptions!$C$73:$E$73,$B$3))+(1-INDEX(Assumptions!$C$28:$E$28,$B$3))*(INDEX(Assumptions!$C$98:$E$98,$B$3)+$H$29)+G28*INDEX(Assumptions!$C$78:$E$78,$B$3) -> 12355.932 | H30: =SUMPRODUCT(B30:G30,B16:G16)/H16 -> 12354.579 | I30: consumables + kit (pre-step) + trainer standard cost + EMI subvention; gateway below
A31: First-course contribution before CAC | B31: =B28-B30 -> 41847.458 | C31: =C28-C30 -> 41847.458 | D31: =D28-D30 -> 41847.458 | E31: =E28-E30 -> 41847.458 | F31: =F28-F30 -> 41017.78 | G31: =G28-G30 -> 41847.458 | H31: =H28-H30 -> 41781.168
A32: Contribution margin % (before CAC) | B32: =IFERROR(B31/B28,0) -> 0.77204503 | C32: =IFERROR(C31/C28,0) -> 0.77204503 | D32: =IFERROR(D31/D28,0) -> 0.77204503 | E32: =IFERROR(E31/E28,0) -> 0.77204503 | F32: =IFERROR(F31/F28,0) -> 0.76874541 | G32: =IFERROR(G31/G28,0) -> 0.77204503 | H32: =H31/H28 -> 0.77178519
A33: Follow-on contribution within 24 months (LTV add-on) | H33: =(1-INDEX(Assumptions!$C$28:$E$28,$B$3))*INDEX(Assumptions!$C$92:$E$92,$B$3)*((INDEX(Assumptions!$C$21:$E$21,$B$3)-INDEX(Assumptions!$C$19:$E$19,$B$3))/(1+INDEX(Assumptions!$C$15:$E$15,$B$3)*INDEX(Assumptions!$C$16:$E$16,$B$3))-INDEX(Assumptions!$C$97:$E$97,$B$3)-2*$H$29)+INDEX(Assumptions!$C$91:$E$91,$B$3)*(INDEX(Assumptions!$C$22:$E$22,$B$3)/(1+INDEX(Assumptions!$C$15:$E$15,$B$3)*INDEX(Assumptions!$C$16:$E$16,$B$3))-INDEX(Assumptions!$C$100:$E$100,$B$3))+INDEX(Assumptions!$C$69:$E$69,$B$3)*INDEX(Assumptions!$C$74:$E$74,$B$3)*(INDEX(Assumptions!$C$24:$E$24,$B$3)/(1+INDEX(Assumptions!$C$15:$E$15,$B$3)*INDEX(Assumptions!$C$16:$E$16,$B$3))-INDEX(Assumptions!$C$103:$E$103,$B$3))+INDEX(Assumptions!$C$28:$E$28,$B$3)*IF(INDEX(Assumptions!$C$94:$E$94,$B$3)<=7,INDEX(Assumptions!$C$93:$E$93,$B$3),0) -> 8747.161 | I33: L2->L3 upgrade + masterclasses + Pro Circle renewal + kit margin
A34: LTV: 24-month contribution per career student (before CAC) | B34: =B31+$H$33 -> 50594.619 | C34: =C31+$H$33 -> 50594.619 | D34: =D31+$H$33 -> 50594.619 | E34: =E31+$H$33 -> 50594.619 | F34: =F31+$H$33 -> 49764.941 | G34: =G31+$H$33 -> 50594.619 | H34: =H31+H33 -> 50528.329
A35: F. Webinar + regional pop-up route (S7; additive to target)
A36: Online parents' sessions per month x registrants | G36: =INDEX(Assumptions!$C$83:$E$83,$B$3)*INDEX(Assumptions!$C$84:$E$84,$B$3) -> 30 | I36: A-ECO-31 x A-ECO-32
A37: Webinar enrolments = registrants x attend x counselling booked x CTWA counselled->enrolled | G37: =G36*INDEX(Assumptions!$C$63:$E$63,$B$3)*INDEX(Assumptions!$C$64:$E$64,$B$3)*INDEX(Assumptions!$C$44:$E$44,$B$3)*INDEX(Assumptions!$C$45:$E$45,$B$3) -> 0.756 | I37: A-GRO-26a/b; A-GRO-18c/d
A38: Pop-up events per month (A-ECO-33) x paid attendees | G38: =INDEX(Assumptions!$C$89:$E$89,$B$3)*INDEX(Assumptions!$C$85:$E$85,$B$3) -> 16 | I38: A-BM-06a
A39: Pop-up enrolments = attendees x attendee->enrol (A-BM-06d) | G39: =G38*INDEX(Assumptions!$C$88:$E$88,$B$3) -> 1.76
A40: Webinar promo + net pop-up cost (event cost - ticket revenue ex-GST) | G40: =G36*INDEX(Assumptions!$C$82:$E$82,$B$3)+INDEX(Assumptions!$C$89:$E$89,$B$3)*(INDEX(Assumptions!$C$87:$E$87,$B$3)-INDEX(Assumptions!$C$85:$E$85,$B$3)*INDEX(Assumptions!$C$86:$E$86,$B$3)/(1+INDEX(Assumptions!$C$15:$E$15,$B$3))) -> 8674.5763
A41: G. CAC, payback and totals
A42: CAC per enrolment (channel spend / enrolled) | B42: =IFERROR(B24/B16,0) -> 5445.0758 | C42: =IFERROR(C24/C16,0) -> 7233.7963 | D42: =IFERROR(D24/D16,0) -> 17500 | E42: =IFERROR(E24/E16,0) -> 3000 | F42: =IFERROR(F24/F16,0) -> -1844.3731 | G42: =IFERROR(G24/G16,0) -> 3447.7648 | H42: =H24/H16 -> 6282.6001
A43: CAC as % of first-course revenue | B43: =IFERROR(B42/B28,0) -> 0.10045637 | C43: =IFERROR(C42/C28,0) -> 0.13345653 | D43: =IFERROR(D42/D28,0) -> 0.32285804 | E43: =IFERROR(E42/E28,0) -> 0.055347092 | F43: =IFERROR(F42/F28,0) -> -0.034566799 | G43: =IFERROR(G42/G28,0) -> 0.063607919 | H43: =H42/H28 -> 0.11605271
A44: LTV / CAC (24-month contribution) | B44: =IF(B42<=0,"n/m (self-funding)",B34/B42) -> 9.2918117 | C44: =IF(C42<=0,"n/m (self-funding)",C34/C42) -> 6.9942001 | D44: =IF(D42<=0,"n/m (self-funding)",D34/D42) -> 2.8911211 | E44: =IF(E42<=0,"n/m (self-funding)",E34/E42) -> 16.864873 | F44: =IF(F42<=0,"n/m (self-funding)",F34/F42) -> n/m (self-funding) | G44: =IF(G42<=0,"n/m (self-funding)",G34/G42) -> 14.674614 | H44: =H34/H42 -> 8.0425824
A45: CAC payback (months) = CAC / (first-course contribution / payment months) | B45: =IF(B42<=0,0,B42/(B31/INDEX(Assumptions!$C$90:$E$90,$B$3))) -> 0.26023448 | C45: =IF(C42<=0,0,C42/(C31/INDEX(Assumptions!$C$90:$E$90,$B$3))) -> 0.34572214 | D45: =IF(D42<=0,0,D42/(D31/INDEX(Assumptions!$C$90:$E$90,$B$3))) -> 0.836371 | E45: =IF(E42<=0,0,E42/(E31/INDEX(Assumptions!$C$90:$E$90,$B$3))) -> 0.14337789 | F45: =IF(F42<=0,0,F42/(F31/INDEX(Assumptions!$C$90:$E$90,$B$3))) -> 0 | G45: =IF(G42<=0,0,G42/(G31/INDEX(Assumptions!$C$90:$E$90,$B$3))) -> 0.16477774 | H45: =H42/(H31/INDEX(Assumptions!$C$90:$E$90,$B$3)) -> 0.30073837 | I45: BM M3 definition; A-ECO-34 payment months
A46: Paid-only CAC (CTWA + Search + Taster net + webinar/pop-up) | H46: =(B24+C24+F24+G24)/(B16+C16+F16+G16) -> 4419.0962 | I46: excludes organic content and referral rewards
A47: Variable acquisition cost per target career enrolment (for business_forecast) | H47: =(B24+C24+E24+F24)/H7 -> 3495.8447 | I47: (CTWA + Search + Taster net + referral rewards) / target enrolments; organic content is a fixed team cost there
A48: Paid-route media CAC: (CTWA + Search + Taster net) / their enrolments (for business_forecast) | H48: =(B24+C24+F24)/(B16+C16+F16) -> 4826.4078 | I48: Growth G4 'media CAC per paid career enrolment'
A49: Counselling conversations per month (career leads x 2.5 + other leads x 0.5) | H49: =H17*2.5+H58*0.5 -> 564.53771 | I49: A-GRO §10.4 method
A50: Counsellor FTE needed (A-GRO-38 x 24 days) | H50: =H49/(INDEX(Assumptions!$C$77:$E$77,$B$3)*24) -> 0.78408015
A51: Fully loaded CAC incl. counsellor, performance freelancer and martech | H51: =(H24+MAX(1,ROUNDUP(H50,0))*INDEX(Assumptions!$C$112:$E$112,$B$3)+INDEX(Assumptions!$C$115:$E$115,$B$3)+INDEX(Assumptions!$C$111:$E$111,$B$3))/H16 -> 11316.157 | I51: (channel spend + A-GRO-45 x FTE + A-GRO-48 + A-GRO-42) / enrolments; Growth G4 definition
A52: Media spend per month on career routes (CTWA + Search + Taster + pop-up/webinar) | H52: =B24+C24+F24+G24 -> 37633.023
A53: Check: organic leads derived vs A-GRO-43 ; referral leads vs A-GRO-44 | D53: =D17-INDEX(Assumptions!$C$79:$E$79,$B$3) -> -0.12759171 | E53: =E17-INDEX(Assumptions!$C$80:$E$80,$B$3) -> -0.038612728 | I53: Growth agent check values
A55: H. Other products: masterclass (L4) and self-makeup (L1-S5) acquisition
A56: Seats per month (A-GRO §10.3: L4 24 base; L1-S5 15 base) - scaled with target | B56: =2.4*$H$7 -> 24 | C56: =1.5*$H$7 -> 15 | I56: L4 = 12 x target/5 ; L1-S5 = 1.5 x target
A57: Lead -> purchase (A-GRO-27 / A-GRO-28) | B57: =INDEX(Assumptions!$C$65:$E$65,$B$3) -> 0.25 | C57: =INDEX(Assumptions!$C$66:$E$66,$B$3) -> 0.17
A58: Leads needed | B58: =B56/B57 -> 96 | C58: =C56/C57 -> 88.235294 | H58: =B58+C58 -> 184.23529
A59: Paid media (paid share x CPL x leads) | B59: =B58*INDEX(Assumptions!$C$40:$E$40,$B$3)*INDEX(Assumptions!$C$38:$E$38,$B$3) -> 7200 | C59: =C58*INDEX(Assumptions!$C$41:$E$41,$B$3)*INDEX(Assumptions!$C$39:$E$39,$B$3) -> 10588.235 | I59: A-GRO-18b, A-GRO-16/17
A60: Media per seat sold (for business_forecast) | B60: =B59/B56 -> 300 | C60: =C59/C56 -> 705.88235
A61: Columns: B = L4 masterclass, C = L1-S5 self-makeup

Sheet Funnel_Conservative
A1: Instrumented funnel by channel - Conservative (per month, steady state months 7-12)
A2: Target-driven: career enrolment target (A-GRO-01) x route mix / route conversion = leads; leads x cost = spend. Webinar/pop-up is the regional (S7) route, additive to the target.
A3: Scenario index | B3: 1 | C3: =CHOOSE(B3,"Conservative","Base","Aggressive") -> Conservative
A5: Stage / metric | B5: Meta -> WhatsApp (CTWA) | C5: Google Search | D5: Organic IG / content / GBP | E5: Referral / alumni / walk-in | F5: Paid Career Taster | G5: Webinar + regional pop-up | H5: Total / blended | I5: Notes
A6: A. Volumes
A7: Career enrolment target per month (A-GRO-01) | H7: =INDEX(Assumptions!$C$27:$E$27,$B$3) -> 6 | I7: steady state, months 7-12
A8: Route mix (A-GRO-03) | B8: =INDEX(Assumptions!$C$29:$E$29,$B$3) -> 0.3 | C8: =INDEX(Assumptions!$C$30:$E$30,$B$3) -> 0.2 | D8: =INDEX(Assumptions!$C$31:$E$31,$B$3) -> 0.2 | E8: =INDEX(Assumptions!$C$32:$E$32,$B$3) -> 0.2 | F8: =INDEX(Assumptions!$C$33:$E$33,$B$3) -> 0.1 | H8: =SUM(B8:F8) -> 1
A9: B. Stage conversion (scenario sets; base rates assume the <5-min SLA is met)
A10: Lead -> Qualified lead | B10: =INDEX(Assumptions!$C$42:$E$42,$B$3) -> 0.35 | C10: =INDEX(Assumptions!$C$46:$E$46,$B$3) -> 0.4 | D10: =INDEX(Assumptions!$C$50:$E$50,$B$3) -> 0.3 | E10: =INDEX(Assumptions!$C$54:$E$54,$B$3) -> 0.6 | F10: =INDEX(Assumptions!$C$58:$E$58,$B$3) -> 0.75 | I10: Taster: ticket->attend / attend->counselled / counselled->enrolled ; Webinar/pop-up: see block F
A11: QL -> Counselled / visit / demo | B11: =INDEX(Assumptions!$C$43:$E$43,$B$3) -> 0.45 | C11: =INDEX(Assumptions!$C$47:$E$47,$B$3) -> 0.5 | D11: =INDEX(Assumptions!$C$51:$E$51,$B$3) -> 0.45 | E11: =INDEX(Assumptions!$C$55:$E$55,$B$3) -> 0.7 | F11: =INDEX(Assumptions!$C$59:$E$59,$B$3) -> 0.5
A12: Counselled -> Applied (token) | B12: =INDEX(Assumptions!$C$44:$E$44,$B$3) -> 0.25 | C12: =INDEX(Assumptions!$C$48:$E$48,$B$3) -> 0.28 | D12: =INDEX(Assumptions!$C$52:$E$52,$B$3) -> 0.25 | E12: =INDEX(Assumptions!$C$56:$E$56,$B$3) -> 0.5 | F12: =INDEX(Assumptions!$C$60:$E$60,$B$3) -> 0.16
A13: Applied -> Enrolled (fee paid) | B13: =INDEX(Assumptions!$C$45:$E$45,$B$3) -> 0.75 | C13: =INDEX(Assumptions!$C$49:$E$49,$B$3) -> 0.75 | D13: =INDEX(Assumptions!$C$53:$E$53,$B$3) -> 0.75 | E13: =INDEX(Assumptions!$C$57:$E$57,$B$3) -> 0.8 | F13: =1 -> 1
A14: Overall lead -> enrolled | B14: =B10*B11*B12*B13 -> 0.02953125 | C14: =C10*C11*C12*C13 -> 0.042 | D14: =D10*D11*D12*D13 -> 0.0253125 | E14: =E10*E11*E12*E13 -> 0.168 | F14: =F10*F11*F12*F13 -> 0.06 | G14: =IFERROR(G16/G17,0) -> 0.009375 | H14: =H16/H17 -> 0.034123491 | I14: product of stages (Growth agent: CTWA 2.95/5.28/8.70%)
A15: C. Funnel counts per month
A16: Enrolled (target x mix) | B16: =$H$7*B8 -> 1.8 | C16: =$H$7*C8 -> 1.2 | D16: =$H$7*D8 -> 1.2 | E16: =$H$7*E8 -> 1.2 | F16: =$H$7*F8 -> 0.6 | G16: =G37+G39 -> 0.28125 | H16: =SUM(B16:G16) -> 6.28125
A17: Leads (Taster: tickets sold) | B17: =IFERROR(B16/B14,0) -> 60.952381 | C17: =IFERROR(C16/C14,0) -> 28.571429 | D17: =IFERROR(D16/D14,0) -> 47.407407 | E17: =IFERROR(E16/E14,0) -> 7.1428571 | F17: =IFERROR(F16/F14,0) -> 10 | G17: =G36+G38 -> 30 | H17: =SUM(B17:G17) -> 184.07407 | I17: enrolled / overall rate
A18: Qualified leads (Taster: attended) | B18: =B17*B10 -> 21.333333 | C18: =C17*C10 -> 11.428571 | D18: =D17*D10 -> 14.222222 | E18: =E17*E10 -> 4.2857143 | F18: =F17*F10 -> 7.5 | H18: =SUM(B18:G18) -> 58.769841
A19: Counselled / visited | B19: =B18*B11 -> 9.6 | C19: =C18*C11 -> 5.7142857 | D19: =D18*D11 -> 6.4 | E19: =E18*E11 -> 3 | F19: =F18*F11 -> 3.75 | H19: =SUM(B19:G19) -> 28.464286
A20: Applied (token paid) | B20: =B19*B12 -> 2.4 | C20: =C19*C12 -> 1.6 | D20: =D19*D12 -> 1.6 | E20: =E19*E12 -> 1.5 | F20: =F19*F12 -> 0.6 | H20: =SUM(B20:G20) -> 7.7
A21: Enrolled (check = target x mix) | B21: =B20*B13 -> 1.8 | C21: =C20*C13 -> 1.2 | D21: =D20*D13 -> 1.2 | E21: =E20*E13 -> 1.2 | F21: =F20*F13 -> 0.6 | G21: =G16 -> 0.28125 | H21: =SUM(B21:G21) -> 6.28125
A22: D. Cost per lead and channel spend (₹ per month)
A23: Cost per lead / ticket | B23: =(1-INDEX(Assumptions!$C$76:$E$76,$B$3))*INDEX(Assumptions!$C$34:$E$34,$B$3)+INDEX(Assumptions!$C$76:$E$76,$B$3)*INDEX(Assumptions!$C$35:$E$35,$B$3) -> 585 | C23: =INDEX(Assumptions!$C$36:$E$36,$B$3) -> 800 | F23: =INDEX(Assumptions!$C$37:$E$37,$B$3) -> 700 | I23: CTWA blends tricity and regional CPL by out-of-town share; organic = content cost / leads; referral = reward per enrolment
A24: Media / reward / content spend | B24: =B17*B23 -> 35657.143 | C24: =C17*C23 -> 22857.143 | D24: =INDEX(Assumptions!$C$114:$E$114,$B$3)+INDEX(Assumptions!$C$117:$E$117,$B$3) -> 12000 | E24: =E16*INDEX(Assumptions!$C$71:$E$71,$B$3) -> 6000 | F24: =F17*(F23+INDEX(Assumptions!$C$102:$E$102,$B$3))-F17*INDEX(Assumptions!$C$18:$E$18,$B$3)/(1+INDEX(Assumptions!$C$15:$E$15,$B$3)) -> 1533.8983 | G24: =G40 -> 4500 | H24: =SUM(B24:G24) -> 82548.184 | I24: Organic: shooter/editor (A-GRO-47) + SEO (A-GRO-50); fixed team cost, shown for CAC visibility
A25: of which taster ticket revenue offset (ex-GST) | F25: =-F17*INDEX(Assumptions!$C$18:$E$18,$B$3)/(1+INDEX(Assumptions!$C$15:$E$15,$B$3)) -> -8466.1017 | I25: Growth §11 note 3
A26: E. Unit economics per enrolled career student (₹, ex-GST)
A27: Steady-state L3 realised fee (incl. GST if quoted inclusive) | H27: =IF(INDEX(Assumptions!$C$94:$E$94,$B$3)<=7,INDEX(Assumptions!$C$21:$E$21,$B$3),INDEX(Assumptions!$C$10:$E$10,$B$3)) -> 40000 | I27: A-BM-02 after price step (A-ECO-104 <= month 7), else CA-02
A28: First-course revenue per career enrolment (ex-GST) | B28: =(INDEX(Assumptions!$C$28:$E$28,$B$3)*$H$27+(1-INDEX(Assumptions!$C$28:$E$28,$B$3))*INDEX(Assumptions!$C$19:$E$19,$B$3))/(1+INDEX(Assumptions!$C$15:$E$15,$B$3)*INDEX(Assumptions!$C$16:$E$16,$B$3)) -> 29661.017 | C28: =(INDEX(Assumptions!$C$28:$E$28,$B$3)*$H$27+(1-INDEX(Assumptions!$C$28:$E$28,$B$3))*INDEX(Assumptions!$C$19:$E$19,$B$3))/(1+INDEX(Assumptions!$C$15:$E$15,$B$3)*INDEX(Assumptions!$C$16:$E$16,$B$3)) -> 29661.017 | D28: =(INDEX(Assumptions!$C$28:$E$28,$B$3)*$H$27+(1-INDEX(Assumptions!$C$28:$E$28,$B$3))*INDEX(Assumptions!$C$19:$E$19,$B$3))/(1+INDEX(Assumptions!$C$15:$E$15,$B$3)*INDEX(Assumptions!$C$16:$E$16,$B$3)) -> 29661.017 | E28: =(INDEX(Assumptions!$C$28:$E$28,$B$3)*$H$27+(1-INDEX(Assumptions!$C$28:$E$28,$B$3))*INDEX(Assumptions!$C$19:$E$19,$B$3))/(1+INDEX(Assumptions!$C$15:$E$15,$B$3)*INDEX(Assumptions!$C$16:$E$16,$B$3)) -> 29661.017 | F28: =(INDEX(Assumptions!$C$28:$E$28,$B$3)*$H$27+(1-INDEX(Assumptions!$C$28:$E$28,$B$3))*INDEX(Assumptions!$C$19:$E$19,$B$3)-INDEX(Assumptions!$C$18:$E$18,$B$3))/(1+INDEX(Assumptions!$C$15:$E$15,$B$3)*INDEX(Assumptions!$C$16:$E$16,$B$3)) -> 28814.407 | G28: =(INDEX(Assumptions!$C$28:$E$28,$B$3)*$H$27+(1-INDEX(Assumptions!$C$28:$E$28,$B$3))*INDEX(Assumptions!$C$19:$E$19,$B$3))/(1+INDEX(Assumptions!$C$15:$E$15,$B$3)*INDEX(Assumptions!$C$16:$E$16,$B$3)) -> 29661.017 | H28: =SUMPRODUCT(B28:G28,B16:G16)/H16 -> 29580.147 | I28: L3 share x L3 + L2 share x L2; taster route nets the ₹999 credit
A29: Trainer standard cost per seat-month (trainer + assistant / slots / fill) | H29: =(INDEX(Assumptions!$C$105:$E$105,$B$3)+INDEX(Assumptions!$C$106:$E$106,$B$3))/INDEX(Assumptions!$C$107:$E$107,$B$3)/INDEX(Assumptions!$C$108:$E$108,$B$3) -> 4062.5 | I29: A-BM-04b/c, A-ECO-46/47
A30: Variable delivery cost per career enrolment | B30: =INDEX(Assumptions!$C$28:$E$28,$B$3)*(INDEX(Assumptions!$C$97:$E$97,$B$3)+IF(INDEX(Assumptions!$C$94:$E$94,$B$3)<=7,0,INDEX(Assumptions!$C$14:$E$14,$B$3))+INDEX(Assumptions!$C$109:$E$109,$B$3)*$H$29+$H$27/(1+INDEX(Assumptions!$C$15:$E$15,$B$3)*INDEX(Assumptions!$C$16:$E$16,$B$3))*INDEX(Assumptions!$C$72:$E$72,$B$3)*INDEX(Assumptions!$C$73:$E$73,$B$3))+(1-INDEX(Assumptions!$C$28:$E$28,$B$3))*(INDEX(Assumptions!$C$98:$E$98,$B$3)+$H$29)+B28*INDEX(Assumptions!$C$78:$E$78,$B$3) -> 21680.085 | C30: =INDEX(Assumptions!$C$28:$E$28,$B$3)*(INDEX(Assumptions!$C$97:$E$97,$B$3)+IF(INDEX(Assumptions!$C$94:$E$94,$B$3)<=7,0,INDEX(Assumptions!$C$14:$E$14,$B$3))+INDEX(Assumptions!$C$109:$E$109,$B$3)*$H$29+$H$27/(1+INDEX(Assumptions!$C$15:$E$15,$B$3)*INDEX(Assumptions!$C$16:$E$16,$B$3))*INDEX(Assumptions!$C$72:$E$72,$B$3)*INDEX(Assumptions!$C$73:$E$73,$B$3))+(1-INDEX(Assumptions!$C$28:$E$28,$B$3))*(INDEX(Assumptions!$C$98:$E$98,$B$3)+$H$29)+C28*INDEX(Assumptions!$C$78:$E$78,$B$3) -> 21680.085 | D30: =INDEX(Assumptions!$C$28:$E$28,$B$3)*(INDEX(Assumptions!$C$97:$E$97,$B$3)+IF(INDEX(Assumptions!$C$94:$E$94,$B$3)<=7,0,INDEX(Assumptions!$C$14:$E$14,$B$3))+INDEX(Assumptions!$C$109:$E$109,$B$3)*$H$29+$H$27/(1+INDEX(Assumptions!$C$15:$E$15,$B$3)*INDEX(Assumptions!$C$16:$E$16,$B$3))*INDEX(Assumptions!$C$72:$E$72,$B$3)*INDEX(Assumptions!$C$73:$E$73,$B$3))+(1-INDEX(Assumptions!$C$28:$E$28,$B$3))*(INDEX(Assumptions!$C$98:$E$98,$B$3)+$H$29)+D28*INDEX(Assumptions!$C$78:$E$78,$B$3) -> 21680.085 | E30: =INDEX(Assumptions!$C$28:$E$28,$B$3)*(INDEX(Assumptions!$C$97:$E$97,$B$3)+IF(INDEX(Assumptions!$C$94:$E$94,$B$3)<=7,0,INDEX(Assumptions!$C$14:$E$14,$B$3))+INDEX(Assumptions!$C$109:$E$109,$B$3)*$H$29+$H$27/(1+INDEX(Assumptions!$C$15:$E$15,$B$3)*INDEX(Assumptions!$C$16:$E$16,$B$3))*INDEX(Assumptions!$C$72:$E$72,$B$3)*INDEX(Assumptions!$C$73:$E$73,$B$3))+(1-INDEX(Assumptions!$C$28:$E$28,$B$3))*(INDEX(Assumptions!$C$98:$E$98,$B$3)+$H$29)+E28*INDEX(Assumptions!$C$78:$E$78,$B$3) -> 21680.085 | F30: =INDEX(Assumptions!$C$28:$E$28,$B$3)*(INDEX(Assumptions!$C$97:$E$97,$B$3)+IF(INDEX(Assumptions!$C$94:$E$94,$B$3)<=7,0,INDEX(Assumptions!$C$14:$E$14,$B$3))+INDEX(Assumptions!$C$109:$E$109,$B$3)*$H$29+$H$27/(1+INDEX(Assumptions!$C$15:$E$15,$B$3)*INDEX(Assumptions!$C$16:$E$16,$B$3))*INDEX(Assumptions!$C$72:$E$72,$B$3)*INDEX(Assumptions!$C$73:$E$73,$B$3))+(1-INDEX(Assumptions!$C$28:$E$28,$B$3))*(INDEX(Assumptions!$C$98:$E$98,$B$3)+$H$29)+F28*INDEX(Assumptions!$C$78:$E$78,$B$3) -> 21659.766 | G30: =INDEX(Assumptions!$C$28:$E$28,$B$3)*(INDEX(Assumptions!$C$97:$E$97,$B$3)+IF(INDEX(Assumptions!$C$94:$E$94,$B$3)<=7,0,INDEX(Assumptions!$C$14:$E$14,$B$3))+INDEX(Assumptions!$C$109:$E$109,$B$3)*$H$29+$H$27/(1+INDEX(Assumptions!$C$15:$E$15,$B$3)*INDEX(Assumptions!$C$16:$E$16,$B$3))*INDEX(Assumptions!$C$72:$E$72,$B$3)*INDEX(Assumptions!$C$73:$E$73,$B$3))+(1-INDEX(Assumptions!$C$28:$E$28,$B$3))*(INDEX(Assumptions!$C$98:$E$98,$B$3)+$H$29)+G28*INDEX(Assumptions!$C$78:$E$78,$B$3) -> 21680.085 | H30: =SUMPRODUCT(B30:G30,B16:G16)/H16 -> 21678.144 | I30: consumables + kit (pre-step) + trainer standard cost + EMI subvention; gateway below
A31: First-course contribution before CAC | B31: =B28-B30 -> 7980.9322 | C31: =C28-C30 -> 7980.9322 | D31: =D28-D30 -> 7980.9322 | E31: =E28-E30 -> 7980.9322 | F31: =F28-F30 -> 7154.6407 | G31: =G28-G30 -> 7980.9322 | H31: =H28-H30 -> 7902.0029
A32: Contribution margin % (before CAC) | B32: =IFERROR(B31/B28,0) -> 0.26907143 | C32: =IFERROR(C31/C28,0) -> 0.26907143 | D32: =IFERROR(D31/D28,0) -> 0.26907143 | E32: =IFERROR(E31/E28,0) -> 0.26907143 | F32: =IFERROR(F31/F28,0) -> 0.24830081 | G32: =IFERROR(G31/G28,0) -> 0.26907143 | H32: =H31/H28 -> 0.26713873
A33: Follow-on contribution within 24 months (LTV add-on) | H33: =(1-INDEX(Assumptions!$C$28:$E$28,$B$3))*INDEX(Assumptions!$C$92:$E$92,$B$3)*((INDEX(Assumptions!$C$21:$E$21,$B$3)-INDEX(Assumptions!$C$19:$E$19,$B$3))/(1+INDEX(Assumptions!$C$15:$E$15,$B$3)*INDEX(Assumptions!$C$16:$E$16,$B$3))-INDEX(Assumptions!$C$97:$E$97,$B$3)-2*$H$29)+INDEX(Assumptions!$C$91:$E$91,$B$3)*(INDEX(Assumptions!$C$22:$E$22,$B$3)/(1+INDEX(Assumptions!$C$15:$E$15,$B$3)*INDEX(Assumptions!$C$16:$E$16,$B$3))-INDEX(Assumptions!$C$100:$E$100,$B$3))+INDEX(Assumptions!$C$69:$E$69,$B$3)*INDEX(Assumptions!$C$74:$E$74,$B$3)*(INDEX(Assumptions!$C$24:$E$24,$B$3)/(1+INDEX(Assumptions!$C$15:$E$15,$B$3)*INDEX(Assumptions!$C$16:$E$16,$B$3))-INDEX(Assumptions!$C$103:$E$103,$B$3))+INDEX(Assumptions!$C$28:$E$28,$B$3)*IF(INDEX(Assumptions!$C$94:$E$94,$B$3)<=7,INDEX(Assumptions!$C$93:$E$93,$B$3),0) -> 3023.3835 | I33: L2->L3 upgrade + masterclasses + Pro Circle renewal + kit margin
A34: LTV: 24-month contribution per career student (before CAC) | B34: =B31+$H$33 -> 11004.316 | C34: =C31+$H$33 -> 11004.316 | D34: =D31+$H$33 -> 11004.316 | E34: =E31+$H$33 -> 11004.316 | F34: =F31+$H$33 -> 10178.024 | G34: =G31+$H$33 -> 11004.316 | H34: =H31+H33 -> 10925.386
A35: F. Webinar + regional pop-up route (S7; additive to target)
A36: Online parents' sessions per month x registrants | G36: =INDEX(Assumptions!$C$83:$E$83,$B$3)*INDEX(Assumptions!$C$84:$E$84,$B$3) -> 30 | I36: A-ECO-31 x A-ECO-32
A37: Webinar enrolments = registrants x attend x counselling booked x CTWA counselled->enrolled | G37: =G36*INDEX(Assumptions!$C$63:$E$63,$B$3)*INDEX(Assumptions!$C$64:$E$64,$B$3)*INDEX(Assumptions!$C$44:$E$44,$B$3)*INDEX(Assumptions!$C$45:$E$45,$B$3) -> 0.28125 | I37: A-GRO-26a/b; A-GRO-18c/d
A38: Pop-up events per month (A-ECO-33) x paid attendees | G38: =INDEX(Assumptions!$C$89:$E$89,$B$3)*INDEX(Assumptions!$C$85:$E$85,$B$3) -> 0 | I38: A-BM-06a
A39: Pop-up enrolments = attendees x attendee->enrol (A-BM-06d) | G39: =G38*INDEX(Assumptions!$C$88:$E$88,$B$3) -> 0
A40: Webinar promo + net pop-up cost (event cost - ticket revenue ex-GST) | G40: =G36*INDEX(Assumptions!$C$82:$E$82,$B$3)+INDEX(Assumptions!$C$89:$E$89,$B$3)*(INDEX(Assumptions!$C$87:$E$87,$B$3)-INDEX(Assumptions!$C$85:$E$85,$B$3)*INDEX(Assumptions!$C$86:$E$86,$B$3)/(1+INDEX(Assumptions!$C$15:$E$15,$B$3))) -> 4500
A41: G. CAC, payback and totals
A42: CAC per enrolment (channel spend / enrolled) | B42: =IFERROR(B24/B16,0) -> 19809.524 | C42: =IFERROR(C24/C16,0) -> 19047.619 | D42: =IFERROR(D24/D16,0) -> 10000 | E42: =IFERROR(E24/E16,0) -> 5000 | F42: =IFERROR(F24/F16,0) -> 2556.4972 | G42: =IFERROR(G24/G16,0) -> 16000 | H42: =H24/H16 -> 13141.999
A43: CAC as % of first-course revenue | B43: =IFERROR(B42/B28,0) -> 0.66786395 | C43: =IFERROR(C42/C28,0) -> 0.64217687 | D43: =IFERROR(D42/D28,0) -> 0.33714286 | E43: =IFERROR(E42/E28,0) -> 0.16857143 | F43: =IFERROR(F42/F28,0) -> 0.088722881 | G43: =IFERROR(G42/G28,0) -> 0.53942857 | H43: =H42/H28 -> 0.44428446
A44: LTV / CAC (24-month contribution) | B44: =IF(B42<=0,"n/m (self-funding)",B34/B42) -> 0.55550632 | C44: =IF(C42<=0,"n/m (self-funding)",C34/C42) -> 0.57772657 | D44: =IF(D42<=0,"n/m (self-funding)",D34/D42) -> 1.1004316 | E44: =IF(E42<=0,"n/m (self-funding)",E34/E42) -> 2.2008631 | F44: =IF(F42<=0,"n/m (self-funding)",F34/F42) -> 3.9812382 | G44: =IF(G42<=0,"n/m (self-funding)",G34/G42) -> 0.68776973 | H44: =H34/H42 -> 0.83133365
A45: CAC payback (months) = CAC / (first-course contribution / payment months) | B45: =IF(B42<=0,0,B42/(B31/INDEX(Assumptions!$C$90:$E$90,$B$3))) -> 7.4463195 | C45: =IF(C42<=0,0,C42/(C31/INDEX(Assumptions!$C$90:$E$90,$B$3))) -> 7.1599226 | D45: =IF(D42<=0,0,D42/(D31/INDEX(Assumptions!$C$90:$E$90,$B$3))) -> 3.7589594 | E45: =IF(E42<=0,0,E42/(E31/INDEX(Assumptions!$C$90:$E$90,$B$3))) -> 1.8794797 | F45: =IF(F42<=0,0,F42/(F31/INDEX(Assumptions!$C$90:$E$90,$B$3))) -> 1.0719604 | G45: =IF(G42<=0,0,G42/(G31/INDEX(Assumptions!$C$90:$E$90,$B$3))) -> 6.014335 | H45: =H42/(H31/INDEX(Assumptions!$C$90:$E$90,$B$3)) -> 4.9893678 | I45: BM M3 definition; A-ECO-34 payment months
A46: Paid-only CAC (CTWA + Search + Taster net + webinar/pop-up) | H46: =(B24+C24+F24+G24)/(B16+C16+F16+G16) -> 16630.772 | I46: excludes organic content and referral rewards
A47: Variable acquisition cost per target career enrolment (for business_forecast) | H47: =(B24+C24+E24+F24)/H7 -> 11008.031 | I47: (CTWA + Search + Taster net + referral rewards) / target enrolments; organic content is a fixed team cost there
A48: Paid-route media CAC: (CTWA + Search + Taster net) / their enrolments (for business_forecast) | H48: =(B24+C24+F24)/(B16+C16+F16) -> 16680.051 | I48: Growth G4 'media CAC per paid career enrolment'
A49: Counselling conversations per month (career leads x 2.5 + other leads x 0.5) | H49: =H17*2.5+H58*0.5 -> 553.18519 | I49: A-GRO §10.4 method
A50: Counsellor FTE needed (A-GRO-38 x 24 days) | H50: =H49/(INDEX(Assumptions!$C$77:$E$77,$B$3)*24) -> 0.92197531
A51: Fully loaded CAC incl. counsellor, performance freelancer and martech | H51: =(H24+MAX(1,ROUNDUP(H50,0))*INDEX(Assumptions!$C$112:$E$112,$B$3)+INDEX(Assumptions!$C$115:$E$115,$B$3)+INDEX(Assumptions!$C$111:$E$111,$B$3))/H16 -> 17599.711 | I51: (channel spend + A-GRO-45 x FTE + A-GRO-48 + A-GRO-42) / enrolments; Growth G4 definition
A52: Media spend per month on career routes (CTWA + Search + Taster + pop-up/webinar) | H52: =B24+C24+F24+G24 -> 64548.184
A53: Check: organic leads derived vs A-GRO-43 ; referral leads vs A-GRO-44 | D53: =D17-INDEX(Assumptions!$C$79:$E$79,$B$3) -> 22.407407 | E53: =E17-INDEX(Assumptions!$C$80:$E$80,$B$3) -> 2.1428571 | I53: Growth agent check values
A55: H. Other products: masterclass (L4) and self-makeup (L1-S5) acquisition
A56: Seats per month (A-GRO §10.3: L4 24 base; L1-S5 15 base) - scaled with target | B56: =2.4*$H$7 -> 14.4 | C56: =1.5*$H$7 -> 9 | I56: L4 = 12 x target/5 ; L1-S5 = 1.5 x target
A57: Lead -> purchase (A-GRO-27 / A-GRO-28) | B57: =INDEX(Assumptions!$C$65:$E$65,$B$3) -> 0.15 | C57: =INDEX(Assumptions!$C$66:$E$66,$B$3) -> 0.1
A58: Leads needed | B58: =B56/B57 -> 96 | C58: =C56/C57 -> 90 | H58: =B58+C58 -> 186
A59: Paid media (paid share x CPL x leads) | B59: =B58*INDEX(Assumptions!$C$40:$E$40,$B$3)*INDEX(Assumptions!$C$38:$E$38,$B$3) -> 20160 | C59: =C58*INDEX(Assumptions!$C$41:$E$41,$B$3)*INDEX(Assumptions!$C$39:$E$39,$B$3) -> 28800 | I59: A-GRO-18b, A-GRO-16/17
A60: Media per seat sold (for business_forecast) | B60: =B59/B56 -> 1400 | C60: =C59/C56 -> 3200
A61: Columns: B = L4 masterclass, C = L1-S5 self-makeup

Sheet Funnel_Base
A1: Instrumented funnel by channel - Base (per month, steady state months 7-12)
A2: Target-driven: career enrolment target (A-GRO-01) x route mix / route conversion = leads; leads x cost = spend. Webinar/pop-up is the regional (S7) route, additive to the target.
A3: Scenario index | B3: 2 | C3: =CHOOSE(B3,"Conservative","Base","Aggressive") -> Base
A5: Stage / metric | B5: Meta -> WhatsApp (CTWA) | C5: Google Search | D5: Organic IG / content / GBP | E5: Referral / alumni / walk-in | F5: Paid Career Taster | G5: Webinar + regional pop-up | H5: Total / blended | I5: Notes
A6: A. Volumes
A7: Career enrolment target per month (A-GRO-01) | H7: =INDEX(Assumptions!$C$27:$E$27,$B$3) -> 10 | I7: steady state, months 7-12
A8: Route mix (A-GRO-03) | B8: =INDEX(Assumptions!$C$29:$E$29,$B$3) -> 0.3 | C8: =INDEX(Assumptions!$C$30:$E$30,$B$3) -> 0.2 | D8: =INDEX(Assumptions!$C$31:$E$31,$B$3) -> 0.2 | E8: =INDEX(Assumptions!$C$32:$E$32,$B$3) -> 0.2 | F8: =INDEX(Assumptions!$C$33:$E$33,$B$3) -> 0.1 | H8: =SUM(B8:F8) -> 1
A9: B. Stage conversion (scenario sets; base rates assume the <5-min SLA is met)
A10: Lead -> Qualified lead | B10: =INDEX(Assumptions!$C$42:$E$42,$B$3) -> 0.4 | C10: =INDEX(Assumptions!$C$46:$E$46,$B$3) -> 0.45 | D10: =INDEX(Assumptions!$C$50:$E$50,$B$3) -> 0.38 | E10: =INDEX(Assumptions!$C$54:$E$54,$B$3) -> 0.7 | F10: =INDEX(Assumptions!$C$58:$E$58,$B$3) -> 0.82 | I10: Taster: ticket->attend / attend->counselled / counselled->enrolled ; Webinar/pop-up: see block F
A11: QL -> Counselled / visit / demo | B11: =INDEX(Assumptions!$C$43:$E$43,$B$3) -> 0.55 | C11: =INDEX(Assumptions!$C$47:$E$47,$B$3) -> 0.6 | D11: =INDEX(Assumptions!$C$51:$E$51,$B$3) -> 0.55 | E11: =INDEX(Assumptions!$C$55:$E$55,$B$3) -> 0.75 | F11: =INDEX(Assumptions!$C$59:$E$59,$B$3) -> 0.65
A12: Counselled -> Applied (token) | B12: =INDEX(Assumptions!$C$44:$E$44,$B$3) -> 0.3 | C12: =INDEX(Assumptions!$C$48:$E$48,$B$3) -> 0.32 | D12: =INDEX(Assumptions!$C$52:$E$52,$B$3) -> 0.3 | E12: =INDEX(Assumptions!$C$56:$E$56,$B$3) -> 0.55 | F12: =INDEX(Assumptions!$C$60:$E$60,$B$3) -> 0.2
A13: Applied -> Enrolled (fee paid) | B13: =INDEX(Assumptions!$C$45:$E$45,$B$3) -> 0.8 | C13: =INDEX(Assumptions!$C$49:$E$49,$B$3) -> 0.8 | D13: =INDEX(Assumptions!$C$53:$E$53,$B$3) -> 0.8 | E13: =INDEX(Assumptions!$C$57:$E$57,$B$3) -> 0.87 | F13: =1 -> 1
A14: Overall lead -> enrolled | B14: =B10*B11*B12*B13 -> 0.0528 | C14: =C10*C11*C12*C13 -> 0.06912 | D14: =D10*D11*D12*D13 -> 0.05016 | E14: =E10*E11*E12*E13 -> 0.2512125 | F14: =F10*F11*F12*F13 -> 0.1066 | G14: =IFERROR(G16/G17,0) -> 0.054695652 | H14: =H16/H17 -> 0.066233427 | I14: product of stages (Growth agent: CTWA 2.95/5.28/8.70%)
A15: C. Funnel counts per month
A16: Enrolled (target x mix) | B16: =$H$7*B8 -> 3 | C16: =$H$7*C8 -> 2 | D16: =$H$7*D8 -> 2 | E16: =$H$7*E8 -> 2 | F16: =$H$7*F8 -> 1 | G16: =G37+G39 -> 2.516 | H16: =SUM(B16:G16) -> 12.516
A17: Leads (Taster: tickets sold) | B17: =IFERROR(B16/B14,0) -> 56.818182 | C17: =IFERROR(C16/C14,0) -> 28.935185 | D17: =IFERROR(D16/D14,0) -> 39.872408 | E17: =IFERROR(E16/E14,0) -> 7.9613873 | F17: =IFERROR(F16/F14,0) -> 9.380863 | G17: =G36+G38 -> 46 | H17: =SUM(B17:G17) -> 188.96803 | I17: enrolled / overall rate
A18: Qualified leads (Taster: attended) | B18: =B17*B10 -> 22.727273 | C18: =C17*C10 -> 13.020833 | D18: =D17*D10 -> 15.151515 | E18: =E17*E10 -> 5.5729711 | F18: =F17*F10 -> 7.6923077 | H18: =SUM(B18:G18) -> 64.1649
A19: Counselled / visited | B19: =B18*B11 -> 12.5 | C19: =C18*C11 -> 7.8125 | D19: =D18*D11 -> 8.3333333 | E19: =E18*E11 -> 4.1797283 | F19: =F18*F11 -> 5 | H19: =SUM(B19:G19) -> 37.825562
A20: Applied (token paid) | B20: =B19*B12 -> 3.75 | C20: =C19*C12 -> 2.5 | D20: =D19*D12 -> 2.5 | E20: =E19*E12 -> 2.2988506 | F20: =F19*F12 -> 1 | H20: =SUM(B20:G20) -> 12.048851
A21: Enrolled (check = target x mix) | B21: =B20*B13 -> 3 | C21: =C20*C13 -> 2 | D21: =D20*D13 -> 2 | E21: =E20*E13 -> 2 | F21: =F20*F13 -> 1 | G21: =G16 -> 2.516 | H21: =SUM(B21:G21) -> 12.516
A22: D. Cost per lead and channel spend (₹ per month)
A23: Cost per lead / ticket | B23: =(1-INDEX(Assumptions!$C$76:$E$76,$B$3))*INDEX(Assumptions!$C$34:$E$34,$B$3)+INDEX(Assumptions!$C$76:$E$76,$B$3)*INDEX(Assumptions!$C$35:$E$35,$B$3) -> 287.5 | C23: =INDEX(Assumptions!$C$36:$E$36,$B$3) -> 500 | F23: =INDEX(Assumptions!$C$37:$E$37,$B$3) -> 400 | I23: CTWA blends tricity and regional CPL by out-of-town share; organic = content cost / leads; referral = reward per enrolment
A24: Media / reward / content spend | B24: =B17*B23 -> 16335.227 | C24: =C17*C23 -> 14467.593 | D24: =INDEX(Assumptions!$C$114:$E$114,$B$3)+INDEX(Assumptions!$C$117:$E$117,$B$3) -> 35000 | E24: =E16*INDEX(Assumptions!$C$71:$E$71,$B$3) -> 6000 | F24: =F17*(F23+INDEX(Assumptions!$C$102:$E$102,$B$3))-F17*INDEX(Assumptions!$C$18:$E$18,$B$3)/(1+INDEX(Assumptions!$C$15:$E$15,$B$3)) -> -1844.3731 | G24: =G40 -> 8674.5763 | H24: =SUM(B24:G24) -> 78633.023 | I24: Organic: shooter/editor (A-GRO-47) + SEO (A-GRO-50); fixed team cost, shown for CAC visibility
A25: of which taster ticket revenue offset (ex-GST) | F25: =-F17*INDEX(Assumptions!$C$18:$E$18,$B$3)/(1+INDEX(Assumptions!$C$15:$E$15,$B$3)) -> -7941.934 | I25: Growth §11 note 3
A26: E. Unit economics per enrolled career student (₹, ex-GST)
A27: Steady-state L3 realised fee (incl. GST if quoted inclusive) | H27: =IF(INDEX(Assumptions!$C$94:$E$94,$B$3)<=7,INDEX(Assumptions!$C$21:$E$21,$B$3),INDEX(Assumptions!$C$10:$E$10,$B$3)) -> 80000 | I27: A-BM-02 after price step (A-ECO-104 <= month 7), else CA-02
A28: First-course revenue per career enrolment (ex-GST) | B28: =(INDEX(Assumptions!$C$28:$E$28,$B$3)*$H$27+(1-INDEX(Assumptions!$C$28:$E$28,$B$3))*INDEX(Assumptions!$C$19:$E$19,$B$3))/(1+INDEX(Assumptions!$C$15:$E$15,$B$3)*INDEX(Assumptions!$C$16:$E$16,$B$3)) -> 54203.39 | C28: =(INDEX(Assumptions!$C$28:$E$28,$B$3)*$H$27+(1-INDEX(Assumptions!$C$28:$E$28,$B$3))*INDEX(Assumptions!$C$19:$E$19,$B$3))/(1+INDEX(Assumptions!$C$15:$E$15,$B$3)*INDEX(Assumptions!$C$16:$E$16,$B$3)) -> 54203.39 | D28: =(INDEX(Assumptions!$C$28:$E$28,$B$3)*$H$27+(1-INDEX(Assumptions!$C$28:$E$28,$B$3))*INDEX(Assumptions!$C$19:$E$19,$B$3))/(1+INDEX(Assumptions!$C$15:$E$15,$B$3)*INDEX(Assumptions!$C$16:$E$16,$B$3)) -> 54203.39 | E28: =(INDEX(Assumptions!$C$28:$E$28,$B$3)*$H$27+(1-INDEX(Assumptions!$C$28:$E$28,$B$3))*INDEX(Assumptions!$C$19:$E$19,$B$3))/(1+INDEX(Assumptions!$C$15:$E$15,$B$3)*INDEX(Assumptions!$C$16:$E$16,$B$3)) -> 54203.39 | F28: =(INDEX(Assumptions!$C$28:$E$28,$B$3)*$H$27+(1-INDEX(Assumptions!$C$28:$E$28,$B$3))*INDEX(Assumptions!$C$19:$E$19,$B$3)-INDEX(Assumptions!$C$18:$E$18,$B$3))/(1+INDEX(Assumptions!$C$15:$E$15,$B$3)*INDEX(Assumptions!$C$16:$E$16,$B$3)) -> 53356.78 | G28: =(INDEX(Assumptions!$C$28:$E$28,$B$3)*$H$27+(1-INDEX(Assumptions!$C$28:$E$28,$B$3))*INDEX(Assumptions!$C$19:$E$19,$B$3))/(1+INDEX(Assumptions!$C$15:$E$15,$B$3)*INDEX(Assumptions!$C$16:$E$16,$B$3)) -> 54203.39 | H28: =SUMPRODUCT(B28:G28,B16:G16)/H16 -> 54135.748 | I28: L3 share x L3 + L2 share x L2; taster route nets the ₹999 credit
A29: Trainer standard cost per seat-month (trainer + assistant / slots / fill) | H29: =(INDEX(Assumptions!$C$105:$E$105,$B$3)+INDEX(Assumptions!$C$106:$E$106,$B$3))/INDEX(Assumptions!$C$107:$E$107,$B$3)/INDEX(Assumptions!$C$108:$E$108,$B$3) -> 2800 | I29: A-BM-04b/c, A-ECO-46/47
A30: Variable delivery cost per career enrolment | B30: =INDEX(Assumptions!$C$28:$E$28,$B$3)*(INDEX(Assumptions!$C$97:$E$97,$B$3)+IF(INDEX(Assumptions!$C$94:$E$94,$B$3)<=7,0,INDEX(Assumptions!$C$14:$E$14,$B$3))+INDEX(Assumptions!$C$109:$E$109,$B$3)*$H$29+$H$27/(1+INDEX(Assumptions!$C$15:$E$15,$B$3)*INDEX(Assumptions!$C$16:$E$16,$B$3))*INDEX(Assumptions!$C$72:$E$72,$B$3)*INDEX(Assumptions!$C$73:$E$73,$B$3))+(1-INDEX(Assumptions!$C$28:$E$28,$B$3))*(INDEX(Assumptions!$C$98:$E$98,$B$3)+$H$29)+B28*INDEX(Assumptions!$C$78:$E$78,$B$3) -> 12355.932 | C30: =INDEX(Assumptions!$C$28:$E$28,$B$3)*(INDEX(Assumptions!$C$97:$E$97,$B$3)+IF(INDEX(Assumptions!$C$94:$E$94,$B$3)<=7,0,INDEX(Assumptions!$C$14:$E$14,$B$3))+INDEX(Assumptions!$C$109:$E$109,$B$3)*$H$29+$H$27/(1+INDEX(Assumptions!$C$15:$E$15,$B$3)*INDEX(Assumptions!$C$16:$E$16,$B$3))*INDEX(Assumptions!$C$72:$E$72,$B$3)*INDEX(Assumptions!$C$73:$E$73,$B$3))+(1-INDEX(Assumptions!$C$28:$E$28,$B$3))*(INDEX(Assumptions!$C$98:$E$98,$B$3)+$H$29)+C28*INDEX(Assumptions!$C$78:$E$78,$B$3) -> 12355.932 | D30: =INDEX(Assumptions!$C$28:$E$28,$B$3)*(INDEX(Assumptions!$C$97:$E$97,$B$3)+IF(INDEX(Assumptions!$C$94:$E$94,$B$3)<=7,0,INDEX(Assumptions!$C$14:$E$14,$B$3))+INDEX(Assumptions!$C$109:$E$109,$B$3)*$H$29+$H$27/(1+INDEX(Assumptions!$C$15:$E$15,$B$3)*INDEX(Assumptions!$C$16:$E$16,$B$3))*INDEX(Assumptions!$C$72:$E$72,$B$3)*INDEX(Assumptions!$C$73:$E$73,$B$3))+(1-INDEX(Assumptions!$C$28:$E$28,$B$3))*(INDEX(Assumptions!$C$98:$E$98,$B$3)+$H$29)+D28*INDEX(Assumptions!$C$78:$E$78,$B$3) -> 12355.932 | E30: =INDEX(Assumptions!$C$28:$E$28,$B$3)*(INDEX(Assumptions!$C$97:$E$97,$B$3)+IF(INDEX(Assumptions!$C$94:$E$94,$B$3)<=7,0,INDEX(Assumptions!$C$14:$E$14,$B$3))+INDEX(Assumptions!$C$109:$E$109,$B$3)*$H$29+$H$27/(1+INDEX(Assumptions!$C$15:$E$15,$B$3)*INDEX(Assumptions!$C$16:$E$16,$B$3))*INDEX(Assumptions!$C$72:$E$72,$B$3)*INDEX(Assumptions!$C$73:$E$73,$B$3))+(1-INDEX(Assumptions!$C$28:$E$28,$B$3))*(INDEX(Assumptions!$C$98:$E$98,$B$3)+$H$29)+E28*INDEX(Assumptions!$C$78:$E$78,$B$3) -> 12355.932 | F30: =INDEX(Assumptions!$C$28:$E$28,$B$3)*(INDEX(Assumptions!$C$97:$E$97,$B$3)+IF(INDEX(Assumptions!$C$94:$E$94,$B$3)<=7,0,INDEX(Assumptions!$C$14:$E$14,$B$3))+INDEX(Assumptions!$C$109:$E$109,$B$3)*$H$29+$H$27/(1+INDEX(Assumptions!$C$15:$E$15,$B$3)*INDEX(Assumptions!$C$16:$E$16,$B$3))*INDEX(Assumptions!$C$72:$E$72,$B$3)*INDEX(Assumptions!$C$73:$E$73,$B$3))+(1-INDEX(Assumptions!$C$28:$E$28,$B$3))*(INDEX(Assumptions!$C$98:$E$98,$B$3)+$H$29)+F28*INDEX(Assumptions!$C$78:$E$78,$B$3) -> 12339 | G30: =INDEX(Assumptions!$C$28:$E$28,$B$3)*(INDEX(Assumptions!$C$97:$E$97,$B$3)+IF(INDEX(Assumptions!$C$94:$E$94,$B$3)<=7,0,INDEX(Assumptions!$C$14:$E$14,$B$3))+INDEX(Assumptions!$C$109:$E$109,$B$3)*$H$29+$H$27/(1+INDEX(Assumptions!$C$15:$E$15,$B$3)*INDEX(Assumptions!$C$16:$E$16,$B$3))*INDEX(Assumptions!$C$72:$E$72,$B$3)*INDEX(Assumptions!$C$73:$E$73,$B$3))+(1-INDEX(Assumptions!$C$28:$E$28,$B$3))*(INDEX(Assumptions!$C$98:$E$98,$B$3)+$H$29)+G28*INDEX(Assumptions!$C$78:$E$78,$B$3) -> 12355.932 | H30: =SUMPRODUCT(B30:G30,B16:G16)/H16 -> 12354.579 | I30: consumables + kit (pre-step) + trainer standard cost + EMI subvention; gateway below
A31: First-course contribution before CAC | B31: =B28-B30 -> 41847.458 | C31: =C28-C30 -> 41847.458 | D31: =D28-D30 -> 41847.458 | E31: =E28-E30 -> 41847.458 | F31: =F28-F30 -> 41017.78 | G31: =G28-G30 -> 41847.458 | H31: =H28-H30 -> 41781.168
A32: Contribution margin % (before CAC) | B32: =IFERROR(B31/B28,0) -> 0.77204503 | C32: =IFERROR(C31/C28,0) -> 0.77204503 | D32: =IFERROR(D31/D28,0) -> 0.77204503 | E32: =IFERROR(E31/E28,0) -> 0.77204503 | F32: =IFERROR(F31/F28,0) -> 0.76874541 | G32: =IFERROR(G31/G28,0) -> 0.77204503 | H32: =H31/H28 -> 0.77178519
A33: Follow-on contribution within 24 months (LTV add-on) | H33: =(1-INDEX(Assumptions!$C$28:$E$28,$B$3))*INDEX(Assumptions!$C$92:$E$92,$B$3)*((INDEX(Assumptions!$C$21:$E$21,$B$3)-INDEX(Assumptions!$C$19:$E$19,$B$3))/(1+INDEX(Assumptions!$C$15:$E$15,$B$3)*INDEX(Assumptions!$C$16:$E$16,$B$3))-INDEX(Assumptions!$C$97:$E$97,$B$3)-2*$H$29)+INDEX(Assumptions!$C$91:$E$91,$B$3)*(INDEX(Assumptions!$C$22:$E$22,$B$3)/(1+INDEX(Assumptions!$C$15:$E$15,$B$3)*INDEX(Assumptions!$C$16:$E$16,$B$3))-INDEX(Assumptions!$C$100:$E$100,$B$3))+INDEX(Assumptions!$C$69:$E$69,$B$3)*INDEX(Assumptions!$C$74:$E$74,$B$3)*(INDEX(Assumptions!$C$24:$E$24,$B$3)/(1+INDEX(Assumptions!$C$15:$E$15,$B$3)*INDEX(Assumptions!$C$16:$E$16,$B$3))-INDEX(Assumptions!$C$103:$E$103,$B$3))+INDEX(Assumptions!$C$28:$E$28,$B$3)*IF(INDEX(Assumptions!$C$94:$E$94,$B$3)<=7,INDEX(Assumptions!$C$93:$E$93,$B$3),0) -> 8747.161 | I33: L2->L3 upgrade + masterclasses + Pro Circle renewal + kit margin
A34: LTV: 24-month contribution per career student (before CAC) | B34: =B31+$H$33 -> 50594.619 | C34: =C31+$H$33 -> 50594.619 | D34: =D31+$H$33 -> 50594.619 | E34: =E31+$H$33 -> 50594.619 | F34: =F31+$H$33 -> 49764.941 | G34: =G31+$H$33 -> 50594.619 | H34: =H31+H33 -> 50528.329
A35: F. Webinar + regional pop-up route (S7; additive to target)
A36: Online parents' sessions per month x registrants | G36: =INDEX(Assumptions!$C$83:$E$83,$B$3)*INDEX(Assumptions!$C$84:$E$84,$B$3) -> 30 | I36: A-ECO-31 x A-ECO-32
A37: Webinar enrolments = registrants x attend x counselling booked x CTWA counselled->enrolled | G37: =G36*INDEX(Assumptions!$C$63:$E$63,$B$3)*INDEX(Assumptions!$C$64:$E$64,$B$3)*INDEX(Assumptions!$C$44:$E$44,$B$3)*INDEX(Assumptions!$C$45:$E$45,$B$3) -> 0.756 | I37: A-GRO-26a/b; A-GRO-18c/d
A38: Pop-up events per month (A-ECO-33) x paid attendees | G38: =INDEX(Assumptions!$C$89:$E$89,$B$3)*INDEX(Assumptions!$C$85:$E$85,$B$3) -> 16 | I38: A-BM-06a
A39: Pop-up enrolments = attendees x attendee->enrol (A-BM-06d) | G39: =G38*INDEX(Assumptions!$C$88:$E$88,$B$3) -> 1.76
A40: Webinar promo + net pop-up cost (event cost - ticket revenue ex-GST) | G40: =G36*INDEX(Assumptions!$C$82:$E$82,$B$3)+INDEX(Assumptions!$C$89:$E$89,$B$3)*(INDEX(Assumptions!$C$87:$E$87,$B$3)-INDEX(Assumptions!$C$85:$E$85,$B$3)*INDEX(Assumptions!$C$86:$E$86,$B$3)/(1+INDEX(Assumptions!$C$15:$E$15,$B$3))) -> 8674.5763
A41: G. CAC, payback and totals
A42: CAC per enrolment (channel spend / enrolled) | B42: =IFERROR(B24/B16,0) -> 5445.0758 | C42: =IFERROR(C24/C16,0) -> 7233.7963 | D42: =IFERROR(D24/D16,0) -> 17500 | E42: =IFERROR(E24/E16,0) -> 3000 | F42: =IFERROR(F24/F16,0) -> -1844.3731 | G42: =IFERROR(G24/G16,0) -> 3447.7648 | H42: =H24/H16 -> 6282.6001
A43: CAC as % of first-course revenue | B43: =IFERROR(B42/B28,0) -> 0.10045637 | C43: =IFERROR(C42/C28,0) -> 0.13345653 | D43: =IFERROR(D42/D28,0) -> 0.32285804 | E43: =IFERROR(E42/E28,0) -> 0.055347092 | F43: =IFERROR(F42/F28,0) -> -0.034566799 | G43: =IFERROR(G42/G28,0) -> 0.063607919 | H43: =H42/H28 -> 0.11605271
A44: LTV / CAC (24-month contribution) | B44: =IF(B42<=0,"n/m (self-funding)",B34/B42) -> 9.2918117 | C44: =IF(C42<=0,"n/m (self-funding)",C34/C42) -> 6.9942001 | D44: =IF(D42<=0,"n/m (self-funding)",D34/D42) -> 2.8911211 | E44: =IF(E42<=0,"n/m (self-funding)",E34/E42) -> 16.864873 | F44: =IF(F42<=0,"n/m (self-funding)",F34/F42) -> n/m (self-funding) | G44: =IF(G42<=0,"n/m (self-funding)",G34/G42) -> 14.674614 | H44: =H34/H42 -> 8.0425824
A45: CAC payback (months) = CAC / (first-course contribution / payment months) | B45: =IF(B42<=0,0,B42/(B31/INDEX(Assumptions!$C$90:$E$90,$B$3))) -> 0.26023448 | C45: =IF(C42<=0,0,C42/(C31/INDEX(Assumptions!$C$90:$E$90,$B$3))) -> 0.34572214 | D45: =IF(D42<=0,0,D42/(D31/INDEX(Assumptions!$C$90:$E$90,$B$3))) -> 0.836371 | E45: =IF(E42<=0,0,E42/(E31/INDEX(Assumptions!$C$90:$E$90,$B$3))) -> 0.14337789 | F45: =IF(F42<=0,0,F42/(F31/INDEX(Assumptions!$C$90:$E$90,$B$3))) -> 0 | G45: =IF(G42<=0,0,G42/(G31/INDEX(Assumptions!$C$90:$E$90,$B$3))) -> 0.16477774 | H45: =H42/(H31/INDEX(Assumptions!$C$90:$E$90,$B$3)) -> 0.30073837 | I45: BM M3 definition; A-ECO-34 payment months
A46: Paid-only CAC (CTWA + Search + Taster net + webinar/pop-up) | H46: =(B24+C24+F24+G24)/(B16+C16+F16+G16) -> 4419.0962 | I46: excludes organic content and referral rewards
A47: Variable acquisition cost per target career enrolment (for business_forecast) | H47: =(B24+C24+E24+F24)/H7 -> 3495.8447 | I47: (CTWA + Search + Taster net + referral rewards) / target enrolments; organic content is a fixed team cost there
A48: Paid-route media CAC: (CTWA + Search + Taster net) / their enrolments (for business_forecast) | H48: =(B24+C24+F24)/(B16+C16+F16) -> 4826.4078 | I48: Growth G4 'media CAC per paid career enrolment'
A49: Counselling conversations per month (career leads x 2.5 + other leads x 0.5) | H49: =H17*2.5+H58*0.5 -> 564.53771 | I49: A-GRO §10.4 method
A50: Counsellor FTE needed (A-GRO-38 x 24 days) | H50: =H49/(INDEX(Assumptions!$C$77:$E$77,$B$3)*24) -> 0.78408015
A51: Fully loaded CAC incl. counsellor, performance freelancer and martech | H51: =(H24+MAX(1,ROUNDUP(H50,0))*INDEX(Assumptions!$C$112:$E$112,$B$3)+INDEX(Assumptions!$C$115:$E$115,$B$3)+INDEX(Assumptions!$C$111:$E$111,$B$3))/H16 -> 11316.157 | I51: (channel spend + A-GRO-45 x FTE + A-GRO-48 + A-GRO-42) / enrolments; Growth G4 definition
A52: Media spend per month on career routes (CTWA + Search + Taster + pop-up/webinar) | H52: =B24+C24+F24+G24 -> 37633.023
A53: Check: organic leads derived vs A-GRO-43 ; referral leads vs A-GRO-44 | D53: =D17-INDEX(Assumptions!$C$79:$E$79,$B$3) -> -0.12759171 | E53: =E17-INDEX(Assumptions!$C$80:$E$80,$B$3) -> -0.038612728 | I53: Growth agent check values
A55: H. Other products: masterclass (L4) and self-makeup (L1-S5) acquisition
A56: Seats per month (A-GRO §10.3: L4 24 base; L1-S5 15 base) - scaled with target | B56: =2.4*$H$7 -> 24 | C56: =1.5*$H$7 -> 15 | I56: L4 = 12 x target/5 ; L1-S5 = 1.5 x target
A57: Lead -> purchase (A-GRO-27 / A-GRO-28) | B57: =INDEX(Assumptions!$C$65:$E$65,$B$3) -> 0.25 | C57: =INDEX(Assumptions!$C$66:$E$66,$B$3) -> 0.17
A58: Leads needed | B58: =B56/B57 -> 96 | C58: =C56/C57 -> 88.235294 | H58: =B58+C58 -> 184.23529
A59: Paid media (paid share x CPL x leads) | B59: =B58*INDEX(Assumptions!$C$40:$E$40,$B$3)*INDEX(Assumptions!$C$38:$E$38,$B$3) -> 7200 | C59: =C58*INDEX(Assumptions!$C$41:$E$41,$B$3)*INDEX(Assumptions!$C$39:$E$39,$B$3) -> 10588.235 | I59: A-GRO-18b, A-GRO-16/17
A60: Media per seat sold (for business_forecast) | B60: =B59/B56 -> 300 | C60: =C59/C56 -> 705.88235
A61: Columns: B = L4 masterclass, C = L1-S5 self-makeup

Sheet Funnel_Aggressive
A1: Instrumented funnel by channel - Aggressive (per month, steady state months 7-12)
A2: Target-driven: career enrolment target (A-GRO-01) x route mix / route conversion = leads; leads x cost = spend. Webinar/pop-up is the regional (S7) route, additive to the target.
A3: Scenario index | B3: 3 | C3: =CHOOSE(B3,"Conservative","Base","Aggressive") -> Aggressive
A5: Stage / metric | B5: Meta -> WhatsApp (CTWA) | C5: Google Search | D5: Organic IG / content / GBP | E5: Referral / alumni / walk-in | F5: Paid Career Taster | G5: Webinar + regional pop-up | H5: Total / blended | I5: Notes
A6: A. Volumes
A7: Career enrolment target per month (A-GRO-01) | H7: =INDEX(Assumptions!$C$27:$E$27,$B$3) -> 15 | I7: steady state, months 7-12
A8: Route mix (A-GRO-03) | B8: =INDEX(Assumptions!$C$29:$E$29,$B$3) -> 0.3 | C8: =INDEX(Assumptions!$C$30:$E$30,$B$3) -> 0.2 | D8: =INDEX(Assumptions!$C$31:$E$31,$B$3) -> 0.2 | E8: =INDEX(Assumptions!$C$32:$E$32,$B$3) -> 0.2 | F8: =INDEX(Assumptions!$C$33:$E$33,$B$3) -> 0.1 | H8: =SUM(B8:F8) -> 1
A9: B. Stage conversion (scenario sets; base rates assume the <5-min SLA is met)
A10: Lead -> Qualified lead | B10: =INDEX(Assumptions!$C$42:$E$42,$B$3) -> 0.45 | C10: =INDEX(Assumptions!$C$46:$E$46,$B$3) -> 0.5 | D10: =INDEX(Assumptions!$C$50:$E$50,$B$3) -> 0.45 | E10: =INDEX(Assumptions!$C$54:$E$54,$B$3) -> 0.8 | F10: =INDEX(Assumptions!$C$58:$E$58,$B$3) -> 0.9 | I10: Taster: ticket->attend / attend->counselled / counselled->enrolled ; Webinar/pop-up: see block F
A11: QL -> Counselled / visit / demo | B11: =INDEX(Assumptions!$C$43:$E$43,$B$3) -> 0.65 | C11: =INDEX(Assumptions!$C$47:$E$47,$B$3) -> 0.65 | D11: =INDEX(Assumptions!$C$51:$E$51,$B$3) -> 0.65 | E11: =INDEX(Assumptions!$C$55:$E$55,$B$3) -> 0.8 | F11: =INDEX(Assumptions!$C$59:$E$59,$B$3) -> 0.8
A12: Counselled -> Applied (token) | B12: =INDEX(Assumptions!$C$44:$E$44,$B$3) -> 0.35 | C12: =INDEX(Assumptions!$C$48:$E$48,$B$3) -> 0.35 | D12: =INDEX(Assumptions!$C$52:$E$52,$B$3) -> 0.35 | E12: =INDEX(Assumptions!$C$56:$E$56,$B$3) -> 0.6 | F12: =INDEX(Assumptions!$C$60:$E$60,$B$3) -> 0.25
A13: Applied -> Enrolled (fee paid) | B13: =INDEX(Assumptions!$C$45:$E$45,$B$3) -> 0.85 | C13: =INDEX(Assumptions!$C$49:$E$49,$B$3) -> 0.85 | D13: =INDEX(Assumptions!$C$53:$E$53,$B$3) -> 0.85 | E13: =INDEX(Assumptions!$C$57:$E$57,$B$3) -> 0.92 | F13: =1 -> 1
A14: Overall lead -> enrolled | B14: =B10*B11*B12*B13 -> 0.08701875 | C14: =C10*C11*C12*C13 -> 0.0966875 | D14: =D10*D11*D12*D13 -> 0.08701875 | E14: =E10*E11*E12*E13 -> 0.35328 | F14: =F10*F11*F12*F13 -> 0.18 | G14: =IFERROR(G16/G17,0) -> 0.101775 | H14: =H16/H17 -> 0.10811932 | I14: product of stages (Growth agent: CTWA 2.95/5.28/8.70%)
A15: C. Funnel counts per month
A16: Enrolled (target x mix) | B16: =$H$7*B8 -> 4.5 | C16: =$H$7*C8 -> 3 | D16: =$H$7*D8 -> 3 | E16: =$H$7*E8 -> 3 | F16: =$H$7*F8 -> 1.5 | G16: =G37+G39 -> 8.142 | H16: =SUM(B16:G16) -> 23.142
A17: Leads (Taster: tickets sold) | B17: =IFERROR(B16/B14,0) -> 51.712993 | C17: =IFERROR(C16/C14,0) -> 31.027796 | D17: =IFERROR(D16/D14,0) -> 34.475329 | E17: =IFERROR(E16/E14,0) -> 8.4918478 | F17: =IFERROR(F16/F14,0) -> 8.3333333 | G17: =G36+G38 -> 80 | H17: =SUM(B17:G17) -> 214.0413 | I17: enrolled / overall rate
A18: Qualified leads (Taster: attended) | B18: =B17*B10 -> 23.270847 | C18: =C17*C10 -> 15.513898 | D18: =D17*D10 -> 15.513898 | E18: =E17*E10 -> 6.7934783 | F18: =F17*F10 -> 7.5 | H18: =SUM(B18:G18) -> 68.592121
A19: Counselled / visited | B19: =B18*B11 -> 15.12605 | C19: =C18*C11 -> 10.084034 | D19: =D18*D11 -> 10.084034 | E19: =E18*E11 -> 5.4347826 | F19: =F18*F11 -> 6 | H19: =SUM(B19:G19) -> 46.7289
A20: Applied (token paid) | B20: =B19*B12 -> 5.2941176 | C20: =C19*C12 -> 3.5294118 | D20: =D19*D12 -> 3.5294118 | E20: =E19*E12 -> 3.2608696 | F20: =F19*F12 -> 1.5 | H20: =SUM(B20:G20) -> 17.113811
A21: Enrolled (check = target x mix) | B21: =B20*B13 -> 4.5 | C21: =C20*C13 -> 3 | D21: =D20*D13 -> 3 | E21: =E20*E13 -> 3 | F21: =F20*F13 -> 1.5 | G21: =G16 -> 8.142 | H21: =SUM(B21:G21) -> 23.142
A22: D. Cost per lead and channel spend (₹ per month)
A23: Cost per lead / ticket | B23: =(1-INDEX(Assumptions!$C$76:$E$76,$B$3))*INDEX(Assumptions!$C$34:$E$34,$B$3)+INDEX(Assumptions!$C$76:$E$76,$B$3)*INDEX(Assumptions!$C$35:$E$35,$B$3) -> 139.5 | C23: =INDEX(Assumptions!$C$36:$E$36,$B$3) -> 300 | F23: =INDEX(Assumptions!$C$37:$E$37,$B$3) -> 200 | I23: CTWA blends tricity and regional CPL by out-of-town share; organic = content cost / leads; referral = reward per enrolment
A24: Media / reward / content spend | B24: =B17*B23 -> 7213.9625 | C24: =C17*C23 -> 9308.3387 | D24: =INDEX(Assumptions!$C$114:$E$114,$B$3)+INDEX(Assumptions!$C$117:$E$117,$B$3) -> 50000 | E24: =E16*INDEX(Assumptions!$C$71:$E$71,$B$3) -> 6000 | F24: =F17*(F23+INDEX(Assumptions!$C$102:$E$102,$B$3))-F17*INDEX(Assumptions!$C$18:$E$18,$B$3)/(1+INDEX(Assumptions!$C$15:$E$15,$B$3)) -> -3721.7514 | G24: =G40 -> -3413.5593 | H24: =SUM(B24:G24) -> 65386.99 | I24: Organic: shooter/editor (A-GRO-47) + SEO (A-GRO-50); fixed team cost, shown for CAC visibility
A25: of which taster ticket revenue offset (ex-GST) | F25: =-F17*INDEX(Assumptions!$C$18:$E$18,$B$3)/(1+INDEX(Assumptions!$C$15:$E$15,$B$3)) -> -7055.0847 | I25: Growth §11 note 3
A26: E. Unit economics per enrolled career student (₹, ex-GST)
A27: Steady-state L3 realised fee (incl. GST if quoted inclusive) | H27: =IF(INDEX(Assumptions!$C$94:$E$94,$B$3)<=7,INDEX(Assumptions!$C$21:$E$21,$B$3),INDEX(Assumptions!$C$10:$E$10,$B$3)) -> 100000 | I27: A-BM-02 after price step (A-ECO-104 <= month 7), else CA-02
A28: First-course revenue per career enrolment (ex-GST) | B28: =(INDEX(Assumptions!$C$28:$E$28,$B$3)*$H$27+(1-INDEX(Assumptions!$C$28:$E$28,$B$3))*INDEX(Assumptions!$C$19:$E$19,$B$3))/(1+INDEX(Assumptions!$C$15:$E$15,$B$3)*INDEX(Assumptions!$C$16:$E$16,$B$3)) -> 70762.712 | C28: =(INDEX(Assumptions!$C$28:$E$28,$B$3)*$H$27+(1-INDEX(Assumptions!$C$28:$E$28,$B$3))*INDEX(Assumptions!$C$19:$E$19,$B$3))/(1+INDEX(Assumptions!$C$15:$E$15,$B$3)*INDEX(Assumptions!$C$16:$E$16,$B$3)) -> 70762.712 | D28: =(INDEX(Assumptions!$C$28:$E$28,$B$3)*$H$27+(1-INDEX(Assumptions!$C$28:$E$28,$B$3))*INDEX(Assumptions!$C$19:$E$19,$B$3))/(1+INDEX(Assumptions!$C$15:$E$15,$B$3)*INDEX(Assumptions!$C$16:$E$16,$B$3)) -> 70762.712 | E28: =(INDEX(Assumptions!$C$28:$E$28,$B$3)*$H$27+(1-INDEX(Assumptions!$C$28:$E$28,$B$3))*INDEX(Assumptions!$C$19:$E$19,$B$3))/(1+INDEX(Assumptions!$C$15:$E$15,$B$3)*INDEX(Assumptions!$C$16:$E$16,$B$3)) -> 70762.712 | F28: =(INDEX(Assumptions!$C$28:$E$28,$B$3)*$H$27+(1-INDEX(Assumptions!$C$28:$E$28,$B$3))*INDEX(Assumptions!$C$19:$E$19,$B$3)-INDEX(Assumptions!$C$18:$E$18,$B$3))/(1+INDEX(Assumptions!$C$15:$E$15,$B$3)*INDEX(Assumptions!$C$16:$E$16,$B$3)) -> 69916.102 | G28: =(INDEX(Assumptions!$C$28:$E$28,$B$3)*$H$27+(1-INDEX(Assumptions!$C$28:$E$28,$B$3))*INDEX(Assumptions!$C$19:$E$19,$B$3))/(1+INDEX(Assumptions!$C$15:$E$15,$B$3)*INDEX(Assumptions!$C$16:$E$16,$B$3)) -> 70762.712 | H28: =SUMPRODUCT(B28:G28,B16:G16)/H16 -> 70707.837 | I28: L3 share x L3 + L2 share x L2; taster route nets the ₹999 credit
A29: Trainer standard cost per seat-month (trainer + assistant / slots / fill) | H29: =(INDEX(Assumptions!$C$105:$E$105,$B$3)+INDEX(Assumptions!$C$106:$E$106,$B$3))/INDEX(Assumptions!$C$107:$E$107,$B$3)/INDEX(Assumptions!$C$108:$E$108,$B$3) -> 2181.8182 | I29: A-BM-04b/c, A-ECO-46/47
A30: Variable delivery cost per career enrolment | B30: =INDEX(Assumptions!$C$28:$E$28,$B$3)*(INDEX(Assumptions!$C$97:$E$97,$B$3)+IF(INDEX(Assumptions!$C$94:$E$94,$B$3)<=7,0,INDEX(Assumptions!$C$14:$E$14,$B$3))+INDEX(Assumptions!$C$109:$E$109,$B$3)*$H$29+$H$27/(1+INDEX(Assumptions!$C$15:$E$15,$B$3)*INDEX(Assumptions!$C$16:$E$16,$B$3))*INDEX(Assumptions!$C$72:$E$72,$B$3)*INDEX(Assumptions!$C$73:$E$73,$B$3))+(1-INDEX(Assumptions!$C$28:$E$28,$B$3))*(INDEX(Assumptions!$C$98:$E$98,$B$3)+$H$29)+B28*INDEX(Assumptions!$C$78:$E$78,$B$3) -> 10816.025 | C30: =INDEX(Assumptions!$C$28:$E$28,$B$3)*(INDEX(Assumptions!$C$97:$E$97,$B$3)+IF(INDEX(Assumptions!$C$94:$E$94,$B$3)<=7,0,INDEX(Assumptions!$C$14:$E$14,$B$3))+INDEX(Assumptions!$C$109:$E$109,$B$3)*$H$29+$H$27/(1+INDEX(Assumptions!$C$15:$E$15,$B$3)*INDEX(Assumptions!$C$16:$E$16,$B$3))*INDEX(Assumptions!$C$72:$E$72,$B$3)*INDEX(Assumptions!$C$73:$E$73,$B$3))+(1-INDEX(Assumptions!$C$28:$E$28,$B$3))*(INDEX(Assumptions!$C$98:$E$98,$B$3)+$H$29)+C28*INDEX(Assumptions!$C$78:$E$78,$B$3) -> 10816.025 | D30: =INDEX(Assumptions!$C$28:$E$28,$B$3)*(INDEX(Assumptions!$C$97:$E$97,$B$3)+IF(INDEX(Assumptions!$C$94:$E$94,$B$3)<=7,0,INDEX(Assumptions!$C$14:$E$14,$B$3))+INDEX(Assumptions!$C$109:$E$109,$B$3)*$H$29+$H$27/(1+INDEX(Assumptions!$C$15:$E$15,$B$3)*INDEX(Assumptions!$C$16:$E$16,$B$3))*INDEX(Assumptions!$C$72:$E$72,$B$3)*INDEX(Assumptions!$C$73:$E$73,$B$3))+(1-INDEX(Assumptions!$C$28:$E$28,$B$3))*(INDEX(Assumptions!$C$98:$E$98,$B$3)+$H$29)+D28*INDEX(Assumptions!$C$78:$E$78,$B$3) -> 10816.025 | E30: =INDEX(Assumptions!$C$28:$E$28,$B$3)*(INDEX(Assumptions!$C$97:$E$97,$B$3)+IF(INDEX(Assumptions!$C$94:$E$94,$B$3)<=7,0,INDEX(Assumptions!$C$14:$E$14,$B$3))+INDEX(Assumptions!$C$109:$E$109,$B$3)*$H$29+$H$27/(1+INDEX(Assumptions!$C$15:$E$15,$B$3)*INDEX(Assumptions!$C$16:$E$16,$B$3))*INDEX(Assumptions!$C$72:$E$72,$B$3)*INDEX(Assumptions!$C$73:$E$73,$B$3))+(1-INDEX(Assumptions!$C$28:$E$28,$B$3))*(INDEX(Assumptions!$C$98:$E$98,$B$3)+$H$29)+E28*INDEX(Assumptions!$C$78:$E$78,$B$3) -> 10816.025 | F30: =INDEX(Assumptions!$C$28:$E$28,$B$3)*(INDEX(Assumptions!$C$97:$E$97,$B$3)+IF(INDEX(Assumptions!$C$94:$E$94,$B$3)<=7,0,INDEX(Assumptions!$C$14:$E$14,$B$3))+INDEX(Assumptions!$C$109:$E$109,$B$3)*$H$29+$H$27/(1+INDEX(Assumptions!$C$15:$E$15,$B$3)*INDEX(Assumptions!$C$16:$E$16,$B$3))*INDEX(Assumptions!$C$72:$E$72,$B$3)*INDEX(Assumptions!$C$73:$E$73,$B$3))+(1-INDEX(Assumptions!$C$28:$E$28,$B$3))*(INDEX(Assumptions!$C$98:$E$98,$B$3)+$H$29)+F28*INDEX(Assumptions!$C$78:$E$78,$B$3) -> 10800.786 | G30: =INDEX(Assumptions!$C$28:$E$28,$B$3)*(INDEX(Assumptions!$C$97:$E$97,$B$3)+IF(INDEX(Assumptions!$C$94:$E$94,$B$3)<=7,0,INDEX(Assumptions!$C$14:$E$14,$B$3))+INDEX(Assumptions!$C$109:$E$109,$B$3)*$H$29+$H$27/(1+INDEX(Assumptions!$C$15:$E$15,$B$3)*INDEX(Assumptions!$C$16:$E$16,$B$3))*INDEX(Assumptions!$C$72:$E$72,$B$3)*INDEX(Assumptions!$C$73:$E$73,$B$3))+(1-INDEX(Assumptions!$C$28:$E$28,$B$3))*(INDEX(Assumptions!$C$98:$E$98,$B$3)+$H$29)+G28*INDEX(Assumptions!$C$78:$E$78,$B$3) -> 10816.025 | H30: =SUMPRODUCT(B30:G30,B16:G16)/H16 -> 10815.037 | I30: consumables + kit (pre-step) + trainer standard cost + EMI subvention; gateway below
A31: First-course contribution before CAC | B31: =B28-B30 -> 59946.687 | C31: =C28-C30 -> 59946.687 | D31: =D28-D30 -> 59946.687 | E31: =E28-E30 -> 59946.687 | F31: =F28-F30 -> 59115.316 | G31: =G28-G30 -> 59946.687 | H31: =H28-H30 -> 59892.8
A32: Contribution margin % (before CAC) | B32: =IFERROR(B31/B28,0) -> 0.84715079 | C32: =IFERROR(C31/C28,0) -> 0.84715079 | D32: =IFERROR(D31/D28,0) -> 0.84715079 | E32: =IFERROR(E31/E28,0) -> 0.84715079 | F32: =IFERROR(F31/F28,0) -> 0.84551791 | G32: =IFERROR(G31/G28,0) -> 0.84715079 | H32: =H31/H28 -> 0.84704614
A33: Follow-on contribution within 24 months (LTV add-on) | H33: =(1-INDEX(Assumptions!$C$28:$E$28,$B$3))*INDEX(Assumptions!$C$92:$E$92,$B$3)*((INDEX(Assumptions!$C$21:$E$21,$B$3)-INDEX(Assumptions!$C$19:$E$19,$B$3))/(1+INDEX(Assumptions!$C$15:$E$15,$B$3)*INDEX(Assumptions!$C$16:$E$16,$B$3))-INDEX(Assumptions!$C$97:$E$97,$B$3)-2*$H$29)+INDEX(Assumptions!$C$91:$E$91,$B$3)*(INDEX(Assumptions!$C$22:$E$22,$B$3)/(1+INDEX(Assumptions!$C$15:$E$15,$B$3)*INDEX(Assumptions!$C$16:$E$16,$B$3))-INDEX(Assumptions!$C$100:$E$100,$B$3))+INDEX(Assumptions!$C$69:$E$69,$B$3)*INDEX(Assumptions!$C$74:$E$74,$B$3)*(INDEX(Assumptions!$C$24:$E$24,$B$3)/(1+INDEX(Assumptions!$C$15:$E$15,$B$3)*INDEX(Assumptions!$C$16:$E$16,$B$3))-INDEX(Assumptions!$C$103:$E$103,$B$3))+INDEX(Assumptions!$C$28:$E$28,$B$3)*IF(INDEX(Assumptions!$C$94:$E$94,$B$3)<=7,INDEX(Assumptions!$C$93:$E$93,$B$3),0) -> 18188.099 | I33: L2->L3 upgrade + masterclasses + Pro Circle renewal + kit margin
A34: LTV: 24-month contribution per career student (before CAC) | B34: =B31+$H$33 -> 78134.786 | C34: =C31+$H$33 -> 78134.786 | D34: =D31+$H$33 -> 78134.786 | E34: =E31+$H$33 -> 78134.786 | F34: =F31+$H$33 -> 77303.415 | G34: =G31+$H$33 -> 78134.786 | H34: =H31+H33 -> 78080.899
A35: F. Webinar + regional pop-up route (S7; additive to target)
A36: Online parents' sessions per month x registrants | G36: =INDEX(Assumptions!$C$83:$E$83,$B$3)*INDEX(Assumptions!$C$84:$E$84,$B$3) -> 40 | I36: A-ECO-31 x A-ECO-32
A37: Webinar enrolments = registrants x attend x counselling booked x CTWA counselled->enrolled | G37: =G36*INDEX(Assumptions!$C$63:$E$63,$B$3)*INDEX(Assumptions!$C$64:$E$64,$B$3)*INDEX(Assumptions!$C$44:$E$44,$B$3)*INDEX(Assumptions!$C$45:$E$45,$B$3) -> 2.142 | I37: A-GRO-26a/b; A-GRO-18c/d
A38: Pop-up events per month (A-ECO-33) x paid attendees | G38: =INDEX(Assumptions!$C$89:$E$89,$B$3)*INDEX(Assumptions!$C$85:$E$85,$B$3) -> 40 | I38: A-BM-06a
A39: Pop-up enrolments = attendees x attendee->enrol (A-BM-06d) | G39: =G38*INDEX(Assumptions!$C$88:$E$88,$B$3) -> 6
A40: Webinar promo + net pop-up cost (event cost - ticket revenue ex-GST) | G40: =G36*INDEX(Assumptions!$C$82:$E$82,$B$3)+INDEX(Assumptions!$C$89:$E$89,$B$3)*(INDEX(Assumptions!$C$87:$E$87,$B$3)-INDEX(Assumptions!$C$85:$E$85,$B$3)*INDEX(Assumptions!$C$86:$E$86,$B$3)/(1+INDEX(Assumptions!$C$15:$E$15,$B$3))) -> -3413.5593
A41: G. CAC, payback and totals
A42: CAC per enrolment (channel spend / enrolled) | B42: =IFERROR(B24/B16,0) -> 1603.1028 | C42: =IFERROR(C24/C16,0) -> 3102.7796 | D42: =IFERROR(D24/D16,0) -> 16666.667 | E42: =IFERROR(E24/E16,0) -> 2000 | F42: =IFERROR(F24/F16,0) -> -2481.1676 | G42: =IFERROR(G24/G16,0) -> -419.25317 | H42: =H24/H16 -> 2825.4684
A43: CAC as % of first-course revenue | B43: =IFERROR(B42/B28,0) -> 0.022654626 | C43: =IFERROR(C42/C28,0) -> 0.043847663 | D43: =IFERROR(D42/D28,0) -> 0.23552894 | E43: =IFERROR(E42/E28,0) -> 0.028263473 | F43: =IFERROR(F42/F28,0) -> -0.035487785 | G43: =IFERROR(G42/G28,0) -> -0.0059247754 | H43: =H42/H28 -> 0.039959763
A44: LTV / CAC (24-month contribution) | B44: =IF(B42<=0,"n/m (self-funding)",B34/B42) -> 48.739723 | C44: =IF(C42<=0,"n/m (self-funding)",C34/C42) -> 25.18219 | D44: =IF(D42<=0,"n/m (self-funding)",D34/D42) -> 4.6880872 | E44: =IF(E42<=0,"n/m (self-funding)",E34/E42) -> 39.067393 | F44: =IF(F42<=0,"n/m (self-funding)",F34/F42) -> n/m (self-funding) | G44: =IF(G42<=0,"n/m (self-funding)",G34/G42) -> n/m (self-funding) | H44: =H34/H42 -> 27.634674
A45: CAC payback (months) = CAC / (first-course contribution / payment months) | B45: =IF(B42<=0,0,B42/(B31/INDEX(Assumptions!$C$90:$E$90,$B$3))) -> 0.026742141 | C45: =IF(C42<=0,0,C42/(C31/INDEX(Assumptions!$C$90:$E$90,$B$3))) -> 0.051758983 | D45: =IF(D42<=0,0,D42/(D31/INDEX(Assumptions!$C$90:$E$90,$B$3))) -> 0.27802482 | E45: =IF(E42<=0,0,E42/(E31/INDEX(Assumptions!$C$90:$E$90,$B$3))) -> 0.033362978 | F45: =IF(F42<=0,0,F42/(F31/INDEX(Assumptions!$C$90:$E$90,$B$3))) -> 0 | G45: =IF(G42<=0,0,G42/(G31/INDEX(Assumptions!$C$90:$E$90,$B$3))) -> 0 | H45: =H42/(H31/INDEX(Assumptions!$C$90:$E$90,$B$3)) -> 0.047175427 | I45: BM M3 definition; A-ECO-34 payment months
A46: Paid-only CAC (CTWA + Search + Taster net + webinar/pop-up) | H46: =(B24+C24+F24+G24)/(B16+C16+F16+G16) -> 547.60183 | I46: excludes organic content and referral rewards
A47: Variable acquisition cost per target career enrolment (for business_forecast) | H47: =(B24+C24+E24+F24)/H7 -> 1253.37 | I47: (CTWA + Search + Taster net + referral rewards) / target enrolments; organic content is a fixed team cost there
A48: Paid-route media CAC: (CTWA + Search + Taster net) / their enrolments (for business_forecast) | H48: =(B24+C24+F24)/(B16+C16+F16) -> 1422.2833 | I48: Growth G4 'media CAC per paid career enrolment'
A49: Counselling conversations per month (career leads x 2.5 + other leads x 0.5) | H49: =H17*2.5+H58*0.5 -> 631.53182 | I49: A-GRO §10.4 method
A50: Counsellor FTE needed (A-GRO-38 x 24 days) | H50: =H49/(INDEX(Assumptions!$C$77:$E$77,$B$3)*24) -> 0.65784564
A51: Fully loaded CAC incl. counsellor, performance freelancer and martech | H51: =(H24+MAX(1,ROUNDUP(H50,0))*INDEX(Assumptions!$C$112:$E$112,$B$3)+INDEX(Assumptions!$C$115:$E$115,$B$3)+INDEX(Assumptions!$C$111:$E$111,$B$3))/H16 -> 6714.5014 | I51: (channel spend + A-GRO-45 x FTE + A-GRO-48 + A-GRO-42) / enrolments; Growth G4 definition
A52: Media spend per month on career routes (CTWA + Search + Taster + pop-up/webinar) | H52: =B24+C24+F24+G24 -> 9386.9905
A53: Check: organic leads derived vs A-GRO-43 ; referral leads vs A-GRO-44 | D53: =D17-INDEX(Assumptions!$C$79:$E$79,$B$3) -> -25.524671 | E53: =E17-INDEX(Assumptions!$C$80:$E$80,$B$3) -> -3.5081522 | I53: Growth agent check values
A55: H. Other products: masterclass (L4) and self-makeup (L1-S5) acquisition
A56: Seats per month (A-GRO §10.3: L4 24 base; L1-S5 15 base) - scaled with target | B56: =2.4*$H$7 -> 36 | C56: =1.5*$H$7 -> 22.5 | I56: L4 = 12 x target/5 ; L1-S5 = 1.5 x target
A57: Lead -> purchase (A-GRO-27 / A-GRO-28) | B57: =INDEX(Assumptions!$C$65:$E$65,$B$3) -> 0.35 | C57: =INDEX(Assumptions!$C$66:$E$66,$B$3) -> 0.25
A58: Leads needed | B58: =B56/B57 -> 102.85714 | C58: =C56/C57 -> 90 | H58: =B58+C58 -> 192.85714
A59: Paid media (paid share x CPL x leads) | B59: =B58*INDEX(Assumptions!$C$40:$E$40,$B$3)*INDEX(Assumptions!$C$38:$E$38,$B$3) -> 1542.8571 | C59: =C58*INDEX(Assumptions!$C$41:$E$41,$B$3)*INDEX(Assumptions!$C$39:$E$39,$B$3) -> 3600 | I59: A-GRO-18b, A-GRO-16/17
A60: Media per seat sold (for business_forecast) | B60: =B59/B56 -> 42.857143 | C60: =C59/C56 -> 160
A61: Columns: B = L4 masterclass, C = L1-S5 self-makeup

Sheet Speed_to_Lead
A1: Effect of speed-to-lead discipline (H7) - Base scenario, per month
A2: Same enrolment target with and without the <5-min SLA (A-GRO-24 multiplies Lead->QL when the SLA is missed), and the alternative view: enrolments lost at the same media budget.
A4: Metric | B4: Meta CTWA | C4: Google Search | D4: Organic | E4: Total (3 lead routes) | F4: Notes
A5: Enrolments target (routes as Funnel_Base) | B5: =Funnel_Base!B16 -> 3 | C5: =Funnel_Base!C16 -> 2 | D5: =Funnel_Base!D16 -> 2 | E5: =SUM(B5:D5) -> 7
A6: Leads needed - SLA met | B6: =Funnel_Base!B17 -> 56.818182 | C6: =Funnel_Base!C17 -> 28.935185 | D6: =Funnel_Base!D17 -> 39.872408 | E6: =SUM(B6:D6) -> 125.62578
A7: Leads needed - SLA missed (Lead->QL x A-GRO-24) | B7: =Funnel_Base!B17/Assumptions!$D$61 -> 84.803256 | C7: =Funnel_Base!C17/Assumptions!$D$61 -> 43.186844 | D7: =Funnel_Base!D17/Assumptions!$D$61 -> 59.511057 | E7: =SUM(B7:D7) -> 187.50116
A8: Spend - SLA met (₹) | B8: =Funnel_Base!B24 -> 16335.227 | C8: =Funnel_Base!C24 -> 14467.593 | D8: =Funnel_Base!D24 -> 35000 | E8: =SUM(B8:D8) -> 65802.82
A9: Spend - SLA missed (₹) | B9: =Funnel_Base!B24/Assumptions!$D$61 -> 24380.936 | C9: =Funnel_Base!C24/Assumptions!$D$61 -> 21593.422 | D9: =Funnel_Base!D24/Assumptions!$D$61 -> 52238.806 | E9: =SUM(B9:D9) -> 98213.164
A10: CAC - SLA met (₹) | B10: =Funnel_Base!B42 -> 5445.0758 | C10: =Funnel_Base!C42 -> 7233.7963 | D10: =Funnel_Base!D42 -> 17500 | E10: =IFERROR(SUMPRODUCT(B10:D10,B5:D5)/SUM(B5:D5),0) -> 9400.4028
A11: CAC - SLA missed (₹) | B11: =Funnel_Base!B42/Assumptions!$D$61 -> 8126.9787 | C11: =Funnel_Base!C42/Assumptions!$D$61 -> 10796.711 | D11: =Funnel_Base!D42/Assumptions!$D$61 -> 26119.403 | E11: =IFERROR(SUMPRODUCT(B11:D11,B5:D5)/SUM(B5:D5),0) -> 14030.452
A12: Extra spend per month to hit the same target (₹) | B12: =Funnel_Base!B24*(1/Assumptions!$D$61-1) -> 8045.709 | C12: =Funnel_Base!C24*(1/Assumptions!$D$61-1) -> 7125.8292 | D12: =Funnel_Base!D24*(1/Assumptions!$D$61-1) -> 17238.806 | E12: =SUM(B12:D12) -> 32410.344
A13: Alternative: enrolments at the SAME budget if SLA missed | B13: =Funnel_Base!B16*Assumptions!$D$61 -> 2.01 | C13: =Funnel_Base!C16*Assumptions!$D$61 -> 1.34 | D13: =Funnel_Base!D16*Assumptions!$D$61 -> 1.34 | E13: =SUM(B13:D13) -> 4.69
A14: Enrolments lost per month at the same budget | B14: =Funnel_Base!B16*(1-Assumptions!$D$61) -> 0.99 | C14: =Funnel_Base!C16*(1-Assumptions!$D$61) -> 0.66 | D14: =Funnel_Base!D16*(1-Assumptions!$D$61) -> 0.66 | E14: =SUM(B14:D14) -> 2.31
A15: Contribution lost per month (lost enrolments x contribution) | B15: =Funnel_Base!B16*(1-Assumptions!$D$61)*Funnel_Base!B31 -> 41428.983 | C15: =Funnel_Base!C16*(1-Assumptions!$D$61)*Funnel_Base!C31 -> 27619.322 | D15: =Funnel_Base!D16*(1-Assumptions!$D$61)*Funnel_Base!D31 -> 27619.322 | E15: =SUM(B15:D15) -> 96667.627
A17: Annual contribution lost at the same budget (x12) | E17: =E15*12 -> 1160011.5
A18: Founder-touch: counselled->applied falls by 1/A-GRO-25 when fully team-led; enrolments lost at same leads (all routes) | E18: =Funnel_Base!H16*(1-1/Assumptions!$D$62) -> 2.5032
A20: Reading: missing the SLA costs ~1/0.67 = 1.5x the media for the same enrolments - more than the gap between base and optimistic CPL. Process discipline before budget (H7).

Sheet Popup_Events
A1: Regional pop-up discovery workshop economics (per event) - BM spec M5
A4: Metric | B4: Conservative | C4: Base | D4: Aggressive | E4: Notes
A5: Paid attendees | B5: =Assumptions!$C$85 -> 25 | C5: =Assumptions!$D$85 -> 32 | D5: =Assumptions!$E$85 -> 40 | E5: A-BM-06a
A6: Ticket price (incl. GST) | B6: =Assumptions!$C$86 -> 999 | C6: =Assumptions!$D$86 -> 1499 | D6: =Assumptions!$E$86 -> 1499 | E6: A-BM-06b
A7: Ticket revenue ex-GST | B7: =B5*B6/(1+Assumptions!$C$15) -> 21165.254 | C7: =C5*C6/(1+Assumptions!$D$15) -> 40650.847 | D7: =D5*D6/(1+Assumptions!$E$15) -> 50813.559
A8: Event cost | B8: =Assumptions!$C$87 -> 60000 | C8: =Assumptions!$D$87 -> 52000 | D8: =Assumptions!$E$87 -> 45000 | E8: A-BM-06c
A9: Event net result (before enrolments) | B9: =B7-B8 -> -38834.746 | C9: =C7-C8 -> -11349.153 | D9: =D7-D8 -> 5813.5593
A10: Breakeven paid attendance | B10: =B8/(B6/(1+Assumptions!$C$15)) -> 70.870871 | C10: =C8/(C6/(1+Assumptions!$D$15)) -> 40.933956 | D10: =D8/(D6/(1+Assumptions!$E$15)) -> 35.423616 | E10: BM: ~36 at ₹1,499
A11: Enrolments per event (attendee->enrol A-BM-06d) | B11: =B5*Assumptions!$C$88 -> 2 | C11: =C5*Assumptions!$D$88 -> 3.52 | D11: =D5*Assumptions!$E$88 -> 6
A12: CAC per enrolment (net event cost / enrolments) | B12: =IF(B9>=0,0,-B9/B11) -> 19417.373 | C12: =IF(C9>=0,0,-C9/C11) -> 3224.1911 | D12: =IF(D9>=0,0,-D9/D11) -> 0 | E12: 0 = event self-funding
A13: Attendee->enrol needed for CAC <= ₹8,000 | B13: =MAX(0,-B9)/(8000*B5) -> 0.19417373 | C13: =MAX(0,-C9)/(8000*C5) -> 0.044332627 | D13: =MAX(0,-D9)/(8000*D5) -> 0 | E13: BM M5 threshold
A14: Contribution from enrolments (x Funnel career contribution) | B14: =B11*Funnel_Conservative!G31 -> 15961.864 | C14: =C11*Funnel_Base!G31 -> 147303.05 | D14: =D11*Funnel_Aggressive!G31 -> 359680.12
A15: Event total contribution incl. enrolments | B15: =B9+B14 -> -22872.881 | C15: =C9+C14 -> 135953.9 | D15: =D9+D14 -> 365493.68
